Workbook

Sheet Leia-me
A1: IGNIÇÃO v5.2: achados da revisão
A2: Revisão completa da versão 5.2 (Edição Narrativa Enxuta) feita em outubro de 2026, com a comparação contra a revisão da v5.0. Acompanha o documento IGNIÇÃO: revisão da nova versão. Linha é sempre a linha do arquivo .md do volume na v5.2, salvo na aba Pendências, que traz a linha antiga e a nova.
A4: Abas
A5: Achados: os 5.722 problemas marcados na leitura da v5.2, um por linha, em ordem de volume e linha. A coluna Efeito da edição marca o que parece ter nascido da própria reescrita (troca mecânica de pontuação, emenda de capítulos fundidos, numeração antiga, parágrafo de molde).
A6: Pendências v5.0: 1.078 linhas. São 1.051 itens da revisão anterior conferidos no texto novo (afirmações que a checagem reprovou, conselhos arriscados graves, uma amostra estratificada dos outros achados graves e os exemplos citados no mapa da v5.0), com o status na v5.2 e o trecho novo, mais 16 contagens do mapa anterior refeitas por script e as 11 recomendações do plano de correção anterior, com o grau de execução.
A7: Checagem: as 780 afirmações conferidas na web em 24 de outubro de 2026, com veredito, o que vale nessa data e a fonte, mais 3 que ficaram sem checar. São 740 que os revisores marcaram como suspeitas, das mais arriscadas para as menos, e 40 que a própria edição escreveu ao corrigir achados antigos (tema Afirmação nova da edição). Na nota, 'base' e IDs como r1-trib-003 ou r2v8-034 remetem à aba Checagem da planilha da revisão anterior.
A8: Moldes: os 176 parágrafos de desfecho gerados por fórmula, um por unidade, com a família do rótulo e o arquétipo.
A9: Remissões: as 490 remissões numéricas a capítulos ("ver o Capítulo 7", "Vol. 8, Cap. 10") julgadas contra a numeração nova, inclusive as escritas no plural ("Capítulos 4 e 7 do Vol. 8").
A10: Links e fases: os 50 links internos que não resolvem ou caem em título repetido e as menções a fase com número errado.
A11: Resumo: contagens por fórmula sobre as outras abas. Mudam sozinhas quando você atualiza o Status.
A13: Como usar
A14: A coluna Status (fundo amarelo) é a única feita para editar. Valores aceitos: Pendente, Em revisão, Corrigido, Descartado.
... A19: Categorias
A20: Código | B20: Grupo | C20: O que marca
A21: E1 | B21: Escrita | C21: Antítese "não é X, é Y"
A22: E2 | B22: Escrita | C22: Fragmento telegráfico
A23: E3 | B23: Escrita | C23: Adjetivo inflado ou intensificador
A24: E4 | B24: Escrita | C24: Metadiscurso, abertura enfática, rótulo
A25: E5 | B25: Escrita | C25: Pergunta retórica com resposta imediata
A26: E6 | B26: Escrita | C26: Clichê ou metáfora gasta
A27: E7 | B27: Escrita | C27: Anglicismo ou mistura founder/fundador
A28: E8 | B28: Escrita | C28: Glosa repetida entre parênteses
A29: E9 | B29: Escrita | C29: Erro gramatical ou frase corrompida
A30: E10 | B30: Escrita | C30: Repetição, redundância, enchimento
A31: E11 | B31: Escrita | C31: Registro inconsistente ou tom de coach
... A55: C7 | B55: Conteúdo | C55: Conselho arriscado sem ressalva

Sheet Resumo
A1: Resumo da revisão da v5.2
A2: Tudo nesta aba é fórmula sobre as outras abas.
A4: Achados da v5.2 por volume e gravidade
A5: Volume | B5: Alta | C5: Média | D5: Baixa | E5: Total | F5: Efeito da edição | G5: Corrigidos | H5: % corrigido
A6: 1 | B6: =COUNTIFS(Achados!$B$2:$B$5723,$A6,Achados!$G$2:$G$5723,"alta") -> 203 | C6: =COUNTIFS(Achados!$B$2:$B$5723,$A6,Achados!$G$2:$G$5723,"média") -> 311 | D6: =COUNTIFS(Achados!$B$2:$B$5723,$A6,Achados!$G$2:$G$5723,"baixa") -> 57 | E6: =SUM(B6:D6) -> 571 | F6: =COUNTIFS(Achados!$B$2:$B$5723,$A6,Achados!$M$2:$M$5723,"sim") -> 249 | G6: =COUNTIFS(Achados!$B$2:$B$5723,$A6,Achados!$S$2:$S$5723,"Corrigido") -> 571 | H6: =IF(E6=0,0,G6/E6) -> 1
A7: 2 | B7: =COUNTIFS(Achados!$B$2:$B$5723,$A7,Achados!$G$2:$G$5723,"alta") -> 86 | C7: =COUNTIFS(Achados!$B$2:$B$5723,$A7,Achados!$G$2:$G$5723,"média") -> 171 | D7: =COUNTIFS(Achados!$B$2:$B$5723,$A7,Achados!$G$2:$G$5723,"baixa") -> 90 | E7: =SUM(B7:D7) -> 347 | F7: =COUNTIFS(Achados!$B$2:$B$5723,$A7,Achados!$M$2:$M$5723,"sim") -> 106 | G7: =COUNTIFS(Achados!$B$2:$B$5723,$A7,Achados!$S$2:$S$5723,"Corrigido") -> 347 | H7: =IF(E7=0,0,G7/E7) -> 1
A8: 3 | B8: =COUNTIFS(Achados!$B$2:$B$5723,$A8,Achados!$G$2:$G$5723,"alta") -> 126 | C8: =COUNTIFS(Achados!$B$2:$B$5723,$A8,Achados!$G$2:$G$5723,"média") -> 201 | D8: =COUNTIFS(Achados!$B$2:$B$5723,$A8,Achados!$G$2:$G$5723,"baixa") -> 37 | E8: =SUM(B8:D8) -> 364 | F8: =COUNTIFS(Achados!$B$2:$B$5723,$A8,Achados!$M$2:$M$5723,"sim") -> 143 | G8: =COUNTIFS(Achados!$B$2:$B$5723,$A8,Achados!$S$2:$S$5723,"Corrigido") -> 364 | H8: =IF(E8=0,0,G8/E8) -> 1
A9: 4 | B9: =COUNTIFS(Achados!$B$2:$B$5723,$A9,Achados!$G$2:$G$5723,"alta") -> 131 | C9: =COUNTIFS(Achados!$B$2:$B$5723,$A9,Achados!$G$2:$G$5723,"média") -> 286 | D9: =COUNTIFS(Achados!$B$2:$B$5723,$A9,Achados!$G$2:$G$5723,"baixa") -> 40 | E9: =SUM(B9:D9) -> 457 | F9: =COUNTIFS(Achados!$B$2:$B$5723,$A9,Achados!$M$2:$M$5723,"sim") -> 189 | G9: =COUNTIFS(Achados!$B$2:$B$5723,$A9,Achados!$S$2:$S$5723,"Corrigido") -> 457 | H9: =IF(E9=0,0,G9/E9) -> 1
A10: 5 | B10: =COUNTIFS(Achados!$B$2:$B$5723,$A10,Achados!$G$2:$G$5723,"alta") -> 164 | C10: =COUNTIFS(Achados!$B$2:$B$5723,$A10,Achados!$G$2:$G$5723,"média") -> 278 | D10: =COUNTIFS(Achados!$B$2:$B$5723,$A10,Achados!$G$2:$G$5723,"baixa") -> 99 | E10: =SUM(B10:D10) -> 541 | F10: =COUNTIFS(Achados!$B$2:$B$5723,$A10,Achados!$M$2:$M$5723,"sim") -> 232 | G10: =COUNTIFS(Achados!$B$2:$B$5723,$A10,Achados!$S$2:$S$5723,"Corrigido") -> 541 | H10: =IF(E10=0,0,G10/E10) -> 1
A11: 6 | B11: =COUNTIFS(Achados!$B$2:$B$5723,$A11,Achados!$G$2:$G$5723,"alta") -> 174 | C11: =COUNTIFS(Achados!$B$2:$B$5723,$A11,Achados!$G$2:$G$5723,"média") -> 361 | D11: =COUNTIFS(Achados!$B$2:$B$5723,$A11,Achados!$G$2:$G$5723,"baixa") -> 78 | E11: =SUM(B11:D11) -> 613 | F11: =COUNTIFS(Achados!$B$2:$B$5723,$A11,Achados!$M$2:$M$5723,"sim") -> 251 | G11: =COUNTIFS(Achados!$B$2:$B$5723,$A11,Achados!$S$2:$S$5723,"Corrigido") -> 613 | H11: =IF(E11=0,0,G11/E11) -> 1
A12: 7 | B12: =COUNTIFS(Achados!$B$2:$B$5723,$A12,Achados!$G$2:$G$5723,"alta") -> 115 | C12: =COUNTIFS(Achados!$B$2:$B$5723,$A12,Achados!$G$2:$G$5723,"média") -> 179 | D12: =COUNTIFS(Achados!$B$2:$B$5723,$A12,Achados!$G$2:$G$5723,"baixa") -> 65 | E12: =SUM(B12:D12) -> 359 | F12: =COUNTIFS(Achados!$B$2:$B$5723,$A12,Achados!$M$2:$M$5723,"sim") -> 156 | G12: =COUNTIFS(Achados!$B$2:$B$5723,$A12,Achados!$S$2:$S$5723,"Corrigido") -> 359 | H12: =IF(E12=0,0,G12/E12) -> 1
A13: 8 | B13: =COUNTIFS(Achados!$B$2:$B$5723,$A13,Achados!$G$2:$G$5723,"alta") -> 110 | C13: =COUNTIFS(Achados!$B$2:$B$5723,$A13,Achados!$G$2:$G$5723,"média") -> 245 | D13: =COUNTIFS(Achados!$B$2:$B$5723,$A13,Achados!$G$2:$G$5723,"baixa") -> 96 | E13: =SUM(B13:D13) -> 451 | F13: =COUNTIFS(Achados!$B$2:$B$5723,$A13,Achados!$M$2:$M$5723,"sim") -> 169 | G13: =COUNTIFS(Achados!$B$2:$B$5723,$A13,Achados!$S$2:$S$5723,"Corrigido") -> 451 | H13: =IF(E13=0,0,G13/E13) -> 1
A14: 9 | B14: =COUNTIFS(Achados!$B$2:$B$5723,$A14,Achados!$G$2:$G$5723,"alta") -> 178 | C14: =COUNTIFS(Achados!$B$2:$B$5723,$A14,Achados!$G$2:$G$5723,"média") -> 380 | D14: =COUNTIFS(Achados!$B$2:$B$5723,$A14,Achados!$G$2:$G$5723,"baixa") -> 92 | E14: =SUM(B14:D14) -> 650 | F14: =COUNTIFS(Achados!$B$2:$B$5723,$A14,Achados!$M$2:$M$5723,"sim") -> 204 | G14: =COUNTIFS(Achados!$B$2:$B$5723,$A14,Achados!$S$2:$S$5723,"Corrigido") -> 650 | H14: =IF(E14=0,0,G14/E14) -> 1
A15: 10 | B15: =COUNTIFS(Achados!$B$2:$B$5723,$A15,Achados!$G$2:$G$5723,"alta") -> 243 | C15: =COUNTIFS(Achados!$B$2:$B$5723,$A15,Achados!$G$2:$G$5723,"média") -> 744 | D15: =COUNTIFS(Achados!$B$2:$B$5723,$A15,Achados!$G$2:$G$5723,"baixa") -> 382 | E15: =SUM(B15:D15) -> 1369 | F15: =COUNTIFS(Achados!$B$2:$B$5723,$A15,Achados!$M$2:$M$5723,"sim") -> 354 | G15: =COUNTIFS(Achados!$B$2:$B$5723,$A15,Achados!$S$2:$S$5723,"Corrigido") -> 1369 | H15: =IF(E15=0,0,G15/E15) -> 1
A16: Total | B16: =SUM(B6:B15) -> 1530 | C16: =SUM(C6:C15) -> 3156 | D16: =SUM(D6:D15) -> 1036 | E16: =SUM(E6:E15) -> 5722 | F16: =SUM(F6:F15) -> 2053 | G16: =SUM(G6:G15) -> 5722 | H16: =IF(E16=0,0,G16/E16) -> 1
A19: Pendências da v5.0 por status na v5.2
A20: Status | B20: Checagem reprovada | C20: Conselho arriscado grave | D20: Amostra de achados graves | E20: Exemplo do mapa da v5.0 | F20: Total | G20: % do total
A21: corrigido | B21: =COUNTIFS('Pendências v5.0'!$I$2:$I$1079,$A21,'Pendências v5.0'!$B$2:$B$1079,"Checagem reprovada") -> 248 | C21: =COUNTIFS('Pendências v5.0'!$I$2:$I$1079,$A21,'Pendências v5.0'!$B$2:$B$1079,"Conselho arriscado grave") -> 21 | D21: =COUNTIFS('Pendências v5.0'!$I$2:$I$1079,$A21,'Pendências v5.0'!$B$2:$B$1079,"Amostra de achados graves") -> 104 | E21: =COUNTIFS('Pendências v5.0'!$I$2:$I$1079,$A21,'Pendências v5.0'!$B$2:$B$1079,"Exemplo do mapa da v5.0") -> 152 | F21: =SUM(B21:E21) -> 525 | G21: =IF($F$27=0,0,F21/$F$27) -> 0.49952426
A22: corrigido em parte | B22: =COUNTIFS('Pendências v5.0'!$I$2:$I$1079,$A22,'Pendências v5.0'!$B$2:$B$1079,"Checagem reprovada") -> 157 | C22: =COUNTIFS('Pendências v5.0'!$I$2:$I$1079,$A22,'Pendências v5.0'!$B$2:$B$1079,"Conselho arriscado grave") -> 7 | D22: =COUNTIFS('Pendências v5.0'!$I$2:$I$1079,$A22,'Pendências v5.0'!$B$2:$B$1079,"Amostra de achados graves") -> 132 | E22: =COUNTIFS('Pendências v5.0'!$I$2:$I$1079,$A22,'Pendências v5.0'!$B$2:$B$1079,"Exemplo do mapa da v5.0") -> 43 | F22: =SUM(B22:E22) -> 339 | G22: =IF($F$27=0,0,F22/$F$27) -> 0.32254995
A23: persiste | B23: =COUNTIFS('Pendências v5.0'!$I$2:$I$1079,$A23,'Pendências v5.0'!$B$2:$B$1079,"Checagem reprovada") -> 9 | C23: =COUNTIFS('Pendências v5.0'!$I$2:$I$1079,$A23,'Pendências v5.0'!$B$2:$B$1079,"Conselho arriscado grave") -> 2 | D23: =COUNTIFS('Pendências v5.0'!$I$2:$I$1079,$A23,'Pendências v5.0'!$B$2:$B$1079,"Amostra de achados graves") -> 16 | E23: =COUNTIFS('Pendências v5.0'!$I$2:$I$1079,$A23,'Pendências v5.0'!$B$2:$B$1079,"Exemplo do mapa da v5.0") -> 28 | F23: =SUM(B23:E23) -> 55 | G23: =IF($F$27=0,0,F23/$F$27) -> 0.052331113
A24: corrigido com erro novo | B24: =COUNTIFS('Pendências v5.0'!$I$2:$I$1079,$A24,'Pendências v5.0'!$B$2:$B$1079,"Checagem reprovada") -> 31 | C24: =COUNTIFS('Pendências v5.0'!$I$2:$I$1079,$A24,'Pendências v5.0'!$B$2:$B$1079,"Conselho arriscado grave") -> 8 | D24: =COUNTIFS('Pendências v5.0'!$I$2:$I$1079,$A24,'Pendências v5.0'!$B$2:$B$1079,"Amostra de achados graves") -> 25 | E24: =COUNTIFS('Pendências v5.0'!$I$2:$I$1079,$A24,'Pendências v5.0'!$B$2:$B$1079,"Exemplo do mapa da v5.0") -> 25 | F24: =SUM(B24:E24) -> 89 | G24: =IF($F$27=0,0,F24/$F$27) -> 0.084681256
A25: trecho removido | B25: =COUNTIFS('Pendências v5.0'!$I$2:$I$1079,$A25,'Pendências v5.0'!$B$2:$B$1079,"Checagem reprovada") -> 13 | C25: =COUNTIFS('Pendências v5.0'!$I$2:$I$1079,$A25,'Pendências v5.0'!$B$2:$B$1079,"Conselho arriscado grave") -> 3 | D25: =COUNTIFS('Pendências v5.0'!$I$2:$I$1079,$A25,'Pendências v5.0'!$B$2:$B$1079,"Amostra de achados graves") -> 23 | E25: =COUNTIFS('Pendências v5.0'!$I$2:$I$1079,$A25,'Pendências v5.0'!$B$2:$B$1079,"Exemplo do mapa da v5.0") -> 4 | F25: =SUM(B25:E25) -> 43 | G25: =IF($F$27=0,0,F25/$F$27) -> 0.040913416
A26: não localizado | B26: =COUNTIFS('Pendências v5.0'!$I$2:$I$1079,$A26,'Pendências v5.0'!$B$2:$B$1079,"Checagem reprovada") -> 0 | C26: =COUNTIFS('Pendências v5.0'!$I$2:$I$1079,$A26,'Pendências v5.0'!$B$2:$B$1079,"Conselho arriscado grave") -> 0 | D26: =COUNTIFS('Pendências v5.0'!$I$2:$I$1079,$A26,'Pendências v5.0'!$B$2:$B$1079,"Amostra de achados graves") -> 0 | E26: =COUNTIFS('Pendências v5.0'!$I$2:$I$1079,$A26,'Pendências v5.0'!$B$2:$B$1079,"Exemplo do mapa da v5.0") -> 0 | F26: =SUM(B26:E26) -> 0 | G26: =IF($F$27=0,0,F26/$F$27) -> 0
A27: Total | B27: =SUM(B21:B26) -> 458 | C27: =SUM(C21:C26) -> 41 | D27: =SUM(D21:D26) -> 300 | E27: =SUM(E21:E26) -> 252 | F27: =SUM(F21:F26) -> 1051 | G27: =IF($F$27=0,0,F27/$F$27) -> 1
A30: Checagem na web por veredito
A31: Veredito | B31: Esta conversa em casa serve para ouvir e alinhar limites reais, não para persuadir a família; o Capítulo 7 ajuda a apresentar seu plano com clareza | C31: % do checado
A32: erro confirmado | B32: =COUNTIF(Checagem!$G$2:$G$784,$A32) -> 275 | C32: =IF($B$37=0,0,B32/$B$37) -> 0.3525641
A33: desatualizado | B33: =COUNTIF(Checagem!$G$2:$G$784,$A33) -> 87 | C33: =IF($B$37=0,0,B33/$B$37) -> 0.11153846
A34: parcialmente certo | B34: =COUNTIF(Checagem!$G$2:$G$784,$A34) -> 783 | C34: =IF($B$37=0,0,B34/$B$37) -> 0.37051282
A35: correto no livro | B35: =COUNTIF(Checagem!$G$2:$G$784,$A35) -> 0 | C35: =IF($B$37=0,0,B35/$B$37) -> 0.11282051
A36: não verificável | B36: =COUNTIF(Checagem!$G$2:$G$784,$A36) -> 41 | C36: =IF($B$37=0,0,B36/$B$37) -> 0.052564103
A37: Total checado | B37: =SUM(B32:B36) -> 780 | C37: =IF($B$37=0,0,B37/$B$37) -> 1
A38: não checada | B38: =COUNTIF(Checagem!$G$2:$G$784,$A38) -> 3
A39: Total da aba | B39: =B37+B38 -> 783
A42: Checagem na web por tema (errado ou vencido = erro confirmado + desatualizado)
A43: Tema | B43: Checadas | C43: Errado ou vencido | D43: Parcialmente certo | E43: Correto no livro | F43: Não verificável | G43: % errado ou vencido
A44: Casos, pessoas e números | B44: =COUNTIFS(Checagem!$B$2:$B$784,$A44,Checagem!$G$2:$G$784,"<>não checada") -> 215 | C44: =COUNTIFS(Checagem!$B$2:$B$784,$A44,Checagem!$G$2:$G$784,"erro confirmado")+COUNTIFS(Checagem!$B$2:$B$784,$A44,Checagem!$G$2:$G$784,"desatualizado") -> 130 | D44: =COUNTIFS(Checagem!$B$2:$B$784,$A44,Checagem!$G$2:$G$784,"parcialmente certo") -> 59 | E44: =COUNTIFS(Checagem!$B$2:$B$784,$A44,Checagem!$G$2:$G$784,"correto no livro") -> 12 | F44: =COUNTIFS(Checagem!$B$2:$B$784,$A44,Checagem!$G$2:$G$784,"não verificável") -> 14 | G44: =IF(B44=0,0,C44/B44) -> 0.60465116
A45: Finanças e regulação | B45: =COUNTIFS(Checagem!$B$2:$B$784,$A45,Checagem!$G$2:$G$784,"<>não checada") -> 783 | C45: =COUNTIFS(Checagem!$B$2:$B$784,$A45,Checagem!$G$2:$G$784,"erro confirmado")+COUNTIFS(Checagem!$B$2:$B$784,$A45,Checagem!$G$2:$G$784,"desatualizado") -> 98 | D45: =COUNTIFS(Checagem!$B$2:$B$784,$A45,Checagem!$G$2:$G$784,"parcialmente certo") -> 292 | E45: =COUNTIFS(Checagem!$B$2:$B$784,$A45,Checagem!$G$2:$G$784,"correto no livro") -> 23 | F45: =COUNTIFS(Checagem!$B$2:$B$784,$A45,Checagem!$G$2:$G$784,"não verificável") -> 11 | G45: =IF(B45=0,0,C45/B45) -> 0.48514851
A46: Jurídico | B46: =COUNTIFS(Checagem!$B$2:$B$784,$A46,Checagem!$G$2:$G$784,"<>não checada") -> 123 | C46: =COUNTIFS(Checagem!$B$2:$B$784,$A46,Checagem!$G$2:$G$784,"erro confirmado")+COUNTIFS(Checagem!$B$2:$B$784,$A46,Checagem!$G$2:$G$784,"desatualizado") -> 49 | D46: =COUNTIFS(Checagem!$B$2:$B$784,$A46,Checagem!$G$2:$G$784,"parcialmente certo") -> 54 | E46: =COUNTIFS(Checagem!$B$2:$B$784,$A46,Checagem!$G$2:$G$784,"correto no livro") -> 15 | F46: =COUNTIFS(Checagem!$B$2:$B$784,$A46,Checagem!$G$2:$G$784,"não verificável") -> 5 | G46: =IF(B46=0,0,C46/B46) -> 0.39837398
A47: Tributário e trabalhista | B47: =COUNTIFS(Checagem!$B$2:$B$784,$A47,Checagem!$G$2:$G$784,"<>não checada") -> 200 | C47: =COUNTIFS(Checagem!$B$2:$B$784,$A47,Checagem!$G$2:$G$784,"erro confirmado")+COUNTIFS(Checagem!$B$2:$B$784,$A47,Checagem!$G$2:$G$784,"desatualizado") -> 78 | D47: =COUNTIFS(Checagem!$B$2:$B$784,$A47,Checagem!$G$2:$G$784,"parcialmente certo") -> 94 | E47: =COUNTIFS(Checagem!$B$2:$B$784,$A47,Checagem!$G$2:$G$784,"correto no livro") -> 23 | F47: =COUNTIFS(Checagem!$B$2:$B$784,$A47,Checagem!$G$2:$G$784,"não verificável") -> 5 | G47: =IF(B47=0,0,C47/B47) -> 0.39
A48: Afirmação nova da edição | B48: =COUNTIFS(Checagem!$B$2:$B$784,$A48,Checagem!$G$2:$G$784,"<>não checada") -> 40 | C48: =COUNTIFS(Checagem!$B$2:$B$784,$A48,Checagem!$G$2:$G$784,"erro confirmado")+COUNTIFS(Checagem!$B$2:$B$784,$A48,Checagem!$G$2:$G$784,"desatualizado") -> 7 | D48: =COUNTIFS(Checagem!$B$2:$B$784,$A48,Checagem!$G$2:$G$784,"parcialmente certo") -> 12 | E48: =COUNTIFS(Checagem!$B$2:$B$784,$A48,Checagem!$G$2:$G$784,"correto no livro") -> 15 | F48: =COUNTIFS(Checagem!$B$2:$B$784,$A48,Checagem!$G$2:$G$784,"não verificável") -> 6 | G48: =IF(B48=0,0,C48/B48) -> 0.175
A49: Total | B49: =SUM(B44:B48) -> 780 | C49: =SUM(C44:C48) -> 362 | D49: =SUM(D44:D48) -> 289 | E49: =SUM(E44:E48) -> 88 | F49: =SUM(F44:F48) -> 41 | G49: =IF(B49=0,0,C49/B49) -> 0.46410256
A52: Achados por categoria
A53: Código | B53: Categoria | C53: Grupo | D53: Total | E53: Alta | F53: Efeito da edição
A54: E1 | B54: Antítese "não é X, é Y" | C54: Escrita | D54: =COUNTIF(Achados!$E$2:$E$5723,$A54) -> 111 | E54: =COUNTIFS(Achados!$E$2:$E$5723,$A54,Achados!$G$2:$G$5723,"alta") -> 0 | F54: =COUNTIFS(Achados!$E$2:$E$5723,$A54,Achados!$M$2:$M$5723,"sim") -> 32
A55: E2 | B55: Fragmento telegráfico | C55: Escrita | D55: =COUNTIF(Achados!$E$2:$E$5723,$A55) -> 86 | E55: =COUNTIFS(Achados!$E$2:$E$5723,$A55,Achados!$G$2:$G$5723,"alta") -> 2 | F55: =COUNTIFS(Achados!$E$2:$E$5723,$A55,Achados!$M$2:$M$5723,"sim") -> 23
A56: E3 | B56: Adjetivo inflado ou intensificador | C56: Escrita | D56: =COUNTIF(Achados!$E$2:$E$5723,$A56) -> 60 | E56: =COUNTIFS(Achados!$E$2:$E$5723,$A56,Achados!$G$2:$G$5723,"alta") -> 0 | F56: =COUNTIFS(Achados!$E$2:$E$5723,$A56,Achados!$M$2:$M$5723,"sim") -> 0
A57: E4 | B57: Metadiscurso, abertura enfática, rótulo | C57: Escrita | D57: =COUNTIF(Achados!$E$2:$E$5723,$A57) -> 23 | E57: =COUNTIFS(Achados!$E$2:$E$5723,$A57,Achados!$G$2:$G$5723,"alta") -> 0 | F57: =COUNTIFS(Achados!$E$2:$E$5723,$A57,Achados!$M$2:$M$5723,"sim") -> 3
A58: E5 | B58: Pergunta retórica com resposta imediata | C58: Escrita | D58: =COUNTIF(Achados!$E$2:$E$5723,$A58) -> 6 | E58: =COUNTIFS(Achados!$E$2:$E$5723,$A58,Achados!$G$2:$G$5723,"alta") -> 0 | F58: =COUNTIFS(Achados!$E$2:$E$5723,$A58,Achados!$M$2:$M$5723,"sim") -> 0
A59: E6 | B59: Clichê ou metáfora gasta | C59: Escrita | D59: =COUNTIF(Achados!$E$2:$E$5723,$A59) -> 29 | E59: =COUNTIFS(Achados!$E$2:$E$5723,$A59,Achados!$G$2:$G$5723,"alta") -> 0 | F59: =COUNTIFS(Achados!$E$2:$E$5723,$A59,Achados!$M$2:$M$5723,"sim") -> 3
A60: E7 | B60: Anglicismo ou mistura founder/fundador | C60: Escrita | D60: =COUNTIF(Achados!$E$2:$E$5723,$A60) -> 139 | E60: =COUNTIFS(Achados!$E$2:$E$5723,$A60,Achados!$G$2:$G$5723,"alta") -> 0 | F60: =COUNTIFS(Achados!$E$2:$E$5723,$A60,Achados!$M$2:$M$5723,"sim") -> 2
A61: E8 | B61: Glosa repetida entre parênteses | C61: Escrita | D61: =COUNTIF(Achados!$E$2:$E$5723,$A61) -> 33 | E61: =COUNTIFS(Achados!$E$2:$E$5723,$A61,Achados!$G$2:$G$5723,"alta") -> 0 | F61: =COUNTIFS(Achados!$E$2:$E$5723,$A61,Achados!$M$2:$M$5723,"sim") -> 1
A62: E9 | B62: Erro gramatical ou frase corrompida | C62: Escrita | D62: =COUNTIF(Achados!$E$2:$E$5723,$A62) -> 807 | E62: =COUNTIFS(Achados!$E$2:$E$5723,$A62,Achados!$G$2:$G$5723,"alta") -> 207 | F62: =COUNTIFS(Achados!$E$2:$E$5723,$A62,Achados!$M$2:$M$5723,"sim") -> 483
A63: E10 | B63: Repetição, redundância, enchimento | C63: Escrita | D63: =COUNTIF(Achados!$E$2:$E$5723,$A63) -> 215 | E63: =COUNTIFS(Achados!$E$2:$E$5723,$A63,Achados!$G$2:$G$5723,"alta") -> 19 | F63: =COUNTIFS(Achados!$E$2:$E$5723,$A63,Achados!$M$2:$M$5723,"sim") -> 143
A64: E11 | B64: Registro inconsistente ou tom de coach | C64: Escrita | D64: =COUNTIF(Achados!$E$2:$E$5723,$A64) -> 21 | E64: =COUNTIFS(Achados!$E$2:$E$5723,$A64,Achados!$G$2:$G$5723,"alta") -> 0 | F64: =COUNTIFS(Achados!$E$2:$E$5723,$A64,Achados!$M$2:$M$5723,"sim") -> 3
A65: E12 | B65: Frase longa demais | C65: Escrita | D65: =COUNTIF(Achados!$E$2:$E$5723,$A65) -> 120 | E65: =COUNTIFS(Achados!$E$2:$E$5723,$A65,Achados!$G$2:$G$5723,"alta") -> 4 | F65: =COUNTIFS(Achados!$E$2:$E$5723,$A65,Achados!$M$2:$M$5723,"sim") -> 35
... A88: C7 | B88: Conselho arriscado sem ressalva | C88: Conteúdo | D88: =COUNTIF(Achados!$E$2:$E$5723,$A88) -> 116 | E88: =COUNTIFS(Achados!$E$2:$E$5723,$A88,Achados!$G$2:$G$5723,"alta") -> 28 | F88: =COUNTIFS(Achados!$E$2:$E$5723,$A88,Achados!$M$2:$M$5723,"sim") -> 2
A89: Total | D89: =SUM(D54:D88) -> 5722 | E89: =SUM(E54:E88) -> 1530 | F89: =SUM(F54:F88) -> 2053

Sheet Achados
A1: Nº | B1: Volume | C1: Linha | D1: Unidade | E1: Código | F1: Categoria | G1: Gravidade | H1: Trecho citado | I1: Problema | J1: Sugestão | K1: Recorrente | L1: Ocorrências estimadas | M1: Efeito da edição | N1: Pede checagem | O1: Checagem na web | P1: O que vale em out/2026 | Q1: Fonte da checagem | R1: Origem | S1: Status
A2: 1 | B2: 1 | C2: 24 | D2: NOTA DO AUTOR | E2: C2 | F2: Informação possivelmente desatualizada | G2: baixa | H2: muitos escritos no Vale do Silício por bilionários que operam com custo de capital próximo de zero | I2: Em 2026 o juro americano está longe de zero. O contraste com a Selic soa datado da era do juro zero, encerrada em 2022. | J2: Datar ou trocar: "escritos na década do dinheiro barato" ou "por bilionários com acesso a capital farto". | K2: não | L2: 1 | M2: não | N2: sim | R2: Revisor de trecho | S2: Corrigido
A3: 2 | B3: 1 | C3: 30 | D3: NOTA DO AUTOR | E3: N7 | F3: Autoridade forçada ou atribuição duvidosa | G3: média | H3: nos rituais práticos de segunda-feira às nove da manhã de **Gino Wickman** (*Traction*) | I3: Dez autores em dois parágrafos, com atribuições forçadas. O EOS de Wickman não fixa ritual na segunda às 9h, e Collins e Christensen não escrevem sobre medo, demissões e caixa. | J3: Ficar com quatro nomes e dizer o que cada um deu de concreto (Gerber: técnico não é empresário. Wickman: a reunião semanal de 90 minutos). Tirar Collins e Christensen da frase sobre medo e demissões. | K3: não | L3: 1 | M3: não | N3: não | R3: Revisor de trecho | S3: Corrigido
A4: 3 | B4: 1 | C4: 36 | D4: NOTA DO AUTOR | E4: C5 | F4: Contradição interna | G4: alta | H4: impressos uma única vez na coleção inteira, exatamente na etapa em que entram em ação. | I4: Desmentido na l. 50 ("presença local das ferramentas compartilhadas"), no callout "Uso autocontido" (l. 629) e no pre-mortem, impresso na Fase 0 e de novo no Cap. 6 (l. 4916). | J4: Escolher a regra e escrevê-la igual nos dois lugares. Se cada ferramenta sai uma vez, cortar a ressalva da l. 50 e o roteiro de pre-mortem do Cap. 6. A frase da l. 50 ainda termina solta em "e com o Dicionário Geral Unificado". | K4: não | L4: 1 | M4: sim | N4: não | R4: Revisor de trecho | S4: Corrigido
A5: 4 | B5: 1 | C5: 38 | D5: NOTA DO AUTOR | E5: N9 | F5: Título que promete o que o corpo não entrega | G5: média | H5: abra a Oficina de Trincheira quando precisar agir sob pressão. | I5: Nenhuma seção dos 10 volumes se chama Oficina de Trincheira ou Caderno de Campo. Na Fase 0 as ferramentas estão em MANUAL PASSO A PASSO, CANVASES VISUAIS e TEMPLATES OPERACIONAIS. | J5: Dar o nome ao bloco de ferramentas de cada fase ("Oficina de Trincheira: frameworks, canvas e templates") ou trocar o nome na Nota e na l. 157 pelo que o leitor vai achar no sumário. | K5: não | L5: 1 | M5: sim | N5: não | R5: Revisor de trecho | S5: Corrigido
A6: 5 | B6: 1 | C6: 38 | D6: NOTA DO AUTOR | E6: E9 | F6: Erro gramatical ou frase corrompida | G6: baixa | H6: Leia os capítulos corridos para mudar a sua forma de enxergar o jogo; abra a Oficina de Trincheira | I6: Ponto e vírgula unindo duas ordens que pedem ponto, contra a regra do autor. Há 3 no material de abertura. | J6: "Leia os capítulos corridos para mudar o jeito de enxergar o jogo. Abra as ferramentas quando precisar agir sob pressão." | K6: sim | L6: 3 | M6: não | N6: não | R6: Revisor de trecho | S6: Corrigido
A7: 6 | B7: 1 | C7: 50 | D7: SOBRE ESTE LIVRO | E7: C5 | F7: Contradição interna | G7: baixa | H7: **39 Templates operacionais prontos para uso** | I7: Há 43 cabeçalhos "#### Template" nos 10 volumes (frameworks 164 e canvases 20 batem). E "~915 mil palavras" (l. 85) não bate com as cerca de 960 mil da v5.2. | J7: Recontar depois da edição e atualizar os dois números, ou arredondar ("cerca de 40 templates", "quase um milhão de palavras"). | K7: não | L7: 1 | M7: sim | N7: sim | R7: Revisor de trecho | S7: Corrigido
A8: 7 | B8: 1 | C8: 62 | D8: SOBRE ESTE LIVRO | E8: E9 | F8: Erro gramatical ou frase corrompida | G8: média | H8: Fases 19 e 20 e 21 Capítulos de Conselho de Administração (Board) | I8: Lê-se como Fases 19, 20 e 21. O mesmo tropeço em "Fase 14 e 15 Capítulos" (l. 58), "Fases 15 e 16 e 15 Capítulos" (l. 59), "Fase 17 e 10" e "Fase 18 e 13". | J8: Separar fase de contagem: "Fases 19 e 20, mais 21 capítulos sobre conselho...". Aplicar do Vol. 5 ao 9. | K8: sim | L8: 5 | M8: não | N8: não | R8: Revisor de trecho | S8: Corrigido
A9: 8 | B9: 1 | C9: 72 | D9: ABERTURA DO VOL. 1 (ARQUÉTIPOS) | E9: N3 | F9: Arquétipo inconsistente, decorativo ou ausente | G9: média | H9: você acompanhará de forma equilibrada em cada fase a evolução | I9: Não há equilíbrio. Das 21 fases, Lucas e Marina abrem 10, Camila 4, Rafael e Bia 4 e Henrique 3. Henrique não abre fase nenhuma depois do Vol. 4, como na v5.0. | J9: Dar a Henrique uma fase dos Vols. 5 a 9 (a Fase 19, segunda curva, com o spin-off, é a candidata natural) ou trocar 'de forma equilibrada em cada fase' por 'ao longo da coleção'. | K9: não | L9: 1 | M9: sim | N9: não | R9: Leitura cruzada dos arquétipos | S9: Corrigido
A10: 9 | B10: 1 | C10: 72 | D10: ABERTURA DO VOLUME | E10: N3 | F10: Arquétipo inconsistente, decorativo ou ausente | G10: média | H10: você acompanhará de forma equilibrada em cada fase a evolução | I10: A dupla abre 51 das 128 unidades dos Vols. 1 a 9 (40%) e assina 68 dos 175 moldes. Camila abre cerca de 22 (17%). O equilíbrio prometido não existe. | J10: Passar aberturas da dupla nos Vols. 6 e 7 para Camila e para Rafael e Bia, ou trocar a promessa por "com o arquétipo que melhor ilustra cada tema". | K10: não | L10: 1 | M10: não | N10: não | R10: Leitura cruzada dos arquétipos | S10: Corrigido
A11: 10 | B11: 1 | C11: 72 | D11: OS 4 FUNDADORES (TABELA) | E11: N3 | F11: Arquétipo inconsistente, decorativo ou ausente | G11: média | H11: você acompanhará de forma equilibrada em cada fase a evolução, os tropeços financeiros, os impasses societários, os pivôs e as vitórias de **quatro arquétipos | I11: Na Fase 0 só Camila tem arco. Henrique é um nome na l. 169, Rafael e Bia aparecem num exemplo corrompido (l. 968), Lucas e Marina num desfecho de molde (l. 604). | J11: Atenuar ("os quatro ao longo do volume, um ou dois por fase") ou dar a cada um uma cena curta. Ex.: Henrique faz o Teste do Extrato com a renda irregular de quem vende para prefeituras. | K11: não | L11: 1 | M11: não | N11: não | R11: Revisor de trecho | S11: Corrigido
A12: 11 | B12: 1 | C12: 76 | D12: OS 4 FUNDADORES (TABELA) | E12: E7 | F12: Anglicismo ou mistura founder/fundador | G12: média | H12: negociam *Series A* em São Paulo | I12: Contra a regra do autor (Série A). A tabela também acumula glosas: churn (cancelamento de clientes), M&A (fusão e aquisição), Spin-off (cisão societária). | J12: "negociam a Série A em São Paulo". Deixar as glosas para o Dicionário do Vol. 10 ou para a primeira ocorrência no texto corrido. | K12: não | L12: 1 | M12: não | N12: não | R12: Revisor de trecho | S12: Corrigido
A13: 12 | B13: 1 | C13: 77 | D13: OS 4 FUNDADORES (TABELA) | E13: C3 | F13: Erro factual provável | G13: média | H13: Compra equipamento caro por impulso (*custo afundado*) | I13: Comprar por impulso não é custo afundado. A falácia é insistir num gasto ruim porque já se pagou por ele. O rótulo ensina o conceito errado. | J13: "Compra equipamento caro por impulso e depois insiste nele para não admitir a perda (falácia do custo afundado)". | K13: não | L13: 1 | M13: não | N13: não | R13: Revisor de trecho | S13: Corrigido
... A33: 32 | B33: 1 | C33: 165 | D33: FASE 0 | E33: N1 | F33: Abertura sem tensão ou em fórmula | G33: média | H33: Ao longo desta Fase 0, Camila refaz essa conta pelo método do Passo 1 (separando o piso de sobrevivência doméstica do capital da clínica), senta com o marido no Passo 4 | I33: A cena entrega o arco inteiro no primeiro parágrafo, em forma de índice de passos. A tensão do cheque especial morre antes de o corpo começar. | J33: Parar a cena no risco: "se levasse mais de quatro meses para empatar, a família entraria no cheque especial". Mostrar Camila de novo no Passo 1, no Passo 4 e no Espelho. | K33: não | L33: 1 | M33: não | N33: não | R33: Revisor de trecho | S33: Corrigido
A34: 33 | B34: 1 | C34: 167 | D34: FASE 0 | E34: E9 | F34: Erro gramatical ou frase corrompida | G34: alta | H34: encerra muito mais negócios na largada do que a escassez de boas ideias, quando na vida real a maioria morre porque o fundador quebrou emocional ou financeiramente seis meses antes | I34: O "quando" cola duas teses e desmente a primeira. A segunda ("a maioria morre porque o fundador quebrou") fica atribuída ao Sebrae, que não mede isso. | J34: Partir: "Os estudos de sobrevivência do Sebrae apontam falta de planejamento e de capital de giro. Na prática, o fundador costuma quebrar antes do negócio." Tirar o negrito da frase inteira. | K34: não | L34: 1 | M34: sim | N34: sim | O34: parcialmente certo | P34: Os estudos do Sebrae-SP atribuem o fechamento a uma soma de fatores: falta de planejamento prévio, gestão fraca, comportamento empreendedor, economia, políticas públicas e problemas pessoais. Falta de capital aparece como dificuldade. Nenhum mede que a maioria morre porque o fundador quebrou. | Q34: https://www.legisweb.com.br/noticia/?id=895 | R34: Revisor de trecho | S34: Corrigido
A35: 34 | B35: 1 | C35: 174 | D35: FASE 0 | E35: S4 | F35: Remissão quebrada ou em excesso | G35: alta | H35: leia da abertura até o fim de "Permissão para dizer 'ainda não'" e pare. | I35: Não existe seção com esse título. Virou "Quando não empreender agora" (l. 180). A l. 564 repete a remissão para o título antigo. | J35: "leia até o fim de 'Quando não empreender agora: os 10 sinais' e pare". Corrigir também a l. 564. | K35: não | L35: 1 | M35: sim | N35: não | R35: Revisor de trecho | S35: Corrigido
A36: 35 | B36: 1 | C36: 178 | D36: FASE 0 | E36: E1 | F36: Antítese "não é X, é Y" | G36: média | H36: A maioria das desistências não acontece porque a ideia era ruim. Acontece porque o empreendedor não aguentou a pressão. | I36: Antítese "não é X, é Y" em série na fase: l. 182, 272, 370, 386, 612, 694, 949, 1318 e outras. Vira cadência de molde. | J36: Manter duas que carregam tese (a permissão da l. 612, a de Ivanov na l. 949). Nas outras, afirmar direto: "A maioria desiste porque não aguenta a pressão." | K36: sim | L36: 16 | M36: não | N36: não | R36: Revisor de trecho | S36: Corrigido
A37: 36 | B37: 1 | C37: 214 | D37: FASE 0 | E37: E9 | F37: Erro gramatical ou frase corrompida | G37: alta | H37: Retorno financeiro real, quando vem, vem em sete a doze. | I37: Frase truncada, sem a unidade. O prazo também não sai de Hamilton (2000), que achou renda menor mesmo depois de dez anos. | J37: "Quando vem, o retorno financeiro real costuma chegar entre o sétimo e o décimo segundo ano." Deixar claro o que é dado de Hamilton e o que é estimativa do autor. | K37: não | L37: 1 | M37: sim | N37: sim | O37: erro confirmado | P37: Hamilton (2000) achou renda inicial menor e crescimento de renda menor que no emprego, com diferença mediana de 35% para quem está no negócio há 10 anos. O prazo de sete a doze anos não vem dele, e a frase do livro está truncada, sem 'anos'. | Q37: https://profiles.wustl.edu/en/publications/does-entrepreneurship-pay-an-empirical-analysis-of-the-returns-to/ | R37: Revisor de trecho | S37: Corrigido
A38: 37 | B38: 1 | C38: 220 | D38: FASE 0 | E38: E9 | F38: Erro gramatical ou frase corrompida | G38: alta | H38: Aos país que dizem "estabilize". | I38: "país" (nação) no lugar de "pais". Repete na l. 254: "sobre cônjuge, país ou amigos próximos". Provável correção automática de acento. | J38: "Aos pais que dizem 'estabilize'." e "sobre cônjuge, pais ou amigos próximos". | K38: sim | L38: 2 | M38: sim | N38: não | R38: Revisor de trecho | S38: Corrigido
A39: 38 | B39: 1 | C39: 231 | D39: FASE 0 | E39: C5 | F39: Contradição interna | G39: alta | H39: Os sinais 1 e 2 (reserva financeira inexistente e quadro agudo de saúde mental sem tratamento) são eliminatórios por si sós | I39: O sinal 2 é período emocionalmente turbulento. Saúde mental sem tratamento é o sinal 9. O leitor que se avalia aplica a regra eliminatória ao sinal errado. | J39: "Os sinais 1 e 9 (reserva inexistente e saúde mental sem tratamento)". Conferir se a ordem da lista mudou nesta edição. | K39: não | L39: 1 | M39: sim | N39: não | R39: Revisor de trecho | S39: Corrigido
A40: 39 | B40: 1 | C40: 242 | D40: FASE 0 | E40: C5 | F40: Contradição interna | G40: alta | H40: Se for menor que seis meses, não peça demissão agora: valide em paralelo ao emprego. | I40: Dá a entender que 6 meses bastam para sair. Fluxograma (l. 186), Passo 7, números (l. 334) e alerta (l. 623) pedem 12 para dedicação integral. Conselho financeiro arriscado. | J40: "Abaixo de 12 meses, não peça demissão. Entre 6 e 12, valide em paralelo ao emprego. Abaixo de 6, monte reserva antes de começar." | K40: não | L40: 1 | M40: não | N40: não | R40: Revisor de trecho | S40: Corrigido
A41: 40 | B41: 1 | C41: 242 | D41: FASE 0 | E41: S4 | F41: Remissão quebrada ou em excesso | G41: alta | H41: consulte um advogado trabalhista e veja os Capítulos 4 e 7 do Vol. 8) | I41: O Cap. 7 do Vol. 8 é Direito do Consumidor. Justa causa está no Cap. 6 (Trabalho) e titularidade de software no Cap. 3 (Propriedade Intelectual). | J41: "veja os Capítulos 3, 4 e 6 do Vol. 8". | K41: não | L41: 1 | M41: sim | N41: não | R41: Revisor de trecho | S41: Corrigido
A42: 41 | B42: 1 | C42: 253 | D42: FASE 0 | E42: E11 | F42: Registro inconsistente ou tom de coach | G42: média | H42: Esta conversa em casa serve para ouvir e alinhar limites reais, não para persuadir a família; o Capítulo 7 ajuda a apresentar seu plano com clareza | I42: Título de callout virou parágrafo com ponto e vírgula. E o corpo contradiz o título: chama o capítulo de persuasão de "ferramenta direta para a conversa desta etapa". | J42: Título curto: "Ouvir antes de convencer". Corpo: "O Capítulo 7 ajuda a expor o plano com clareza. Se o cônjuge recusar com bons motivos, isso entra na decisão como dado." | K42: não | L42: 1 | M42: sim | N42: não | R42: Revisor de trecho | S42: Corrigido
A43: 42 | B43: 1 | C43: 263 | D43: FASE 0 | E43: C5 | F43: Contradição interna | G43: média | H43: parcial em paralelo ao emprego (*part-time*, de 10 a 20 horas semanais, com reserva mínima de 6 meses) | I43: A l. 335 dá 15 a 25 horas para o meio período. A trava (l. 538) exige 10 horas protegidas, o teto do projeto lateral (5 a 10). | J43: Uma tabela única e repetida igual: lateral 5 a 10 h, parcial 15 a 20 h, integral 40 h ou mais. Usar no Passo 7, nos números da l. 335 e na trava. | K43: não | L43: 1 | M43: não | N43: não | R43: Revisor de trecho | S43: Corrigido
A44: 43 | B44: 1 | C44: 272 | D44: FASE 0 | E44: C1 | F44: Dado sem fonte ou precisão inventada | G44: média | H44: São observações baseadas na experiência de ter acompanhado mais de três mil fundadores no Y Combinator | I44: Os ensaios citados são de 2008 a 2010, quando a YC tinha financiado poucas centenas de empresas. Mesmo até 2014 o número parece inflado. | J44: "baseadas nas centenas de fundadores que Graham acompanhou na YC", ou tirar o número. | K44: não | L44: 1 | M44: não | N44: sim | R44: Revisor de trecho | S44: Corrigido
A45: 44 | B45: 1 | C45: 277 | D45: FASE 0 | E45: S5 | F45: Duplicação com outro capítulo ou volume | G45: média | H45: Outros três do mesmo autor (*What We Look for in Founders*, *Before the Startup* e *You Weren't Meant to Have a Boss*) entram resumidos | I45: What We Look for in Founders já está no título do terceiro ensaio (l. 310) e volta resumido na l. 326. Os "três mais três" são cinco. | J45: Tirar o ensaio do título da l. 310 (a imagem do running back pode ser citada sem virar seção) ou do resumo da l. 326. Ajustar a contagem. | K45: não | L45: 1 | M45: não | N45: não | R45: Revisor de trecho | S45: Corrigido
A46: 45 | B46: 1 | C46: 285 | D46: FASE 0 | E46: E9 | F46: Erro gramatical ou frase corrompida | G46: baixa | H46: Loops abertos são imãs mentais que roubam a sua capacidade de pensar em trabalho profundo. | I46: Grafias fora do padrão em série: imãs (ímãs), auto-exclusão, auto-crítica, subrepresentar, contra-medidas, "o por quê", "Por quê melhor?", "Independente do modelo". | J46: Corrigir: ímãs, autoexclusão, autocrítica, sub-representar, contramedidas, o porquê, "Por que melhor?", Independentemente. | K46: sim | L46: 9 | M46: não | N46: não | R46: Revisor de trecho | S46: Corrigido
A47: 46 | B47: 1 | C47: 308 | D47: FASE 0 | E47: N7 | F47: Autoridade forçada ou atribuição duvidosa | G47: baixa | H47: A formulação é uma síntese das duas teses centrais que Graham repete em ensaios e palestras, não citação literal de uma única frase. | I47: O ensaio Be Relentlessly Resourceful parece trazer a frase quase literal (destino e caminho). Se trouxer, a ressalva está errada. | J47: Conferir no ensaio. Se a frase estiver lá, citar a fonte e cortar a ressalva. | K47: não | L47: 1 | M47: não | N47: sim | R47: Revisor de trecho | S47: Corrigido
A48: 47 | B48: 1 | C48: 341 | D48: FASE 0 | E48: E3 | F48: Adjetivo inflado ou intensificador | G48: média | H48: Reconhecer os sinais cedo é crítico. | I48: Intensificador vazio em série: crítico (l. 249, 251, 341, 411, 477, 818), essencial (388, 772, 1248), profundo (411, 578, 580). Cerca de 25 na fase. | J48: Cortar o adjetivo ou dizer o porquê: "Reconheça os sinais cedo. Nesta fase o burnout se disfarça de procrastinação." | K48: sim | L48: 25 | M48: não | N48: não | R48: Revisor de trecho | S48: Corrigido
A49: 48 | B49: 1 | C49: 353 | D49: FASE 0 | E49: E9 | F49: Erro gramatical ou frase corrompida | G49: média | H49: Founder em Fase 0 vê anúncio de rodada de seed (primeira rodada de investimento externo) de par: e não vê os 18 meses de rejeição que antecederam. | I49: Dois-pontos antes de "e" quebra a frase, provável troca mecânica de travessão. "Founder" e "Social media" no mesmo trecho. | J49: "O fundador em Fase 0 vê o anúncio da rodada seed de um colega e não vê os 18 meses de recusa que vieram antes. Rede social como régua emocional nesta fase envenena devagar." | K49: não | L49: 1 | M49: sim | N49: não | R49: Revisor de trecho | S49: Corrigido
... A68: 67 | B68: 1 | C68: 566 | D68: FASE 0 | E68: C5 | F68: Contradição interna | G68: média | H68: Aplique a regra da **reserva ÷ (custo mínimo mensal × 1,5)**: o fator de 1,5 cobre o custo imprevisto que você esqueceu de listar, enquanto dividir a receita projetada por dois | I68: Segunda fórmula de runway, sem dizer a qual delas valem os limites de 6 e 12 meses. "Dividir a receita projetada por dois" não está na fórmula. | J68: Uma fórmula só (a conservadora, que o Ritual usa) e os limites calculados sobre ela. Se a receita entra, escrever: reserva ÷ (custo mínimo × 1,5 menos metade da receita mensal esperada). | K68: não | L68: 1 | M68: não | N68: não | R68: Revisor de trecho | S68: Corrigido
A69: 68 | B69: 1 | C69: 578 | D69: FASE 0 | E69: C3 | F69: Erro factual provável | G69: média | H69: Em 2013, David Vélez era sócio da Sequoia Capital. | I69: Em 2013 Vélez já fundava o Nubank, e a l. 702 o chama de ex-Sequoia no mesmo ano. O cargo de sócio também é duvidoso. | J69: "Vélez tinha passado por Morgan Stanley, General Atlantic e Sequoia, onde estudava a América Latina." Alinhar com a l. 702. | K69: não | L69: 1 | M69: não | N69: sim | O69: parcialmente certo | P69: Vélez passou por Morgan Stanley, Goldman Sachs e General Atlantic e chegou a sócio da Sequoia, que em 2011 o encarregou de abrir frente no Brasil, plano depois engavetado. Em 2013, aos 31 anos, ele cofundou o Nubank, e por isso não era mais da Sequoia naquele ano. | Q69: https://en.wikipedia.org/wiki/David_V%C3%A9lez | R69: Revisor de trecho | S69: Corrigido
A70: 69 | B70: 1 | C70: 592 | D70: FASE 0 | E70: S6 | F70: Seção desproporcional ou fora de lugar | G70: média | H70: você precisa responder por que a sua trajetória específica conversa com a dor escolhida e quanto tempo o seu caixa pessoal sustenta a travessia | I70: O caso não diz nada sobre caixa pessoal. Metade dele é PMF, rodadas e IPO, e três das quatro lições (crédito, NPS, captação) são das Fases 11 a 14. | J70: Cortar "Travessia ao PMF" e "Do PMF à escala" (ou levar à Fase 13). Na Fase 0, ficar com a complementaridade dos três e com o que cada um arriscou ao largar o emprego. | K70: não | L70: 1 | M70: não | N70: não | R70: Revisor de trecho | S70: Corrigido
A71: 70 | B71: 1 | C71: 596 | D71: FASE 0 | E71: C5 | F71: Contradição interna | G71: média | H71: 3. **NPS sustentado acima de 80** é raro e gera efeito composto | I71: A l. 586 trata o NPS de 80 como relato que varia. A lição vira fato. A lição 4 ("diluição abaixo da média") não tem fonte, e a seed de 2013 veio antes de qualquer marco. | J71: "NPS alto, perto de 80 em relatos da empresa, é raro em serviços financeiros e...". Na lição 4, cortar a diluição ou dar número com fonte. | K71: não | L71: 1 | M71: não | N71: não | R71: Revisor de trecho | S71: Corrigido
A72: 71 | B72: 1 | C72: 604 | D72: FASE 0 | E72: N3 | F72: Arquétipo inconsistente, decorativo ou ausente | G72: alta | H72: permitiu que **Lucas e Marina**, a partir de São Paulo e Florianópolis, blindassem a margem operacional e reduzissem o retrabalho da equipe. | I72: A Fase 0 é de Camila: abre com ela (1:165) e volta no Espelho (1:608) e no fechamento (1:1316). O molde dá o desfecho a Lucas e Marina, na primeira unidade do livro. | J72: Cortar o molde. O item 1 do Espelho (1:608) e o fechamento já retomam Camila. | K72: não | L72: 1 | M72: sim | N72: não | R72: Leitura cruzada dos arquétipos | S72: Corrigido
A73: 72 | B73: 1 | C73: 604 | D73: FASE 0 | E73: S7 | F73: Artefato de formatação ou texto de bastidor | G73: alta | H73: **Resultado na trincheira (PREPARAÇÃO DO EMPREENDEDOR):** A disciplina descrita em *O Espelho da Fase 0 e o Ritual de Segunda-Feira* permitiu que **Lucas e Marina** | I73: Desfecho de molde. A fase é de Camila, e Lucas e Marina não têm margem operacional nem equipe na Fase 0. Vem antes do Espelho que diz resumir. | J73: Cortar. Se quiser um resultado, usar Camila: "Com 14 meses de reserva, Camila assinou a locação sem entrar no cheque especial." | K73: não | L73: 1 | M73: sim | N73: não | R73: Revisor de trecho | S73: Corrigido
A74: 73 | B74: 1 | C74: 604 | D74: FASE 0 | E74: N3 | F74: Arquétipo inconsistente, decorativo ou ausente | G74: média | H74: permitiu que **Lucas e Marina**, a partir de São Paulo e Florianópolis, blindassem a margem operacional e reduzissem o retrabalho da equipe. | I74: Molde com a dupla numa fase aberta por Camila. Fala em margem e equipe quando a dupla nem tem empresa: a ideia nasce na Fase 1 e a folha é zero (1:6189). | J74: Cortar o molde ou fechar com Camila e a cena dela, o orçamento da casa separado do Pix da clínica. | K74: não | L74: 1 | M74: sim | N74: não | R74: Leitura cruzada dos arquétipos | S74: Corrigido
A75: 74 | B75: 1 | C75: 608 | D75: FASE 0 | E75: C5 | F75: Contradição interna | G75: alta | H75: (Quando a Dra. Camila fez essa conta em Belo Horizonte antes de ampliar a clínica, somou 9 pontos nas três perguntas e adiou a reforma em três meses até recompor a reserva.), sua família dorme em paz | I75: Na Fase 0 Camila ainda vai abrir a clínica e só assina o ponto com 14 meses de reserva (1:165, 1:1320). 'Ampliar' e 'reforma' contradizem isso. O parêntese ainda parte a pergunta ao meio. | J75: Tirar o parêntese da pergunta e pôr no fim do item: 'Quando Camila fez essa conta, somou 9 pontos e adiou a assinatura do ponto comercial até juntar 14 meses de reserva.' | K75: não | L75: 1 | M75: sim | N75: não | R75: Leitura cruzada dos arquétipos | S75: Corrigido
A76: 75 | B76: 1 | C76: 608 | D76: FASE 0 | E76: E9 | F76: Erro gramatical ou frase corrompida | G76: alta | H76: somou 9 pontos nas três perguntas e adiou a reforma em três meses até recompor a reserva.), sua família dorme em paz ou você precisará tomar decisões desesperadas no mês 5? | I76: Parêntese enxertado no meio da pergunta. Depois de ".)" a frase segue com vírgula e perde o sujeito. | J76: "...sem vender patrimônio essencial? Sua família dorme em paz ou você vai decidir no desespero no mês 5?" O exemplo de Camila vai para uma frase própria depois da pergunta. | K76: não | L76: 1 | M76: sim | N76: não | R76: Revisor de trecho | S76: Corrigido
A77: 76 | B77: 1 | C77: 608 | D77: FASE 0 | E77: C5 | F77: Contradição interna | G77: alta | H77: Quando a Dra. Camila fez essa conta em Belo Horizonte antes de ampliar a clínica | I77: Na abertura Camila acabou de sair do emprego e nem assinou o ponto. Aqui amplia clínica e adia reforma. E "9 pontos nas três perguntas" não tem escala: só a 1ª é pontuada. | J77: Retomar a abertura: "No domingo da cena, Camila tirou 2 no Teste do Extrato. Só assinou a locação quando a nota chegou a 5, com 14 meses de reserva." Dar nota de 1 a 5 às três perguntas. | K77: não | L77: 1 | M77: não | N77: não | R77: Revisor de trecho | S77: Corrigido
A78: 77 | B78: 1 | C78: 614 | D78: FASE 0 | E78: N5 | F78: Ritual de Segunda-Feira vago ou desconectado | G78: média | H78: faça o check-in de quatro notas (sono, energia, humor e relações) e conduza a conversa de alinhamento com seu cônjuge ou família usando os quatro tópicos do Passo 4 desta fase. | I78: As quatro notas não são as do protocolo (energia, clareza, relações, sentido, l. 361). E repetir toda sexta a conversa formal do Passo 4 (1 a 2 horas) não cabe em 15 minutos. | J78: Segunda: runway conservador, horas e ponto de parada (15 min). Sexta: as quatro notas do protocolo (10 min). Conversa do Passo 4: uma vez por mês ou quando o runway cair abaixo do limite. | K78: não | L78: 1 | M78: não | N78: não | R78: Revisor de trecho | S78: Corrigido
A79: 78 | B79: 1 | C79: 620 | D79: FASE 0 | E79: S4 | F79: Remissão quebrada ou em excesso | G79: média | H79: Exercícios de autoconhecimento concluídos (FMF Check, teste de personalidade, análise de forças). | I79: Nenhum desses exercícios está na Fase 0. O FMF Check só existe nos Vols. 2 a 4 e o FMF é definido na Fase 1. O "fit diferencial" da trava (l. 540) fica sem definição. | J79: Trocar pelos exercícios que a fase entrega (Teste do Banho, cinco obstáculos, matriz de autoavaliação) e remeter o FMF à Fase 1. | K79: não | L79: 1 | M79: não | N79: não | R79: Revisor de trecho | S79: Corrigido
A80: 79 | B80: 1 | C80: 630 | D80: FASE 0 | E80: N9 | F80: Título que promete o que o corpo não entrega | G80: média | H80: exemplo aplicado aos arquétipos da coleção e armadilhas para execução imediata nesta **Fase 0**. | I80: Só o Hedgehog tem exemplo de arquétipo, e incoerente. Effectuation, Primeiros Princípios, Cynefin, Vieses e Pre-mortem usam Nubank, SpaceX, SDRs e expansão ao México. | J80: Cortar a promessa ou dar a cada ferramenta um parágrafo com um arquétipo diante da decisão de largada (ex.: Henrique no Cynefin, Rafael e Bia no pre-mortem). | K80: não | L80: 1 | M80: não | N80: não | R80: Revisor de trecho | S80: Corrigido
A81: 80 | B81: 1 | C81: 650 | D81: FASE 0 | E81: E9 | F81: Erro gramatical ou frase corrompida | G81: média | H81: Passo 1: Círculo 1 é franqueza direta. | I81: Frase sem sentido, provável troca automática de "brutal" por "direta". O par redundante volta na Nota (l. 30) e no Passo 2 (l. 247). | J81: "Passo 1: no Círculo 1, seja honesto até doer." Na l. 30 e na l. 247, basta "franqueza". | K81: sim | L81: 3 | M81: sim | N81: não | R81: Revisor de trecho | S81: Corrigido
... A122: 121 | B122: 1 | C122: 1427 | D122: FASE 1 | E122: E9 | F122: Erro gramatical ou frase corrompida | G122: alta | H122: Dropbox pareceu assim antes de existir. Airbnb pareceu pior ainda. O Airbnb soava ainda pior em 2007: | I122: Emenda deixou duas versões da mesma frase em sequência. | J122: 'Dropbox pareceu assim antes de existir. O Airbnb soava ainda pior em 2007: dois designers, Brian Chesky e Joe Gebbia, alugando três colchões de ar...' | K122: não | L122: 1 | M122: sim | N122: não | R122: Revisor de trecho | S122: Corrigido
A123: 122 | B123: 1 | C123: 1441 | D123: FASE 1 | E123: C3 | F123: Erro factual provável | G123: média | H123: A Kovi pegou o modelo americano de car sharing por aplicativo (Turo) e estreitou a wedge para o ICP específico que mais sofria com falta de carro | I123: Turo é aluguel entre pessoas. A Kovi aluga frota própria a motoristas de aplicativo, modelo mais perto de HyreCar ou Splend. A filiação ao Turo parece errada. Wedge e ICP sem tradução. | J123: Verificar a origem do modelo. Se mantido: 'A Kovi adaptou o aluguel semanal de carros para motoristas de aplicativo e começou pelo grupo que mais sofria sem carro próprio.' | K123: não | L123: 1 | M123: não | N123: sim | O123: erro confirmado | P123: A Kovi não faz car sharing entre pessoas, como a Turo. Ela aluga carros das montadoras em leasing e subloca a motoristas de aplicativo, modelo mais perto de HyreCar ou Splend. Em janeiro de 2025 foi comprada pela Moove, investida do Uber. | Q123: https://braziljournal.com/moove-uma-investida-do-uber-compra-a-kovi/ | R123: Revisor de trecho | S123: Corrigido
A124: 123 | B124: 1 | C124: 1447 | D124: FASE 1 | E124: E9 | F124: Erro gramatical ou frase corrompida | G124: alta | H124: abriu espaço para Zoom, Notion e Figma. Slack, Zoom, Notion, Figma. Marketplaces de serviços (2013-2018) abriram 99, iFood, Rappi. | I124: Sobra de versão anterior: a lista solta repete a frase de antes. A 99 aparece em duas ondas e o iFood (2011) cai fora da janela 2013 a 2018. 'Este capítulo' numa fase. | J124: Cortar 'Slack, Zoom, Notion, Figma.' e ajustar: 'Os marketplaces de serviços (2011 a 2018) abriram iFood, Rappi e GetNinjas.' Trocar 'este capítulo' por 'esta fase'. | K124: não | L124: 1 | M124: sim | N124: não | R124: Revisor de trecho | S124: Corrigido
A125: 124 | B125: 1 | C125: 1449 | D125: FASE 1 | E125: C3 | F125: Erro factual provável | G125: alta | H125: tornou-se um dos primeiros negócios digitais relevantes do país (alcançando grande liquidez em 2009), e foi vendido para a Naspers anos depois | I125: A venda do controle do Buscapé à Naspers foi o próprio evento de liquidez de 2009 (cerca de US$ 342 milhões por 91%). 'Anos depois' está errado. O ano de fundação também pede checagem. | J125: '...tornou-se um dos primeiros negócios digitais relevantes do país e vendeu o controle à Naspers em 2009, por cerca de US$ 342 milhões.' Conferir se a fundação foi em 1998 ou 1999. | K125: não | L125: 1 | M125: não | N125: sim | O125: erro confirmado | P125: A venda à Naspers foi o próprio evento de liquidez de 2009. Em 29/9/2009 a Naspers anunciou a compra de 91% do BuscaPé.com por US$ 342 milhões. Não houve venda 'anos depois'. | Q125: https://www.lse.co.uk/rns/NPSN/acquisition-of-brazilian-e-commerce-operator-busca-dr2bzrbas19w1r9.html | R125: Revisor de trecho | S125: Corrigido
A126: 125 | B126: 1 | C126: 1451 | D126: FASE 1 | E126: E9 | F126: Erro gramatical ou frase corrompida | G126: baixa | H126: *qual vertical é muito sensível à capacidade que a tecnologia nova oferece, mas ainda não foi adequadamente endereçado?* | I126: Concordância: 'vertical' é feminino no próprio parágrafo ('essas verticais'). 'Endereçado' é decalque de addressed. | J126: 'Qual vertical depende muito do que a tecnologia nova oferece, mas ainda é mal atendida?' | K126: não | L126: 1 | M126: não | N126: não | R126: Revisor de trecho | S126: Corrigido
A127: 126 | B127: 1 | C127: 1455 | D127: FASE 1 | E127: S4 | F127: Remissão quebrada ou em excesso | G127: alta | H127: deixando o Wardley Map completo para a Fase 6, no Vol. 2 | I127: Não há Wardley Map na Fase 6. O framework completo está nesta mesma Fase 1 (linha 1822) e o canvas está no Vol. 9 (Fase 19). A Fase 6 só remete ao Vol. 9. | J127: Trocar por 'o Wardley Mapping completo está no manual de frameworks ao fim desta fase' ou apontar para o canvas do Vol. 9 e cortar daqui o framework duplicado. | K127: não | L127: 1 | M127: sim | N127: não | R127: Revisor de trecho | S127: Corrigido
A128: 127 | B128: 1 | C128: 1510 | D128: FASE 1 | E128: S7 | F128: Artefato de formatação ou texto de bastidor | G128: média | H128: title "Quatro filtros aplicados às candidatas de Lucas e Marina" | I128: O gráfico promete as candidatas da dupla, mas plota Nubank, iFood, "Sitcom idea" e "Sua ideia ideal". Nenhuma ideia do caderno aparece. | J128: Plotar as candidatas do caderno (pets, contas de bar, chefs, conciliação) ou trocar o título por "Quatro filtros aplicados a candidatas típicas". | K128: não | L128: 1 | M128: não | N128: não | R128: Leitura cruzada dos arquétipos | S128: Corrigido
A129: 128 | B129: 1 | C129: 1510 | D129: FASE 1 | E129: N9 | F129: Título que promete o que o corpo não entrega | G129: média | H129: Quatro filtros aplicados às candidatas de Lucas e Marina | I129: O gráfico promete as candidatas da dupla, mas plota Nubank, iFood, 'Sitcom idea' e 'Sua ideia ideal'. Empresas que já venceram não são candidatas a filtrar. | J129: Plotar as quatro ideias da dupla (rede de tutores, divisor de contas, chefs em casa e conciliação para distribuidoras) ou trocar o título por 'Onde ficam as candidatas depois dos quatro filtros'. | K129: não | L129: 1 | M129: sim | N129: não | R129: Revisor de trecho | S129: Corrigido
A130: 129 | B130: 1 | C130: 1528 | D130: FASE 1 | E130: E9 | F130: Erro gramatical ou frase corrompida | G130: alta | H130: As defesas que sobrevivem são dados proprietários do setor, integração profunda no fluxo de trabalho do cliente, conformidade regulatória local e canal de distribuição próprio com distribuição superior?* | I130: Inserção quebrou o itálico (asteriscos aninhados), virou afirmação em pergunta e criou 'canal próprio com distribuição superior'. A lista ainda se repete na lista de moats logo depois. | J130: Fechar a pergunta após 'engolir sua oferta?'. Em frase própria: 'Em IA, resistem dados do setor, integração no fluxo do cliente, conformidade regulatória local e canal próprio.' Fundir com a lista de moats. | K130: não | L130: 1 | M130: sim | N130: não | R130: Revisor de trecho | S130: Corrigido
A131: 130 | B131: 1 | C131: 1530 | D131: FASE 1 | E131: E1 | F131: Antítese "não é X, é Y" | G131: média | H131: Se você não consegue, não é porque é complicado. É porque você não pensou ainda. | I131: Antítese em série na fase (cerca de 12): 'não por falha de execução, mas...' (1338), 'meio, não fim' (1453), 'destino, não ponto de partida' (1585), 'manter as opções vivas, não...' (2061). | J131: 'Se você não consegue escrever, ainda não pensou o modelo.' Manter no máximo uma antítese por seção. | K131: sim | L131: 12 | M131: não | N131: não | R131: Revisor de trecho | S131: Corrigido
A132: 131 | B132: 1 | C132: 1532 | D132: FASE 1 | E132: C5 | F132: Contradição interna | G132: alta | H132: o app social de pets caiu no Filtro 4 (sem pagador claro), a gamificação de academias caiu no Filtro 1 (zero vivência no setor) e o roteiro de viagens por IA caiu no Filtro 3 | I132: Na abertura (1:1328) as ideias são rede social de pets, divisor de contas de bar com IA e app de chefs. Aqui duas mudaram. A tese passa de distribuidoras médias a pequenas. | J132: Escrever "o app de pets caiu no Filtro 4, o divisor de contas com IA caiu no Filtro 3 e o app de chefs caiu no Filtro 1" e manter "distribuidoras médias", como na abertura e na bíblia. | K132: não | L132: 1 | M132: sim | N132: não | R132: Leitura cruzada dos arquétipos | S132: Corrigido
A133: 132 | B133: 1 | C133: 1532 | D133: FASE 1 | E133: C5 | F133: Contradição interna | G133: alta | H133: o app social de pets caiu no Filtro 4 (sem pagador claro), a gamificação de academias caiu no Filtro 1 (zero vivência no setor) e o roteiro de viagens por IA caiu no Filtro 3 | I133: A abertura (linha 1328) lista outras ideias: rede para tutores de animais, divisor de contas de bar com IA e chefs em casa. Gamificação de academias e roteiro de viagens nunca estiveram no caderno. | J133: Usar as três ideias da abertura: a rede de tutores cai no Filtro 4 (sem pagador claro), o divisor de contas no Filtro 3 (qualquer modelo gratuito resolve) e o app de chefs no Filtro 1 (zero vivência no setor). | K133: não | L133: 1 | M133: sim | N133: não | R133: Revisor de trecho | S133: Corrigido
A134: 133 | B134: 1 | C134: 1532 | D134: FASE 1 | E134: C5 | F134: Contradição interna | G134: média | H134: enquanto a automação de conciliação e cobrança para pequenas distribuidoras passou nos quatro critérios | I134: A abertura fala em distribuidoras médias e a bíblia em distribuidores e empresas médias. Aqui o alvo vira pequenas distribuidoras. | J134: Trocar por 'distribuidoras médias', o recorte da linha 1328 e do arco dos Vols. 5 a 9. | K134: não | L134: 1 | M134: não | N134: não | R134: Revisor de trecho | S134: Corrigido
A135: 134 | B135: 1 | C135: 1564 | D135: FASE 1 | E135: E7 | F135: Anglicismo ou mistura founder/fundador | G135: média | H135: Segunda, Expertise Domain Inventory, duas a três horas. | I135: A semana mistura nomes em inglês (Expertise Domain Inventory, Friction Journal Review, Filter & Choose) com nomes em português (Diário de Fricções, Transferência entre Setores) para as mesmas etapas. | J135: Padronizar em português no diagrama e no texto: Inventário de Domínio, Revisão do Diário de Fricções, Transferência e Ondas, Conversas de Calibragem, Filtrar e Escolher. | K135: sim | L135: 6 | M135: não | N135: não | R135: Revisor de trecho | S135: Corrigido
A136: 135 | B136: 1 | C136: 1574 | D136: FASE 1 | E136: S4 | F136: Remissão quebrada ou em excesso | G136: média | H136: marque uma segunda conversa com o seu parceiro de debate | I136: O 'parceiro de debate' não aparece em nenhum outro ponto do volume e não houve primeira conversa. Resto de versão anterior. | J136: '...marque uma conversa de sessenta minutos com um sócio, mentor ou colega de confiança e leve as três finalistas.' | K136: não | L136: 1 | M136: sim | N136: não | R136: Revisor de trecho | S136: Corrigido
A137: 136 | B137: 1 | C137: 1576 | D137: FASE 1 | E137: S5 | F137: Duplicação com outro capítulo ou volume | G137: média | H137: ### Nove armadilhas clássicas na geração e escolha de ideias | I137: O Capítulo 3 reimprime as mesmas armadilhas (linhas 4434 a 4456, com uma a mais) e também a inversão de Munger (4426), que a Fase 1 já detalha no manual de frameworks. | J137: Deixar a lista completa só aqui e, no Capítulo 3, uma frase com remissão. Ou o inverso, mantendo o callout da linha 1578 apontando para o lugar certo. | K137: não | L137: 1 | M137: sim | N137: não | R137: Revisor de trecho | S137: Corrigido
... A165: 164 | B165: 1 | C165: 2088 | D165: FASE 2 | E165: S3 | F165: Lista onde caberia prosa, excesso de negrito | G165: média | H165: > [!tip] Quadros visuais como complemento opcional aos 7 blocos da DII | I165: A seção central abre com dois callouts seguidos, logo depois de um terceiro (2083). Quatro canvases alternativos aparecem antes do primeiro bloco da DII. | J165: Mover os callouts para depois do template e reduzir a um: 'Se preferir visual, o Lean Canvas (Fase 1) e o Business Model Canvas (fim desta fase) complementam a DII.' | K165: não | L165: 1 | M165: não | N165: não | R165: Revisor de trecho | S165: Corrigido
A166: 165 | B166: 1 | C166: 2092 | D166: FASE 2 | E166: C3 | F166: Erro factual provável | G166: baixa | H166: enquadra a oportunidade de produto em nove blocos: Users & Customers, Problems, Solutions Today, Solution Ideas, How Will Users Use Solution, Adoption Strategy, User Metrics, Business Challenges e Budget | I166: O Opportunity Canvas de Jeff Patton costuma ter dez áreas, com Business Benefits and Metrics, que falta aqui. Os nomes ficam todos em inglês. | J166: Conferir a contagem no original e traduzir: usuários e clientes, problemas, soluções atuais, ideias de solução, uso previsto, estratégia de adoção, métricas de usuário, desafios e métricas de negócio, orçamento. | K166: não | L166: 1 | M166: não | N166: sim | O166: erro confirmado | P166: No site de Jeff Patton o Opportunity Canvas tem dez seções: ideia de solução, problemas, clientes e usuários, soluções atuais, desafios de negócio, o que os usuários farão para obter valor, métricas, estratégia de adoção, impacto no negócio e orçamento. | Q166: https://jpattonassociates.com/opportunity-canvas | R166: Revisor de trecho | S166: Corrigido
A167: 166 | B167: 1 | C167: 2132 | D167: FASE 2 | E167: E1 | F167: Antítese "não é X, é Y" | G167: média | H167: e contra o que você compete (não outro software, mas o custo do analista interno; não a planilha, mas a hora do gestor) | I167: Ponto e vírgula monta antítese dupla. Padrão recorrente na fase, cerca de 26 pontos e vírgulas na prosa, vários no lugar do antigo travessão. | J167: '...e contra o que você compete de fato: o custo do analista interno ou a hora do gestor gasta na planilha.' | K167: sim | L167: 26 | M167: sim | N167: não | R167: Revisor de trecho | S167: Corrigido
A168: 167 | B168: 1 | C168: 2134 | D168: FASE 2 | E168: C5 | F168: Contradição interna | G168: média | H168: "Donos de padaria com 2 a 5 lojas pagam R$ 290 por mês para evitar duas rupturas semanais de farinha" | I168: No caso PadariaPro a mesma hipótese fala em 'duas rupturas mensais' (linha 2214) e o ROI em 'duas a três rupturas por mês' (2212). 'Semanais' quadruplica a dor. | J168: Usar 'duas rupturas mensais de farinha' nas três passagens. | K168: não | L168: 1 | M168: não | N168: não | R168: Revisor de trecho | S168: Corrigido
A169: 168 | B169: 1 | C169: 2138 | D169: FASE 2 | E169: C6 | F169: Lacuna relevante para o fundador brasileiro | G169: média | H169: Escreva dez a vinte e cinco itens organizados em seis categorias: **Demanda** | I169: As seis categorias de incerteza não incluem regulação. Para o fundador brasileiro em saúde, finanças ou governo (Camila, Henrique) a licença, a norma ou o edital costuma ser o risco que mata. | J169: Acrescentar a categoria **Regulação** (precisa de licença, registro ou norma setorial? quem fiscaliza? o comprador público pode contratar sem licitação?) e levá-la ao template da linha 2772. | K169: não | L169: 1 | M169: não | N169: não | R169: Revisor de trecho | S169: Corrigido
A170: 169 | B170: 1 | C170: 2143 | D170: FASE 2 | E170: S4 | F170: Remissão quebrada ou em excesso | G170: alta | H170: já os Capítulos 3 e 9 apoiam o raciocínio em primeiros princípios e a defesa oral de 90 segundos | I170: O Capítulo 3 trata de armadilhas mentais e vieses e não tem primeiros princípios. O framework está na Fase 0 (linha 710), que por sua vez também manda ao Cap. 3. Remissão herdada da numeração antiga. | J170: '...já o framework de Primeiros Princípios da Fase 0 ajuda a decompor o problema e o Capítulo 9 prepara a defesa oral de 90 segundos.' Corrigir também a remissão da linha 710. | K170: não | L170: 1 | M170: sim | N170: não | R170: Revisor de trecho | S170: Corrigido
A171: 170 | B171: 1 | C171: 2177 | D171: FASE 2 | E171: C5 | F171: Contradição interna | G171: baixa | H171: Expliquei a ideia para três a cinco pessoas fora do círculo imediato. Pelo menos quatro de cinco repetiram com precisão | I171: Com três ouvintes o critério 'quatro de cinco' não se aplica. Mínimo e proporção precisam bater. | J171: 'Expliquei a ideia para cinco pessoas fora do círculo imediato e pelo menos quatro repetiram com precisão...' | K171: não | L171: 1 | M171: não | N171: não | R171: Revisor de trecho | S171: Corrigido
A172: 171 | B172: 1 | C172: 2187 | D172: FASE 2 | E172: S6 | F172: Seção desproporcional ou fora de lugar | G172: baixa | H172: **Primeiros passos práticos.** | I172: Os primeiros passos vêm depois da catraca de saída e repetem os sete passos já dados. A ordem confunde: o leitor sai da fase e volta ao começo. | J172: Cortar o bloco ou movê-lo para antes do sétimo passo, como resumo de uma linha. | K172: não | L172: 1 | M172: não | N172: não | R172: Revisor de trecho | S172: Corrigido
A173: 172 | B173: 1 | C173: 2194 | D173: FASE 2 | E173: N2 | F173: Costura ruim entre cena e conteúdo | G173: média | H173: ### Uma DII preenchida na prática: do rascunho vago ao caso PadariaPro | I173: A abertura promete que Henrique reescreve a DII, mas a fase nunca a mostra. O exemplo é a fictícia PadariaPro e o título promete um 'rascunho vago' que não aparece. | J173: Mostrar a DII v0 de Henrique (o jargão da abertura) ao lado da v1 (diretor industrial de usina de etanol de milho, parada de caldeira). A PadariaPro fica como segundo caso. | K173: não | L173: 1 | M173: sim | N173: não | R173: Revisor de trecho | S173: Corrigido
A174: 173 | B174: 1 | C174: 2202 | D174: FASE 2 | E174: C5 | F174: Contradição interna | G174: baixa | H174: abaixo de quarenta anos, familiarizados com apps no celular | I174: O anti-perfil exclui donos acima de cinquenta anos. A faixa de 40 a 50 fica sem lugar, justo no exemplo que ensina recorte preciso. | J174: Usar o mesmo corte nos dois lados, por exemplo 'até 45 anos' no perfil e 'acima de 45 sem familiaridade com apps' no anti-perfil. | K174: não | L174: 1 | M174: não | N174: não | R174: Revisor de trecho | S174: Corrigido
A175: 174 | B175: 1 | C175: 2214 | D175: FASE 2 | E175: C3 | F175: Erro factual provável | G175: baixa | H175: o Pix e o Open Finance, consolidados no país desde 2021 | I175: O Pix começou em novembro de 2020 e o Open Finance entrou em fases até 2022 e segue em expansão. O bloco traz uma hipótese, não as três a cinco pedidas na linha 2134. | J175: 'o Pix, em operação desde 2020, e o Open Finance, em implantação desde 2021...' e acrescentar duas hipóteses testáveis no formato [Persona] [verbo] [objeto]. | K175: não | L175: 1 | M175: não | N175: sim | R175: Revisor de trecho | S175: Corrigido
A176: 175 | B176: 1 | C176: 2236 | D176: FASE 2 | E176: C5 | F176: Contradição interna | G176: alta | H176: Não compete com cardápio impresso; compete com o custo do motoboy próprio e com pedidos perdidos no pico. | I176: Contradiz a linha 1441 (o iFood nasceu digitalizando o guia impresso Disk Cook) e a 2234 (o restaurante tinha motoboy e a logística do iFood veio depois). Em 2011 o iFood não trocava o motoboy. | J176: 'Compete com o cardápio impresso e com o telefone ocupado: o custo que ele ataca é o pedido perdido no pico. A entrega continuava com o motoboy do restaurante.' | K176: não | L176: 1 | M176: não | N176: não | R176: Revisor de trecho | S176: Corrigido
A177: 176 | B177: 1 | C177: 2240 | D177: FASE 2 | E177: N9 | F177: Título que promete o que o corpo não entrega | G177: média | H177: ### Onde o papel mente: esconder incertezas por orgulho e confundir solução com problema | I177: O título promete a armadilha de esconder incertezas por orgulho, que a seção não trata. Duas armadilhas vêm em negrito e duas sem. | J177: Acrescentar a armadilha prometida: 'Esconder incertezas por orgulho. Uma lista com três itens e categorias vazias indica que você ainda não olhou para o risco.' Padronizar o negrito dos rótulos. | K177: não | L177: 1 | M177: não | N177: não | R177: Revisor de trecho | S177: Corrigido
A178: 177 | B178: 1 | C178: 2258 | D178: FASE 2 | E178: S7 | F178: Artefato de formatação ou texto de bastidor | G178: alta | H178: Ao incorporar as balizas de *O Espelho da Fase 2 e o Ritual de Segunda-Feira* na operação em Curitiba, **Henrique** substituiu decisões reativas por indicadores auditáveis de execução semanal. | I178: Variante do molde 'Resultado na trincheira'. Henrique é o arquétipo certo, mas não tem operação: está escrevendo a DII. 'Indicadores auditáveis de execução semanal' não têm relação com a fase. | J178: Trocar por uma linha que retome a cena: 'Henrique passou a DII pelos três cortes abaixo e viu que o bloco Para quem ainda dizia indústria, e não diretor industrial de usina de etanol de milho.' | K178: não | L178: 1 | M178: sim | N178: não | R178: Revisor de trecho | S178: Corrigido
... A226: 225 | B226: 1 | C226: 3239 | D226: FASE 3 | E226: E9 | F226: Erro gramatical ou frase corrompida | G226: alta | H226: Resposta errada se causa é produto, Issue tree não MECE: branches se sobrepõem, análise fragmentada, Analisar tudo: sem priorização, recurso se dilui, Síntese fraca: | I226: A lista de armadilhas foi colada numa frase só, com vírgulas e rótulos em maiúscula no meio. Lê como texto corrompido. | J226: Voltar a lista ou separar em frases: "Pular para a solução sem definir o problema. Montar árvore de questões que não é MECE. Analisar tudo sem priorizar. Sintetizar mal, com 50 dados e nenhum insight. Deixar a conclusão para o fim." | K226: não | L226: 1 | M226: sim | N226: não | R226: Revisor de trecho | S226: Corrigido
A227: 226 | B227: 1 | C227: 3264 | D227: FASE 3 | E227: C3 | F227: Erro factual provável | G227: média | H227: Causa-raiz: **sujeira no ar do chão de fábrica**. Solução: filtro. | I227: No exemplo clássico de Taiichi Ohno, a causa é limalha que entrou na bomba de lubrificação porque faltava um filtro na bomba. "Sujeira no ar" distorce o caso. | J227: "Por quê? Não havia filtro na bomba e entrou limalha de metal. Causa-raiz: falta de filtro. Solução: instalar o filtro." Conferir em Ohno, O Sistema Toyota de Produção. | K227: não | L227: 1 | M227: não | N227: sim | O227: erro confirmado | P227: No exemplo de Ohno, o eixo da bomba se desgastou porque não havia filtro (strainer) na bomba e entrou limalha de metal. A causa-raiz é a falta do filtro na bomba, não sujeira no ar da fábrica. A solução é instalar o filtro. | Q227: https://www.leanblog.org/2026/04/ohno-5-whys-actually-seven/ | R227: Revisor de trecho | S227: Corrigido
A228: 227 | B228: 1 | C228: 3344 | D228: FASE 3 | E228: S4 | F228: Remissão quebrada ou em excesso | G228: alta | H228: ### CANVASES VISUAIS DESTA FASE 4 (FOCO NA ÁRVORE DA TEORIA E PREMISSAS) | I228: Estamos na Fase 3, mas o título e o callout seguinte (l. 3346) dizem "Fase 4" três vezes. Numeração antiga, deslocada em um, como em l. 895 (Fase 0) e 2617 (Fase 2). | J228: "CANVASES VISUAIS DESTA FASE (ÁRVORE DA TEORIA E PREMISSAS)" e "Escopo desta Fase 3: Na Fase 3, o Theory Map...". | K228: não | L228: 1 | M228: sim | N228: não | R228: Revisor de trecho | S228: Corrigido
A229: 228 | B229: 1 | C229: 3352 | D229: FASE 3 | E229: E9 | F229: Erro gramatical ou frase corrompida | G229: média | H229: com uma grade própria de pontuação de Evidência e Impacto adaptada para este livro: (1) o Directed Acyclic Graph (DAG) causal de Judea Pearl | I229: Emenda: os dois-pontos fazem a grade própria parecer composta de DAG, teoria da mudança e Blank e Dorf. E a grade do canvas é de Dúvida e Importância, não de Evidência e Impacto. | J229: "A Theory Map junta três tradições: (1) o DAG de Judea Pearl... (2) a teoria da mudança... (3) a prática de Blank e Dorf... A elas o livro soma uma grade própria de Dúvida e Importância." | K229: não | L229: 1 | M229: sim | N229: não | R229: Revisor de trecho | S229: Corrigido
A230: 229 | B230: 1 | C230: 3360 | D230: FASE 3 | E230: S7 | F230: Artefato de formatação ou texto de bastidor | G230: alta | H230: **Grau de Dúvida sobre a Premissa (D1 a D5)**: quanta incerteza ainda existe sobre este nó? | I230: Define D (Dúvida), mas a fórmula P = K × I, o Mermaid, a tabela da Creditas e o passo 4 usam K, nunca definido. O passo 5 volta a D e troca Importância por Impacto. Renomeação pela metade. | J230: Usar uma letra só. Se for D: "P = D × I", trocar K por D no Mermaid, na tabela e no passo 4, e "K5 (pure assumption)" por "D5 (suposição pura)". | K230: não | L230: 1 | M230: sim | N230: não | R230: Revisor de trecho | S230: Corrigido
A231: 230 | B231: 1 | C231: 3403 | D231: FASE 3 | E231: C5 | F231: Contradição interna | G231: alta | H231: (ou pontuação combinada I × D ≥ 20, como os nós regulatório e de aquisição no exercício retrospectivo da Creditas) | I231: Na tabela da Creditas o nó de aquisição (D) tem P = 12, não 20. Os nós com 20 são B, C e F. E a lista de apostas (l. 3420) inclui E, com P = 15, abaixo da "régua única". | J231: "como os nós regulatório (B) e de aceitação da garantia (C)". Tirar E da lista de apostas bet-the-company ou explicar a exceção. Alinhar com o limiar "P > 12" do passo 4. | K231: não | L231: 1 | M231: não | N231: não | R231: Revisor de trecho | S231: Corrigido
A232: 231 | B232: 1 | C232: 3418 | D232: FASE 3 | E232: S7 | F232: Artefato de formatação ou texto de bastidor | G232: média | H232: | G | Empresa sustentável |: |: |: | Resultado final | | I232: As células vazias receberam ":" no lugar do travessão. Parece erro de digitação. | J232: Deixar as células vazias ou usar "n/a": "| G | Empresa sustentável | | | | Resultado final |". | K232: não | L232: 1 | M232: sim | N232: não | R232: Revisor de trecho | S232: Corrigido
A233: 232 | B233: 1 | C233: 3518 | D233: FASE 3 | E233: C5 | F233: Contradição interna | G233: média | H233: A "operador sente dor" P(A)=70%, A→B "operador reporta dor para dono" P(A→B)=50%, B "dono prioriza resolver" P(B|A)=50% | I233: Lista quatro probabilidades e multiplica três, repete a conta na frase seguinte e chama 15% a 50% de "sweet spot". O Espelho (l. 2997) fala em 15% a 45%. Template pede 6 a 10 atributos, a fase 8 a 15. | J233: Usar só condicionais: P(A)=70%, P(B|A)=50%, P(C|B)=60%, total 21%, numa frase. Uma faixa única em toda a fase e "faixa de trabalho" no lugar de "sweet spot". Em l. 3516, "de 8 a 15 atributos". | K233: não | L233: 1 | M233: não | N233: não | R233: Revisor de trecho | S233: Corrigido
A234: 233 | B234: 1 | C234: 3648 | D234: FASE 3 | E234: E1 | F234: Antítese "não é X, é Y" | G234: média | H234: Fundador que pinta toda a árvore de "alta confiança" não está mapeando teoria, está fazendo declaração de fé. | I234: O fechamento empilha antíteses ("Não como plano estático, mas...", "não está mapeando, está fazendo", "Não dar respostas, mas localizar perguntas"). Padrão também em l. 2844, 2883 e 3387. | J234: Deixar uma e afirmar o resto: "Quem pinta a árvore toda de alta confiança está declarando fé. A Fase 3 serve para achar as perguntas que valem o trabalho de responder." | K234: sim | L234: 10 | M234: não | N234: não | R234: Revisor de trecho | S234: Corrigido
A235: 234 | B235: 1 | C235: 3656 | D235: FASE 3 | E235: C5 | F235: Contradição interna | G235: alta | H235: A segunda metade deste volume reúne os **13 capítulos** de fundação pessoal, cognição, decisão, comunicação, produtividade com IA e ecossistema. | I235: O Vol. 1 tem 12 capítulos, como dizem o Sumário e a página Sobre este livro (l. 54). Número anterior à fusão. | J235: Trocar por "12 capítulos". | K235: não | L235: 1 | M235: sim | N235: não | R235: Revisor de trecho | S235: Corrigido
A236: 235 | B236: 1 | C236: 3672 | D236: CAPÍTULO 1 | E236: N4 | F236: Espelho ausente ou genérico | G236: alta | H236: calcular no Espelho e no Ritual os oito meses extras de fôlego pessoal que essa disciplina garante | I236: A abertura promete usar os números de Lucas (R$ 22 mil para R$ 11 mil) no corpo, no Espelho e no Ritual. Nada disso aparece. O Espelho tem só o molde e perguntas genéricas. | J236: No Espelho: "Lucas cortou o custo fixo de R$ 22 mil para R$ 11 mil e ganhou oito meses. Quanto o seu corte compra?". No corpo, usar os números dele no cálculo do burn familiar. | K236: não | L236: 1 | M236: não | N236: não | R236: Leitura cruzada dos arquétipos | S236: Corrigido
A237: 236 | B237: 1 | C237: 3672 | D237: CAPÍTULO 1 | E237: N2 | F237: Costura ruim entre cena e conteúdo | G237: alta | H237: Ao longo deste Capítulo 1, usamos os números reais de Lucas para demonstrar o cálculo do *burn rate* familiar (cortando o custo fixo doméstico de R$ 22 mil para um piso enxuto de R$ 11 mil mensais) | I237: Promessa não cumprida. O capítulo não volta aos números de Lucas, não roteiriza a conversa dele em casa e o Espelho e o Ritual não calculam os "oito meses extras". Lucas reaparece só como lembrete. | J237: Fazer a conta no Espelho: reserva de Lucas dividida por R$ 22 mil contra a mesma reserva dividida por R$ 11 mil, mostrando de onde saem os oito meses. Ou cortar a promessa da abertura. | K237: não | L237: 1 | M237: não | N237: não | R237: Revisor de trecho | S237: Corrigido
A238: 237 | B238: 1 | C238: 3672 | D238: CAPÍTULO 1 | E238: C5 | F238: Contradição interna | G238: média | H238: abriu mão de R$ 22 mil líquidos mensais, plano de saúde sem coparticipação e bônus anual | I238: R$ 22 mil é o salário líquido e também o custo fixo da casa: Lucas gastaria tudo o que ganhava. E ele evita a conversa "após o sexto mês" aqui, mas "seis meses antes" do décimo em l. 3685. | J238: Separar os números (por exemplo, salário de R$ 22 mil e casa de R$ 16 mil, cortada para R$ 11 mil) e fixar um momento só para o erro (no quarto mês, seis meses antes da crise). | K238: não | L238: 1 | M238: não | N238: não | R238: Revisor de trecho | S238: Corrigido
A239: 238 | B239: 1 | C239: 3674 | D239: CAPÍTULO 1 | E239: N6 | F239: Conceito sem nome ou inflação de frameworks | G239: média | H239: **Imposto do Desespero Doméstico** (medido no painel deste capítulo sempre que a reserva cair abaixo de seis meses) | I239: Conceito com nome próprio que nunca volta. O painel (l. 3736) não mede nada com esse nome. Horowitz e "A Luta" reaparecem na abertura do Cap. 2 (l. 3766), em sequência. | J239: Pôr o indicador no painel ("Imposto do Desespero: alerta quando o runway pessoal cai abaixo de seis meses") e usar o nome no Espelho. Deixar Horowitz em um dos dois capítulos. | K239: não | L239: 1 | M239: não | N239: não | R239: Revisor de trecho | S239: Corrigido
... A249: 248 | B249: 1 | C249: 3717 | D249: CAPÍTULO 1 | E249: S4 | F249: Remissão quebrada ou em excesso | G249: média | H249: Nunca misture (já falamos no [[IGNICAO-Vol-5-Financas-e-Captacao#CAPÍTULO 2 | I249: "Já falamos" aponta para o Vol. 5, que o leitor ainda não leu. O texto exibido traz "Reforma Ibs/cbs" com caixa errada. "Expense reimbursement" fica sem tradução. | J249: "Nunca misture. O Capítulo 2 do Vol. 5 aprofunda o tema." Corrigir para "IBS/CBS" e trocar "expense reimbursement" por "reembolso de despesa". | K249: não | L249: 1 | M249: sim | N249: não | R249: Revisor de trecho | S249: Corrigido
A250: 249 | B250: 1 | C250: 3719 | D250: CAPÍTULO 1 | E250: C3 | F250: Erro factual provável | G250: alta | H250: havendo herdeiros necessários, a sucessão testamentária só alcança metade do patrimônio disponível | I250: Erro jurídico. Com herdeiros necessários, o testador dispõe da metade da herança (art. 1.789 do CC), e essa metade é a parte disponível. "Metade do disponível" seria um quarto. | J250: "havendo herdeiros necessários, o testamento só alcança a metade disponível do patrimônio (art. 1.789 do Código Civil)". | K250: não | L250: 1 | M250: não | N250: não | O250: erro confirmado | P250: Pelo art. 1.789 do Código Civil, havendo herdeiros necessários, o testador só pode dispor da metade da herança. Essa metade é a parte disponível. A outra metade é a legítima. 'Metade do disponível' daria um quarto. | Q250: https://www.peticoesonline.com.br/art-1789-cc | R250: Revisor de trecho | S250: Corrigido
A251: 250 | B251: 1 | C251: 3719 | D251: CAPÍTULO 1 | E251: C7 | F251: Conselho arriscado sem ressalva | G251: alta | H251: se você é casado ou vive em união estável sob comunhão parcial (regime legal padrão quando não há contrato escrito diferente), formalize desde cedo um contrato de convivência ou instrumento pré-nupcial | I251: Quem já é casado não faz pacto pré-nupcial. Precisa de alteração judicial do regime, como o próprio parágrafo diz depois. O conselho leva a um instrumento sem efeito. | J251: "Em união estável, formalize um contrato de convivência. Se vai casar, faça pacto antenupcial. Se já é casado, a mudança de regime exige pedido judicial (art. 1.639, § 2º, do CC)." Em frases curtas, com advogado de família. | K251: não | L251: 1 | M251: não | N251: não | O251: erro confirmado | P251: Pacto antenupcial só vale se feito antes do casamento. Quem já é casado só muda o regime por pedido judicial motivado de ambos os cônjuges (art. 1.639, § 2º, do CC), regra ainda vigente em agosto de 2025. Na união estável, o caminho é o contrato de convivência. | Q251: https://ibdfam.org.br/artigos/2357/ | https://arpensp.org.br/artigo/37329 | R251: Revisor de trecho | S251: Corrigido
A252: 251 | B252: 1 | C252: 3719 | D252: CAPÍTULO 1 | E252: C3 | F252: Erro factual provável | G252: média | H252: cabendo ao acordo de sócios regrar a apuração de haveres nas quotas societárias (art. 1.028 do Código Civil), bens adquiridos após o casamento | I252: O art. 1.028 trata da morte de sócio. Para o cônjuge que se separa vale o art. 1.027, e a apuração segue o art. 1.031 e o contrato social. A vírgula ainda emenda outra frase. | J252: Conferir e reescrever: "O contrato social e o acordo de sócios devem regular a apuração de haveres (arts. 1.027 e 1.031 do CC). Quotas adquiridas durante a união entram na meação." | K252: não | L252: 1 | M252: não | N252: sim | O252: erro confirmado | P252: O art. 1.028 do Código Civil trata da morte de sócio. Para o cônjuge que se separa vale o art. 1.027: ele não vira sócio nem exige logo sua parte na quota e só concorre aos lucros até a liquidação da sociedade. | Q252: https://www.peticoesonline.com.br/art-1028-cc | R252: Revisor de trecho | S252: Corrigido
A253: 252 | B253: 1 | C253: 3721 | D253: CAPÍTULO 1 | E253: E12 | F253: Frase longa demais | G253: alta | H253: segmentos de alta renda do varejo (como Bradesco Prime, Itaú Personnalité, BB Estilo e Santander Select, distintos do private banking propriamente dito) | I253: Frase de mais de 200 palavras com três níveis de parênteses. Dentro do parêntese do private banking, os exemplos são segmentos de varejo "distintos do private banking". O texto se contradiz. | J253: Quebrar as seis frentes em lista executável. Para o banco: "Segmentos de alta renda (Prime, Personnalité, Estilo, Select) aceitam clientes por renda mensal ou volume investido. Private banking exige patrimônio bem maior." | K253: não | L253: 1 | M253: sim | N253: não | R253: Revisor de trecho | S253: Corrigido
A254: 253 | B254: 1 | C254: 3721 | D254: CAPÍTULO 1 | E254: C3 | F254: Erro factual provável | G254: média | H254: a partir de patrimônio líquido declarado de quinhentos mil a um milhão de reais, bancos grandes oferecem canal privado | I254: Private banking no Brasil costuma começar em alguns milhões de reais investidos (o recorte da ANBIMA seria de R$ 3 milhões, a conferir). R$ 500 mil a R$ 1 milhão é alta renda de varejo. | J254: Conferir os pisos atuais e corrigir: "o private banking parte de alguns milhões investidos". | K254: não | L254: 1 | M254: não | N254: sim | O254: erro confirmado | P254: Pela ANBIMA, o private banking reúne investidores com no mínimo R$ 3 milhões em ativos financeiros, conforme a política de cada instituição. De R$ 250 mil a R$ 1 milhão o cliente fica no varejo de alta renda (Personnalité, Prime, Estilo, Select). | Q254: https://www.anbima.com.br/pt_br/imprensa/patrimonio-do-private-banking-avanca-8-1-no-ano.htm | R254: Revisor de trecho | S254: Corrigido
A255: 254 | B255: 1 | C255: 3740 | D255: CAPÍTULO 1 | E255: C5 | F255: Contradição interna | G255: alta | H255: O décimo erro (que fecha a família de proteção patrimonial ao lado do nono erro de aplicar a reserva de emergência em renda variável ou criptoativos voláteis) | I255: O nono erro é "score baixo por descuido". Aplicar a reserva em renda variável, prometido no título, não está na lista. O 8º e o 10º tratam do mesmo pacto. "Os 10 erros" viram "A primeira". | J255: Fundir o oitavo e o décimo (pacto e direitos do cônjuge), incluir "aplicar a reserva em renda variável" como erro próprio e usar o masculino: "O primeiro é...". | K255: não | L255: 1 | M255: sim | N255: não | R255: Revisor de trecho | S255: Corrigido
A256: 255 | B256: 1 | C256: 3746 | D256: CAPÍTULO 1 | E256: S7 | F256: Artefato de formatação ou texto de bastidor | G256: alta | H256: **Síntese prática em DINHEIRO PESSOAL DO FUNDADOR:** Ao incorporarem as balizas de *O Espelho do CPF do Fundador e o Ritual de...* na operação em São Paulo e Florianópolis | I256: Parágrafo-molde com título truncado ("Ritual de..."). Lucas e Marina cabem aqui, mas o desfecho ("indicadores auditáveis") é genérico e não traz os oito meses prometidos na abertura. | J256: Trocar pelo desfecho real de Lucas: o novo custo da casa, o runway recalculado e a recusa ao anjo. Por exemplo: "Com a casa em R$ 11 mil, a reserva de Lucas passou de X para Y meses e ele disse não aos 35%." | K256: não | L256: 1 | M256: sim | N256: não | R256: Revisor de trecho | S256: Corrigido
A257: 256 | B257: 1 | C257: 3751 | D257: CAPÍTULO 1 | E257: N4 | F257: Espelho ausente ou genérico | G257: média | H257: O dinheiro que paga os próximos 12 meses da sua casa está 100% em liquidez diária segura | I257: Contradiz o corpo, que manda só a primeira camada para liquidez diária e o resto para CDB com vencimento, LCI, LCA ou Prefixado. E nenhuma pergunta do Espelho retoma Lucas. | J257: "Os primeiros seis meses estão em liquidez diária e o restante em renda fixa conservadora, ou parte está em cripto e ações?" Abrir o Espelho com a pergunta que Lucas não fez no sexto mês. | K257: não | L257: 1 | M257: não | N257: não | R257: Revisor de trecho | S257: Corrigido
A258: 257 | B258: 1 | C258: 3753 | D258: CAPÍTULO 1 | E258: N5 | F258: Ritual de Segunda-Feira vago ou desconectado | G258: média | H258: e, toda segunda-feira das 9h às 9h15, abra sua planilha pessoal | I258: O rótulo diz 30 minutos "antes do próximo envio importante" e o texto, 15 minutos toda segunda. Mistura tarefas únicas (separar contas, definir retirada) e rotina numa frase de mais de 100 palavras. | J258: Separar: "Uma vez: separe as contas e defina a retirada." e "Toda segunda, das 9h às 9h15: registre os gastos, confira o cartão da empresa, atualize o runway." Trocar "conta física" por "conta de pessoa física". | K258: não | L258: 1 | M258: não | N258: não | R258: Revisor de trecho | S258: Corrigido
A259: 258 | B259: 1 | C259: 3758 | D259: CAPÍTULO 2 | E259: E7 | F259: Anglicismo ou mistura founder/fundador | G259: média | H259: ## CAPÍTULO 2 — SAÚDE MENTAL, DINÂMICA DE CO-FOUNDERS E HUMANIDADE DO FUNDADOR | I259: O título usa CO-FOUNDERS e o corpo alterna cofundadores, cofounders, founder, board, peer support, handoff, one-on-one, red flags, rumination, save. O Sumário já traduz para COFUNDADORES. | J259: Título: "SAÚDE MENTAL, DINÂMICA DE COFUNDADORES E HUMANIDADE DO FUNDADOR". No corpo: cofundadores, fundador, conselho, grupo de pares, passagem de bastão, conversa individual, sinais de alerta, ruminação. | K259: sim | L259: 30 | M259: não | N259: não | R259: Revisor de trecho | S259: Corrigido
A260: 259 | B260: 1 | C260: 3760 | D260: CAPÍTULO 2 | E260: N1 | F260: Abertura sem tensão ou em fórmula | G260: média | H260: Este capítulo une dois pilares inseparáveis da sobrevivência nos primeiros anos: a saúde mental do fundador sob pressão contínua e o desenho societário e relacional entre cofundadores | I260: O capítulo abre com nota editorial sobre a fusão ("une dois pilares", "padronizando o tratamento prático de ambos"), antes da cena. Quebra a promessa de abrir no meio da tensão. | J260: Cortar a frase e abrir direto na cena de Rafael às 4h da manhã. | K260: não | L260: 1 | M260: sim | N260: não | R260: Revisor de trecho | S260: Corrigido
...

Sheet Pendências v5.0
A1: ID | B1: Conjunto | C1: Vol. (v5.0) | D1: Linha (v5.0) | E1: Categoria | F1: Trecho na v5.0 | G1: Problema apontado | H1: O que vale (checagem de out/2026) | I1: Status na v5.2 | J1: Vol. (v5.2) | K1: Linha (v5.2) | L1: Trecho na v5.2 | M1: Também aparece em | N1: Nota | O1: Status
A2: DA-073 | B2: Exemplo do mapa da v5.0 | C2: 1 | D2: 38 | E2: Estrutura e navegação > Promessas da Nota do autor | F2: O rótulo Atos 1 a 4 não aparece em nenhum capítulo | G2: O rótulo Atos 1 a 4 não aparece em nenhum capítulo | I2: corrigido | J2: 1 | K2: 35 | L2: 1. **A Narrativa Viva:** abro sempre no meio da tensão real | N2: A Nota trocou Atos 1 a 4 por A Narrativa Viva. O rótulo não aparece mais. | O2: Corrigido
A3: DA-075 | B3: Exemplo do mapa da v5.0 | C3: 1 | D3: 39 | E3: Estrutura e navegação > Promessas da Nota do autor | F3: Caderno de Campo só aparece na própria Nota do autor | G3: Caderno de Campo só aparece na própria Nota do autor | I3: persiste | J3: 1 | K3: 36 | L3: 2. **A Oficina de Trincheira (Caderno de Campo):** | N3: Continua sendo a única menção na coleção. A mesma frase agora promete ferramentas impressas uma única vez, enquanto Sobre este livro (l. 50) fala em presença local das ferramentas compartilhadas. | O3: Corrigido
A4: DA-028 | B4: Exemplo do mapa da v5.0 | C4: 1 | D4: 629 | E4: Vícios de escrita | F4: Rótulo didático: Lições transferíveis. no caso Nubank da Fase 0 | G4: Rótulo didático: Lições transferíveis. no caso Nubank da Fase 0 | I4: corrigido | J4: 1 | K4: 592 | L4: **O que esse início ensina a quem ainda está na Fase 0:** antes de discutir produto ou rodada de investimento | N4: No Vol. 1 o rótulo virou frase. O mesmo rótulo segue no Vol. 9 (l. 5533, 5614 e 5702), fora do exemplo do mapa. | O4: Corrigido
A5: DA-257 | B5: Exemplo do mapa da v5.0 | C5: 1 | D5: 649 | E5: Mapa por volume | F5: Vol. 1: fórmula de runway corrompida no Ritual da Fase 0 | G5: Vol. 1: fórmula de runway corrompida no Ritual da Fase 0 | I5: corrigido | J5: 1 | K5: 614 | L5: pela fórmula `reserva líquida ÷ (custo mensal mínimo × 1,5)` | N5: O LaTeX quebrado saiu e a margem de 50% agora reduz o runway, em vez de aumentá-lo. | O5: Corrigido
A6: DA-231 | B6: Exemplo do mapa da v5.0 | C6: 1 | D6: 736 | E6: Conteúdo e precisão > Capítulos que se dizem atuais | F6: Walgreens fechou capital (Vol. 1) | G6: Walgreens fechou capital (Vol. 1) | I6: corrigido | J6: 1 | K6: 667 | L6: Walgreens até seu fechamento de capital pela Sycamore Partners em agosto de 2025 | N6: O exemplo de Collins ganhou a ressalva. | O6: Corrigido
A7: DA-076 | B7: Exemplo do mapa da v5.0 | C7: 1 | D7: 1220 | E7: Estrutura e navegação > Remissões com numeração antiga | F7: Team Canvas na Fase 14 (escala e time), deveria ser Fases 15 e 16 | G7: Team Canvas na Fase 14 (escala e time), deveria ser Fases 15 e 16 | I7: corrigido | J7: 1 | K7: 945 | L7: Volte a ele na Fase 16, ao montar a liderança ou ao montar equipe de liderança expandida. | N7: Número certo. A frase nova repete ao montar duas vezes. | O7: Corrigido
A8: DA-061 | B8: Exemplo do mapa da v5.0 | C8: 1 | D8: 1622 | E8: Narrativa > O que funciona e deve ficar | F8: Batismo do conceito: Síndrome da Ideia de Vitrine | G8: Batismo do conceito: Síndrome da Ideia de Vitrine | I8: persiste | J8: 1 | K8: 1332 | L8: Da pergunta de Marina nasce o diagnóstico desta fase, a **Síndrome da Ideia de Vitrine** | N8: Qualidade preservada na abertura da Fase 1. | O8: Corrigido
A9: DA-077 | B9: Exemplo do mapa da v5.0 | C9: 1 | D9: 2451 | E9: Estrutura e navegação > Remissões com numeração antiga | F9: Lean Canvas até a Fase 12 (PMF), deveria ser Fase 13 | G9: Lean Canvas até a Fase 12 (PMF), deveria ser Fase 13 | I9: corrigido | J9: 1 | K9: 1992 | L9: Use o Lean Canvas a partir da Fase 1 (encontrar a ideia) até a Fase 13 (PMF). | N9: Corrigido na única cópia que restou do canvas. | O9: Corrigido
A10: DA-078 | B10: Exemplo do mapa da v5.0 | C10: 1 | D10: 2548 | E10: Estrutura e navegação > Remissões com numeração antiga | F10: Strategy Canvas na Fase 5 (mapeamento de mercado e concorrência), deveria ser Fase 6 | G10: Strategy Canvas na Fase 5 (mapeamento de mercado e concorrência), deveria ser Fase 6 | I10: corrigido | J10: 2 | K10: 4635 | L10: Use o Strategy Canvas na Fase 6 (mapeamento de mercado e concorrência) | N10: A cópia do Vol. 1 saiu. O canvas ficou só no Vol. 2, com o número certo. | O10: Corrigido
A11: DA-079 | B11: Exemplo do mapa da v5.0 | C11: 1 | D11: 2548 | E11: Estrutura e navegação > Remissões com numeração antiga | F11: Strategy Canvas na Fase 15 (reinvenção), deveria ser Fase 19 | G11: Strategy Canvas na Fase 15 (reinvenção), deveria ser Fase 19 | I11: corrigido | J11: 2 | K11: 4635 | L11: retome a ferramenta na Fase 19 (reinvenção e segunda curva, no Volume 9). | N11: Corrigido na única cópia do canvas. | O11: Corrigido
A12: DA-080 | B12: Exemplo do mapa da v5.0 | C12: 1 | D12: 4079 | E12: Estrutura e navegação > Remissões com numeração antiga | F12: Opportunity Canvas na Fase 8 (ideação), deveria ser Fase 9 | G12: Opportunity Canvas na Fase 8 (ideação), deveria ser Fase 9 | I12: corrigido | J12: 3 | K12: 2469 | L12: Use o Opportunity Canvas nesta Fase 9 (antes de abrir a geração de ideias do Passo 1) | N12: A cópia do Vol. 1 saiu. O canvas ficou na Fase 9 do Vol. 3. | O12: Corrigido
A13: DA-031 | B13: Exemplo do mapa da v5.0 | C13: 1 | D13: 4636 | E13: Vícios de escrita | F13: Erro de português: exhaustividade | G13: Erro de português: exhaustividade | I13: corrigido em parte | J13: 1 | K13: 3111 | L13: Passo 5: Teste exhaustividade. | N13: Eram 6 ocorrências (Vols. 1, 2 e 3). Resta 1, no passo a passo do MECE do Vol. 1. | O13: Corrigido
... A28: DA-016 | B28: Exemplo do mapa da v5.0 | C28: 1 | D28: 8309 | E28: Vícios de escrita | F28: Vírgula antes do e: Claude, ChatGPT, e Gemini, todos conseguem analisar planilhas | G28: Vírgula antes do e: Claude, ChatGPT, e Gemini, todos conseguem analisar planilhas | I28: corrigido | J28: 1 | K28: 6357 | L28: Claude, ChatGPT e Gemini processam planilhas e arquivos CSV (desde que previamente limpos de dados pessoais identificáveis) em poucos minutos | N28: Parágrafo reescrito no capítulo de IA fundido (Cap. 10). Vírgulas e fragmentos do original sumiram. | O28: Corrigido
A29: DA-144 | B29: Exemplo do mapa da v5.0 | C29: 2 | E29: Consistência entre volumes > Réguas que mudam dentro do volume | F29: Sessões de pesquisa de 8 a 15 ou 15 a 30, e de uma a cinco personas (Vol. 2, Fase 5) | G29: Sessões de pesquisa de 8 a 15 ou 15 a 30, e de uma a cinco personas (Vol. 2, Fase 5) | I29: corrigido | J29: 2 | K29: 1960 | L29: Para a descoberta inicial do problema (Fase 4), quinze a trinta conversas são a referência | N29: A mesma frase diz que a Fase 5 pede oito a quinze sessões longas, então as duas faixas ganharam contexto. As personas ficaram em duas a quatro em toda a fase. | O29: Corrigido
A30: DA-148 | B30: Exemplo do mapa da v5.0 | C30: 2 | E30: Consistência entre volumes > Fases na numeração antiga | F30: Vol. 2: a Fase 5 se chama Fase 4 e chama a Descoberta de Fase 3 em cerca de 15 passagens | G30: Vol. 2: a Fase 5 se chama Fase 4 e chama a Descoberta de Fase 3 em cerca de 15 passagens | I30: corrigido em parte | J30: 2 | K30: 2912 | L30: Use o VPC depois de fazer pesquisa qualitativa real (Fase 4: entrevistas em profundidade, observação em campo, análise de jornada). | N30: A Descoberta não aparece mais como Fase 3 e o critério de saída está certo. Sobra a nota do VPC, que chama a pesquisa e o Dossiê do Usuário de Fase 4. | O30: Corrigido
A31: DA-258 | B31: Exemplo do mapa da v5.0 | C31: 2 | E31: Mapa por volume | F31: Vol. 2: cerca de 45 frases quebradas no Cap. 3 (casos de fracasso) | G31: Vol. 2: cerca de 45 frases quebradas no Cap. 3 (casos de fracasso) | I31: corrigido em parte | J31: 2 | K31: 5944 | L31: os estudos de caso individuais em profundidade estão no Capítulo 19 do Volume 9 | N31: Amostra por busca: frases de uma ou duas palavras no capítulo caíram de 10 para 7, e sumiram Dinheiro acaba. Mercado muda. Concorrente come. Resta Escolher dói. Conferência completa só por releitura. | O31: Corrigido
A32: DA-214 | B32: Exemplo do mapa da v5.0 | C32: 2 | D32: 287 | E32: Conteúdo e precisão > Casos, pessoas e livros | F32: Cinco perguntas atribuídas ao Mom Test, que vêm da palestra de Eric Migicovsky | G32: Cinco perguntas atribuídas ao Mom Test, que vêm da palestra de Eric Migicovsky | I32: corrigido | J32: 2 | K32: 264 | L32: ##### As cinco perguntas de Eric Migicovsky (Y Combinator), compatíveis com o Mom Test (roteiro mínimo) | N32: Atribuição certa. | O32: Corrigido
A33: DA-015 | B33: Exemplo do mapa da v5.0 | C33: 2 | D33: 651 | E33: Vícios de escrita | F33: Dois-pontos virado vírgula: Passo 1, Prepare agenda sem mencionar sua solução. | G33: Dois-pontos virado vírgula: Passo 1, Prepare agenda sem mencionar sua solução. | I33: corrigido | J33: 2 | K33: 586 | L33: Passo 1. Prepare a pauta sem mencionar a solução, listando de cinco a sete perguntas sobre a rotina real do entrevistado diante do problema. | N33: Exemplo corrigido, mas o Passo 1 usa ponto e os Passos 2 e 3 logo abaixo usam dois-pontos. O subtítulo do molde Como rodar na segunda-feira às 9h continua acima. | O33: Corrigido
A34: DA-082 | B34: Exemplo do mapa da v5.0 | C34: 2 | D34: 1458 | E34: Estrutura e navegação > Remissões com numeração antiga | F34: Empathy Map na Fase 3 (descoberta) e Fase 4 (pesquisa), deveria ser Fase 4 e Fase 5 | G34: Empathy Map na Fase 3 (descoberta) e Fase 4 (pesquisa), deveria ser Fase 4 e Fase 5 | I34: corrigido em parte | J34: 2 | K34: 996 | L34: Use também na Fase 4 (pesquisa) para construir o Customer Profile do VPC (Fase 5) com profundidade emocional. | N34: A primeira menção virou Fase 4 (descoberta do problema). A segunda ainda diz Fase 4 (pesquisa), quando a pesquisa é a Fase 5. | O34: Corrigido
A35: DA-043 | B35: Exemplo do mapa da v5.0 | C35: 2 | D35: 2526 | E35: Narrativa > Arquétipos | F35: Camila troca de profissão: cirurgiã-dentista, fisioterapeuta e médica | G35: Camila troca de profissão: cirurgiã-dentista, fisioterapeuta e médica | I35: corrigido em parte | J35: 2 | K35: 1812 | L35: Intrigada, Camila resolveu sentar na recepção por três dias e conversar com os dez pacientes mais fiéis: não sobre fisioterapia, mas sobre o dia em que decidiram agendar. | N35: Camila é dentista em todos os volumes e as cenas de médica (Vol. 3 e Vol. 9) e de fisioterapia do Vol. 4 saíram. Sobrou não sobre fisioterapia na cena da Fase 5, duas linhas depois de clínica odontológica. | O35: Corrigido
A36: DA-064 | B36: Exemplo do mapa da v5.0 | C36: 2 | D36: 2528 | E36: Narrativa > O que funciona e deve ficar | F36: Fio da paciente Dona Helena do Vol. 2 para o Vol. 3 | G36: Fio da paciente Dona Helena do Vol. 2 para o Vol. 3 | I36: persiste | J36: 2 | K36: 3381 | L36: contratado por pacientes de 55 a 70 anos como Dona Helena era voltar a sorrir e mastigar em festas de família sem medo de dor | N36: Qualidade preservada e reforçada: Dona Helena volta no Fechamento da Fase 5 e reaparece no Vol. 3 (l. 1799). | O36: Corrigido
A37: DA-021 | B37: Exemplo do mapa da v5.0 | C37: 2 | D37: 2585 | E37: Vícios de escrita | F37: Fragmento telegráfico: Anote tudo. O que fez. Quanto tempo. Interrupções. | G37: Fragmento telegráfico: Anote tudo. O que fez. Quanto tempo. Interrupções. | I37: corrigido | J37: 2 | K37: 1842 | L37: Anote o que a pessoa fez, quanto tempo levou em cada tarefa, quem a interrompeu, onde ela se irritou e com quem precisou falar no meio do caminho. | N37: Lista picada virou frase com verbo. | O37: Corrigido
A38: DA-017 | B38: Exemplo do mapa da v5.0 | C38: 2 | D38: 2688 | E38: Vícios de escrita | F38: Símbolo por extenso: Triangulação qualitativa mais quantitativa | G38: Símbolo por extenso: Triangulação qualitativa mais quantitativa | I38: corrigido | J38: 2 | K38: 1946 | L38: ##### Triangulação entre entrevistas e survey | N38: O subtítulo foi renomeado e perdeu o mais no lugar do sinal. | O38: Corrigido
A39: DA-212 | B39: Exemplo do mapa da v5.0 | C39: 2 | D39: 3048 | E39: Conteúdo e precisão > Casos, pessoas e livros | F39: Demand-Side Sales 101 é de Bob Moesta e Greg Engle | G39: Demand-Side Sales 101 é de Bob Moesta e Greg Engle | I39: corrigido em parte | J39: 10 | K39: 10450 | L39: Moesta, Bob. *Demand-Side Sales 101: Stop Selling and Help Your Customers Make Progress.* Lioncrest, 2020. | N39: O Vol. 2 (l. 2192) cita Moesta e Engle. A bibliografia omite Engle e o Vol. 7 (l. 1853) liga o livro a Moesta e Chris Spiek. | O39: Corrigido
A40: DA-252 | B40: Exemplo do mapa da v5.0 | C40: 2 | D40: 3097 | E40: Conteúdo e precisão > Conselho arriscado sem ressalva | F40: Pesquisa de campo em clínica com fichas de pacientes à vista e registro em fotos e vídeos, sem LGPD (Vol. 2) | G40: Pesquisa de campo em clínica com fichas de pacientes à vista e registro em fotos e vídeos, sem LGPD (Vol. 2) | I40: corrigido com erro novo | J40: 2 | K40: 2304 | L40: Entre um atendimento e outro na clínica odontológica, perde de 4 a 5 minutos procurando histórico clínico | N40: Entraram consentimento e proibição de fotografar fichas (l. 2304 e 2356). O exemplo virou meio fisioterapia, meio odontologia (l. 2298 e 2304) e remete à LGPD no Capítulo 10 do Vol. 8, que hoje é o Cap. 9. | O40: Corrigido
A41: DA-213 | B41: Exemplo do mapa da v5.0 | C41: 2 | D41: 3649 | E41: Conteúdo e precisão > Casos, pessoas e livros | F41: Moesta como coautor de Competing Against Luck (Vol. 2 e Vol. 9) | G41: Moesta como coautor de Competing Against Luck (Vol. 2 e Vol. 9) | I41: corrigido | J41: 2 | K41: 2785 | L41: *Competing Against Luck* (2016), escrito com Taddy Hall, Karen Dillon e David S. Duncan. | N41: Coautores certos aqui, no Vol. 1 (l. 1248) e na bibliografia (Vol. 10, l. 10368). A cópia do Vol. 9 saiu. | O41: Corrigido
A42: DA-083 | B42: Exemplo do mapa da v5.0 | C42: 2 | D42: 3974 | E42: Estrutura e navegação > Remissões com numeração antiga | F42: Customer Journey Canvas na Fase 4 (pesquisa), deveria ser Fase 5 | G42: Customer Journey Canvas na Fase 4 (pesquisa), deveria ser Fase 5 | I42: corrigido com erro novo | J42: 2 | K42: 3014 | L42: Em momentos de pivô (ver Capítulo 16 do Volume 4), refaça o mapa da jornada antes de qualquer novo investimento operacional. | N42: A fase virou nesta Fase 5. Na mesma linha, a remissão ao pivô usa o número antigo do capítulo: hoje o pivô é o Cap. 11 do Vol. 4, que tem só 11 capítulos. | O42: Corrigido
A43: DA-024 | B43: Exemplo do mapa da v5.0 | C43: 2 | D43: 4482 | E43: Vícios de escrita | F43: Metáfora gasta: a ponta afiada do machado que racha a tora de madeira | G43: Metáfora gasta: a ponta afiada do machado que racha a tora de madeira | I43: corrigido com erro novo | J43: 2 | K43: 3395 | L43: é o seu primeiro pino da fila Na Fase 6, você vai parar de admirar o oceano pela luneta e escolher o único pino de boliche frontal que, quando derrubado com violência cirúrgica | N43: O machado saiu, mas a troca deixou nova antítese (não é o seu teto, é o seu primeiro pino), um ponto faltando antes de Na Fase 6 e manteve a violência cirúrgica e o oceano pela luneta. | O43: Corrigido
... A50: DA-014 | B50: Exemplo do mapa da v5.0 | C50: 2 | D50: 7722 | E50: Vícios de escrita | F50: Frase partida: O nome precisa ser. Memorável. Duas, ou três palavras. | G50: Frase partida: O nome precisa ser. Memorável. Duas, ou três palavras. | I50: corrigido | J50: 2 | K50: 5856 | L50: Um bom nome precisa ser memorável (duas ou três palavras), fácil de usar em conversa, distinto dos rótulos antigos, capaz de sugerir o problema resolvido | N50: O Pilar 2 do Category Design foi reescrito em frase corrida. O capítulo de Category Design foi fundido ao Cap. 2 do Vol. 2. | O50: Corrigido
A51: DA-140 | B51: Exemplo do mapa da v5.0 | C51: 3 | E51: Consistência entre volumes > Réguas que mudam dentro do volume | F51: Amostra de experimento de 30, 80 a 100, 385 ou 500 a 5.000 na Fase 8 | G51: Amostra de experimento de 30, 80 a 100, 385 ou 500 a 5.000 na Fase 8 | I51: corrigido em parte | J51: 3 | K51: 1199 | L51: Embora os 47 visitantes tenham superado a meta mínima de 30, apenas 7 atenderam às ligações | N51: A Fase 8 ganhou tabela de amostra por técnica (l. 1764 a 1773: survey 100 a 500, landing page 500 a 5.000). O exemplo da landing page ainda usa meta mínima de 30 visitantes. | O51: Corrigido
A52: DA-149 | B52: Exemplo do mapa da v5.0 | C52: 3 | E52: Consistência entre volumes > Fases na numeração antiga | F52: Vol. 3: hipóteses como Fase 6 e experimentos como Fase 7, e o Cap. 1 com três mapas de fases, Fases 1B e 2B e PMF na Fase 12 | G52: Vol. 3: hipóteses como Fase 6 e experimentos como Fase 7, e o Cap. 1 com três mapas de fases, Fases 1B e 2B e PMF na Fase 12 | I52: corrigido | J52: 3 | K52: 3700 | L52: Modelo em validação e estruturação pós-PSF (Fase 12 em diante, rumo ao PMF na Fase 13) | N52: Fases 1B e 2B sumiram e hipóteses e experimentos estão nas Fases 7 e 8. Na l. 3644, a confirmação do PMF ainda aparece como da Fase 12 em diante. | O52: Corrigido
A53: DA-260 | B53: Exemplo do mapa da v5.0 | C53: 3 | E53: Mapa por volume | F53: Vol. 3: framework de Gates sem crédito à Antler | G53: Vol. 3: framework de Gates sem crédito à Antler | I53: corrigido em parte | J53: 10 | K53: 10875 | L53: | Framework de Decisão por Gates | Antler, *The Ten Gates* (Adam French, 2025), adaptado para a coleção | | N53: O Índice de Frameworks dá o crédito, mas o Cap. 2 do Vol. 3 (l. 3757 a 4046), onde o scorecard é ensinado, não cita a Antler. | O53: Corrigido
A54: DA-030 | B54: Exemplo do mapa da v5.0 | C54: 3 | D54: 192 | E54: Vícios de escrita | F54: Erro de português: PORQUÊ IMPORTA no molde de hipótese | G54: Erro de português: PORQUÊ IMPORTA no molde de hipótese | I54: corrigido | J54: 3 | K54: 167 | L54: POR QUE IMPORTA (IMPACTO SE FOR FALSA): [qual o impacto no negócio se a premissa cair] | N54: Grafia corrigida no molde e no exemplo preenchido (l. 297). | O54: Corrigido
A55: DA-259 | B55: Exemplo do mapa da v5.0 | C55: 3 | D55: 192 | E55: Mapa por volume | F55: Vol. 3: as ferramentas da Fase 7 praticam o Teatro da Validação que a fase condena (falta critério de descarte) | G55: Vol. 3: as ferramentas da Fase 7 praticam o Teatro da Validação que a fase condena (falta critério de descarte) | I55: corrigido | J55: 3 | K55: 169 | L55: VAMOS DESCARTAR SE: [critério numérico de refutação] | N55: O molde de hipótese ganhou campo de descarte e zona cinzenta, e ponto de corte ou critério de descarte aparece 12 vezes no Vol. 3 (eram 2). | O55: Corrigido
A56: DA-087 | B56: Exemplo do mapa da v5.0 | C56: 3 | D56: 1279 | E56: Estrutura e navegação > Remissões com numeração antiga | F56: Hypothesis Canvas na Fase 6, deveria ser Fase 7 (cópia do Vol. 3) | G56: Hypothesis Canvas na Fase 6, deveria ser Fase 7 (cópia do Vol. 3) | I56: corrigido | J56: 3 | K56: 705 | L56: Use o Hypothesis Canvas na Fase 7 (formulação rigorosa de hipóteses) como artefato central | N56: Número certo. | O56: Corrigido
A57: DA-088 | B57: Exemplo do mapa da v5.0 | C57: 3 | D57: 1453 | E57: Estrutura e navegação > Remissões com numeração antiga | F57: Banco de Hipóteses: ao iniciar a Fase 6 (priorização), deveria ser Fase 7 | G57: Banco de Hipóteses: ao iniciar a Fase 6 (priorização), deveria ser Fase 7 | I57: corrigido | J57: 3 | K57: 765 | L57: **Quando usar:** no início da Fase 7 (formulação e priorização de hipóteses) | N57: Número certo. | O57: Corrigido
A58: DA-089 | B58: Exemplo do mapa da v5.0 | C58: 3 | D58: 2815 | E58: Estrutura e navegação > Remissões com numeração antiga | F58: Test Card na Fase 7 (experimentos) e Fase 6 (formulação), deveria ser Fase 8 e Fase 7 | G58: Test Card na Fase 7 (experimentos) e Fase 6 (formulação), deveria ser Fase 8 e Fase 7 | I58: corrigido | J58: 3 | K58: 1636 | L58: Use o Test Card na Fase 8 (experimentos de validação do problema e da solução) como artefato central | N58: As duas fases estão certas (Fase 8 e fechamento da Fase 7). | O58: Corrigido
A59: DA-250 | B59: Exemplo do mapa da v5.0 | C59: 3 | D59: 2847 | E59: Conteúdo e precisão > Conselho arriscado sem ressalva | F59: Público semelhante criado a partir de base de e-mails comprada (Vol. 3) | G59: Público semelhante criado a partir de base de e-mails comprada (Vol. 3) | I59: corrigido | J59: 3 | K59: 1668 | L59: nunca compre bases de dados de terceiros: subir lista comprada em plataformas de anúncios viola o art. 7º da LGPD | N59: Base própria com consentimento. | O59: Corrigido
A60: DA-090 | B60: Exemplo do mapa da v5.0 | C60: 3 | D60: 2927 | E60: Estrutura e navegação > Remissões com numeração antiga | F60: Pirate Canvas na Fase 10 (MVP) e Fase 14 (escala), deveria ser Fase 11 e Fase 15 | G60: Pirate Canvas na Fase 10 (MVP) e Fase 14 (escala), deveria ser Fase 11 e Fase 15 | I60: corrigido | J60: 4 | K60: 845 | L60: Use o Pirate Canvas nesta Fase 11 (MVP e primeiros usuários) como estrutura de instrumentação das métricas iniciais | N60: As cópias dos Vols. 3 e 6 saíram. A casa única no Vol. 4 cita Fase 11 e Fase 15. | O60: Corrigido
A61: DA-209 | B61: Exemplo do mapa da v5.0 | C61: 3 | D61: 3386 | E61: Conteúdo e precisão > Casos, pessoas e livros | F61: Fundadores trocados: PlayKids | G61: Fundadores trocados: PlayKids | I61: corrigido | J61: 3 | K61: 2000 | L61: PlayKids, aplicativo infantil criado dentro do grupo Movile em junho de 2013 | N61: Os fundadores errados saíram e o caso fala só do grupo Movile. | O61: Corrigido
A62: DA-091 | B62: Exemplo do mapa da v5.0 | C62: 3 | D62: 4089 | E62: Estrutura e navegação > Remissões com numeração antiga | F62: Opportunity Canvas na Fase 8 (ideação), deveria ser Fase 9 (cópia do Vol. 3) | G62: Opportunity Canvas na Fase 8 (ideação), deveria ser Fase 9 (cópia do Vol. 3) | I62: corrigido | J62: 3 | K62: 2469 | L62: Use o Opportunity Canvas nesta Fase 9 (antes de abrir a geração de ideias do Passo 1) | N62: Número certo. | O62: Corrigido
A63: DA-092 | B63: Exemplo do mapa da v5.0 | C63: 3 | D63: 4200 | E63: Estrutura e navegação > Remissões com numeração antiga | F63: MVP Canvas na Fase 8 (prototipagem e MVP), deveria ser Fase 9 | G63: MVP Canvas na Fase 8 (prototipagem e MVP), deveria ser Fase 9 | I63: corrigido | J63: 3 | K63: 2566 | L63: Use o MVP Canvas no Passo 7 desta Fase 9 (para transformar o conceito escolhido em protótipo testável) | N63: Número certo, com remissão à Fase 11 para o MVP em produção. | O63: Corrigido
A64: DA-093 | B64: Exemplo do mapa da v5.0 | C64: 3 | D64: 4424 | E64: Estrutura e navegação > Remissões com numeração antiga | F64: Lean Canvas até a Fase 12 (PMF), deveria ser Fase 13 (cópia do Vol. 3) | G64: Lean Canvas até a Fase 12 (PMF), deveria ser Fase 13 (cópia do Vol. 3) | I64: corrigido | J64: 1 | K64: 1992 | L64: Use o Lean Canvas a partir da Fase 1 (encontrar a ideia) até a Fase 13 (PMF). | N64: A cópia do Vol. 3 saiu. Fica a casa única no Vol. 1, com o número certo. | O64: Corrigido
A65: DA-115 | B65: Exemplo do mapa da v5.0 | C65: 3 | D65: 4633 | E65: Estrutura e navegação > Remissões com numeração antiga | F65: Remissão a apêndice inexistente: Apêndices BC, que deve virar o Cap. 5 do Vol. 7 | G65: Remissão a apêndice inexistente: Apêndices BC, que deve virar o Cap. 5 do Vol. 7 | I65: corrigido com erro novo | J65: 3 | K65: 2788 | L65: essas rotinas ficam para quando o time passar de cinco a sete pessoas e são detalhadas na Fase 17 e no Capítulo 4 do Volume 7. | N65: Apêndices BC saiu. A frase nova manda as quatro práticas de descoberta para a Fase 17 e o Cap. 4 do Vol. 7, mas o Cap. 4 trata de gestão de engenharia e dívida técnica. Descoberta contínua e OST estão no Cap. 1, e INVEST não aparece no Vol. 7. | O65: Corrigido
... A72: DA-194 | B72: Exemplo do mapa da v5.0 | C72: 3 | D72: 6708 | E72: Conteúdo e precisão > Casos, pessoas e livros | F72: Mercado Livre como plataforma brasileira (Vol. 3) | G72: Mercado Livre como plataforma brasileira (Vol. 3) | I72: corrigido com erro novo | J72: 5 | K72: 1929 | L72: Para brasileiras listadas nos EUA (que reportam formulários 20-F ou 10-K à SEC): PagSeguro, StoneCo, Inter e Nu Holdings (NYSE), além do Mercado Livre (NASDAQ) | N72: O trecho do Vol. 3 saiu na fusão do capítulo de marketplaces. Uma lista nova do Vol. 5 põe o Mercado Livre entre as brasileiras listadas nos EUA e inclui Americanas e Enjoei, que são da B3. | O72: Corrigido
A73: DA-199 | B73: Exemplo do mapa da v5.0 | C73: 3 | D73: 6710 | E73: Conteúdo e precisão > Casos, pessoas e livros | F73: A 99 entrou com a Uber já estabelecida (Vol. 3) | G73: A 99 entrou com a Uber já estabelecida (Vol. 3) | I73: trecho removido | N73: O trecho saiu na fusão do capítulo de marketplaces. O Vol. 9 (l. 5366) conta a ordem certa: táxis primeiro, Uber depois. | O73: Corrigido
A74: DA-052 | B74: Exemplo do mapa da v5.0 | C74: 3 | D74: 7129 | E74: Narrativa > Arquétipos | F74: Henrique é dono de 100% dois parágrafos depois de ganhar um sócio | G74: Henrique é dono de 100% dois parágrafos depois de ganhar um sócio | I74: corrigido | J74: 3 | K74: 4764 | L74: e Henrique financiou toda essa transição com a receita dos próprios clientes. | N74: A frase dos 100% saiu. | O74: Corrigido
A75: DA-029 | B75: Exemplo do mapa da v5.0 | C75: 3 | D75: 7137 | E75: Vícios de escrita | F75: Tom de coach: a rota mais inteligente, lucrativa e soberana de construir um império real | G75: Tom de coach: a rota mais inteligente, lucrativa e soberana de construir um império real | I75: corrigido | J75: 3 | K75: 4772 | L75: costuma ser o caminho mais seguro e rentável para sustentar o desenvolvimento do negócio sem depender do humor do mercado de capitais. | N75: O superlativo saiu. A frase mantém a antítese com ponto e vírgula (não é um plano B para quem não conseguiu Venture Capital). | O75: Corrigido
A76: DA-156 | B76: Exemplo do mapa da v5.0 | C76: 3 | D76: 7256 | E76: Conteúdo e precisão > Regras que o leitor vai aplicar | F76: Dividendos isentos (Vol. 3, dividendos limpos do serviço tech-enabled) | G76: Dividendos isentos (Vol. 3, dividendos limpos do serviço tech-enabled) | I76: corrigido | J76: 3 | K76: 4891 | L76: sujeitos, desde janeiro de 2026 pela Lei 15.270/2025, à retenção de 10% na fonte para dividendos acima de R$ 50 mil mensais por empresa | N76: Dividendos limpos virou lucro distribuível com a ressalva da lei. | O76: Corrigido
A77: DA-139 | B77: Exemplo do mapa da v5.0 | C77: 4 | E77: Consistência entre volumes > Réguas que mudam dentro do volume | F77: Retenção D30 de B2B em 40%, 60%, 70% ou 80% na Fase 11, e saída com dez clientes por oito a doze semanas ou cinco por quatro semanas | G77: Retenção D30 de B2B em 40%, 60%, 70% ou 80% na Fase 11, e saída com dez clientes por oito a doze semanas ou cinco por quatro semanas | I77: corrigido em parte | J77: 4 | K77: 856 | L77: SaaS B2B: retenção da coorte em D30 acima de 60% para usuários ativos (ou acima de 40% no piso mínimo do primeiro piloto | N77: Há tabela de referência da Fase 11 (l. 525, piso de 40%) e os números viraram piso, meta e, na mesma linha, 80% por logo pagante. O critério de saída virou faixa: cinco a dez clientes em quatro a doze semanas (l. 224). | O77: Corrigido
A78: DA-150 | B78: Exemplo do mapa da v5.0 | C78: 4 | E78: Consistência entre volumes > Fases na numeração antiga | F78: Vol. 4: as Fases 12 e 13 se referem a si mesmas como Fase 11 e Fase 12 em cerca de 30 menções | G78: Vol. 4: as Fases 12 e 13 se referem a si mesmas como Fase 11 e Fase 12 em cerca de 30 menções | I78: corrigido | J78: 4 | K78: 1394 | L78: a Fase 12 valida *modelo viável* e a Fase 13 valida *produto amado pelo mercado (PMF)*. | N78: Não achei autorreferência com número antigo nas Fases 12 e 13. A mesma linha diz que os quatro cenários estão no fim da Fase 11, mas eles vêm logo abaixo. | O78: Corrigido
A79: DA-097 | B79: Exemplo do mapa da v5.0 | C79: 4 | D79: 1203 | E79: Estrutura e navegação > Remissões com numeração antiga | F79: Pirate Canvas na Fase 10 e Fase 14, cópia do Vol. 4 | G79: Pirate Canvas na Fase 10 e Fase 14, cópia do Vol. 4 | I79: corrigido | J79: 4 | K79: 845 | L79: já na Fase 15 (Vol. 6, máquina de crescimento e escala) | N79: Corrigido na casa única do canvas. | O79: Corrigido
A80: DA-098 | B80: Exemplo do mapa da v5.0 | C80: 4 | D80: 1308 | E80: Estrutura e navegação > Remissões com numeração antiga | F80: MVP Canvas na Fase 8, cópia do Vol. 4 | G80: MVP Canvas na Fase 8, cópia do Vol. 4 | I80: corrigido | J80: 3 | K80: 2566 | L80: Use o MVP Canvas no Passo 7 desta Fase 9 (para transformar o conceito escolhido em protótipo testável) | N80: A cópia do Vol. 4 saiu. | O80: Corrigido
A81: DA-099 | B81: Exemplo do mapa da v5.0 | C81: 4 | D81: 1424 | E81: Estrutura e navegação > Remissões com numeração antiga | F81: MoSCoW: entrar em Fase 9 (construção), cópia do Vol. 4 | G81: MoSCoW: entrar em Fase 9 (construção), cópia do Vol. 4 | I81: corrigido | J81: 3 | K81: 3411 | L81: imediatamente antes de iniciar a construção do MVP na Fase 11 (Vol. 4). | N81: A cópia do Vol. 4 saiu e a casa única tem o número certo. | O81: Corrigido
A82: DA-058 | B82: Exemplo do mapa da v5.0 | C82: 4 | D82: 1494 | E82: Narrativa > O que funciona e deve ficar | F82: Cena de Bia: autópsia do pedido de R$ 100 que perde R$ 15,50 | G82: Cena de Bia: autópsia do pedido de R$ 100 que perde R$ 15,50 | I82: persiste | J82: 4 | K82: 964 | L82: cada vez que o sininho da loja apitou neste mês, nós tiramos R$ 15,50 do nosso bolso e colocamos dentro da caixa de papelão do cliente. | N82: Qualidade preservada na abertura da Fase 12, com a conta inteira (l. 962). | O82: Corrigido
A83: DA-133 | B83: Exemplo do mapa da v5.0 | C83: 4 | D83: 1579 | E83: Consistência entre volumes > Erros copiados entre volumes | F83: LTV calculado sobre receita nos glossários, contra o Vol. 4 que manda usar margem bruta | G83: LTV calculado sobre receita nos glossários, contra o Vol. 4 que manda usar margem bruta | I83: corrigido | J83: 10 | K83: 9686 | L83: calculada obrigatoriamente sobre a margem bruta e nunca sobre a receita bruta | N83: Glossário único e Vol. 4 (l. 1034) usam margem bruta. | O83: Corrigido
A84: DA-100 | B84: Exemplo do mapa da v5.0 | C84: 4 | D84: 2621 | E84: Estrutura e navegação > Remissões com numeração antiga | F84: Risk Canvas na Fase 11 (modelo de negócio) e Fase 15 (reinvenção), deveria ser Fase 12 e Fase 19 | G84: Risk Canvas na Fase 11 (modelo de negócio) e Fase 15 (reinvenção), deveria ser Fase 12 e Fase 19 | I84: corrigido | J84: 4 | K84: 1782 | L84: Use o Risk Canvas nesta Fase 12 (validação do modelo de negócio) como check-up | N84: As duas fases estão certas (Fase 12 e Fase 19). | O84: Corrigido
A85: DA-101 | B85: Exemplo do mapa da v5.0 | C85: 4 | D85: 2839 | E85: Estrutura e navegação > Remissões com numeração antiga | F85: Fase 11 (modelo viável) e esta Fase 12 (produto amado), deveria ser Fase 12 e Fase 13 | G85: Fase 11 (modelo viável) e esta Fase 12 (produto amado), deveria ser Fase 12 e Fase 13 | I85: corrigido | J85: 4 | K85: 1394 | L85: a Fase 12 valida *modelo viável* e a Fase 13 valida *produto amado pelo mercado (PMF)*. | N85: Números certos. A mesma frase diz que os quatro cenários estão no fim da Fase 11, mas eles vêm logo abaixo, na Fase 12. | O85: Corrigido
A86: DA-261 | B86: Exemplo do mapa da v5.0 | C86: 4 | D86: 3331 | E86: Mapa por volume | F86: Vol. 4: fórmulas de NRR e ICE erradas | G86: Vol. 4: fórmulas de NRR e ICE erradas | I86: corrigido | J86: 4 | K86: 2424 | L86: ICE = Impact × Confidence × Ease (produto simples das três notas de 1 a 10 | N86: O ICE deixou de dividir o produto por 3 e o NRR (l. 5279) segue a fórmula padrão. O exemplo de expansão que contradizia a regra do NRR saiu. | O86: Corrigido
A87: DA-102 | B87: Exemplo do mapa da v5.0 | C87: 4 | D87: 4129 | E87: Estrutura e navegação > Remissões com numeração antiga | F87: Customer Journey Canvas na Fase 4 (pesquisa), cópia do Vol. 4 | G87: Customer Journey Canvas na Fase 4 (pesquisa), cópia do Vol. 4 | I87: corrigido | J87: 2 | K87: 3014 | L87: Use o Customer Journey Canvas nesta Fase 5 como entregável central | N87: A cópia do Vol. 4 saiu. A casa única tem a fase certa (ver o erro novo de capítulo na mesma linha). | O87: Corrigido
A88: DA-127 | B88: Exemplo do mapa da v5.0 | C88: 4 | D88: 4698 | E88: Consistência entre volumes > Erros copiados entre volumes | F88: Magic Number multiplica por 4 um ARR que já é anual (Vol. 4) | G88: Magic Number multiplica por 4 um ARR que já é anual (Vol. 4) | I88: corrigido | J88: 4 | K88: 3343 | L88: **Magic Number:** ARR novo líquido adicionado no trimestre ÷ Gasto de Vendas e Marketing (S&M) do trimestre anterior | N88: Fórmula certa nas l. 1431 e 3343. A l. 5489 ainda divide pelo S&M do mesmo período, sem defasagem, e usa número por extenso. | O88: Corrigido
A89: DA-027 | B89: Exemplo do mapa da v5.0 | C89: 4 | D89: 5732 | E89: Vícios de escrita | F89: Pergunta com resposta: Essa fórmula parece simples. Não é. | G89: Pergunta com resposta: Essa fórmula parece simples. Não é. | I89: corrigido com erro novo | J89: 4 | K89: 4174 | L89: A estrutura da frase parece simples, mas cada palavra obriga uma renúncia estratégica. Cada escolha de palavra tem implicações estratégicas. | N89: A pergunta com resposta saiu, mas a frase nova repete a seguinte quase palavra por palavra, sinal de remendo sem releitura. | O89: Corrigido
A90: DA-026 | B90: Exemplo do mapa da v5.0 | C90: 4 | D90: 7627 | E90: Vícios de escrita | F90: Glosa automática: valuation (avaliação de valor) | G90: Glosa automática: valuation (avaliação de valor) | I90: corrigido | J90: 4 | K90: 5648 | L90: parceria estratégica, contrato B2B e *valuation* em M&A | N90: A glosa saiu e o termo ficou em itálico. A antítese A questão não é se você vai negociar, é se vai negociar bem continua no fim do parágrafo. | O90: Corrigido
... A129: DA-174 | B129: Exemplo do mapa da v5.0 | C129: 6 | D129: 5186 | E129: Conteúdo e precisão > Regras que o leitor vai aplicar | F129: Estorno da comissão quando o cliente cancela (Vol. 4 e Vol. 6) | G129: Estorno da comissão quando o cliente cancela (Vol. 4 e Vol. 6) | I129: corrigido em parte | J129: 6 | K129: 3864 | L129: pagar 100% da comissão ao vendedor no ato da assinatura sem cláusula de estorno (*clawback*) ou gatilho de ativação incentiva o fechamento de clientes fora de perfil | N129: A regra da Lei 3.207 aparece no Vol. 4 (l. 4853) e no Vol. 6 (l. 3910, 3934 e 6359). A lista de armadilhas de RevOps ainda recomenda clawback sem a ressalva para CLT. | O129: Corrigido
A130: DA-106 | B130: Exemplo do mapa da v5.0 | C130: 6 | D130: 5911 | E130: Estrutura e navegação > Remissões com numeração antiga | F130: Conecta-se à Fase 5 (modelo de negócio), deveria ser Fase 12 | G130: Conecta-se à Fase 5 (modelo de negócio), deveria ser Fase 12 | I130: trecho removido | N130: O parágrafo de abertura do antigo Cap. 5 (parcerias com grandes corporações) saiu na fusão. O Vol. 6 não cita mais a Fase 5 nesse sentido. | O130: Corrigido
A131: DA-206 | B131: Exemplo do mapa da v5.0 | C131: 6 | D131: 6776 | E131: Conteúdo e precisão > Casos, pessoas e livros | F131: Fundadores trocados: Loggi | G131: Fundadores trocados: Loggi | I131: corrigido | J131: 6 | K131: 5185 | L131: Fabien Mendez e Arthur Debert (cofundadores da Loggi em 2013) | N131: Fundadores certos. | O131: Corrigido
A132: DA-036 | B132: Exemplo do mapa da v5.0 | C132: 6 | D132: 7214 | E132: Narrativa > Promessas da Nota do autor | F132: Título que promete L10, Rocks e IDS sem ensinar (Vol. 6, Cap. 12) | G132: Título que promete L10, Rocks e IDS sem ensinar (Vol. 6, Cap. 12) | I132: corrigido | J132: 6 | K132: 5515 | L132: **Reunião semanal de liderança no formato L10 (*Level 10 Meeting*, do sistema EOS detalhado no Volume 7):** reúne o CEO e seus seis a oito liderados diretos por 90 minutos em horário fixo | N132: O capítulo foi fundido ao novo Cap. 8 e agora ensina os sete blocos da L10, com Rocks e IDS. A remissão ao EOS detalhado no Volume 7 não foi conferida. | O132: Corrigido
A133: DA-230 | B133: Exemplo do mapa da v5.0 | C133: 6 | D133: 7517 | E133: Conteúdo e precisão > Capítulos que se dizem atuais | F133: Outros avisos de abril ou maio de 2026 (Vol. 5, l. 2226, Vol. 6, l. 7517, Vol. 8, l. 1838, Vol. 9, l. 4120, Vol. 10, l. 2881 e 6513) | G133: Outros avisos de abril ou maio de 2026 (Vol. 5, l. 2226, Vol. 6, l. 7517, Vol. 8, l. 1838, Vol. 9, l. 4120, Vol. 10, l. 2881 e 6513) | I133: corrigido em parte | J133: 6 | K133: 7523 | L133: (ferramentas e referências legais conferidas em abril de 2026) | N133: Os seis avisos listados passaram a outubro de 2026 (ex.: Vol. 5, l. 2018, Vol. 6, l. 5666, Vol. 9, l. 2572, Vol. 10, l. 2897 e 6676). Sobra um aviso de abril de 2026 no capítulo de trabalho remoto. | O133: Corrigido
A134: DA-263 | B134: Exemplo do mapa da v5.0 | C134: 6 | D134: 7564 | E134: Mapa por volume | F134: Vol. 6: título que promete Topgrading | G134: Vol. 6: título que promete Topgrading | I134: corrigido | J134: 6 | K134: 5685 | L134: ### O método Who e Topgrading (ver Fase 16) | N134: O Cap. 9 remete ao framework ensinado na Fase 16 (l. 1631). | O134: Corrigido
A135: DA-137 | B135: Exemplo do mapa da v5.0 | C135: 6 | D135: 7626 | E135: Consistência entre volumes > Erros copiados entre volumes | F135: Bônus atrelado a OKR recomendado e condenado no mesmo Vol. 6 | G135: Bônus atrelado a OKR recomendado e condenado no mesmo Vol. 6 | I135: corrigido | J135: 6 | K135: 5747 | L135: mantendo os OKRs estratégicos desacoplados da fórmula de bônus para evitar conservadorismo deliberado | N135: Uma posição só no Vol. 6 (l. 5560, 5747 e 5962), seguida pelo Vol. 7. | O135: Corrigido
A136: DA-192 | B136: Exemplo do mapa da v5.0 | C136: 6 | D136: 7655 | E136: Conteúdo e precisão > Casos, pessoas e livros | F136: Nubank como Delaware C-corp (Vol. 6) | G136: Nubank como Delaware C-corp (Vol. 6) | I136: corrigido | J136: 6 | K136: 5776 | L136: participação societária relevante atrelada à holding listada na NYSE (Nu Holdings Ltd., constituída nas Ilhas Cayman) | N136: Sede certa. | O136: Corrigido
A137: DA-141 | B137: Exemplo do mapa da v5.0 | C137: 7 | E137: Consistência entre volumes > Réguas que mudam dentro do volume | F137: OKR com revisão quinzenal, mensal ou semanal, teto de 3 ou 5 objetivos e zona-alvo de 0,6 a 0,7 ou de 0,7 a 0,9 (Vol. 7, Fase 17) | G137: OKR com revisão quinzenal, mensal ou semanal, teto de 3 ou 5 objetivos e zona-alvo de 0,6 a 0,7 ou de 0,7 a 0,9 (Vol. 7, Fase 17) | I137: corrigido | J137: 7 | K137: 1570 | L137: Trabalhe com 3 a 5 objetivos por ciclo (quanto menor o time, mais perto de 3) | N137: Check-in semanal, 3 a 5 objetivos e 0,6 a 0,7 para OKR aspiracional em toda a Fase 17. A faixa de 0,7 a 0,9 sumiu. | O137: Corrigido
A138: DA-142 | B138: Exemplo do mapa da v5.0 | C138: 7 | E138: Consistência entre volumes > Réguas que mudam dentro do volume | F138: Severidade de incidente em três escalas: P1 a P3, P0 a P2 e SEV-1 a SEV-4 (Vol. 7) | G138: Severidade de incidente em três escalas: P1 a P3, P0 a P2 e SEV-1 a SEV-4 (Vol. 7) | I138: corrigido | J138: 7 | K138: 1491 | L138: **Severidade (escala única do volume):** `[ ] P0: crítico (serviço indisponível) [ ] P1: alto (degradação severa) [ ] P2: médio (impacto parcial com contorno)` | N138: O Vol. 7 declara P0 a P2 como escala única e a usa nas l. 281, 4464 e 5290. SEV só aparece no título da matriz. | O138: Corrigido
A139: DA-107 | B139: Exemplo do mapa da v5.0 | C139: 7 | D139: 1850 | E139: Estrutura e navegação > Remissões com numeração antiga | F139: Team Canvas na Fase 14 (escala e time), cópia do Vol. 7 | G139: Team Canvas na Fase 14 (escala e time), cópia do Vol. 7 | I139: corrigido | J139: 1 | K139: 945 | L139: Volte a ele na Fase 16, ao montar a liderança ou ao montar equipe de liderança expandida. | N139: A cópia do Vol. 7 saiu. | O139: Corrigido
A140: DA-143 | B140: Exemplo do mapa da v5.0 | C140: 7 | D140: 3126 | E140: Consistência entre volumes > Réguas que mudam dentro do volume | F140: Três réguas de nível de carreira e salários de Staff e Principal que diferem por um fator de dois (Vol. 7) | G140: Três réguas de nível de carreira e salários de Staff e Principal que diferem por um fator de dois (Vol. 7) | I140: corrigido em parte | J140: 7 | K140: 2526 | L140: Nível Staff (L5): de R$ 22 mil a R$ 38 mil mensais em startups SaaS de porte médio (chegando à faixa de R$ 40 mil a R$ 80 mil CLT | N140: As faixas foram ligadas entre si (porte médio contra Série B+) com remissão à tabela do Cap. 4. Mas o Cap. 4 (l. 2710) diz que a Série B+ paga 30% a 50% acima, e a faixa citada é cerca do dobro. | O140: Corrigido
A141: DA-025 | B141: Exemplo do mapa da v5.0 | C141: 7 | D141: 3270 | E141: Vícios de escrita | F141: Glosa automática: career ladders (trilhas de carreira), levels (níveis), performance reviews (avaliações de desempenho) | G141: Glosa automática: career ladders (trilhas de carreira), levels (níveis), performance reviews (avaliações de desempenho) | I141: corrigido em parte | J141: 7 | K141: 2663 | L141: Inclui trilhas de carreira, níveis de senioridade, avaliações de desempenho, desenho organizacional | N141: As três glosas do exemplo viraram português. O mesmo parágrafo ainda glosa Engineering Management, IC, chapters, squads, headcount e Developer Experience. | O141: Corrigido
A142: DA-037 | B142: Exemplo do mapa da v5.0 | C142: 7 | D142: 3611 | E142: Narrativa > Promessas da Nota do autor | F142: Título que promete Strangler Fig sem ensinar (Vol. 7) | G142: Título que promete Strangler Fig sem ensinar (Vol. 7) | I142: trecho removido | N142: O antigo Cap. 5 (dívida técnica) foi fundido e a expressão Strangler Fig não aparece mais na v5.2. A promessa sumiu junto com o título. | O142: Corrigido
A143: DA-049 | B143: Exemplo do mapa da v5.0 | C143: 7 | D143: 3702 | E143: Narrativa > Arquétipos | F143: Lucas tem 40 desenvolvedores em janeiro de 2026 (Vol. 7) | G143: Lucas tem 40 desenvolvedores em janeiro de 2026 (Vol. 7) | I143: persiste | J143: 7 | K143: 3039 | L143: Em janeiro de 2026, Lucas decidiu liberar irrestritamente agentes autônomos de geração de código para todos os quarenta desenvolvedores da sua scaleup | N143: Cena igual. O Vol. 9 (l. 536 e 589) ainda dá à mesma empresa R$ 120 milhões de ARR em 2026, enquanto o Vol. 1 a mostra começando hoje. | O143: Corrigido
A144: DA-227 | B144: Exemplo do mapa da v5.0 | C144: 7 | D144: 3739 | E144: Conteúdo e precisão > Capítulos que se dizem atuais | F144: Windsurf como alternativa aberta, quando foi vendido à Cognition em julho de 2025 (Vol. 7) | G144: Windsurf como alternativa aberta, quando foi vendido à Cognition em julho de 2025 (Vol. 7) | I144: corrigido | J144: 7 | K144: 3076 | L144: Windsurf (antiga Codeium, adquirida pela Cognition em julho de 2025). IDE comercial com fluxos agênticos integrados. | N144: Dono e natureza comercial certos. | O144: Corrigido
A145: DA-175 | B145: Exemplo do mapa da v5.0 | C145: 7 | D145: 4742 | E145: Conteúdo e precisão > Regras que o leitor vai aplicar | F145: Teletrabalho sem controle de jornada se o contrato prevê autonomia de horário | G145: Teletrabalho sem controle de jornada se o contrato prevê autonomia de horário | I145: corrigido com erro novo | J145: 7 | K145: 4087 | L145: apenas o teletrabalho contratado por produção ou por tarefa fica dispensado de marcação de ponto | N145: Regra certa. A mesma frase remete a Volume 6, Capítulo 20, número antigo: o capítulo de trabalho remoto hoje é o 15. | O145: Corrigido
A146: DA-241 | B146: Exemplo do mapa da v5.0 | C146: 7 | D146: 5413 | E146: Conteúdo e precisão > Conselho arriscado sem ressalva | F146: Demissão em massa sem a intervenção sindical prévia exigida pelo STF (Vols. 6, 7 e 9) | G146: Demissão em massa sem a intervenção sindical prévia exigida pelo STF (Vols. 6, 7 e 9) | I146: corrigido com erro novo | J146: 6 | K146: 5131 | L146: cumpra a exigência do STF (Tema 638, RE 999.435) de intervenção sindical prévia em dispensas coletivas (ver Volume 8, Capítulo 7) | N146: O Tema 638 entrou nos três volumes (Vol. 7, l. 4759, Vol. 9, l. 3009 e 3463). A remissão do Vol. 6 aponta para o Cap. 7 do Vol. 8, que hoje é direito do consumidor. | O146: Corrigido
A147: DA-265 | B147: Exemplo do mapa da v5.0 | C147: 8 | E147: Mapa por volume | F147: Vol. 8: decreto anticorrupção desatualizado | G147: Vol. 8: decreto anticorrupção desatualizado | I147: corrigido | J147: 8 | K147: 4452 | L147: O **Decreto 11.129/2022** (que regulamentou a Lei 12.846/2013 e revogou o antigo Decreto 8.420/2015) | N147: A mesma linha ainda fala em Ministério da Transparência ao lado da CGU. | O147: Corrigido
A148: DA-190 | B148: Exemplo do mapa da v5.0 | C148: 8 | D148: 107 | E148: Conteúdo e precisão > Casos, pessoas e livros | F148: Conta Azul como negócio construído sem VC (Vol. 8) | G148: Conta Azul como negócio construído sem VC (Vol. 8) | I148: corrigido | J148: 8 | K148: 100 | L148: enquanto RD Station e Conta Azul escalaram com várias rodadas de venture capital antes de suas saídas | N148: A frase agora fala em saídas das duas empresas, afirmação nova a conferir. | O148: Corrigido
A149: DA-239 | B149: Exemplo do mapa da v5.0 | C149: 8 | D149: 306 | E149: Conteúdo e precisão > Conselho arriscado sem ressalva | F149: Pejotização como modelo no caso da Fase 18 (Vol. 8) | G149: Pejotização como modelo no caso da Fase 18 (Vol. 8) | I149: corrigido | J149: 8 | K149: 288 | L149: Contratação CLT para os colaboradores com rotina fixa, subordinação e dedicação contínua, reservando contrato PJ exclusivamente para prestadores eventuais com autonomia real | N149: O caso agora recomenda CLT para quem tem subordinação. O Vol. 5 (l. 2638) cita o Tema 1.389 do STF. | O149: Corrigido
A150: DA-166 | B150: Exemplo do mapa da v5.0 | C150: 8 | D150: 1120 | E150: Conteúdo e precisão > Regras que o leitor vai aplicar | F150: COCP com prazo de sete anos e isenção de IOF, sigla repetida 42 vezes em cinco volumes | G150: COCP com prazo de sete anos e isenção de IOF, sigla repetida 42 vezes em cinco volumes | I150: corrigido em parte | J150: 8 | K150: 447 | L150: distingue dois contratos de opção que o mercado por vezes agrupa informalmente sob a sigla "COCP" | N150: Prazo de sete anos e isenção de IOF saíram, e o Vol. 8 explica a sigla como informal. Ela ainda aparece 28 vezes, e o Vol. 5 (l. 6400) e o Vol. 10 (glossário l. 9516, legislação l. 10684) a tratam como instrumento da LC 182. | O150: Corrigido
A151: DA-152 | B151: Exemplo do mapa da v5.0 | C151: 8 | D151: 1141 | E151: Consistência entre volumes > Fases na numeração antiga | F151: Vol. 8: o Cap. 1 manda estruturar antes da primeira captação, mas a Fase 18 vem depois da Fase 14. Pedido: portão jurídico mínimo antes da Fase 14 | G151: Vol. 8: o Cap. 1 manda estruturar antes da primeira captação, mas a Fase 18 vem depois da Fase 14. Pedido: portão jurídico mínimo antes da Fase 14 | I151: corrigido em parte | J151: 4 | K151: 2105 | L151: Prossiga para a Fase 14 (capital para escala, Vol. 5) e a Fase 15 (máquina de crescimento, Vol. 6), conduzindo a Fase 18 (estruturação jurídica, Vol. 8) em paralelo. | N151: A saída da Fase 13 manda tocar a Fase 18 em paralelo, e o data room do Vol. 5 cobra cessão de PI e vesting. Não há portão jurídico mínimo com acordo de sócios, vesting, PI e cap table antes da Fase 14. | O151: Corrigido
A152: DA-167 | B152: Exemplo do mapa da v5.0 | C152: 8 | D152: 1354 | E152: Conteúdo e precisão > Regras que o leitor vai aplicar | F152: Venda para o governo: dispensa de até R$ 1,6 milhão pelos arts. 20 e 30 da LC 182 e limite geral de R$ 57,5 mil | G152: Venda para o governo: dispensa de até R$ 1,6 milhão pelos arts. 20 e 30 da LC 182 e limite geral de R$ 57,5 mil | I152: corrigido | J152: 8 | K152: 647 | L152: não se confundindo com a dispensa geral por valor da Nova Lei de Licitações (que em 2026 é de R$ 65.492,11 para compras e serviços comuns | N152: CPSI como licitação especial (arts. 13 a 15) no Vol. 4 (l. 4912), Vol. 8 (l. 424 e 644) e Vol. 10 (l. 2100 e 6731). | O152: Corrigido
A153: DA-264 | B153: Exemplo do mapa da v5.0 | C153: 8 | D153: 1556 | E153: Mapa por volume | F153: Vol. 8: temas do STJ trocados | G153: Vol. 8: temas do STJ trocados | I153: corrigido | J153: 8 | K153: 828 | L153: não responde pela execução fiscal (Tema 962/STJ), mas definiu no Tema 981/STJ que o redirecionamento alcança quem detinha poderes de administração | N153: Os dois temas agora dizem o que decidiram, e o Tema 1.226 entrou para stock options (l. 665). | O153: Corrigido
A154: DA-108 | B154: Exemplo do mapa da v5.0 | C154: 8 | D154: 1807 | E154: Estrutura e navegação > Remissões com numeração antiga | F154: Fase 1 (constituição) com link para a Fase 1, deveria ser Fase 18 | G154: Fase 1 (constituição) com link para a Fase 1, deveria ser Fase 18 | I154: trecho removido | N154: A seção Relação com outros capítulos e fases do Cap. 2 do Vol. 8 saiu inteira. | O154: Corrigido
A155: DA-176 | B155: Exemplo do mapa da v5.0 | C155: 8 | D155: 1906 | E155: Conteúdo e precisão > Regras que o leitor vai aplicar | F155: Registro de marca declaratório | G155: Registro de marca declaratório | I155: corrigido | J155: 8 | K155: 1143 | L155: O sistema brasileiro de marcas é **atributivo** (art. 129 da LPI) | N155: Com a precedência do usuário anterior de boa-fé. | O155: Corrigido
A156: DA-177 | B156: Exemplo do mapa da v5.0 | C156: 8 | D156: 2059 | E156: Conteúdo e precisão > Regras que o leitor vai aplicar | F156: Código do freelancer sem cessão fica com ele | G156: Código do freelancer sem cessão fica com ele | I156: corrigido em parte | J156: 8 | K156: 1302 | L156: o art. 4º da Lei do Software (Lei 9.609/1998) atribui os direitos ao contratante salvo estipulação em contrário | N156: A regra entrou, mas o parágrafo ainda abre com Aqui não há proteção automática e a l. 1105 diz que a startup pode perder a titularidade do código. | O156: Corrigido
A157: DA-171 | B157: Exemplo do mapa da v5.0 | C157: 8 | D157: 2775 | E157: Conteúdo e precisão > Regras que o leitor vai aplicar | F157: Incidente de dados em prazo razoável ou 72 horas (Vol. 8) | G157: Incidente de dados em prazo razoável ou 72 horas (Vol. 8) | I157: corrigido com erro novo | J157: 8 | K157: 4637 | L157: #### Incidente de dados: notificação obrigatória em 72 horas | N157: O texto adota três dias úteis da Res. CD/ANPD 15/2024 em vários pontos, mas o título da l. 4637 diz 72 horas, a tabela LGPD contra GDPR (l. 1837) ainda fala em prazo razoável e a l. 1829 pede aviso em 24 a 48 horas e chama 72 horas de padrão. | O157: Corrigido
A158: DA-173 | B158: Exemplo do mapa da v5.0 | C158: 8 | D158: 3293 | E158: Conteúdo e precisão > Regras que o leitor vai aplicar | F158: Prazos e multas trabalhistas: FGTS e folha até o dia 7, multa de R$ 402,53 a R$ 805,06, aviso de 33 dias com dois anos | G158: Prazos e multas trabalhistas: FGTS e folha até o dia 7, multa de R$ 402,53 a R$ 805,06, aviso de 33 dias com dois anos | I158: corrigido | J158: 8 | K158: 2381 | L158: multa de R$ 3.000,00 por empregado não registrado, reduzida para R$ 800,00 para microempresa ou empresa de pequeno porte | N158: FGTS Digital até o dia 20 (l. 2478), eSocial até o dia 15 (l. 2375) e aviso de 36 dias com dois anos (l. 2539). | O158: Corrigido
A159: DA-219 | B159: Exemplo do mapa da v5.0 | C159: 8 | D159: 3566 | E159: Conteúdo e precisão > Casos, pessoas e livros | F159: SEPROSC no lugar do Seprosp (Vol. 8) | G159: SEPROSC no lugar do Seprosp (Vol. 8) | I159: corrigido em parte | J159: 8 | K159: 2654 | L159: cada estado tem entidades próprias (ex: SEPROSC-SP, SINDPD-SP, SETI-MG). | N159: A l. 2652 agora usa SEPROSP para São Paulo e põe o SEPROSC em Santa Catarina. Duas linhas abaixo sobra SEPROSC-SP. | O159: Corrigido
A160: DA-218 | B160: Exemplo do mapa da v5.0 | C160: 8 | D160: 4199 | E160: Conteúdo e precisão > Casos, pessoas e livros | F160: CNDM como conselho de mediação e arbitragem (Vol. 8) | G160: CNDM como conselho de mediação e arbitragem (Vol. 8) | I160: persiste | J160: 8 | K160: 3209 | L160: Câmaras como CNDM relatam taxa de sucesso de 60 a 70 por cento em disputas contratuais. | N160: A sigla errada continua. O Conima aparece mais adiante (l. 3296). | O160: Corrigido
A161: DA-109 | B161: Exemplo do mapa da v5.0 | C161: 8 | D161: 4445 | E161: Estrutura e navegação > Remissões com numeração antiga | F161: Conecta-se à Fase 5 (estrutura jurídica), deveria ser Fase 18 | G161: Conecta-se à Fase 5 (estrutura jurídica), deveria ser Fase 18 | I161: persiste | J161: 8 | K161: 3542 | L161: Ele se conecta à Fase 5 (estrutura jurídica), ao Capítulo 4 (Vol. 5) (Planejamento Financeiro (FP&A), Orçamento e Revenue Forecasting) (compliance trabalhista) | N161: Fase 5 continua. Os capítulos citados na mesma frase foram renumerados, mas o tema entre parênteses não bate: FP&A para compliance trabalhista, Compensação para planejamento tributário. | O161: Corrigido
A162: DA-229 | B162: Exemplo do mapa da v5.0 | C162: 8 | D162: 4871 | E162: Conteúdo e precisão > Capítulos que se dizem atuais | F162: PL 2338/2023 aguardando o plenário do Senado (Vol. 8) | G162: PL 2338/2023 aguardando o plenário do Senado (Vol. 8) | I162: corrigido | J162: 8 | K162: 3891 | L162: que foi **aprovado pelo Plenário do Senado Federal em dezembro de 2024** e remetido à Câmara dos Deputados | N162: Situação certa no Vol. 8 e também nos Vols. 4 (l. 7066) e 10 (l. 8565). | O162: Corrigido
A163: DA-110 | B163: Exemplo do mapa da v5.0 | C163: 9 | D163: 259 | E163: Estrutura e navegação > Remissões com numeração antiga | F163: O que pivot significa em Fase 15 (vs. Fase 6-9), deveria ser Fase 19 | G163: O que pivot significa em Fase 15 (vs. Fase 6-9), deveria ser Fase 19 | I163: corrigido | J163: 9 | K163: 237 | L163: **O que pivô significa na Fase 19 (em comparação às Fases 8 a 12).** | N163: Fase 19 certa e a faixa antiga 6-9 revista para 8 a 12. | O163: Corrigido
A164: DA-221 | B164: Exemplo do mapa da v5.0 | C164: 9 | D164: 337 | E164: Conteúdo e precisão > Casos, pessoas e livros | F164: E-commerce brasileiro de R$ 100 bilhões em 2015 (Vol. 9) | G164: E-commerce brasileiro de R$ 100 bilhões em 2015 (Vol. 9) | I164: corrigido | J164: 9 | K164: 315 | L164: Mercado de e-commerce BR (~R$ 41,3 bi em 2015, segundo Ebit/Webshoppers, em forte expansão) | N164: Número e fonte certos. | O164: Corrigido
...

Sheet Checagem
A1: ID | B1: Tema | C1: Volume | D1: Linha | E1: Trecho citado | F1: Desconfiança do revisor | G1: Veredito | H1: O que vale em out/2026 | I1: Fonte | J1: Nota para a correção | K1: Status
A2: r2a-caso-020 | B2: Casos, pessoas e números | C2: 1 | D2: 167 | E2: encerra muito mais negócios na largada do que a escassez de boas ideias, quando na vida real a maioria morre porque o fundador quebrou emocional ou financeiramente seis meses antes | F2: O "quando" cola duas teses e desmente a primeira. A segunda ("a maioria morre porque o fundador quebrou") fica atribuída ao Sebrae, que não mede isso. | G2: parcialmente certo | H2: Os estudos do Sebrae-SP atribuem o fechamento a uma soma de fatores: falta de planejamento prévio, gestão fraca, comportamento empreendedor, economia, políticas públicas e problemas pessoais. Falta de capital aparece como dificuldade. Nenhum mede que a maioria morre porque o fundador quebrou. | I2: https://www.legisweb.com.br/noticia/?id=895 | J2: Fonte de 2010 sobre estudos do Sebrae-SP. Partir a frase: o dado do Sebrae numa, a leitura do autor noutra, sem 'quando' e sem negrito. Não achei estudo recente com outra conclusão. | K2: Corrigido
A3: r2a-caso-021 | B3: Casos, pessoas e números | C3: 1 | D3: 214 | E3: Retorno financeiro real, quando vem, vem em sete a doze. | F3: Frase truncada, sem a unidade. O prazo também não sai de Hamilton (2000), que achou renda menor mesmo depois de dez anos. | G3: erro confirmado | H3: Hamilton (2000) achou renda inicial menor e crescimento de renda menor que no emprego, com diferença mediana de 35% para quem está no negócio há 10 anos. O prazo de sete a doze anos não vem dele, e a frase do livro está truncada, sem 'anos'. | I3: https://profiles.wustl.edu/en/publications/does-entrepreneurship-pay-an-empirical-analysis-of-the-returns-to/ | J3: Dizer que a renda mediana segue 35% menor após dez anos (Hamilton) e marcar o prazo de sete a doze anos como estimativa do autor, com 'anos' no fim da frase. | K3: Corrigido
A4: r2a-caso-022 | B4: Casos, pessoas e números | C4: 1 | D4: 578 | E4: Em 2013, David Vélez era sócio da Sequoia Capital. | F4: Em 2013 Vélez já fundava o Nubank, e a l. 702 o chama de ex-Sequoia no mesmo ano. O cargo de sócio também é duvidoso. | G4: parcialmente certo | H4: Vélez passou por Morgan Stanley, Goldman Sachs e General Atlantic e chegou a sócio da Sequoia, que em 2011 o encarregou de abrir frente no Brasil, plano depois engavetado. Em 2013, aos 31 anos, ele cofundou o Nubank, e por isso não era mais da Sequoia naquele ano. | I4: https://en.wikipedia.org/wiki/David_V%C3%A9lez | J4: O cargo de sócio tem apoio na fonte, a data não. Texto sugerido: 'Em 2013, David Vélez, ex-sócio da Sequoia Capital...'. Alinhar com a l. 702 e incluir a General Atlantic. | K4: Corrigido
A5: r2a-caso-023 | B5: Casos, pessoas e números | C5: 1 | D5: 1441 | E5: A Kovi pegou o modelo americano de car sharing por aplicativo (Turo) e estreitou a wedge para o ICP específico que mais sofria com falta de carro | F5: Turo é aluguel entre pessoas. A Kovi aluga frota própria a motoristas de aplicativo, modelo mais perto de HyreCar ou Splend. A filiação ao Turo parece errada. Wedge e ICP sem tradução. | G5: erro confirmado | H5: A Kovi não faz car sharing entre pessoas, como a Turo. Ela aluga carros das montadoras em leasing e subloca a motoristas de aplicativo, modelo mais perto de HyreCar ou Splend. Em janeiro de 2025 foi comprada pela Moove, investida do Uber. | I5: https://braziljournal.com/moove-uma-investida-do-uber-compra-a-kovi/ | J5: Nenhuma fonte liga a Kovi à Turo. Texto sugerido: 'A Kovi adaptou o aluguel de carros para motoristas de aplicativo'. Citar a venda à Moove (2025). | K5: Corrigido
A6: r2a-caso-001 | B6: Casos, pessoas e números | C6: 1 | D6: 1449 | E6: tornou-se um dos primeiros negócios digitais relevantes do país (alcançando grande liquidez em 2009), e foi vendido para a Naspers anos depois | F6: A venda do controle do Buscapé à Naspers foi o próprio evento de liquidez de 2009 (cerca de US$ 342 milhões por 91%). 'Anos depois' está errado. O ano de fundação também pede checagem. | G6: erro confirmado | H6: A venda à Naspers foi o próprio evento de liquidez de 2009. Em 29/9/2009 a Naspers anunciou a compra de 91% do BuscaPé.com por US$ 342 milhões. Não houve venda 'anos depois'. | I6: https://www.lse.co.uk/rns/NPSN/acquisition-of-brazilian-e-commerce-operator-busca-dr2bzrbas19w1r9.html | J6: O comunicado diz que o grupo começou cerca de dez anos antes e que quatro fundadores seguiam na empresa, o que bate com 1999 e com os quatro nomes do livro. | K6: Corrigido
A7: r2a-juri-011 | B7: Jurídico | C7: 1 | D7: 2092 | E7: enquadra a oportunidade de produto em nove blocos: Users & Customers, Problems, Solutions Today, Solution Ideas, How Will Users Use Solution, Adoption Strategy, User Metrics, Business Challenges e Budget | F7: O Opportunity Canvas de Jeff Patton costuma ter dez áreas, com Business Benefits and Metrics, que falta aqui. Os nomes ficam todos em inglês. | G7: erro confirmado | H7: No site de Jeff Patton o Opportunity Canvas tem dez seções: ideia de solução, problemas, clientes e usuários, soluções atuais, desafios de negócio, o que os usuários farão para obter valor, métricas, estratégia de adoção, impacto no negócio e orçamento. | I7: https://jpattonassociates.com/opportunity-canvas | J7: Falta o bloco de impacto no negócio (benefícios e métricas). O artigo do site é de 9/9/2016, e o ano de 2014 citado no Vol. 3 não foi conferido. Traduzir os nomes. | K7: Corrigido
A8: r2a-caso-024 | B8: Casos, pessoas e números | C8: 1 | D8: 3264 | E8: Causa-raiz: **sujeira no ar do chão de fábrica**. Solução: filtro. | F8: No exemplo clássico de Taiichi Ohno, a causa é limalha que entrou na bomba de lubrificação porque faltava um filtro na bomba. "Sujeira no ar" distorce o caso. | G8: erro confirmado | H8: No exemplo de Ohno, o eixo da bomba se desgastou porque não havia filtro (strainer) na bomba e entrou limalha de metal. A causa-raiz é a falta do filtro na bomba, não sujeira no ar da fábrica. A solução é instalar o filtro. | I8: https://www.leanblog.org/2026/04/ohno-5-whys-actually-seven/ | J8: Ajustar também o 5º porquê (l. 3262): 'Não havia filtro na bomba e entrou limalha'. O exemplo é de O Sistema Toyota de Produção, de Taiichi Ohno. | K8: Corrigido
A9: r2a-caso-008 | B9: Casos, pessoas e números | C9: 1 | D9: 3719 | E9: havendo herdeiros necessários, a sucessão testamentária só alcança metade do patrimônio disponível | F9: Erro jurídico. Com herdeiros necessários, o testador dispõe da metade da herança (art. 1.789 do CC), e essa metade é a parte disponível. "Metade do disponível" seria um quarto. | G9: erro confirmado | H9: Pelo art. 1.789 do Código Civil, havendo herdeiros necessários, o testador só pode dispor da metade da herança. Essa metade é a parte disponível. A outra metade é a legítima. 'Metade do disponível' daria um quarto. | I9: https://www.peticoesonline.com.br/art-1789-cc | J9: Texto sugerido: 'o testamento só alcança a metade disponível da herança (art. 1.789 do CC)'. A frase da l. 3719 é longa e mistura sucessão, apuração de haveres e meação. Vale partir. | K9: Corrigido
A10: r2a-fina-006 | B10: Finanças e regulação | C10: 1 | D10: 3719 | E10: se você é casado ou vive em união estável sob comunhão parcial (regime legal padrão quando não há contrato escrito diferente), formalize desde cedo um contrato de convivência ou instrumento pré-nupcial | F10: Quem já é casado não faz pacto pré-nupcial. Precisa de alteração judicial do regime, como o próprio parágrafo diz depois. O conselho leva a um instrumento sem efeito. | G10: erro confirmado | H10: Pacto antenupcial só vale se feito antes do casamento. Quem já é casado só muda o regime por pedido judicial motivado de ambos os cônjuges (art. 1.639, § 2º, do CC), regra ainda vigente em agosto de 2025. Na união estável, o caminho é o contrato de convivência. | I10: https://ibdfam.org.br/artigos/2357/ | https://arpensp.org.br/artigo/37329 | J10: O Provimento 11/2025 do TJ/ES admite a mudança em cartório no ES, com validade discutida. A reforma do CC (PL 4/2025) não estava aprovada em 08/2025. Reescrever em três casos. | K10: Corrigido
A11: r2a-fina-019 | B11: Finanças e regulação | C11: 1 | D11: 3719 | E11: cabendo ao acordo de sócios regrar a apuração de haveres nas quotas societárias (art. 1.028 do Código Civil), bens adquiridos após o casamento | F11: O art. 1.028 trata da morte de sócio. Para o cônjuge que se separa vale o art. 1.027, e a apuração segue o art. 1.031 e o contrato social. A vírgula ainda emenda outra frase. | G11: erro confirmado | H11: O art. 1.028 do Código Civil trata da morte de sócio. Para o cônjuge que se separa vale o art. 1.027: ele não vira sócio nem exige logo sua parte na quota e só concorre aos lucros até a liquidação da sociedade. | I11: https://www.peticoesonline.com.br/art-1028-cc | J11: Art. 1.027 reaproveitado da base (r2v9-caso-009). Citar arts. 1.027 e 1.031 e partir a frase emendada em duas. | K11: Corrigido
A12: r2a-trib-005 | B12: Tributário e trabalhista | C12: 1 | D12: 3721 | E12: a partir de patrimônio líquido declarado de quinhentos mil a um milhão de reais, bancos grandes oferecem canal privado | F12: Private banking no Brasil costuma começar em alguns milhões de reais investidos (o recorte da ANBIMA seria de R$ 3 milhões, a conferir). R$ 500 mil a R$ 1 milhão é alta renda de varejo. | G12: erro confirmado | H12: Pela ANBIMA, o private banking reúne investidores com no mínimo R$ 3 milhões em ativos financeiros, conforme a política de cada instituição. De R$ 250 mil a R$ 1 milhão o cliente fica no varejo de alta renda (Personnalité, Prime, Estilo, Select). | I12: https://www.anbima.com.br/pt_br/imprensa/patrimonio-do-private-banking-avanca-8-1-no-ano.htm | J12: Recorte de comunicado de 2018, repetido com dados de 2022. Reaproveita r1-trib-003 da base para o Personnalité. Tirar 'private banking' do trecho dos R$ 500 mil a 1 milhão. | K12: Corrigido
A13: r2a-caso-025 | B13: Casos, pessoas e números | C13: 1 | D13: 3766 | E13: Segundo estudos de Noam Wasserman em Harvard (*The Founder's Dilemmas*), 65% dos fracassos de startups de alto potencial decorrem de problemas e conflitos de relacionamento no time fundador | F13: O 65% vem de pesquisa com investidores de Gorman e Sahlman (1989), citada por Wasserman, sobre problemas na gestão. A Fase 0 (l. 388) dá outra versão ("até 65%", 10 mil fundadores). | G13: parcialmente certo | H13: Wasserman cita os 65%, mas o dado não é dele. Vem de levantamento de um professor de Harvard com investidores de risco, publicado cerca de 25 anos antes, sobre por que startups de alto potencial falharam. Os 65% são 'problemas de pessoas': entre fundadores, com contratados e com terceiros. | I13: https://stvp.stanford.edu/wp-content/uploads/sites/3/2024/09/reasons-for-failure-in-high-potential-startups-transcript.pdf | J13: A transcrição grafa 'Bill Solomon', ao que tudo indica William Sahlman (Gorman e Sahlman, 1989). Uniformizar com a l. 388, onde os 10 mil fundadores são da base do próprio Wasserman. | K13: Corrigido
... A52: r2a-trib-017 | B52: Tributário e trabalhista | C52: 2 | D52: 3014 | E52: os pagamentos recorrentes via Pix Automático e as regras fiscais da reforma tributária (IBS, CBS e *split payment*) | F52: Em 2026, CBS e IBS estão em ano de teste e o split payment ainda não é obrigatório. Dizer que já mudaram a jornada em 2026 adianta o calendário. | G52: parcialmente certo | H52: Em 2026 a CBS (0,9%) e o IBS (0,1%) estão em fase de teste, e os campos na nota passaram a ser exigidos no regime regular a partir de agosto. O split payment só começa em 2027, opcional, gradual e só entre empresas, sem data para as fases seguintes. | I52: https://www.ibet.com.br/split-payment-comecara-em-2027-com-adesao-opcional-e-gradual/ | https://dock.tech/fluid/blog/banking/pix-automatico/ | J52: Calendário do split payment dado pela Receita em novembro de 2025. Pix Automático procede (lançado em 16/6/2025). Alíquotas de teste da base (r1-trib-013). Usar a redação do revisor. | K52: Corrigido
A53: r2a-fina-009 | B53: Finanças e regulação | C53: 2 | D53: 3035 | E53: Em 2017, o iFood mapeou a jornada de primeira compra para entender por que 40% dos novos cadastros não completavam pedido inicial. | F53: O título diz "reconstrução didática", mas o texto afirma como fato um estudo do iFood, 40% de abandono e três decisões. L1863 cita o caso como prova. Sem fonte. | G53: não verificável | H53: Não há fonte pública para um estudo do iFood de 2017 sobre a jornada de primeira compra, para os 40% de cadastros sem pedido nem para as três decisões citadas. | J53: Busca sem resultado. Escrever como hipótese e sem número, como sugere o revisor, e ajustar a L1863, que usa o caso como evidência. | K53: Corrigido
A54: r2a-trib-021 | B54: Tributário e trabalhista | C54: 2 | D54: 3043 | E54: Foto baixa qualidade, descrição inconsistente, preço sem ICMS visível | F54: Preço ao consumidor já inclui ICMS. Não é dor plausível de quem pede comida. | G54: erro confirmado | H54: O ICMS é calculado por dentro: o próprio imposto integra a base de cálculo e o destaque é mera indicação para controle (LC 87/1996, art. 13, § 1º, I). O preço do cardápio já inclui o ICMS, então 'preço sem ICMS visível' não é dor plausível de quem pede comida. | I54: https://www.legjur.com/legislacao/art/lec_00000871996-13 | https://www.legjur.com/legislacao/htm/lec_00000871996 | J54: A Lei Kandir vale até 2032 (revogada pela LC 214/2025, art. 543, com efeito em 1/1/2033). Usar a sugestão do revisor: preço final sem a taxa de entrega e de embalagem. | K54: Corrigido
A55: r2a-fina-003 | B55: Finanças e regulação | C55: 2 | D55: 3050 | E55: (1) adicionar débito em conta e boleto bancário como alternativas ao cartão recusado: formas de pagamento mais acessíveis para o ICP em 2017 | F55: Boleto compensa em até três dias úteis e não serve a pedido de comida entregue em 40 minutos. A tabela (L3045) recomenda Pix, que só existe desde novembro de 2020. | G55: erro confirmado | H55: O Pix só começou a operar em 16 de novembro de 2020, então não existia no caso de 2017. O boleto pode levar até três dias úteis para compensar e não serve a um pedido de comida entregue na hora. | I55: https://nossomeio.com.br/pix-comeca-a-funcionar-na-proxima-segunda-feira-16/ | https://dock.tech/fluid/blog/banking/bolepix/ | J55: Em 2017 cabem pagamento na entrega (dinheiro ou maquininha) e vale-refeição. Na tabela (L3045), tirar o Pix ou marcar a linha como recomendação de hoje. | K55: Corrigido
A56: r2a-fina-027 | B56: Finanças e regulação | C56: 2 | D56: 3381 | E56: ela trocou o jargão técnico sobre titânio no site por relatos de pacientes reais | F56: Publicidade odontológica segue o Código de Ética do CFO, que limita depoimentos e imagens de pacientes, e dado de saúde é sensível na LGPD. O conselho sai sem ressalva. | G56: parcialmente certo | H56: Usar casos de pacientes é possível, mas com regras. O CFO só admite imagem de diagnóstico e resultado com autorização prévia do paciente por TCLE, veda promessa de resultado e sensacionalismo, e o CROSP proíbe imagem de paciente em perfil de pessoa jurídica. | I56: https://website.cfo.org.br/wp-content/uploads/2019/01/Resolu%c3%a7%c3%a3o-CFO-196-2019.pdf | https://site.crosp.org.br/uploads/arquivo/3724579826b71ed53e3c7d0ff3104a64.pdf | J56: Resolução CFO-196/2019 e cartilha do CROSP. Nenhuma trata de depoimento escrito. Acrescentar: com autorização escrita de cada paciente, sem promessa de resultado e nas regras do CFO. | K56: Corrigido
A57: r2a-fina-028 | B57: Finanças e regulação | C57: 2 | D57: 3559 | E57: concentrado quando o líder detém ≥ 40% ou os quatro maiores somam ≥ 70%; moderado na faixa intermediária; e fragmentado quando os cinco maiores somam < 30%) | F57: Mistura CR4 e CR5 na mesma régua e diz que se inspira no guia do CADE, que hoje trabalha com HHI e não com esses cortes. Vale checar o Guia H de 2016. | G57: parcialmente certo | H57: O Guia H do CADE, lançado em julho de 2016, mede concentração pelo HHI: abaixo de 1.500 não concentrado, de 1.500 a 2.500 moderado e acima de 2.500 altamente concentrado, com atenção a variações acima de 100 pontos. Os cortes de 40%, 70% e 30% não são do CADE, e o CR4 é só métrica complementar. | I57: https://www.conversion.com.br/blog/indice-herfindahl-hirschman-hhi | https://www.conjur.com.br/2016-jul-28/guia-cade-explica-analise-atos-concentracao-horizontal//?print=1 | J57: Faixas de HHI por fonte secundária, o guia em cade.gov.br não foi aberto. Usar um índice só e não atribuir os cortes ao CADE. | K57: Corrigido
A58: r2f-nova-006 | B58: Afirmação nova da edição | C58: 2 | D58: 3699 | E58: Shopify começou como o sistema da própria loja online de snowboards dos fundadores (Snowdevil), resolvendo a dor de pequenos lojistas independentes antes de virar plataforma global de e-commerce. | F58: Afirmação nova que a v5.2 introduziu ao corrigir um achado antigo: A Shopify começou como o sistema da própria loja online de snowboards dos fundadores (Snowdevil), antes de virar plataforma global de e-commerce. | Nota do conferente: A frase sobre a OpenAI saiu e deu lugar à Shopify, nascida da loja de snowboards Snowdevil. A afirmação errada não se repete no livro, e o Vol. 3 (3849) trata a OpenAI de 2015 como laboratório. O caso Shopify é afirmação nova e vale conferir. | G58: correto no livro | H58: Em 2004, Tobias Lütke escreveu o próprio software para a loja online de snowboards Snowdevil, em Ottawa, porque as opções do mercado eram caras e ruins. Outros lojistas pediram para usá-lo e a Shopify foi lançada como plataforma em 2006. | I58: https://www.npr.org/2019/08/02/747660923/shopify-tobias-l-tke | J58: Pode datar: loja em 2004 e plataforma em 2006. | K58: Corrigido
A59: r2a-trib-018 | B59: Tributário e trabalhista | C59: 2 | D59: 4033 | E59: capturar clientes médios SP antes da entrada dos americanos (2026 é a janela). | F59: Prazo que envelhece mal: em outubro de 2026 a janela está fechando. Na l. 4021, a reforma tributária já passou da regulamentação básica (LC 214/2025) e está em transição. | G59: desatualizado | H59: A regulamentação básica da reforma já saiu: LC 214/2025 e LC 227, de 13/1/2026, segunda etapa, que criou o Comitê Gestor do IBS. Em outubro de 2026 a reforma está em transição, com CBS e IBS em teste desde janeiro. | I59: https://documentacao.senior.com.br/exigenciaslegais/noticias/federal/2026/2026-01-14-sancionada-segunda-etapa-da-regulamentacao-da-reforma-tributaria-e-criacao-do-comite-gestor-do-ibs | J59: A 'janela de 2026' é cenário do exemplo e não se confere, mas já venceu. Usar prazo relativo e trocar 'em fase de regulamentação' na l. 4021, como sugere o revisor. | K59: Corrigido
A60: r2a-caso-012 | B60: Casos, pessoas e números | C60: 2 | D60: 4141 | E60: U2, Distribuidora de medicamentos: atratividade média, posição alta → **Zona Amarela. Proteger posição.** | F60: Pela regra da própria seção, atratividade média com posição alta cai na zona verde. U3 (média e baixa) cai na vermelha, não na amarela. Dois dos cinco exemplos estão na zona errada. | G60: erro confirmado | H60: Pela regra da própria seção (verde nas 3 células de cima e da esquerda, vermelha nas 3 de baixo e da direita), atratividade média com posição alta cai na zona verde e atratividade média com posição baixa cai na vermelha. U2 e U3 estão na zona errada. | I60: IGNIÇÃO v5.2, Vol. 2, l. 4118 a 4122 | https://thinkinsights.net/strategy/ge-mckinsey-nine-box-matrix | J60: U2 vai para a Zona Verde (investir para crescer) e U3 para a Vermelha (colher ou sair). U1, U4 e U5 estão certas. A fonte externa põe média e alta em crescer e média e baixa em colher. | K60: Corrigido
A61: r2a-fina-029 | B61: Finanças e regulação | C61: 2 | D61: 4248 | E61: P: eleições 2026, mudança de presidência BCB, possível ajuste na Lei do Marco Legal das Garantias → MONITORAR. | F61: A troca na presidência do Banco Central já ocorreu em janeiro de 2025, com mandato até 2028. Em outubro de 2026 não há mudança no horizonte, e a eleição já está no segundo turno. | G61: erro confirmado | H61: Gabriel Galípolo preside o Banco Central desde 1º de janeiro de 2025, com mandato até 31 de dezembro de 2028. Não há troca na presidência do BC no horizonte de 2026. | I61: https://diariodocomercio.com.br/financas/galipolo-tem-nomeacao-publicada-diario-oficial/ | J61: Usar: resultado das eleições de 2026, composição da diretoria do BC e ajustes no Marco Legal das Garantias (Lei 14.711/2023), monitorar. | K61: Corrigido
A62: r2a-trib-022 | B62: Tributário e trabalhista | C62: 2 | D62: 4464 | E62: Solução de Moore, Bowling Alley Strategy: | F62: A pista de boliche vem de Inside the Tornado (1995). Crossing the Chasm (1991) usa a analogia do Dia D e da cabeça de praia. O boliche é atribuído ao Chasm também nas l. 3395 e 4701. | G62: parcialmente certo | H62: A pista de boliche é de Moore, mas nasceu em Inside the Tornado (1995). Crossing the Chasm (1991) usa a analogia do Dia D e da cabeça de praia, e só as edições revistas citam a reação em cadeia de pinos e resumem o modelo do Tornado em apêndice. | I62: https://www.strategy-business.com/article/16930?gko=5cb33 | https://www.supersummary.com/crossing-the-chasm/summary | J62: Conceito certo, obra e ano errados. Usar a redação do revisor e ajustar as l. 3395 e 4701, que põem o boliche no livro de 1991. | K62: Corrigido
A63: r2a-trib-019 | B63: Tributário e trabalhista | C63: 2 | D63: 4565 | E63: James Currier, Pete Flint, Gigi Levy-Weiss e Omri Atzmon, fundadores da firma de venture capital NFX | F63: A lista de fundadores da NFX merece checagem (Omri Atzmon não costuma constar). O parágrafo seguinte repete a mesma origem e a mesma contagem de 13 tipos. | G63: erro confirmado | H63: A NFX foi fundada em 2015 por James Currier, Stan Chudnovsky e Gigi Levy-Weiss. Pete Flint, cofundador da Trulia, entrou em dezembro de 2016 como sócio-gestor. Omri Atzmon não aparece entre fundadores nem sócios. | I63: https://www.geekwire.com/2017/traditional-vc-model-broken-software-infused-firm-just-raised-150m-fund-fix/ | https://techcrunch.com/2016/12/12/trulia-founder-pete-flint-is-now-a-vc-with-nfx-guild/ | J63: Confirma r1-juri-004 da base. Trocar por 'Currier, Levy-Weiss e Chudnovsky, fundadores, e Flint, sócio desde 2016'. Cortar a repetição da l. 4569. | K63: Corrigido
A64: r2a-trib-006 | B64: Tributário e trabalhista | C64: 2 | D64: 4585 | E64: | 13 | Market Network | Combina SaaS de fluxo de trabalho com rede profissional e marketplace | F64: Na lista da NFX, Market Network é efeito direto e vem logo depois de Personal, entre os mais fortes. Pô-lo em 13º, o mais fraco, inverte a fonte. | G64: erro confirmado | H64: No manual da NFX, Market Networks é o 5º tipo, classificado como efeito de rede direto, logo depois de Personal e antes de Hub-and-Spoke e Marketplace. A lista atual tem 16 tipos. | I64: https://nfx.com/post/network-effects-manual | J64: O manual não declara ordem estrita do mais forte ao mais fraco, só diz que os mais fortes ficam no centro do mapa. Mais seguro tirar a coluna 'Posição' e agrupar por família. | K64: Corrigido
A65: r2a-fina-010 | B65: Finanças e regulação | C65: 2 | D65: 4667 | E65: | Software de gestão integrada | Pouco | Stone Hub (PDV + gestão) | Create | | F65: Tabela de 2014 com detalhes que parecem anacrônicos ou inventados: Stone Hub, hardware próprio "sem comprar da Verifone" (l. 4679), "Ponto-de-Atenção", aluguel zero. | G65: erro confirmado | H65: No prospecto do IPO de 2018, Stone Hub é a rede de polos locais de venda e atendimento, perto dos clientes, e não software de PDV e gestão. O prospecto não cita Ponto-de-Atenção nem Stone Box. | I65: https://www.sec.gov/Archives/edgar/data/1745431/000119312518289511/d580263df1.htm | J65: Reaproveitado da base (r2v9-fina-020 e r1-fina-044). Hardware próprio e aluguel zero em 2014 não têm fonte. Marcar o que não estiver no F-1 como hipótese didática. | K65: Corrigido
... A83: r2a-fina-013 | B83: Finanças e regulação | C83: 3 | D83: 2493 | E83: Em 2022, a Hotmart já dominava infoprodutos médios e grandes (creators que vendiam cursos de R$ 300+ a milhares de alunos). Identificou uma oportunidade adjacente: | F83: O título avisa que é reconstrução hipotética e que o Sparkle real focava comunidades, mas o corpo narra como fato a estratégia da Hotmart e batiza o produto de "Hotmart Sparkle". | G83: erro confirmado | H83: O Sparkle real da Hotmart é um app de comunidades com assinaturas, lançado por volta de 2020, e não um checkout enxuto para microcreators. Não há fonte para a aposta de 2022 nem para os números do canvas. | I83: https://tecnoblog.net/responde/o-que-e-o-sparkle-a-volta-das-comunidades/ | J83: Reaproveitado da base (r1-fina-045). O canvas (L2502 e L2507) chama o produto de Hotmart Sparkle. Usar plataforma fictícia no corpo e no canvas. | K83: Corrigido
A84: r2a-fina-014 | B84: Finanças e regulação | C84: 3 | D84: 2588 | E84: A Wildlife Studios, fundada em São Paulo e um dos maiores estúdios de jogos para celular do mundo, testou em 2022 um novo mecanismo de monetização para seu jogo *Sniper 3D* | F84: O título diz "simulação didática com métricas hipotéticas", mas o corpo afirma que a Wildlife testou em 2022 e dá resultado (17% em D7) e decisão de expandir como fatos. | G84: não verificável | H84: Não há fonte pública para um teste de season pass da Wildlife Studios no Sniper 3D em 2022, nem para a conversão de 17% em D7 e a decisão de expandir. | J84: Reaproveitado da base (r1-juri-018 e r1-juri-019), busca anterior sem resultado. Usar estúdio fictício ou escrever tudo no condicional. | K84: Corrigido
A85: r2a-fina-015 | B85: Finanças e regulação | C85: 3 | D85: 2912 | E85: Antes de abrir a venda para todos, fizeram piloto com poucas empresas: como ilustração de validação enxuta no recrutamento corporativo | F85: Mesma mistura do caso PlayKids: título "caso real", frase que afirma o piloto, ressalva "como ilustração" no meio e resultado narrado como fato ("viraram primeiros cases"). | G85: não verificável | H85: A Gupy foi fundada em 2015 por Mariana Dias, Bruna Guimarães, Guilherme Dias e Robson Ventura, como diz o livro. Não há fonte pública para o piloto com cinco a oito empresas nem para os primeiros cases. | I85: https://forbes.com.br/forbes-tech/2022/01/os-proximos-passos-da-gupy-apos-meio-bilhao-em-aporte/ | J85: Fundação e sócios reaproveitados da base (r1-juri-006). Manter o fato público e escrever o piloto no condicional, sem o nome Gupy. | K85: Corrigido
A86: r2a-fina-016 | B86: Finanças e regulação | C86: 3 | D86: 3837 | E86: dez mil escritórios de advocacia imobiliária no país vezes R$ 12 mil de receita anual média vezes 15% de penetração, resultando em R$ 180 milhões de ARR potencial | F86: A conta dá R$ 18 milhões, não 180. Com R$ 18 milhões o Gate 3 reprova pelo critério do próprio capítulo (caminho para R$ 100 milhões de receita recorrente) e a decisão "prosseguir" cai. | G86: erro confirmado | H86: Dez mil escritórios vezes R$ 12 mil vezes 15% dão R$ 18 milhões de ARR, não R$ 180 milhões. Com R$ 18 milhões, o Gate 3 reprova pelo próprio corte do capítulo, que pede caminho para R$ 100 milhões de receita recorrente. | I86: cálculo próprio a partir de v03 L3837 e do critério do Gate 3 em v03 L3799 | J86: Ou corrigir os fatores para fechar R$ 180 milhões, ou manter R$ 18 milhões e mudar a decisão do Gate 3 para iterar ou matar, o que rende exemplo melhor. | K86: Corrigido
A87: r2a-fina-033 | B87: Finanças e regulação | C87: 3 | D87: 3939 | E87: A fonte típica é fomento público (FINEP, CNPq, Embrapii, e FAP estaduais) | F87: A EMBRAPII financia P&D com empresa parceira em maturidade intermediária (por volta de TRL 3 a 6), não pesquisa em TRL 1 a 3. Falta também o plural de "FAP". | G87: parcialmente certo | H87: A EMBRAPII financia projetos com empresa parceira cujas entregas ficam entre TRL 3 e TRL 6, cobrindo até um terço do valor com recurso não reembolsável. Não é fonte típica para pesquisa em TRL 1 a 3, ao contrário de CNPq e FAPs. | I87: https://wp.ufpel.edu.br/embrapii/?p=357 | J87: Fonte é página de uma unidade EMBRAPII (UFPel). Tirar a EMBRAPII da lista de TRL 1 a 3 e citá-la na faixa de TRL 4 a 6. Corrigir FAP estaduais para FAPs estaduais. | K87: Corrigido
A88: r2f-nova-022 | B88: Afirmação nova da edição | C88: 3 | D88: 3946 | E88: Já uma startup de biotech pode levar cinco anos de operação para avançar do TRL 3 (prova de conceito experimental em laboratório ou modelo animal) ao TRL 6, quando se iniciam os ensaios clínicos de Fase 1 em humanos | F88: Afirmação nova que a v5.2 introduziu ao corrigir um achado antigo: Na escala biomédica de TRL, os ensaios clínicos de Fase 2 e de Fase 3 correspondem aos TRLs 7 e 8, respectivamente. | Nota do conferente: A frase não está mais partida e põe a Fase 1 clínica no TRL 6, como a fonte. Mas acrescenta que as Fases 2 e 3 correspondem aos TRLs 7 e 8, e a referência põe as duas no TRL 7. Vale conferir. | G88: erro confirmado | H88: Na escala biomédica do Departamento de Defesa dos EUA, TRL 3 é prova de conceito em laboratório ou animal, TRL 6 é o ensaio clínico de Fase 1 e o TRL 7 cobre as Fases 2 e 3, sem dar um TRL próprio à Fase 3. | I88: https://cdmrp.health.mil/jwmrp/pdfs/Biomedical%20Product%20Guidelines.pdf | J88: Reaproveitado de r1-caso-015 (PDF bloqueado hoje). Trocar o parêntese por 'com as Fases 2 e 3 no TRL 7'. | K88: Corrigido
A89: r2f-nova-023 | B89: Afirmação nova da edição | C89: 3 | D89: 3960 | E89: | CRL 5 | Piloto pago em andamento com cliente real (equivalente à Fase 11, MVP em operação no Vol. 4; já o encerramento da Fase 10 corresponde ao CRL 4). | | F89: Afirmação nova que a v5.2 introduziu ao corrigir um achado antigo: O CRL (Commercial Readiness Level) deriva do KTH Innovation Readiness Level e foi adaptado por programas brasileiros como o Radar Petrobras, em escala de nove níveis. | Nota do conferente: Saiu o Fase 10/10 e o CRL 5 foi para a Fase 11 com piloto pago. Persistem o Fase 7/8 no CRL 3 (3:3958) e o CRL 4 posto na Fase 11 em curso (3:3959), contra o fim da Fase 10 dito em 3:3960. Erro novo: 3:3950 promete escala de 1 a 9, e a tabela para no | G89: parcialmente certo | H89: O KTH Innovation Readiness Level, da KTH Innovation (Suécia), tem seis dimensões de 1 a 9, e nele CRL quer dizer Customer Readiness Level, maturidade de cliente, não Commercial Readiness Level. Não achei adaptação do CRL pelo 'Radar Petrobras'. | I89: https://www.inside.dtu.dk/en/research/commercialisation-and-patenting/patents-and-software/kth-innovation-readiness-level | J89: Trocar o nome por Customer Readiness Level, tirar o Radar Petrobras sem fonte e completar a tabela até o CRL 9 (hoje para no 7). Persistem as fases trocadas nos CRL 3 a 5. | K89: Corrigido
A90: r2a-fina-034 | B90: Finanças e regulação | C90: 3 | D90: 4228 | E90: App Store (Apple, e Google Play). Quinze a trinta por cento de fee. | F90: Comissões e regras de pagamento externo das lojas mudaram desde 2024 (DMA na UE, Epic v. Apple nos EUA, processo da Apple no CADE). Também põe o Google Play dentro da App Store. | G90: desatualizado | H90: Desde 18 de junho de 2026, por acordo com o Cade de dezembro de 2025, a Apple permite no Brasil lojas alternativas e pagamento de terceiros. A comissão da App Store sobre bens digitais vai até 21%, cai a 10% para pequenas empresas e assinaturas após o 1º ano, e é de 5% para apps vendidos fora da loja. | I90: https://www.poder360.com.br/poder-tech/apple-libera-apps-de-lojas-rivais-e-pagamentos-externos-no-brasil/ | J90: Comissões do Google Play no Brasil não foram conferidas. Separar App Store e Google Play e datar: regras da Apple no Brasil a partir de junho de 2026. | K90: Corrigido
A91: r2a-fina-035 | B91: Finanças e regulação | C91: 3 | D91: 4417 | E91: Efeitos de rede não são uma coisa, são cinco coisas diferentes que operam de formas diferentes. | F91: Antítese que promete cinco tipos de efeito de rede e não lista nenhum. O livro de Chen organiza cinco etapas, não cinco tipos. Parece confusão entre as duas coisas. | G91: erro confirmado | H91: Em The Cold Start Problem, Chen organiza a vida de uma rede em cinco etapas (Cold Start, Tipping Point, Escape Velocity, Hitting the Ceiling e The Moat) e divide os efeitos de rede em três forças: aquisição, engajamento e economia. Não há cinco tipos de efeito de rede no livro. | I91: https://sachinrekhi.com/andrew-chen-the-cold-start-problem | J91: Fonte é resumo do livro. Trocar por: Chen divide a vida de uma rede em cinco etapas e os efeitos de rede em três forças. A L4413 já lista as etapas. | K91: Corrigido
A92: r2a-juri-013 | B92: Jurídico | C92: 3 | D92: 4423 | E92: A rede atômica (*Atomic Network*) consistia em concentrar dezenas de restaurantes de entrega rápida e consumidores num mesmo bairro paulistano antes de abrir a cidade inteira | F92: Detalhe operacional atribuído ao iFood sem fonte e apresentado como fato. Pede registro público do lançamento bairro a bairro. | G92: não verificável | H92: O iFood nasceu em 2011, ligado à Disk Cook, como guia impresso de cardápios com central telefônica, e em dois anos fazia quase 200 mil pedidos por mês. Nenhuma fonte aberta registra lançamento concentrado num bairro paulistano e replicado bairro a bairro. | I92: https://forbes.com.br/forbes-tech/2021/08/o-mundo-dos-unicornios-ifood/ | https://exame.com/pme/cardapio-ampliado/ | J92: Apresentar como leitura do método ('Visto pela lente de Chen...'), como sugere o revisor. Em 2011 os restaurantes já tinham entrega própria (base r1-fina-002). | K92: Corrigido
A93: r2a-juri-001 | B93: Jurídico | C93: 3 | D93: 4441 | E93: um único contrato corporativo habilitou 1.200 funcionários para triagem odontológica digital e atendimento preventivo na clínica, derrubando o custo de aquisição inicial para R$ 2,50 por vida cadastrada | F93: Mensalidade por vida com direito a atendimento odontológico pode configurar plano odontológico (Lei 9.656/1998, registro na ANS). O capítulo vende o modelo como saída sem ressalva. | G93: parcialmente certo | H93: A Lei 9.656/1998 sujeita à ANS a prestação continuada de serviços ou cobertura de custos assistenciais, inclusive odontológicos, a preço pré ou pós estabelecido (art. 1º, I e § 1º), e só operadora autorizada pode vender esse produto (art. 8º). Programa pago por vida para dar acesso a atendimento pode ser enquadrado como plano. | I93: https://www.planalto.gov.br/ccivil_03/leis/l9656.htm | J93: O caso não é falso, mas omite o risco. O enquadramento depende do contrato: cobrar por serviço prestado ou operar com operadora registrada reduz o risco. Normas do CFO não conferidas. | K93: Corrigido
A94: r2a-fina-004 | B94: Finanças e regulação | C94: 3 | D94: 4451 | E94: Hiandros e Evino vendem atacado para restaurantes e bares (B), que servem aos consumidores finais (C). | F94: A Evino é e-commerce de vinho para consumidor final, não atacadista de bares. "Hiandros" não parece empresa conhecida e pode ser nome inventado. | G94: erro confirmado | H94: A Evino, fundada em 2013, é e-commerce de vinhos que vende sobretudo ao consumidor final. Venda direta a restaurantes e hotéis vem da Grand Cru, importadora que a Evino comprou em 2021. Não há empresa conhecida chamada Hiandros. | I94: https://braziljournal.com/evino-compra-a-grand-cru-e-ja-fatura-r-700-mi | J94: Busca por Hiandros sem resultado. Para food service, usar a Grand Cru com fonte ou cortar a frase. | K94: Corrigido
A95: r2a-fina-036 | B95: Finanças e regulação | C95: 3 | D95: 4510 | E95: governança de subcredenciamento e BaaS endurecidas pelo BCB entre 2024 e 2026 | F95: Regra citada sem número de norma, numa frase de 90 palavras. O leitor não sabe que exigência mudou nem o que fazer com ela. | G95: correto no livro | H95: A Resolução Conjunta nº 16, de 28/11/2025 (CMN e BCB), regulou o BaaS: o prestador deve ser instituição autorizada, responde por KYC e PLD, só pode usar o tomador em tarefas acessórias e não se exime perante o BC. Contratos antigos devem se adequar até 31/12/2026. | I95: https://www.demarest.com.br/bc-e-cmn-regulamentam-banking-as-a-service/ | J95: Pix e IPs: Res. BCB 494, 496 e 498 de 2025 (base, r2v10-fina-016). Subcredenciamento não conferido. Citar as normas e partir a frase em três. | K95: Corrigido
A96: r2a-fina-037 | B96: Finanças e regulação | C96: 3 | D96: 4556 | E96: Escalar operações sem preparar compliance. Enterprise no Brasil exige SOC 2 e ISO. Sem isso, perde deals mesmo com produto competitivo. | F96: Generalização duvidosa. SOC 2 é padrão americano. Aqui pesam o questionário do comprador, a ISO 27001 e, em banco, a Resolução CMN 4.893. A linha 4513 chama o mesmo item de diferencial. | G96: parcialmente certo | H96: Nenhuma norma obriga o fornecedor a ter SOC 2 ou ISO. Bancos seguem a Resolução CMN 4.893/2021, alterada pela 5.274/2025, que exige diligência reforçada, cláusulas de auditoria e monitoramento de terceiros relevantes, com adequação até 1º/03/2026. Certificações ajudam a passar nessa avaliação. | I96: https://okai.com.br/artigo/nova-regulacao-de-seguranca-cibernetica-para-ifs-ips-e-outras-instituicoes | J96: Para IPs e corretoras vale a Res. BCB 85, alterada pela 538/2025. Usar a redação do revisor com a norma atualizada e cortar a repetição entre L4513 e L4556. | K96: Corrigido
... A370: r2c-trib-019 | B370: Tributário e trabalhista | C370: 8 | D370: 2948 | E370: ÍNDICE RA 1000 (metodologia pública do Reclame Aqui baseada em quatro indicadores: Índice de Resposta ≥ 90%, Índice de Solução ≥ 90%, Média das Avaliações dos consumidores ≥ 7,0 | F370: O cabeçalho cita os quatro indicadores do selo. A árvore logo abaixo lista cinco itens diferentes (tempo de resposta, reclamação que volta) com pesos sem fonte. Os blocos se contradizem. | G370: parcialmente certo | H370: O cabeçalho está certo. O RA1000 pede ao menos 50 reclamações avaliadas, mais de 90% respondidas e mais de 90% solucionadas, nota média de 7 ou mais e 70% ou mais de clientes que voltariam a fazer negócio. Tempo de resposta e reclamação que volta não estão entre os critérios. | I370: https://www.gwmmotors.com.br/pt/media-center/news/2025/gwm-conquista-selo-ra1000-e-reafirma-excelencia-no-atendimento-ao-cliente | J370: Fonte é notícia de empresa premiada (out. 2025), não a página do Reclame Aqui. A árvore com pesos não tem fonte. Apagar e deixar os critérios em lista. | K370: Corrigido
A371: r2c-caso-035 | B371: Casos, pessoas e números | C371: 8 | D371: 3008 | E371: **Casos relevantes no segmento de fintechs e e-commerces** | F371: Promete casos e entrega "situações típicas" sem nome, ano ou valor. Black Friday e Senacon aparecem duas vezes, o art. 13 da Lei 7.347 três vezes. A faixa da linha 3006 não tem fonte. | G371: não verificável | H371: O trecho não traz caso com nome, ano ou valor que se possa conferir, só situações típicas. A faixa de condenações de R$ 500 mil a dezenas de milhões (linha 3006) não tem fonte. | J371: Problema editorial confirmado na leitura do texto. Renomear para 'Situações que mais geram ação coletiva' e dar fonte à faixa ou retirá-la. | K371: Corrigido
A372: r2c-caso-025 | B372: Casos, pessoas e números | C372: 8 | D372: 3030 | E372: A Senacon atua em articulação com o CONAR (que editou o Guia de Publicidade por Influenciadores Digitais) | F372: Senacon é órgão público e o CONAR é autorregulação privada. "Atua em articulação" sugere parceria formal sem fonte. O Guia do CONAR aparece três vezes em doze linhas. | G372: correto no livro | H372: Em 17/7/2026 o CONAR assinou acordo de cooperação técnica com a Senacon e a Secretaria de Direitos Digitais do Ministério da Justiça, com troca de informações e canal para órgãos de defesa do consumidor pedirem análise de campanhas ao CONAR. A Senacon multa, o CONAR não. | I372: https://propmark.com.br/mercado/conar-firma-acordo-com-governo-para-fiscalizacao-de-publicidade-digital/ | J372: O revisor errou ao dizer que não há parceria formal. Vale citar o acordo de 2026 e deixar claro que o CONAR só recomenda. Corte as repetições do Guia, como pede o revisor. | K372: Corrigido
A373: r2c-juri-024 | B373: Jurídico | C373: 8 | D373: 3041 | E373: Cancelamento proposit. difícil Art. 51, IV - prática abusiva | F373: O art. 51 trata de cláusula nula, não de prática abusiva (art. 39). "Roach motel", três linhas abaixo, é o mesmo padrão com outro enquadramento. | G373: erro confirmado | H373: O art. 51 do CDC trata de cláusulas nulas de pleno direito, e o inciso IV mira obrigações iníquas que põem o consumidor em desvantagem exagerada. Prática abusiva é o art. 39. Dificultar o cancelamento cabe melhor como prática abusiva, e no comércio eletrônico o Decreto 7.962/2013 garante o arrependimento pela mesma ferramenta da contratação. | I373: https://www.legjur.com/legislacao/nivel/lei_00080781990/-capitulo-vi-da-protecao-contratual | https://idec.org.br/em-acao/artigo/novas-regras-de-comercio-eletronico-entram-em-vigor-no-proximo-dia-15-de-maio | J373: Fundir com 'Roach motel'. Para serviço regulado pela União, o novo decreto do SAC (13.135/2026, em vigor em 2/11/2026) exige cancelamento pelo mesmo canal (r1-trib-012). | K373: Corrigido
A374: r2c-fina-012 | B374: Finanças e regulação | C374: 8 | D374: 3075 | E374: (obrigatório para setores regulados e recomendado como canal de resolução rápida nos demais) | F374: A Portaria Senacon 15/2020 obriga o cadastro por faturamento, volume de reclamações e segmento, incluindo plataformas digitais de venda. Um marketplace como o da cena pode estar obrigado. | G374: erro confirmado | H374: A Portaria Senacon 15/2020 obriga o cadastro de serviços públicos e atividades essenciais, de plataformas digitais de transporte, entrega de comida ou venda de produtos próprios ou de terceiros ao consumidor final e das 200 empresas mais reclamadas no Sindec. Vale para quem fatura ao menos R$ 100 milhões, tem média de mil reclamações por mês ou mais de 500 processos de consumo. | I374: https://www.normasbrasil.com.br/norma/portaria-15-2020_392604.html | J374: O critério não é 'setor regulado'. Um marketplace acima desses limites está obrigado. Ajustar também a linha 3068. Alterações após 2020 não conferidas. | K374: Corrigido
A375: r2c-trib-031 | B375: Tributário e trabalhista | C375: 8 | D375: 3101 | E375: Vedação de cumular comissão de permanência com juros remuneratórios, correção monetária ou multa moratória (Súmula 472 do STJ e normas do CMN) | F375: O CMN vedou a comissão de permanência nas operações contratadas a partir de 2021 (conferir a resolução). O item a trata como encargo ainda em uso. | G375: desatualizado | H375: Em contratos firmados desde 1º/9/2017, o atraso só admite juros remuneratórios à taxa do contrato, multa e juros de mora, e qualquer outro encargo é vedado (Res. CMN 4.558/2017). A Res. CMN 4.882/2020, em vigor desde 1º/2/2021, manteve a regra. A comissão de permanência não cabe em contrato novo. | I375: https://normativos.bcb.gov.br/Lists/Normativos/Attachments/50345/Res_4558_v2_L.pdf | https://www.barbieriadvogados.com/comissao-de-permanencia-regime-juridico/ | J375: O revisor errou a data: a vedação é de 2017, só consolidada em 2021. A Súmula 472 do STJ fica para contratos antigos. O texto da Res. 4.882 foi lido só na fonte secundária. | K375: Corrigido
A376: r2c-juri-033 | B376: Jurídico | C376: 8 | D376: 3104 | E376: - [ ] Cláusula de liquidação antecipada com redução proporcional de juros (Lei 10.931/2004) | F376: Repete o item da linha 3101 (art. 52, § 2º, do CDC) com outra base legal. A Lei 10.931/2004 trata de CCB e patrimônio de afetação, não do desconto na quitação antecipada. | G376: erro confirmado | H376: A Lei 10.931/2004 trata de patrimônio de afetação, LCI, CCI e Cédula de Crédito Bancário e não garante liquidação antecipada com redução proporcional de juros. Esse direito do consumidor está no art. 52, § 2º, do CDC, já citado no item da l. 3101. | I376: https://www2.camara.leg.br/legin/fed/lei/2004/lei-10931-2-agosto-2004-533165-publicacaooriginal-16396-pl.html | https://www.legjur.com/legislacao/nivel/lei_00080781990/-capitulo-vi-da-protecao-contratual | J376: Os arts. 13 e 46 da Lei 10.931 falam de resgate antecipado de títulos imobiliários, sem desconto de juros. Apagar o item, como sugere o revisor. | K376: Corrigido
A377: r2c-fina-040 | B377: Finanças e regulação | C377: 8 | D377: 3124 | E377: Nota Técnica SENACON 2023 Dark patterns - enquadramento legal | F377: Norma sem número. Na linha acima, "Res. CMN 4.881" também precisa de checagem: o CET é regulado desde a Res. CMN 3.517/2007. | G377: não verificável | H377: Não foi encontrada nota técnica da Senacon de 2023 sobre dark patterns: panorama do Ibrac de julho de 2026 não cita nenhuma e registra a NT 3/2025 da Defensoria do Paraná, que aponta falta de regulamentação específica. A Res. CMN 4.881/2020 rege o CET desde 1º/2/2021 e revogou a 3.517/2007. | I377: https://ibrac.org.br/wp-content/uploads/2026/07/Apresentacao-_-Dark-patterns.pdf | https://www.bcb.gov.br/content/estabilidadefinanceira/especialnor/Resolu%C3%A7%C3%A3o4881.pdf | J377: O revisor errou sobre a 4.881, o livro acerta na l. 3123. Cortar a linha da nota técnica ou citar o REsp 1.737.428/RS (STJ, 2020) e o Acórdão Anatel 389/2024. | K377: Corrigido
A378: r2c-caso-014 | B378: Casos, pessoas e números | C378: 8 | D378: 3125 | E378: Código CONAR - Anexo P Publicidade digital e influenciadores | F378: No Código do CONAR, o Anexo P trata de cervejas e vinhos. Influenciadores estão no Guia de Publicidade por Influenciadores Digitais (2021) e, em parte, no Anexo Q (testemunhais). | G378: erro confirmado | H378: No Código do CONAR, o Anexo P trata de cervejas e vinhos e o Anexo Q de testemunhais, atestados e endossos. As regras para influenciadores estão no Guia de Publicidade por Influenciadores Digitais, lançado pelo CONAR em dezembro de 2020. | I378: https://www.icict.fiocruz.br/sites/www.icict.fiocruz.br/files/Cod Bras de Autorregulamentacao Publica_Conar.pdf | https://www.meioemensagem.com.br/home/comunicacao/2020/12/09/conar-lanca-guia-para-publicidade-com-influenciadores.html | J378: O guia saiu em 9/12/2020, não em 2021 como diz o revisor. Trocar a linha por 'Guia CONAR de Publicidade por Influenciadores Digitais (2020)'. | K378: Corrigido
A379: r2c-fina-028 | B379: Finanças e regulação | C379: 8 | D379: 3209 | E379: Câmaras como CNDM relatam taxa de sucesso de 60 a 70 por cento em disputas contratuais. | F379: Sigla CNDM não identificada (o conselho do setor é o CONIMA, citado na linha 3296). Taxa de sucesso sem fonte nem ano. | G379: erro confirmado | H379: CNDM é o Conselho Nacional dos Direitos da Mulher (Lei 7.353/1985), e o conselho do setor é o CONIMA, que reúne câmaras de mediação e arbitragem e não presta mediação. A taxa de 60% a 70% não tem fonte. | I379: https://www.planalto.gov.br/ccivil_03/leis/1980-1988/l7353.htm | J379: Reaproveitado da base (r2v8-045, mesma frase na versão anterior). Cortar o número ou citar câmara real (CAM-CCBC, CAMARB) com relatório e ano. | K379: Corrigido
A380: r2c-caso-036 | B380: Casos, pessoas e números | C380: 8 | D380: 3209 | E380: Sem força de coisa julgada se não houver homologacao judicial ou registro em câmara. | F380: Registro em câmara não dá força de coisa julgada. O acordo de mediação é título executivo extrajudicial e, homologado, judicial (art. 20, parágrafo único, da Lei 13.140/2015). | G380: parcialmente certo | H380: O termo final de mediação com acordo é título executivo extrajudicial e, homologado em juízo, título executivo judicial (Lei 13.140/2015, art. 20, parágrafo único). Registro em câmara não dá força de coisa julgada. | I380: https://www.planalto.gov.br/ccivil_03/_ato2015-2018/2015/lei/l13140.htm | J380: A taxa de sucesso de 60 a 70% atribuída à CNDM não foi conferida. Usar a redação do revisor. | K380: Corrigido
A381: r2c-caso-037 | B381: Casos, pessoas e números | C381: 8 | D381: 3269 | E381: (2) **protesto em cartório** da nota fiscal acompanhada do comprovante de entrega/prestação do serviço (duplicata mercantil ou de serviço) | F381: Nota fiscal não é título protestável. Protesta-se a duplicata, mercantil ou de serviço, apoiada na nota e no comprovante de entrega. | G381: parcialmente certo | H381: Protesta-se a duplicata, mercantil ou de serviço, inclusive por indicações do portador (Lei 5.474/1968, art. 13). A nota fiscal e o comprovante de entrega servem de lastro. Para executar duplicata não aceita é preciso protesto e prova da entrega (art. 15, II). | I381: https://www.planalto.gov.br/ccivil_03/leis/l5474compilado.htm | J381: A Lei 5.474 não fala em protesto de nota fiscal. A redação do revisor serve. | K381: Corrigido
A382: r2c-juri-034 | B382: Jurídico | C382: 8 | D382: 3343 | E382: A defesa administrativa no CARF tem taxa de êxito historicamente entre 30% e 50% dependendo da matéria. | F382: Estatística sem fonte nem período. Depois da volta do voto de qualidade (Lei 14.689/2023), as taxas podem ter mudado. | G382: não verificável | H382: Não achei fonte para a faixa de 30% a 50%. O relatório do CARF de janeiro a agosto de 2016 deu 52% das decisões favoráveis ao contribuinte, total ou parcialmente (53% no recurso voluntário), com grande variação por matéria. Desde a Lei 14.689/2023, o empate volta a ser resolvido pelo voto de qualidade. | I382: https://www.conjur.com.br/wp-content/uploads/2023/09/relatorio-carf.pdf | J382: Dado de 2016, anterior à volta do voto de qualidade (Lei 14.689 conforme r1-trib-038 da base). Usar a redação do revisor ou citar fonte com ano. | K382: Corrigido
A383: r2c-trib-040 | B383: Tributário e trabalhista | C383: 8 | D383: 3346 | E383: pode reduzir multas e juros em 50% a 100% sobre o valor principal | F383: Contradiz a linha 3313 (desconto nunca sobre o principal) e confunde a base. REFIS e Pert são programas antigos. Hoje a via regular é a transação da Lei 13.988/2020. | G383: erro confirmado | H383: Na transação da Lei 13.988/2020, os descontos alcançam só multas, juros e encargos de créditos irrecuperáveis ou de difícil recuperação, nunca o principal. A redução total fica limitada a 65% da dívida, ou 70% para pessoa física, ME e EPP. | I383: https://www.planalto.gov.br/ccivil_03/_ato2019-2022/2020/lei/l13988.htm | J383: REFIS e Pert foram programas pontuais. A via federal regular são os editais de transação da PGFN. Trocar também 'janelas REFIS' na l. 3535 e alinhar com a l. 3313. | K383: Corrigido
... A784: r2e-trib-044 | B784: Tributário e trabalhista | C784: 10 | D784: 10724 | E784: Instrução Normativa RFB 2.296/2025. Disciplina operacional da Receita Federal sobre limites de apuração, benefícios fiscais e regras de transição tributária | F784: Nenhum volume cita essa IN e a descrição é genérica, sem objeto definido. Há risco de número inexistente ou trocado. | G784: erro confirmado | H784: A IN RFB 2.296, de 3/12/2025, existe, mas trata de outro tema: altera a IN 1.700/2017 sobre perdas no recebimento de créditos de instituições financeiras e sobre o uso de lucros acumulados na base do JCP. Não disciplina limites de apuração nem transição tributária. | I784: https://www.reformatributaria.com/wp-content/uploads/2025/12/instrucao-normativa-receita-jcp-2296-2025.pdf | J784: DOU de 4/12/2025. Quem regulamentou a LC 224 foi a IN RFB 2.305/2025 (exceções à redução de 10%). Trocar a entrada ou cortá-la. | K784: Corrigido

Sheet Moldes
A1: Volume | B1: Linha | C1: Unidade | D1: Título da unidade | E1: Família do rótulo | F1: Arquétipo do molde | G1: Arquétipo da abertura | H1: Título truncado | I1: Parágrafo | J1: Status
A2: 1 | B2: 604 | C2: FASE 0 | D2: FASE 0 — PREPARAÇÃO DO EMPREENDEDOR | E2: Resultado na trincheira | F2: Lucas e Marina | G2: Dra. Camila | H2: não | I2: **Resultado na trincheira (PREPARAÇÃO DO EMPREENDEDOR):** A disciplina descrita em *O Espelho da Fase 0 e o Ritual de Segunda-Feira* permitiu que **Lucas e Marina**, a partir de São Paulo e Florianópolis, blindassem a margem operacional e reduzissem o retrabalho da equipe. | J2: Corrigido
A3: 1 | B3: 1654 | C3: FASE 1 | D3: FASE 1 — ENCONTRAR A IDEIA | E3: Fechamento operacional | F3: Lucas e Marina | G3: Lucas e Marina | H3: não | I3: **Fechamento operacional (ENCONTRAR A IDEIA):** Em São Paulo e Florianópolis, a aplicação rigorosa do roteiro de *O Espelho da Fase 1 e o Ritual de Segunda-Feira* por **Lucas e Marina** converteu incerteza estratégica em cadência mensurável de entrega. | J3: Corrigido
A4: 1 | B4: 2258 | C4: FASE 2 | D4: FASE 2 — ARTICULAÇÃO E CAPTURA DA IDEIA | E4: Síntese prática | F4: Henrique | G4: Henrique | H4: não | I4: **Síntese prática em ARTICULAÇÃO E CAPTURA DA IDEIA:** Ao incorporar as balizas de *O Espelho da Fase 2 e o Ritual de Segunda-Feira* na operação em Curitiba, **Henrique** substituiu decisões reativas por indicadores auditáveis de execução semanal. | J4: Corrigido
A5: 1 | B5: 2992 | C5: FASE 3 | D5: FASE 3 — CONSTRUÇÃO DA TEORIA DO NEGÓCIO | E5: Governança prática | F5: Rafael e Bia | G5: Rafael e Bia | H5: não | I5: **Governança prática em CONSTRUÇÃO DA TEORIA DO NEGÓCIO:** Ao documentarem os padrões de *O Espelho da Fase 3 e o Ritual de Segunda-Feira* na operação de Recife e Goiânia, **Rafael e Bia** criaram uma trava clara contra desvios de escopo e queima ineficiente de capital. | J5: Corrigido
A6: 1 | B6: 3746 | C6: CAPÍTULO 1 | D6: CAPÍTULO 1 — DINHEIRO PESSOAL DO FUNDADOR | E6: Síntese prática | F6: Lucas e Marina | G6: Lucas e Marina | H6: sim | I6: **Síntese prática em DINHEIRO PESSOAL DO FUNDADOR:** Ao incorporarem as balizas de *O Espelho do CPF do Fundador e o Ritual de...* na operação em São Paulo e Florianópolis, **Lucas e Marina** substituíram decisões reativas por indicadores auditáveis de execução semanal. | J6: Corrigido
A7: 1 | B7: 4321 | C7: CAPÍTULO 2 | D7: CAPÍTULO 2 — SAÚDE MENTAL, DINÂMICA DE CO-FOUNDERS E HUMANIDADE DO FUNDADOR | E7: Virada de chave | F7: Rafael e Bia | G7: Rafael e Bia | H7: sim | I7: **Virada de chave em SAÚDE MENTAL, DINÂMICA DE CO-FOUNDERS E HUMANIDADE DO...:** Foi aplicando o checklist de *O Espelho da Sociedade e da Mente: Ritual de...* no dia a dia em Recife e Goiânia que **Rafael e Bia** destravaram o próximo degrau de escala sustentável do negócio. | J7: Corrigido
A8: 1 | B8: 4486 | C8: CAPÍTULO 3 | D8: CAPÍTULO 3 — ARMADILHAS MENTAIS E VIESES | E8: Fechamento operacional | F8: Dra. Camila | G8: Dra. Camila | H8: não | I8: **Fechamento operacional (ARMADILHAS MENTAIS E VIESES):** Em Belo Horizonte, a aplicação rigorosa do roteiro de *O Espelho Cognitivo e o Ritual de Segunda-Feira* por a **Dra. Camila** converteu incerteza estratégica em cadência mensurável de entrega. | J8: Corrigido
A9: 1 | B9: 4799 | C9: CAPÍTULO 5 | D9: CAPÍTULO 5 — DIVERSIDADE DE JORNADAS: CASOS ALÉM DO CÂNONE | E9: Impacto direto no caixa e na execução | F9: Henrique | G9: Henrique | H9: sim | I9: **Impacto direto no caixa e na execução (DIVERSIDADE DE JORNADAS: CASOS ALÉM DO CÂNONE):** Com o filtro de *O Espelho da Sua Vantagem Assimétrica: Ritual de...* implantado em Curitiba, **Henrique** eliminou o improviso comercial e encurtou o ciclo de decisão. | J9: Corrigido
A10: 1 | B10: 5060 | C10: CAPÍTULO 6 | D10: CAPÍTULO 6 — TOMADA DE DECISÃO COMO DISCIPLINA | E10: Resultado na trincheira | F10: Lucas e Marina | G10: Lucas e Marina | H10: não | I10: **Resultado na trincheira (TOMADA DE DECISÃO COMO DISCIPLINA):** A disciplina descrita em *O Espelho da Decisão e o Ritual de Segunda-Feira* permitiu que **Lucas e Marina**, a partir de São Paulo e Florianópolis, blindassem a margem operacional e reduzissem o retrabalho da equipe. | J10: Corrigido
A11: 1 | B11: 5383 | C11: CAPÍTULO 7 | D11: CAPÍTULO 7 — INFLUÊNCIA E PERSUASÃO SEM AUTORIDADE FORMAL | E11: Impacto direto no caixa e na execução | F11: Henrique | G11: Henrique | H11: não | I11: **Impacto direto no caixa e na execução (INFLUÊNCIA E PERSUASÃO SEM AUTORIDADE FORMAL):** Com o filtro de *O Espelho da Influência e o Ritual de Segunda-Feira* implantado em Curitiba, **Henrique** eliminou o improviso comercial e encurtou o ciclo de decisão. | J11: Corrigido
A12: 1 | B12: 5764 | C12: CAPÍTULO 8 | D12: CAPÍTULO 8 — COMUNICAÇÃO ESCRITA PARA NEGÓCIOS | E12: Resultado na trincheira | F12: Lucas e Marina | G12: Lucas e Marina | H12: não | I12: **Resultado na trincheira (COMUNICAÇÃO ESCRITA PARA NEGÓCIOS):** A disciplina descrita em *O Espelho da Escrita e o Ritual de Segunda-Feira* permitiu que **Lucas e Marina**, a partir de São Paulo e Florianópolis, blindassem a margem operacional e reduzissem o retrabalho da equipe. | J12: Corrigido
A13: 1 | B13: 6174 | C13: CAPÍTULO 9 | D13: CAPÍTULO 9 — APRESENTAÇÃO E FALA EM PÚBLICO | E13: Fechamento operacional | F13: Henrique | G13: Henrique | H13: não | I13: **Fechamento operacional (APRESENTAÇÃO E FALA EM PÚBLICO):** Em Curitiba, a aplicação rigorosa do roteiro de *O Espelho do Palco e o Ritual de Segunda-Feira* por **Henrique** converteu incerteza estratégica em cadência mensurável de entrega. | J13: Corrigido
... A128: 9 | B128: 6093 | C128: CAPÍTULO 21 | D128: CAPÍTULO 21 — A EMPRESA CASH COW (DIVIDENDOS PERPÉTUOS), HOLDINGS PATRIMONIAIS, | E128: Da teoria à rotina operacional | F128: Dra. Camila | G128: Dra. Camila | H128: sim | I128: **Da teoria à rotina operacional (A EMPRESA CASH COW (DIVIDENDOS PERPÉTUOS), HOLDINGS...):** Na revisão mensal em Belo Horizonte, a **Dra. Camila** transformou o protocolo de *O Espelho do Patrimônio Perene: Você Construiu...* em critério obrigatório antes de liberar novos recursos do orçamento. | J128: Corrigido
A129: 9 | B129: 6156 | C129: ? | E129: Síntese prática | F129: Lucas e Marina | H129: sim | I129: **Síntese prática em EPÍLOGO:** Ao incorporarem as balizas de *O Espelho Final da Jornada: Que Tipo de...* na operação em São Paulo e Florianópolis, **Lucas e Marina** substituíram decisões reativas por indicadores auditáveis de execução semanal. | J129: Corrigido
A130: 10 | B130: 381 | C130: CAPÍTULO 1 | D130: CAPÍTULO 1 — A ECONOMIA DA INOVAÇÃO E SEUS ATORES: UNIVERSIDADE, ESTADO, CORPORA | E130: Resultado na trincheira | F130: Dra. Camila | G130: Dra. Camila | H130: sim | I130: **Resultado na trincheira (A ECONOMIA DA INOVAÇÃO E SEUS ATORES: UNIVERSIDADE,...):** A disciplina descrita em *Filtro de Alinhamento e Prontidão: Perguntas de...* permitiu que a **Dra. Camila**, a partir de Belo Horizonte, blindasse a margem operacional e reduzisse o retrabalho da equipe. | J130: Corrigido
