Workbook

Sheet Leia-me
A1: IGNIÇÃO v5.0: achados da revisão
A2: Revisão completa dos 10 volumes feita em outubro de 2026. Cada linha da aba Achados é um problema marcado por um revisor, com a linha do arquivo .md do volume, o trecho citado e a correção sugerida.
A4: Abas
A5: Achados: os 5.621 achados, um por linha, em ordem de volume e linha. Use os filtros do cabeçalho para ver um volume, uma categoria ou só a gravidade alta.
A6: Checagem: as afirmações conferidas na web contra lei, norma, documento oficial da empresa ou imprensa de referência, com o veredito, o que vale em outubro de 2026 e o link da fonte.
A7: Resumo: contagens por volume, categoria e veredito, calculadas por fórmula a partir das outras abas. Mudam sozinhas quando você atualiza o Status.
A9: Como usar
A10: A coluna Status (fundo amarelo) é a única feita para editar. Valores aceitos: Pendente, Em revisão, Corrigido, Descartado. Todas começam como Pendente.
A11: Gravidade alta: erro factual, frase corrompida, contradição, conselho arriscado, promessa da edição quebrada ou passagem que um leitor exigente usaria para desacreditar o livro. Média: vício recorrente que cansa ou enfraquece o texto. Baixa: polimento.
A12: Pede checagem = sim marca afirmações que o revisor não conseguiu confirmar só com o texto. Quando a coluna Checagem na web está vazia, a afirmação ainda não foi conferida.
A13: Os revisores também erram: na checagem, 5 suspeitas se mostraram certas no livro. Outras 128 saíram parcialmente certas, com um detalhe que ainda pede conserto. Nenhuma correção de lei, número ou caso real deve entrar no livro sem a fonte primária aberta.
A14: Linha é a linha do arquivo .md do volume na versão revisada. Se o arquivo mudar, busque pelo trecho citado.
... A17: Categorias
A18: Código | B18: Grupo | C18: O que marca
A19: E1 | B19: Escrita | C19: Antítese "não é X, é Y"
A20: E2 | B20: Escrita | C20: Fragmento telegráfico
A21: E3 | B21: Escrita | C21: Adjetivo inflado ou intensificador
A22: E4 | B22: Escrita | C22: Metadiscurso, abertura enfática, rótulo
A23: E5 | B23: Escrita | C23: Pergunta retórica com resposta imediata
A24: E6 | B24: Escrita | C24: Clichê ou metáfora gasta
A25: E7 | B25: Escrita | C25: Anglicismo ou mistura founder/fundador
A26: E8 | B26: Escrita | C26: Glosa repetida entre parênteses
A27: E9 | B27: Escrita | C27: Erro gramatical ou frase corrompida
A28: E10 | B28: Escrita | C28: Repetição, redundância, enchimento
A29: E11 | B29: Escrita | C29: Registro inconsistente ou tom de coach
... A53: C7 | B53: Conteúdo | C53: Conselho arriscado sem ressalva

Sheet Resumo
A1: Resumo dos achados
A2: Tudo nesta aba é fórmula sobre as abas Achados e Checagem.
A4: Achados por volume e gravidade
A5: Volume | B5: Alta | C5: Média | D5: Baixa | E5: Total | F5: Corrigidos | G5: % corrigido
A6: 1 | B6: =COUNTIFS(Achados!$B$2:$B$5622,$A6,Achados!$G$2:$G$5622,"alta") -> 150 | C6: =COUNTIFS(Achados!$B$2:$B$5622,$A6,Achados!$G$2:$G$5622,"média") -> 384 | D6: =COUNTIFS(Achados!$B$2:$B$5622,$A6,Achados!$G$2:$G$5622,"baixa") -> 18 | E6: =SUM(B6:D6) -> 552 | F6: =COUNTIFS(Achados!$B$2:$B$5622,$A6,Achados!$R$2:$R$5622,"Corrigido") -> 0 | G6: =IF(E6=0,0,F6/E6) -> 0
A7: 2 | B7: =COUNTIFS(Achados!$B$2:$B$5622,$A7,Achados!$G$2:$G$5622,"alta") -> 124 | C7: =COUNTIFS(Achados!$B$2:$B$5622,$A7,Achados!$G$2:$G$5622,"média") -> 207 | D7: =COUNTIFS(Achados!$B$2:$B$5622,$A7,Achados!$G$2:$G$5622,"baixa") -> 35 | E7: =SUM(B7:D7) -> 366 | F7: =COUNTIFS(Achados!$B$2:$B$5622,$A7,Achados!$R$2:$R$5622,"Corrigido") -> 0 | G7: =IF(E7=0,0,F7/E7) -> 0
A8: 3 | B8: =COUNTIFS(Achados!$B$2:$B$5622,$A8,Achados!$G$2:$G$5622,"alta") -> 188 | C8: =COUNTIFS(Achados!$B$2:$B$5622,$A8,Achados!$G$2:$G$5622,"média") -> 255 | D8: =COUNTIFS(Achados!$B$2:$B$5622,$A8,Achados!$G$2:$G$5622,"baixa") -> 14 | E8: =SUM(B8:D8) -> 457 | F8: =COUNTIFS(Achados!$B$2:$B$5622,$A8,Achados!$R$2:$R$5622,"Corrigido") -> 0 | G8: =IF(E8=0,0,F8/E8) -> 0
A9: 4 | B9: =COUNTIFS(Achados!$B$2:$B$5622,$A9,Achados!$G$2:$G$5622,"alta") -> 190 | C9: =COUNTIFS(Achados!$B$2:$B$5622,$A9,Achados!$G$2:$G$5622,"média") -> 325 | D9: =COUNTIFS(Achados!$B$2:$B$5622,$A9,Achados!$G$2:$G$5622,"baixa") -> 25 | E9: =SUM(B9:D9) -> 540 | F9: =COUNTIFS(Achados!$B$2:$B$5622,$A9,Achados!$R$2:$R$5622,"Corrigido") -> 0 | G9: =IF(E9=0,0,F9/E9) -> 0
A10: 5 | B10: =COUNTIFS(Achados!$B$2:$B$5622,$A10,Achados!$G$2:$G$5622,"alta") -> 224 | C10: =COUNTIFS(Achados!$B$2:$B$5622,$A10,Achados!$G$2:$G$5622,"média") -> 291 | D10: =COUNTIFS(Achados!$B$2:$B$5622,$A10,Achados!$G$2:$G$5622,"baixa") -> 30 | E10: =SUM(B10:D10) -> 545 | F10: =COUNTIFS(Achados!$B$2:$B$5622,$A10,Achados!$R$2:$R$5622,"Corrigido") -> 0 | G10: =IF(E10=0,0,F10/E10) -> 0
A11: 6 | B11: =COUNTIFS(Achados!$B$2:$B$5622,$A11,Achados!$G$2:$G$5622,"alta") -> 228 | C11: =COUNTIFS(Achados!$B$2:$B$5622,$A11,Achados!$G$2:$G$5622,"média") -> 384 | D11: =COUNTIFS(Achados!$B$2:$B$5622,$A11,Achados!$G$2:$G$5622,"baixa") -> 19 | E11: =SUM(B11:D11) -> 631 | F11: =COUNTIFS(Achados!$B$2:$B$5622,$A11,Achados!$R$2:$R$5622,"Corrigido") -> 0 | G11: =IF(E11=0,0,F11/E11) -> 0
A12: 7 | B12: =COUNTIFS(Achados!$B$2:$B$5622,$A12,Achados!$G$2:$G$5622,"alta") -> 115 | C12: =COUNTIFS(Achados!$B$2:$B$5622,$A12,Achados!$G$2:$G$5622,"média") -> 231 | D12: =COUNTIFS(Achados!$B$2:$B$5622,$A12,Achados!$G$2:$G$5622,"baixa") -> 17 | E12: =SUM(B12:D12) -> 363 | F12: =COUNTIFS(Achados!$B$2:$B$5622,$A12,Achados!$R$2:$R$5622,"Corrigido") -> 0 | G12: =IF(E12=0,0,F12/E12) -> 0
A13: 8 | B13: =COUNTIFS(Achados!$B$2:$B$5622,$A13,Achados!$G$2:$G$5622,"alta") -> 170 | C13: =COUNTIFS(Achados!$B$2:$B$5622,$A13,Achados!$G$2:$G$5622,"média") -> 196 | D13: =COUNTIFS(Achados!$B$2:$B$5622,$A13,Achados!$G$2:$G$5622,"baixa") -> 1 | E13: =SUM(B13:D13) -> 367 | F13: =COUNTIFS(Achados!$B$2:$B$5622,$A13,Achados!$R$2:$R$5622,"Corrigido") -> 0 | G13: =IF(E13=0,0,F13/E13) -> 0
A14: 9 | B14: =COUNTIFS(Achados!$B$2:$B$5622,$A14,Achados!$G$2:$G$5622,"alta") -> 255 | C14: =COUNTIFS(Achados!$B$2:$B$5622,$A14,Achados!$G$2:$G$5622,"média") -> 375 | D14: =COUNTIFS(Achados!$B$2:$B$5622,$A14,Achados!$G$2:$G$5622,"baixa") -> 8 | E14: =SUM(B14:D14) -> 638 | F14: =COUNTIFS(Achados!$B$2:$B$5622,$A14,Achados!$R$2:$R$5622,"Corrigido") -> 0 | G14: =IF(E14=0,0,F14/E14) -> 0
A15: 10 | B15: =COUNTIFS(Achados!$B$2:$B$5622,$A15,Achados!$G$2:$G$5622,"alta") -> 325 | C15: =COUNTIFS(Achados!$B$2:$B$5622,$A15,Achados!$G$2:$G$5622,"média") -> 714 | D15: =COUNTIFS(Achados!$B$2:$B$5622,$A15,Achados!$G$2:$G$5622,"baixa") -> 123 | E15: =SUM(B15:D15) -> 1162 | F15: =COUNTIFS(Achados!$B$2:$B$5622,$A15,Achados!$R$2:$R$5622,"Corrigido") -> 0 | G15: =IF(E15=0,0,F15/E15) -> 0
A16: Total | B16: =SUM(B6:B15) -> 1969 | C16: =SUM(C6:C15) -> 3362 | D16: =SUM(D6:D15) -> 290 | E16: =SUM(E6:E15) -> 5621 | F16: =SUM(F6:F15) -> 0 | G16: =IF(E16=0,0,F16/E16) -> 0
A17: Volume é o arquivo onde o achado está. Aparato e arquétipos entram no volume da linha citada.
A19: Checagem na web por veredito
A20: Veredito | B20: Afirmações | C20: % do checado
A21: erro confirmado | B21: =COUNTIF(Checagem!$F$2:$F$494,$A21) -> 245 | C21: =IF($B$27=0,0,B21/$B$27) -> 0.4969574
A22: desatualizado | B22: =COUNTIF(Checagem!$F$2:$F$494,$A22) -> 85 | C22: =IF($B$27=0,0,B22/$B$27) -> 0.17241379
A23: parcialmente certo | B23: =COUNTIF(Checagem!$F$2:$F$494,$A23) -> 128 | C23: =IF($B$27=0,0,B23/$B$27) -> 0.25963489
A24: correto no livro | B24: =COUNTIF(Checagem!$F$2:$F$494,$A24) -> 5 | C24: =IF($B$27=0,0,B24/$B$27) -> 0.010141988
A25: não verificável | B25: =COUNTIF(Checagem!$F$2:$F$494,$A25) -> 23 | C25: =IF($B$27=0,0,B25/$B$27) -> 0.046653144
A26: não checada | B26: =COUNTIF(Checagem!$F$2:$F$494,$A26) -> 7 | C26: =IF($B$27=0,0,B26/$B$27) -> 0.014198783
A27: Total | B27: =SUM(B21:B26) -> 493 | C27: =IF($B$27=0,0,B27/$B$27) -> 1
A30: Achados por categoria
A31: Código | B31: Categoria | C31: Grupo | D31: Total | E31: Alta
A32: E1 | B32: Antítese "não é X, é Y" | C32: Escrita | D32: =COUNTIF(Achados!$E$2:$E$5622,$A32) -> 77 | E32: =COUNTIFS(Achados!$E$2:$E$5622,$A32,Achados!$G$2:$G$5622,"alta") -> 0
A33: E2 | B33: Fragmento telegráfico | C33: Escrita | D33: =COUNTIF(Achados!$E$2:$E$5622,$A33) -> 73 | E33: =COUNTIFS(Achados!$E$2:$E$5622,$A33,Achados!$G$2:$G$5622,"alta") -> 8
A34: E3 | B34: Adjetivo inflado ou intensificador | C34: Escrita | D34: =COUNTIF(Achados!$E$2:$E$5622,$A34) -> 70 | E34: =COUNTIFS(Achados!$E$2:$E$5622,$A34,Achados!$G$2:$G$5622,"alta") -> 0
A35: E4 | B35: Metadiscurso, abertura enfática, rótulo | C35: Escrita | D35: =COUNTIF(Achados!$E$2:$E$5622,$A35) -> 34 | E35: =COUNTIFS(Achados!$E$2:$E$5622,$A35,Achados!$G$2:$G$5622,"alta") -> 0
A36: E5 | B36: Pergunta retórica com resposta imediata | C36: Escrita | D36: =COUNTIF(Achados!$E$2:$E$5622,$A36) -> 7 | E36: =COUNTIFS(Achados!$E$2:$E$5622,$A36,Achados!$G$2:$G$5622,"alta") -> 0
A37: E6 | B37: Clichê ou metáfora gasta | C37: Escrita | D37: =COUNTIF(Achados!$E$2:$E$5622,$A37) -> 39 | E37: =COUNTIFS(Achados!$E$2:$E$5622,$A37,Achados!$G$2:$G$5622,"alta") -> 1
A38: E7 | B38: Anglicismo ou mistura founder/fundador | C38: Escrita | D38: =COUNTIF(Achados!$E$2:$E$5622,$A38) -> 141 | E38: =COUNTIFS(Achados!$E$2:$E$5622,$A38,Achados!$G$2:$G$5622,"alta") -> 7
A39: E8 | B39: Glosa repetida entre parênteses | C39: Escrita | D39: =COUNTIF(Achados!$E$2:$E$5622,$A39) -> 51 | E39: =COUNTIFS(Achados!$E$2:$E$5622,$A39,Achados!$G$2:$G$5622,"alta") -> 1
A40: E9 | B40: Erro gramatical ou frase corrompida | C40: Escrita | D40: =COUNTIF(Achados!$E$2:$E$5622,$A40) -> 555 | E40: =COUNTIFS(Achados!$E$2:$E$5622,$A40,Achados!$G$2:$G$5622,"alta") -> 199
A41: E10 | B41: Repetição, redundância, enchimento | C41: Escrita | D41: =COUNTIF(Achados!$E$2:$E$5622,$A41) -> 52 | E41: =COUNTIFS(Achados!$E$2:$E$5622,$A41,Achados!$G$2:$G$5622,"alta") -> 1
A42: E11 | B42: Registro inconsistente ou tom de coach | C42: Escrita | D42: =COUNTIF(Achados!$E$2:$E$5622,$A42) -> 18 | E42: =COUNTIFS(Achados!$E$2:$E$5622,$A42,Achados!$G$2:$G$5622,"alta") -> 2
A43: E12 | B43: Frase longa demais | C43: Escrita | D43: =COUNTIF(Achados!$E$2:$E$5622,$A43) -> 38 | E43: =COUNTIFS(Achados!$E$2:$E$5622,$A43,Achados!$G$2:$G$5622,"alta") -> 1
... A66: C7 | B66: Conselho arriscado sem ressalva | C66: Conteúdo | D66: =COUNTIF(Achados!$E$2:$E$5622,$A66) -> 194 | E66: =COUNTIFS(Achados!$E$2:$E$5622,$A66,Achados!$G$2:$G$5622,"alta") -> 83
A67: Total | D67: =SUM(D32:D66) -> 5621 | E67: =SUM(E32:E66) -> 1969

Sheet Achados
A1: Nº | B1: Volume | C1: Linha | D1: Unidade | E1: Código | F1: Categoria | G1: Gravidade | H1: Trecho citado | I1: Problema | J1: Sugestão | K1: Recorrente | L1: Ocorrências estimadas | M1: Pede checagem | N1: Checagem na web | O1: O que vale em out/2026 | P1: Fonte da checagem | Q1: Origem | R1: Pendente
A2: 1 | B2: 1 | C2: 24 | D2: Nota do autor | E2: E3 | F2: Adjetivo inflado ou intensificador | G2: média | H2: e da solidão brutal de quem carrega o CPF na linha de tiro | I2: Adjetivos da lista de cortes concentrados na Nota: 'solidão brutal' (24), 'foco obsessivo' (32), 'negócios silenciosos' (35), 'armadilhas invisíveis' (38), além do rótulo 'Mais importante:' (35). | J2: Na 24: "e da solidão de quem responde com o próprio CPF". Na 35, abrir direto ("Você não fará esta travessia sozinho") e trocar "negócios silenciosos do interior" por "negócios do interior que nunca saíram no jornal". | K2: sim | L2: 5 | M2: não | Q2: Revisor de trecho | R2: Corrigido
A3: 2 | B3: 1 | C3: 24 | D3: Nota do autor | E3: C2 | F3: Informação possivelmente desatualizada | G3: média | H3: de 5.570 legislações municipais de nota fiscal | I3: Com a reforma tributária, a NFS-e de padrão nacional deve valer para os municípios desde 2026. Falar em 5.570 legislações de nota fiscal pode soar datado em outubro de 2026. | J3: Verificar a situação da NFS-e nacional e reescrever, por exemplo: "de um ISS que ainda muda de cidade para cidade enquanto a reforma tributária não conclui a transição". | K3: não | L3: 1 | M3: sim | Q3: Revisor de trecho | R3: Corrigido
A4: 3 | B4: 1 | C4: 29 | D4: Nota do autor | E4: E11 | F4: Registro inconsistente ou tom de coach | G4: baixa | H4: - De **Michael Gerber** (*O Mito do Empreendedor*), trouxemos a conversa direta, olho no olho | I4: A Nota alterna 'eu' (resisti, cometi, escrevi) e 'nós' (trouxemos) para o mesmo autor. E a passagem pessoal sobre influências virou lista com marcadores. | J4: Manter a primeira pessoa do singular e passar a lista a dois parágrafos de prosa: o que cada autor mudou na prática do autor, com um caso próprio. | K4: não | L4: 1 | M4: não | Q4: Revisor de trecho | R4: Corrigido
A5: 4 | B5: 1 | C5: 35 | D5: Nota do autor | E5: N3 | F5: Arquétipo inconsistente, decorativo ou ausente | G5: alta | H5: você acompanhará ao longo dos volumes a jornada viva de | I5: Em 148 das 149 unidades que abrem com arquétipo, ele some antes da linha 17 e não volta no corpo, no Espelho, no Ritual ou na Oficina. Só Dona Helena (2:2528, 3:3167) liga duas cenas. | J5: Dar ao arquétipo da abertura uma volta no fecho de cada unidade: um parágrafo antes do Espelho com o desfecho da cena e os números dela aplicados à ferramenta, mais uma linha de memória por volume ("no Vol. 1, Lucas..."). | K5: sim | L5: 148 | M5: não | Q5: Leitura cruzada dos arquétipos | R5: Corrigido
A6: 5 | B6: 1 | C6: 38 | D6: Nota do autor | E6: N9 | F6: Título que promete o que o corpo não entrega | G6: alta | H6: 1. **A Narrativa de Trincheira (Atos 1 a 4):** abrimos sempre no meio da tensão real | I6: A Nota promete narrativa em 'Atos 1 a 4', mas nenhuma fase ou capítulo do volume marca atos. O leitor procura a estrutura anunciada e não a encontra. | J6: Cortar "(Atos 1 a 4)" ou marcar os atos nas fases. Se a estrutura real é cena, diagnóstico, armadilhas, Espelho e Ritual, descrever assim. | K6: não | L6: 1 | M6: não | Q6: Revisor de trecho | R6: Corrigido
A7: 6 | B7: 1 | C7: 43 | D7: Nota do autor | E7: E6 | F7: Clichê ou metáfora gasta | G7: média | H7: Boa subida — e nos vemos na trincheira. | I7: Metáforas misturadas na Nota: trincheira, cicatriz e linha de tiro (guerra) convivem com subida, topo da montanha e pedra (escalada). A imagem central da obra se dilui. | J7: Escolher uma imagem. Se for o caderno de campo da linha 22, manter o caderno aberto às onze da noite e cortar subida, pedra e a despedida na trincheira. Fechar com uma frase sobre como usar o livro. | K7: sim | L7: 7 | M7: não | Q7: Revisor de trecho | R7: Corrigido
A8: 7 | B8: 1 | C8: 76 | D8: Os 4 Fundadores | E8: N3 | F8: Arquétipo inconsistente, decorativo ou ausente | G8: média | H8: você acompanhará de perto a evolução, os tropeços, as brigas societárias, os pivôs e as vitórias de | I8: Distribuição torta: Lucas e Marina abrem 62 de 149 unidades (42%), Camila 24 (16%). Henrique não abre fase depois do Vol. 4. Rafael e Bia abrem 3 de 23 unidades nos Vols. 1 e 2. | J8: Trocar 8 a 10 aberturas de Lucas e Marina nos Vols. 4 a 6 por outros arquétipos (ex.: Vol. 5, Cap. 11 com a crise de caixa de Rafael e Bia, Vol. 4, Cap. 9 com o medo de cobrar de Camila) e dar a Henrique uma abertura de fase entre 14 e 20. | K8: não | L8: 1 | M8: não | Q8: Leitura cruzada dos arquétipos | R8: Corrigido
A9: 8 | B9: 1 | C9: 80 | D9: Os 4 Fundadores | E9: N3 | F9: Arquétipo inconsistente, decorativo ou ausente | G9: média | H9: Descobrem o poder do *Vertical SaaS + Embedded Finance* | I9: O produto nunca fica vertical: é tesouraria para qualquer empresa média (2:7658, 4:6905, 6:5971). O crédito embutido só aparece no agente de 8:4811. | J9: Ou trocar a promessa por "tesouraria preditiva com crédito embutido", ou verticalizar numa cena dos Vols. 5 ou 6 (foco em distribuidores, o que casa com a distribuidora de 2:90 e a varejista de 8:2396). | K9: não | L9: 1 | M9: não | Q9: Leitura cruzada dos arquétipos | R9: Corrigido
A10: 9 | B10: 1 | C10: 81 | D10: Os 4 Fundadores | E10: N3 | F10: Arquétipo inconsistente, decorativo ou ausente | G10: média | H10: Mistura contas de casa com o CNPJ, compra equipamento caro por impulso (*custo afundado*) e tem medo de cobrar o que vale | I10: Só o custo afundado vira cena (1:6161). Contas misturadas e medo de cobrar não aparecem nas 29 cenas de Camila. Em 4:5684 ela já cobra R$ 480 por sessão sem conflito. | J10: Abrir o Vol. 4, Cap. 9 (preço) com Camila cobrando abaixo da tabela por vergonha e pôr as contas misturadas na cena de 5:1776: a escola dos filhos paga com o PIX da clínica explica parte do lucro que não vira caixa. | K10: não | L10: 1 | M10: não | Q10: Leitura cruzada dos arquétipos | R10: Corrigido
A11: 10 | B11: 1 | C11: 82 | D11: Os 4 Fundadores | E11: C5 | F11: Contradição interna | G11: baixa | H11: Aprende a vender para comitês complexos de 7 decisores | I11: O capítulo de vendas complexas (Vol. 6, Cap. 2) organiza o comitê em 6 cadeiras. E o fomento de Henrique (5:8061) é Finep e EMBRAPII, sem o BNDES prometido. | J11: "comitês complexos de seis cadeiras" e "subvenção Finep e EMBRAPII", ou acrescentar o BNDES na cena de 5:8061. | K11: não | L11: 1 | M11: não | Q11: Leitura cruzada dos arquétipos | R11: Corrigido
A12: 11 | B12: 1 | C12: 83 | D12: Os 4 Fundadores | E12: C5 | F12: Contradição interna | G12: média | H12: **Rafael** (27, criativo de marketing no Recife) e **Bia** (28, engenheira de produção em Goiânia | I12: A bíblia põe cada sócio numa cidade e não diz onde fica a empresa. As cenas alternam Recife (14), Goiânia (5) e as duas (5), com os dois juntos na cozinha, na sala e no escritório. | J12: Completar a tabela: "sede e marketing em Recife (Rafael), centro de distribuição e operações em Goiânia (Bia)". Nas cenas a dois, dizer quem viajou. | K12: não | L12: 1 | M12: não | Q12: Leitura cruzada dos arquétipos | R12: Corrigido
A13: 12 | B13: 1 | C13: 83 | D13: Os 4 Fundadores | E13: N3 | F13: Arquétipo inconsistente, decorativo ou ausente | G13: média | H13: sofrem com ruptura de estoque e descobrem o peso da cadeia logística e tributária brasileira | I13: Nenhuma das 29 cenas de Rafael e Bia mostra ruptura de estoque, embora Bia seja "obcecada por estoque". A marca omnichannel prometida também não chega (9:112). | J13: Usar Rafael e Bia na abertura de um capítulo de operação do Vol. 4 ou 7: a Black Friday que vende o que não há no centro de distribuição de Goiânia, com o custo da ruptura na conta. | K13: não | L13: 1 | M13: não | Q13: Leitura cruzada dos arquétipos | R13: Corrigido
... A50: 49 | B50: 1 | C50: 436 | D50: FASE 0 | E50: E9 | F50: Erro gramatical ou frase corrompida | G50: alta | H50: o [[#Canvas: Team Canvas (Alex Ivanov, 2015)|Canvas: Team Canvas (Alex Ivanov, 2015)]] (Alex Ivanov, 2015) é o template | I50: A substituição mecânica duplicou autor e ano e gerou a frase 'Canvas: Team Canvas (Alex Ivanov, 2015) (Fase 0) também é referenciado'. O callout de uso prático ficou ilegível. | J50: Reescrever: "Quando o time tem dois ou mais cofundadores, use o Team Canvas (Alex Ivanov, 2015) para alinhar pessoas, objetivos, papéis, valores, forças e regras antes do primeiro conflito." Cortar a frase seguinte. | K50: não | L50: 1 | M50: não | Q50: Revisor de trecho | R50: Corrigido
A51: 50 | B51: 1 | C51: 448 | D51: FASE 0 | E51: C3 | F51: Erro factual provável | G51: alta | H51: O terceiro perfil é o especialista de domínio, ou hipster. | I51: Na tríade conhecida hacker, hustler e hipster, o hipster é o designer. O texto redefine o termo e depois cria o design como quarto perfil. Quem conhece a tríade desconfia do resto. | J51: Manter a tríade original, com o hipster como design, e tratar o especialista do setor à parte. Ou largar os apelidos e falar em técnico, comercial e especialista do setor. | K51: não | L51: 1 | M51: não | N51: não checada | O51: Não checada nesta rodada. | Q51: Revisor de trecho | R51: Corrigido
A52: 51 | B52: 1 | C52: 474 | D52: FASE 0 | E52: N7 | F52: Autoridade forçada ou atribuição duvidosa | G52: média | H52: A formalização vem do modelo Antler para founding teams. | I52: Atribuição sem fonte. Não há referência pública conhecida de um 'modelo Antler' com cinco perfis fundadores. Parece autoridade emprestada. | J52: Verificar. Sem fonte, assumir como proposta do autor: "Em produtos complexos, a meu ver, os três perfis viram cinco." | K52: não | L52: 1 | M52: sim | Q52: Revisor de trecho | R52: Corrigido
A53: 52 | B53: 1 | C53: 480 | D53: FASE 0 | E53: E9 | F53: Erro gramatical ou frase corrompida | G53: média | H53: O padrão de três (Técnico mais Comercial mais Domínio) serve estágios pré-Série A. | I53: Troca mecânica de símbolos por palavras: '+' virou 'mais' (480, 657, 1549) e 'vs.' virou 'contra' ('gastar contra poupar', 493, 'Como trata garçom contra como trata CEO', 513). | J53: Reescrever: "O trio técnico, comercial e de domínio basta antes da Série A" e "Como trata o garçom e como trata o CEO". Buscar " mais " e " contra " entre substantivos em todo o volume. | K53: sim | L53: 6 | M53: não | Q53: Revisor de trecho | R53: Corrigido
A54: 53 | B54: 1 | C54: 502 | D54: FASE 0 | E54: N7 | F54: Autoridade forçada ou atribuição duvidosa | G54: média | H54: Use estruturas como o "Relationship Red Flags" do Founder Institute ou o founder compatibility interview do Nathan Rose. | I54: Duas referências que o leitor não vai achar: não há registro conhecido desses roteiros com esses nomes. Na 504, as opções 'primeira, segunda, terceira' viram 'opções A ou B'. | J54: Verificar. Sem fonte, trocar por um roteiro próprio de dez perguntas no Caderno de Campo e uniformizar a numeração das opções. | K54: não | L54: 1 | M54: sim | Q54: Revisor de trecho | R54: Corrigido
A55: 54 | B55: 1 | C55: 512 | D55: FASE 0 | E55: E9 | F55: Erro gramatical ou frase corrompida | G55: média | H55: 5. Discordância em regime patrimonial. Um quer muito, outro quer médio. | I55: O termo 'regime patrimonial' vem do direito de família (regime de bens). O sentido aqui é ambição de patrimônio ou de tamanho da empresa. | J55: Reescrever: "5. Ambição desalinhada. Um quer construir algo enorme, o outro quer uma empresa de ritmo sustentável." | K55: não | L55: 1 | M55: não | Q55: Revisor de trecho | R55: Corrigido
A56: 55 | B56: 1 | C56: 524 | D56: FASE 0 | E56: C5 | F56: Contradição interna | G56: média | H56: - [ ] Trabalhamos juntos em projeto com prazo e entrega por pelo menos 4 semanas. | I56: Três prazos para testar o sócio: três a seis meses (500), pelo menos quatro semanas (524), quatro a oito semanas com 'seis semanas' na mesma linha (558). | J56: Fixar piso e ideal, "no mínimo seis semanas, idealmente três meses", e repetir igual nos três pontos. | K56: não | L56: 1 | M56: não | Q56: Revisor de trecho | R56: Corrigido
A57: 56 | B57: 1 | C57: 535 | D57: FASE 0 | E57: C7 | F57: Conselho arriscado sem ressalva | G57: média | H57: O FAST (Founder Advisor Standard Template, criado por Adeo Ressi no Founder Institute em 2011), contrato padrão para formalizar a relação com advisors | I57: FAST é modelo americano. Numa LTDA, dar de 0,1% a 1% a advisor (578) exige alteração contratual ou opção de compra, e vesting de quotas pede contrato próprio. Falta a ressalva. | J57: Acrescentar: "No Brasil a maioria das startups nasce LTDA. Participação para advisor ou vesting entre sócios pede contrato de opção ou cláusula no acordo de quotistas. Valide com advogado." Alinhar a faixa ao Cap. 13 (0,1% a 0,5%). | K57: não | L57: 1 | M57: não | Q57: Revisor de trecho | R57: Corrigido
A58: 57 | B58: 1 | C58: 542 | D58: FASE 0 | E58: S5 | F58: Duplicação com outro capítulo ou volume | G58: média | H58: Sobre equity split, três princípios. Divisão cinquenta-cinquenta exata é comum mas gera conflito em decisões empatadas. | I58: Sobrepõe o Cap. 2 do volume ('As bombas-relógio societárias: 50/50 sem desempate, falta de vesting', linha 5771). E o vesting 'agressivo' da 537 vira 'padrão' aqui. | J58: Deixar na Fase 0 a decisão de ter ou não sócio e o teste antes de fundar. Equity, 50/50 e vesting ficam no Cap. 2, com remissão de uma linha. | K58: não | L58: 1 | M58: não | Q58: Revisor de trecho | R58: Corrigido
A59: 58 | B59: 1 | C59: 548 | D59: FASE 0 | E59: S7 | F59: Artefato de formatação | G59: média | H59: Capítulo 11 (IA COMO CO-PILOTO DO FUNDADOR (2026)) | I59: Remissões geradas por script com o título em caixa alta entre parênteses, às vezes aninhados ou dobrados ('Capítulo 12 (...) (Vol. 6)'). São 23 no trecho e pesam na leitura. | J59: Padrão curto: "o Capítulo 11 (IA como copiloto)" ou só "o Capítulo 11", com o link no número. | K59: sim | L59: 23 | M59: não | Q59: Revisor de trecho | R59: Corrigido
A60: 59 | B60: 1 | C60: 557 | D60: FASE 0 | E60: C2 | F60: Informação possivelmente desatualizada | G60: média | H60: **Antler** opera no Brasil, com programa residencial intensivo em que squads se formam ao longo de algumas semanas. | I60: Lista que muda rápido: presença da Antler no Brasil, fim da On Deck, o que é 'BU21', Distrito e ACE hoje. Na 559, Fenabrave não é evento de fundadores e o Startup Weekend pode ter acabado. | J60: Verificar item por item, datar a lista ("programas ativos em 2026") e cortar o que não se confirmar, como "BU21" e Fenabrave. | K60: não | L60: 1 | M60: sim | Q60: Revisor de trecho | R60: Corrigido
A61: 60 | B61: 1 | C61: 579 | D61: FASE 0 | E61: C5 | F61: Contradição interna | G61: média | H61: - [ ] Mapeei pessoas afetadas pela decisão (cônjuge, pais, dependentes) e tenho concordância explícita delas, documentada em um parágrafo. | I61: A trava exige concordância explícita de cônjuge e pais. O fluxograma aceita família neutra e o sinal 7 só barra oposição forte. Os pais como condição aparecem só aqui. | J61: Reescrever: "...e tive a conversa estruturada com elas, com apoio ou neutralidade registrados em um parágrafo. Oposição forte aciona o sinal 7." | K61: não | L61: 1 | M61: não | Q61: Revisor de trecho | R61: Corrigido
A62: 61 | B62: 1 | C62: 596 | D62: FASE 0 | E62: N9 | F62: Título que promete o que o corpo não entrega | G62: média | H62: ### Onde os otimistas tropeçam: otimismo financeiro, sociedade de bar e fuga disfarçada | I62: O título promete 'fuga disfarçada', mas o corpo traz 'subestimar impacto psicológico'. O resumo operacional (660 a 663) lista um terceiro trio de armadilhas. | J62: Unificar as três armadilhas da fase e usar as mesmas no título, no corpo e no resumo. | K62: não | L62: 1 | M62: não | Q62: Revisor de trecho | R62: Corrigido
A63: 62 | B63: 1 | C63: 611 | D63: FASE 0 | E63: S6 | F63: Seção desproporcional ou fora de lugar | G63: média | H63: ### CASO BRASILEIRO — Nubank: do reconhecimento da dor à confirmação de modelo | I63: O único caso real da fase fala de PMF, fila, NPS, rodadas e IPO, e apresenta os sócios três vezes (615, 617, 621). Nada sobre runway pessoal, família ou motivação, o tema da Fase 0. | J63: Reduzir o Nubank a um parágrafo sobre o "por que eu" de cada sócio e trocar o caso por um de preparação pessoal (fundador que montou reserva antes de sair). Levar PMF e IPO à Fase 13. | K63: não | L63: 1 | M63: não | Q63: Revisor de trecho | R63: Corrigido
... A74: 73 | B74: 1 | C74: 730 | D74: FASE 0 | E74: E9 | F74: Erro gramatical ou frase corrompida | G74: média | H74: Collins descreve companies que levaram 4+ anos para descobrir seu hedgehog. | I74: Palavras inglesas soltas no meio da frase, restos de tradução: 'companies' (730), 'rituals' (841), 'recipient' (957), 'wasted' (1010), 'governments' (1028), 'Conflicts' (1255). | J74: Reescrever: "Collins descreve empresas que levaram mais de quatro anos para achar o seu conceito do ouriço." Buscar e traduzir os demais. | K74: sim | L74: 7 | M74: não | Q74: Revisor de trecho | R74: Corrigido
A75: 74 | B75: 1 | C75: 736 | D75: FASE 0 | E75: C2 | F75: Informação possivelmente desatualizada | G75: média | H75: Walgreens (exemplo de Collins): | I75: Exemplo sem ressalva em 2026: a Walgreens encolheu e saiu da bolsa em 2025, comprada por um fundo. E os 15x de Collins cobrem 1975 a 2000, não 'por 15 anos' como diz a linha 741. | J75: Verificar e acrescentar uma frase: a Walgreens que Collins estudou perdeu o rumo duas décadas depois, lembrete de que o foco precisa ser revisto. Corrigir o período. | K75: não | L75: 1 | M75: sim | N75: desatualizado | O75: A Walgreens Boots Alliance foi comprada pela Sycamore Partners e saiu da Nasdaq em agosto de 2025, como empresa de capital fechado. O exemplo de Collins pede essa ressalva. | P75: https://www.sec.gov/Archives/edgar/data/1618921/000119312525190603/d87240dex991.htm | Q75: Revisor de trecho | R75: Corrigido
A76: 75 | B76: 1 | C76: 743 | D76: FASE 0 | E76: N3 | F76: Arquétipo inconsistente, decorativo ou ausente | G76: média | H76: Startup brasileira (aplicando): | I76: Onde a bíblia faria diferença, o manual usa empresa hipotética (Hedgehog), squad da Loggi (Team Canvas) e Série A (template). E o 'exemplo brasileiro' prometido (704) falta em vários frameworks. | J76: Preencher o Hedgehog com Lucas e Marina, o Team Canvas com Rafael e Bia antes do acordo de sócios e o template de advisor com Camila decidindo se pede demissão. | K76: sim | L76: 4 | M76: não | Q76: Revisor de trecho | R76: Corrigido
A77: 76 | B77: 1 | C77: 756 | D77: FASE 0 | E77: C5 | F77: Contradição interna | G77: alta | H77: Muito early: hedgehog emerge com tempo e iteração, Em organizações sem estabilidade para perseguir por 5+ anos. | I77: A ferramenta manda ficar na gaveta quando é cedo demais, e o livro a põe na Fase 0, antes da ideia. A lista virou vírgulas com 'Em' maiúsculo, falha repetida em 850, 1014 e 1072. | J77: Levar o Hedgehog para a Fase 2 ou 3, ou adaptá-lo à pessoa: "em que você pode ser muito bom, o que paga as suas contas e o que você ama". Refazer essas listas como itens. | K77: não | L77: 1 | M77: não | Q77: Revisor de trecho | R77: Corrigido
A78: 77 | B78: 1 | C78: 785 | D78: FASE 0 | E78: C3 | F78: Erro factual provável | G78: alta | H78: Fundadores seriais brasileiros. Quando David Vélez criou o Nubank | I78: Vélez é colombiano e o Nubank foi sua primeira empresa. Kalim também não era fundador serial. O pensamento entre aspas é atribuído a Vélez sem fonte, e o Nubank nasceu com aporte de fundos. | J78: Trocar o rótulo por "Como fundadores experientes aplicam" e usar fato verificável, sem monólogo inventado. Ou escolher um caso de fato efetual, de quem começou com o que tinha à mão. | K78: não | L78: 1 | M78: sim | N78: erro confirmado | O78: David Vélez é colombiano e vinha de fundos de investimento (General Atlantic e Sequoia), sem empresa própria registrada antes do Nubank. O Nubank começou com cerca de US$ 2 milhões de Sequoia e Kaszek. | P78: https://forbes.com.br/forbes-money/2021/07/como-david-velez-enfrentou-os-gigantes-do-setor-bancario-brasileiro-e-criou-o-banco-digital-mais-valioso-do-mundo/ | Q78: Revisor de trecho | R78: Corrigido
A79: 78 | B79: 1 | C79: 801 | D79: FASE 0 | E79: S5 | F79: Duplicação com outro capítulo ou volume | G79: média | H79: #### Framework: First Principles Thinking (Aristóteles, ~350 a.C.; popularizado por Elon Musk, anos 2010) | I79: Ferramentas copiadas em outros volumes: First Principles (v02), Cynefin, Red Team e Pre-mortem (v03), Valor Esperado (v03, v08), Pre-mortem (v09), Team Canvas (v06, v07), template de advisor (v02). | J79: Manter cada ferramenta inteira em um só volume e, nos outros, um parágrafo com o uso específico da fase e a remissão. | K79: sim | L79: 10 | M79: não | Q79: Revisor de trecho | R79: Corrigido
A80: 79 | B80: 1 | C80: 805 | D80: FASE 0 | E80: E9 | F80: Erro gramatical ou frase corrompida | G80: alta | H80: que definia "primeiros princípios" como "o primeiro basis from which a thing is known" | I80: Citação de Aristóteles meio traduzida, com português e inglês misturados, justo na seção sobre a origem do método. | J80: Reescrever: 'que definia primeiro princípio como "o primeiro ponto a partir do qual algo é conhecido" (Metafísica, livro V)'. Conferir o livro indicado na bibliografia, que diz livro IV (854). | K80: não | L80: 1 | M80: não | Q80: Revisor de trecho | R80: Corrigido
A81: 80 | B81: 1 | C81: 930 | D81: FASE 0 | E81: C1 | F81: Dado sem fonte ou precisão inventada | G81: média | H81: 90% das startups falham — mas todo fundador tem razões para acreditar que a sua é a exceção. | I81: O trecho que ensina a buscar a taxa-base usa uma taxa-base sem fonte, e 'falhar' muda de sentido conforme o estudo. | J81: Citar fonte e recorte (por exemplo, sobrevivência de empresas em cinco anos segundo IBGE ou Sebrae) ou escrever "a maioria das startups não chega a dar retorno". | K81: não | L81: 1 | M81: sim | Q81: Revisor de trecho | R81: Corrigido
A82: 81 | B82: 1 | C82: 934 | D82: FASE 0 | E82: E9 | F82: Erro gramatical ou frase corrompida | G82: média | H82: Não é possível eliminar vieses cognitivos — são fiados em arquitetura neural. | I82: A palavra 'fiados' está trocada (talvez de 'hardwired'). Na mesma linha, remissões aninhadas como '(Framework: Pre-mortem (Gary Klein, 2007) (Fase 0))' parecem saída de script. | J82: Reescrever: "Não dá para eliminar vieses: eles fazem parte de como o cérebro funciona. Dá para criar processos que os atenuem, como o pre-mortem e o red team desta fase." | K82: não | L82: 1 | M82: não | Q82: Revisor de trecho | R82: Corrigido
A83: 82 | B83: 1 | C83: 977 | D83: FASE 0 | E83: C5 | F83: Contradição interna | G83: média | H83: Passo 1, Após plano existir. Fazer pre-mortem antes de existir plano gera lista teórica sem tração. | I83: Contradiz a linha 681, que indica o pre-mortem antes da decisão de empreender. Na Fase 0 ainda não há plano de negócio, então a regra do manual veta o uso que a fase propõe. | J83: Adaptar: "Na Fase 0, o plano é a sua decisão de vida (sair do emprego em março, viver da reserva por 12 meses). Faça o pre-mortem desse plano." | K83: não | L83: 1 | M83: não | Q83: Revisor de trecho | R83: Corrigido
A84: 83 | B84: 1 | C84: 991 | D84: FASE 0 | E84: S6 | F84: Seção desproporcional ou fora de lugar | G84: alta | H84: Pre-mortem antes de iniciar expansão para México: | I84: O manual da Fase 0 foi escrito para empresa com time: SDRs e AEs (823), M&A (893, 1058), expansão ao México, pivô com ARR (1136), Série A (1377). O leitor ainda decide se empreende. | J84: Reescrever os exemplos para a decisão pessoal: pre-mortem de "larguei o emprego e deu errado em 18 meses", valor esperado de ficar na CLT ou empreender, red team com cônjuge e advisor. Usar as crenças da linha 675. | K84: sim | L84: 7 | M84: não | Q84: Revisor de trecho | R84: Corrigido
A85: 84 | B85: 1 | C85: 1105 | D85: FASE 0 | E85: E9 | F85: Erro gramatical ou frase corrompida | G85: média | H85: EV = (0.4 × 5M) + (0.4 × 1M) + (0.2 × 0) = R$ 2.4M. | I85: Decimais com ponto e 'M' à inglesa (12 casos no trecho). Para o leitor brasileiro, 'R$ 2.4M' se lê errado, e a linha 649 usa vírgula. | J85: Reescrever: "VE = (0,4 × 5) + (0,4 × 1) + (0,2 × 0) = R$ 2,4 milhões". Traduzir EV por VE (valor esperado) em todo o bloco. | K85: sim | L85: 12 | M85: não | Q85: Revisor de trecho | R85: Corrigido
A86: 85 | B86: 1 | C86: 1160 | D86: FASE 0 | E86: E9 | F86: Erro gramatical ou frase corrompida | G86: alta | H86: jogar russos roleta com EV positivo mas 17% de morte não é decisão racional | I86: Frase corrompida: 'russos roleta' no lugar de 'roleta-russa'. | J86: Reescrever: "(jogar roleta-russa com valor esperado positivo e 17% de chance de morrer não é decisão racional)". | K86: não | L86: 1 | M86: não | Q86: Revisor de trecho | R86: Corrigido
A87: 86 | B87: 1 | C87: 1220 | D87: FASE 0 | E87: C5 | F87: Contradição interna | G87: alta | H87: Use o Team Canvas na Fase 14 (escala e time) como artefato de onboarding de novos squads | I87: Contradiz a Fase 0 (436 manda usar antes de começar), e a Fase 14 é 'Capital para escala', não time. Bloco colado dos Vols. 6 e 7 sem ajuste, com quatro durações de sessão (1176, 1220, 1226, 1228). | J87: Reescrever: "Use o Team Canvas quando dois ou mais sócios decidem fundar juntos, antes do acordo de sócios. Volte a ele na Fase 16, ao montar a liderança." Fixar uma duração, 90 minutos. | K87: não | L87: 1 | M87: não | Q87: Revisor de trecho | R87: Corrigido
A88: 87 | B88: 1 | C88: 1243 | D88: FASE 0 | E88: C4 | F88: Caso real com detalhe possivelmente inventado | G88: alta | H88: Quando a Loggi decidiu expandir de São Paulo para 15 cidades em 12 meses (2019), formou um squad de expansão | I88: Documento interno atribuído a empresa real, com falas de funcionários e metas (NPS ≥ 45, CAC ≤ R$ 800) sem fonte. Parece inventado. A cronologia da expansão da Loggi também pede checagem. | J88: Verificar. Sem fonte pública, trocar por caso fictício declarado, de preferência Rafael e Bia preenchendo o canvas antes de formalizar a sociedade. | K88: não | L88: 1 | M88: sim | Q88: Revisor de trecho | R88: Corrigido
A89: 88 | B89: 1 | C89: 1283 | D89: FASE 0 | E89: C2 | F89: Informação possivelmente desatualizada | G89: baixa | H89: - [teamcanvas.com](https://www.teamcanvas.com) — Alex Ivanov mantém o site com templates e estudos de caso. | I89: Referências que podem ter envelhecido: o site do Team Canvas parece ser theteamcanvas.com, a Cognitive Edge (910) virou The Cynefin Company e Graham publicou ensaios depois de 2024 (1541). | J89: Verificar e atualizar: domínio do Team Canvas, nome atual da empresa de Snowden e "mais de duzentos ensaios desde 1993". | K89: sim | L89: 3 | M89: sim | Q89: Revisor de trecho | R89: Corrigido
A90: 89 | B90: 1 | C90: 1294 | D90: FASE 0 | E90: E9 | F90: Erro gramatical ou frase corrompida | G90: alta | H90: Template: Entrevista com Especialista de Mercado (mapa de setor · Fases 3-5) (Fase 1) (especialista) | I90: Remissão corrompida por script: três parênteses seguidos, 'Fases 3-5' e 'Fase 1' juntos, sem link. O leitor não sabe para onde ir. | J90: Reescrever: "volte para a Entrevista de Problema ou para a Entrevista com Especialista de Mercado, as duas na Fase 1", com links. | K90: não | L90: 1 | M90: não | Q90: Revisor de trecho | R90: Corrigido
A91: 90 | B91: 1 | C91: 1535 | D91: FASE 0 | E91: S6 | F91: Seção desproporcional ou fora de lugar | G91: média | H91: #### Leituras fundamentais (livros) | I91: As leituras da Fase 0 tratam de cliente, produto e vendas (Mom Test, Running Lean, Predictable Revenue). Nada sobre finanças pessoais ou sócios. Faltam Gerber, que abre a fase, e Wasserman (425). | J91: Para a Fase 0: O Mito do Empreendedor (Gerber), The Founder's Dilemmas (Wasserman), O Lado Difícil das Situações Difíceis (Horowitz). Levar as demais à Fase 4. | K91: não | L91: 1 | M91: não | Q91: Revisor de trecho | R91: Corrigido
A92: 91 | B92: 1 | C92: 1537 | D92: FASE 0 | E92: C3 | F92: Erro factual provável | G92: alta | H92: *Jobs to Be Done*, de Anthony Ulwick e Clayton Christensen | I92: Não existe livro com esse título escrito pelos dois. Ulwick publicou 'Jobs to be Done: Theory to Practice' (2016) e Christensen 'Competing Against Luck' (2016), de escolas rivais. | J92: Citar as duas obras separadas, com autor e ano, e dizer em uma linha que divergem. | K92: não | L92: 1 | M92: não | N92: erro confirmado | O92: São dois livros: 'Jobs to be Done: Theory to Practice', de Anthony Ulwick (2016), e 'Competing Against Luck', de Clayton Christensen, Taddy Hall e Karen Dillon (2016). | P92: https://www.goodreads.com/book/show/32809558 | Q92: Revisor de trecho | R92: Corrigido
A93: 92 | B93: 1 | C93: 1537 | D93: FASE 0 | E93: E9 | F93: Erro gramatical ou frase corrompida | G93: média | H93: *tração*, de Gabriel Weinberg | I93: Título em minúscula, resto da troca mecânica de 'Traction'. Falta o coautor Justin Mares. | J93: Usar "*Traction*, de Gabriel Weinberg e Justin Mares" e conferir o título da edição brasileira, se houver. | K93: não | L93: 1 | M93: não | Q93: Revisor de trecho | R93: Corrigido
A94: 93 | B94: 1 | C94: 1541 | D94: FASE 0 | E94: N7 | F94: Autoridade forçada ou atribuição duvidosa | G94: média | H94: Boa parte do que eu articulo nesse livro tem raiz naqueles textos. | I94: Graham é a autoridade de fato da Fase 0 (seis ensaios, lista de 27 textos, one-pager), mas não está entre os dez livros da Nota do autor. E a referência do livro inteiro mora dentro da Fase 0. | J94: Incluir Graham na Nota ou reduzir o peso dele aqui. Mover "Ensaios canônicos" e "Startups em 13 frases" para um apêndice do volume. Trocar "nesse livro" por "neste livro". | K94: não | L94: 1 | M94: não | Q94: Revisor de trecho | R94: Corrigido
A95: 94 | B95: 1 | C95: 1588 | D95: FASE 0 | E95: C3 | F95: Erro factual provável | G95: média | H95: "A startup pode ter mais potencial de longo prazo, mas você sempre vai interromper o trabalho nela para trabalhar em outra coisa." | I95: A tradução apaga o ponto de Graham: as piores distrações são as que pagam (emprego, consultoria). Isso bate de frente com 'empreenda em paralelo' e com Lucas e Marina vendendo serviço. | J95: Traduzir fiel ("para atender quem paga você agora") e assumir a divergência: "No Brasil, vender serviço muitas vezes financia o produto. Limite as horas e marque a data de corte." | K95: não | L95: 1 | M95: sim | Q95: Revisor de trecho | R95: Corrigido
A96: 95 | B96: 1 | C96: 1592 | D96: FASE 0 | E96: S4 | F96: Remissão quebrada ou em excesso | G96: média | H96: Aplicação: apêndice sobre Pivot. | I96: Não há apêndice sobre pivô no volume. Remissão herdada de estrutura antiga, repetida no Cap. 3 (6290). | J96: Apontar para o capítulo de pivô do Vol. 4, com link. | K96: não | L96: 1 | M96: não | Q96: Revisor de trecho | R96: Corrigido
A97: 96 | B97: 1 | C97: 1600 | D97: FASE 0 | E97: S7 | F97: Artefato de formatação | G97: baixa | H97: > Referenciado em: Fase 0. | I97: Bastidor de script vazado: dentro da Fase 0, o callout diz que o bloco é referenciado na Fase 0. A ressalva de checagem da 335 ('não citação literal') tem a mesma origem. | J97: Cortar o callout. Na 335, escrever a síntese como do autor, sem aspas, e tirar a ressalva. | K97: sim | L97: 2 | M97: não | Q97: Revisor de trecho | R97: Corrigido
A98: 97 | B98: 1 | C98: 1606 | D98: FASE 0 | E98: E10 | F98: Repetição, redundância, enchimento | G98: média | H98: Empreender não é primariamente um ato técnico. É um ato psicológico, e financeiro, sustentado por meses, ou anos. | I98: O fechamento repete quase palavra por palavra a linha 197, e 'qualquer crise do negócio derruba tudo' (1610) também vem de lá. O leitor reconhece a cópia. | J98: Fechar com o que mudou: voltar a Camila com o dossiê pronto, dizer o que ela decidiu e o que a Fase 1 vai pedir. | K98: não | L98: 1 | M98: não | Q98: Revisor de trecho | R98: Corrigido
A99: 98 | B99: 1 | C99: 1608 | D99: FASE 0 | E99: E12 | F99: Frase longa demais | G99: média | H99: A diferença entre quem faz certo, e quem falha, está na honestidade do diagnóstico inicial. | I99: Vírgulas soltas herdadas da troca mecânica de travessões, como em 'psicológico, e financeiro, sustentado por meses, ou anos' (1606) e na lista de indicadores do caso Nubank (625). | J99: Reescrever: "A diferença entre quem acerta e quem falha está na honestidade do diagnóstico." Na 625, uma frase por indicador. | K99: sim | L99: 8 | M99: não | Q99: Revisor de trecho | R99: Corrigido
A100: 99 | B100: 1 | C100: 1618 | D100: FASE 1 | E100: N3 | F100: Arquétipo inconsistente, decorativo ou ausente | G100: alta | H100: Em uma cafeteria em Pinheiros, **Lucas** (engenheiro de software recém-saído de um grande banco) mostra orgulhoso para **Marina** (sua futura sócia comercial) um caderno com três ideias | I100: Lucas e Marina aparecem só aqui e em L1622. Em 1.539 linhas nenhum método ou filtro é aplicado ao caso deles e a fase termina sem voltar à cena. Arquétipo decorativo. | J100: Fazer Lucas e Marina atravessarem a fase: Lucas roda o Método 1 sobre o que viu no banco, as três ideias do caderno caem nos 4 filtros e sobra uma dor B2B que prepara o arco do Vol. 1 a 4. A Lição de bolso fecha com o caderno reescrito. | K100: não | L100: 1 | M100: não | Q100: Revisor de trecho | R100: Corrigido
A101: 100 | B101: 1 | C101: 1618 | D101: FASE 1 | E101: E9 | F101: Erro gramatical ou frase corrompida | G101: média | H101: qual dessas três pessoas acordou às sete da manhã suando frio e disposta a passar o cartão corporativo para resolver isso? | I101: A pergunta trata ideias como pessoas e cobra cartão corporativo de três ideias de consumo (pets, conta de bar, chef em casa). O leitor atento tropeça na lógica da cena. | J101: Reescrever: "Lucas, quem usaria cada uma dessas ideias, e qual dessas pessoas perdeu tempo ou dinheiro com isso na última terça a ponto de pagar?" Se quiser manter o cartão corporativo, use-o como a deixa que leva o casal ao B2B. | K101: não | L101: 1 | M101: não | Q101: Revisor de trecho | R101: Corrigido
A102: 101 | B102: 1 | C102: 1620 | D102: FASE 1 | E102: N7 | F102: Autoridade forçada ou atribuição duvidosa | G102: média | H102: Peter Thiel abre *De Zero a Um* perguntando qual verdade importante você enxerga e quase ninguém concorda. | I102: Thiel entra como trampolim decorativo. A tese do tédio é a Schlep Blindness de Graham, que a fase só cita na tabela de métricas (L2013), em inglês e sem explicação. | J102: Ancorar a tese em Graham: problemas trabalhosos e chatos afastam quase todos os fundadores, e por isso sobram (o caso dele é a Stripe). A pergunta de Thiel pode abrir o Espelho. | K102: não | L102: 1 | M102: não | Q102: Revisor de trecho | R102: Corrigido
A103: 102 | B103: 1 | C103: 1620 | D103: FASE 1 | E103: E3 | F103: Adjetivo inflado ou intensificador | G103: média | H103: Na geração de ideias, a verdade contraintuitiva é brutal: **as ideias mais lucrativas do Brasil quase nunca parecem "geniais" ou cinematográficas à primeira vista | I103: Adjetivo da lista proibida (brutal) e negrito numa frase inteira de quatro linhas, com travessão no meio. O parágrafo grita em vez de afirmar. | J103: "Na geração de ideias, a resposta contraintuitiva é esta: as ideias que mais dão lucro parecem problemas operacionais chatos, que todo mundo aprendeu a tolerar." Sem negrito e sem "do Brasil", que o texto não sustenta. | K103: não | L103: 1 | M103: não | Q103: Revisor de trecho | R103: Corrigido
A104: 103 | B104: 1 | C104: 1622 | D104: FASE 1 | E104: N1 | F104: Abertura sem tensão ou em fórmula | G104: média | H104: Chamamos o erro de Lucas de | I104: Abertura na mesma fórmula das Fases 0, 2 e 3: cena "Em [cidade], [arquétipo]", autor do cânone com frase em negrito, depois "Chamamos... de [Nome]". Em leitura corrida, o molde aparece. | J104: Variar nesta fase: abrir direto na pergunta de Marina, guardar Thiel ou Graham para depois do primeiro método e deixar o nome do erro nascer da fala da cena. | K104: não | L104: 1 | M104: não | Q104: Revisor de trecho | R104: Corrigido
... A126: 125 | B126: 1 | C126: 1786 | D126: FASE 1 | E126: S7 | F126: Artefato de formatação | G126: média | H126: Capítulo 5 (IDEA → WEDGE → SCALE: O FRAMEWORK ANTLER COMO LENTE TRANSVERSAL) (Vol. 3)]] | I126: Rótulo de link gerado por script, com o título inteiro em caixa alta entre parênteses e "(Vol. 3)". Em L1930 há parênteses aninhados. O callout ainda diz "founders". | J126: Rótulo curto, como "Capítulo 5 do Vol. 3". Fundir os callouts de L1929 e L1932 numa linha só. | K126: sim | L126: 6 | M126: não | Q126: Revisor de trecho | R126: Corrigido
A127: 126 | B127: 1 | C127: 1794 | D127: FASE 1 | E127: C3 | F127: Erro factual provável | G127: alta | H127: Wellhub (anteriormente Gympass) não começou pensando "academias para empresas". Começou pelo departamento de RH de empresa grande | I127: Provável erro: o Gympass nasceu vendendo diárias avulsas ao consumidor e depois migrou para o benefício corporativo. E a frase se contradiz: RH pagando academia é "academias para empresas". | J127: Verificar a origem. Se a virada se confirmar, o caso fica melhor como cunha achada no caminho: começou no consumidor, encontrou no RH um comprador com orçamento e cresceu ali. | K127: não | L127: 1 | M127: sim | N127: erro confirmado | O127: O Gympass, fundado em 2012, começou vendendo ao consumidor final (B2C). Depois de conflitos de repasse com as academias, reestruturou o modelo para venda direta a empresas. | P127: https://neofeed.com.br/videos/vida-de-startup/por-que-as-academias-quase-faliram-o-gympass | Q127: Revisor de trecho | R127: Corrigido
A128: 127 | B128: 1 | C128: 1813 | D128: FASE 1 | E128: E3 | F128: Adjetivo inflado ou intensificador | G128: média | H128: ### A peneira implacável: os 4 filtros que matam ideias sedutoras antes que elas matem seu caixa | I128: Adjetivos da lista proibida e intensificadores em série: implacável, brutal (L1620), catastrófico (L1640), críticos (L1699), gigante (L1892, L1948), Fundamental (L1907), inimitável (L2469). | J128: Título: "Quatro filtros antes do caixa". No corpo, trocar o adjetivo pelo custo concreto: "anos perdidos", "seis meses de salário". | K128: sim | L128: 15 | M128: não | Q128: Revisor de trecho | R128: Corrigido
A129: 128 | B129: 1 | C129: 1819 | D129: FASE 1 | E129: N8 | F129: Abstração sem caso concreto | G129: baixa | H129: title "Mapa de qualidade de ideia (posições ilustrativas, não pontuação calculada)" | I129: Gráfico decorativo: põe Nubank e iFood num eixo de FMF sem dizer de quem, ignora o filtro de defesa e admite que as posições são inventadas. | J129: Trocar por uma tabela com os 4 filtros aplicados às três ideias de Lucas e à candidata que sobrou. | K129: não | L129: 1 | M129: não | Q129: Revisor de trecho | R129: Corrigido
A130: 129 | B130: 1 | C130: 1837 | D130: FASE 1 | E130: C6 | F130: Lacuna relevante para o fundador brasileiro | G130: média | H130: o que impede um incumbente grande, Nubank, iFood, Mercado Livre, Magazine Luiza, Natura, Google, de copiar em dezoito meses e te esmagar | I130: Em 2026 o risco de defesa mais comum para ideia com IA é o dono do modelo (OpenAI, Google, Anthropic) lançar o recurso. O filtro ignora isso, e é o caso de Lucas e Marina. | J130: Acrescentar a pergunta "Se o próximo modelo de IA fizer isso sozinho, o que sobra?". Respostas que sobrevivem: dado próprio, integração com o sistema do cliente, regulação, distribuição. | K130: não | L130: 1 | M130: não | Q130: Revisor de trecho | R130: Corrigido
A131: 130 | B131: 1 | C131: 1839 | D131: FASE 1 | E131: E9 | F131: Erro gramatical ou frase corrompida | G131: média | H131: são dos piores ofensores. Morrem a maioria. | I131: Concordância e decalque do inglês (offenders). O mesmo deslize em "juros alto que favorece" (L1835) e "Quatro a sete métodos aumenta" (L1954). | J131: "estão entre as que mais morrem." Corrigir para "juros altos que favorecem" e "aumentam". | K131: sim | L131: 4 | M131: não | Q131: Revisor de trecho | R131: Corrigido
A132: 131 | B132: 1 | C132: 1841 | D132: FASE 1 | E132: N8 | F132: Abstração sem caso concreto | G132: média | H132: No fim dos quatro filtros, idealmente você tem três a cinco ideias-candidatas finais. Escolha uma. | I132: Os filtros nunca são aplicados a um caso. O leitor recebe quatro perguntas e nenhum exemplo de resposta boa ou ruim, apesar da cena pronta no início da fase. | J132: Inserir tabela curta: as três ideias do caderno de Lucas e a dor que ele conhece do banco, uma linha por filtro e o veredito. Mostra na prática o que é resposta honesta. | K132: não | L132: 1 | M132: não | Q132: Revisor de trecho | R132: Corrigido
A133: 132 | B133: 1 | C133: 1846 | D133: FASE 1 | E133: C5 | F133: Contradição interna | G133: alta | H133: ### Protocolo de 5 dias: como sair do zero para uma Lista Curta blindada em uma semana | I133: Promete Lista Curta em uma semana, mas L1644 diz que menos de duas semanas indica escolha precipitada e o Método 2 pede diário de duas semanas antes da terça. | J133: Assumir a semana como fechamento: ela vem depois de duas semanas de diário de fricções. Título: "Cinco dias para fechar a Lista Curta", com o pré-requisito dito na primeira linha. | K133: não | L133: 1 | M133: não | Q133: Revisor de trecho | R133: Corrigido
A134: 133 | B134: 1 | C134: 1865 | D134: FASE 1 | E134: C5 | F134: Contradição interna | G134: alta | H134: Quinta : Technology Wave + Wedge | I134: Diagrama e prosa divergem: no gráfico a quinta é Onda e Cunha (Métodos 5 e 6), no texto (L1881) é conversa de calibragem. O Método 5 cai na quarta e na quinta. Métodos 3 e 7 somem. | J134: Escolher uma versão e atualizar gráfico e prosa juntos. Por exemplo: quarta com Métodos 4, 5 e 6, quinta com as conversas de calibragem, Métodos 3 e 7 como tarefa da quinta à noite. | K134: não | L134: 1 | M134: não | Q134: Revisor de trecho | R134: Corrigido
A135: 134 | B135: 1 | C135: 1883 | D135: FASE 1 | E135: C5 | F135: Contradição interna | G135: alta | H135: Consolide toda a lista gerada (deve ter vinte a quarenta itens). | I135: A meta de candidatas muda cinco vezes: 15 a 30 (L1628, L1815, L1938), 20 a 40 aqui, 20 ou mais (L2011), Regra das 20 (L1969) e mais de 40 como indisciplina (L1952). | J135: Fixar uma faixa, por exemplo 20 a 30, e repetir o mesmo número no checklist, no Espelho, nas métricas e no Resumo operacional. | K135: não | L135: 1 | M135: não | Q135: Revisor de trecho | R135: Corrigido
A136: 135 | B136: 1 | C136: 1887 | D136: FASE 1 | E136: N9 | F136: Título que promete o que o corpo não entrega | G136: alta | H136: ### As 5 ciladas clássicas: da ideia "Tinder de X" ao perfeccionismo paralisante | I136: O título promete cinco ciladas, "Tinder de X" e perfeccionismo. O corpo lista nove armadilhas e não trata de nenhuma das duas. | J136: Retitular "Nove armadilhas desta fase" ou cortar para cinco (cansaço, setor quente, plataforma, hobby, cópia dos EUA) e fundir "Uber for X" com o Método 4. | K136: não | L136: 1 | M136: não | Q136: Revisor de trecho | R136: Corrigido
A137: 136 | B137: 1 | C137: 1894 | D137: FASE 1 | E137: E1 | F137: Antítese "não é X, é Y" | G137: média | H137: Setor quente não é ideia. É contexto. | I137: Antítese em dois fragmentos ("não é X. É Y.") repetida na fase: L1628, L1635, L1691, L1731, L1839, L1896, L1909. Vira tique e achata o argumento. | J137: Manter uma por seção. Aqui: "Setor quente é contexto. A ideia é o problema específico que alguém paga para resolver dentro dele." | K137: sim | L137: 12 | M137: não | Q137: Revisor de trecho | R137: Corrigido
A138: 137 | B138: 1 | C138: 1902 | D138: FASE 1 | E138: C2 | F138: Informação possivelmente desatualizada | G138: média | H138: Mas quantas pessoas, especificamente, pagariam R$ 80 no quilo? | I138: Em 2026 o café comum de supermercado já se aproxima desse preço por quilo, e o especial custa várias vezes mais. O número não descreve mais o premium. | J138: Verificar o preço atual e falar em pacote de 250 g de café especial, ou em proporção: "quantas pessoas pagam três vezes o preço do café do mercado?". | K138: não | L138: 1 | M138: sim | Q138: Revisor de trecho | R138: Corrigido
A139: 138 | B139: 1 | C139: 1904 | D139: FASE 1 | E139: C2 | F139: Informação possivelmente desatualizada | G139: média | H139: comportamento cultural (baixa disposição a comprar pets online, alta informalidade em pagamentos) | I139: "Comprar pets online" lê-se como comprar animais. E informalidade alta nos pagamentos não descreve o Brasil do Pix, onde o pagamento digital é massivo. | J139: Trocar por diferenças que se sustentam em 2026: parcelamento sem juros como expectativa, Pix e boleto no lugar do cartão, desconfiança de cobrança recorrente automática. | K139: não | L139: 1 | M139: sim | Q139: Revisor de trecho | R139: Corrigido
... A163: 162 | B163: 1 | C163: 2289 | D163: FASE 1 | E163: N2 | F163: Costura ruim entre cena e conteúdo | G163: média | H163: "Como construir cultura saudável em empresa em escala?" | I163: O exemplo trata de cultura em empresa grande, longe da fase, que vende a Inversion como "peneira final" de ideias. A lista promete 15 itens e mostra 9 mais "etc.". | J163: Exemplo da fase: "Como garantir que meu app para contadores fracasse?" Respostas: ninguém troca de sistema no meio do ano fiscal, o contador não decide sozinho. Cortar "etc.". | K163: não | L163: 1 | M163: não | Q163: Revisor de trecho | R163: Corrigido
A164: 163 | B164: 1 | C164: 2317 | D164: FASE 1 | E164: C3 | F164: Erro factual provável | G164: alta | H164: Clark, K. & Vesterlund, L. (2013). "Decision by default". Research sobre como inversion reduz viés. | I164: Referência com cara de inventada: não há trabalho conhecido de Clark e Vesterlund com esse título sobre inversão. Bibliografia falsa basta para desacreditar o livro. | J164: Verificar. Se não existir, cortar. Alternativas reais: a palestra de Munger sobre a psicologia do erro humano (1995) ou o pre-mortem de Gary Klein (HBR, 2007), já usado na Fase 0. | K164: não | L164: 1 | M164: sim | N164: não verificável | O164: Não achei trabalho de Clark e Vesterlund chamado 'Decision by default'. Lise Vesterlund pesquisa doações e diferenças de gênero, não inversão. | P164: https://en.wikipedia.org/wiki/Lise_Vesterlund | Q164: Revisor de trecho | R164: Corrigido
A165: 164 | B165: 1 | C165: 2386 | D165: FASE 1 | E165: C5 | F165: Contradição interna | G165: média | H165: "Se tivesse uma varinha mágica, o que mudaria?" | I165: Pergunta hipotética sobre o futuro listada como "Bem feito (Mom Test)", contra a regra 2 da seção (L2337) e a lista NÃO PERGUNTAR do template (L2676). | J165: Trocar por pergunta de passado: "Da última vez que isso deu errado, o que você fez no dia seguinte?". | K165: não | L165: 1 | M165: não | Q165: Revisor de trecho | R165: Corrigido
A166: 165 | B166: 1 | C166: 2392 | D166: FASE 1 | E166: C5 | F166: Contradição interna | G166: média | H166: Parar cedo (3 entrevistas não bastam): padrão começa a emergir em 8-12, confidence em 15-25. | I166: O número de entrevistas para confiar num padrão muda a cada página: 8 a 12 e 15 a 25 aqui, 5 ou mais (L2794), 5 a 10 (L2829), 15 a 30 (L2887). Sem fonte. | J166: Adotar uma regra única e dizer de onde vem, por exemplo "padrão entre 8 e 12 conversas com o mesmo perfil, decisão com 15 ou mais", e repetir os mesmos números nos templates. | K166: sim | L166: 5 | M166: não | Q166: Revisor de trecho | R166: Corrigido
A167: 166 | B167: 1 | C167: 2451 | D167: FASE 1 | E167: S4 | F167: Remissão quebrada ou em excesso | G167: média | H167: Use o Lean Canvas a partir da Fase 1 (encontrar a ideia) até a Fase 12 (PMF). | I167: A Fase 12 é Validação do Modelo de Negócio. O PMF é a Fase 13 (Vol. 4). | J167: Trocar por "até a Fase 13 (PMF)". | K167: não | L167: 1 | M167: não | Q167: Revisor de trecho | R167: Corrigido
A168: 167 | B168: 1 | C168: 2473 | D168: FASE 1 | E168: C4 | F168: Caso real com detalhe possivelmente inventado | G168: alta | H168: ##### Exemplo brasileiro preenchido — QuintoAndar em 2015 | I168: Canvas reconstruído apresentado como documento da empresa: "O canvas registra..." e "(e se confirmou)" (L2487) atribuem ao QuintoAndar um Lean Canvas de 2015 sem fonte. | J168: Declarar como exercício: "Como teria ficado o Lean Canvas do QuintoAndar em 2015 (reconstrução do autor com dados públicos)". Tirar "registra" e conferir a proposta, que era sem fiador e sem caução. | K168: não | L168: 1 | M168: sim | Q168: Revisor de trecho | R168: Corrigido
A169: 168 | B169: 1 | C169: 2487 | D169: FASE 1 | E169: E4 | F169: Metadiscurso, abertura enfática, rótulo | G169: baixa | H169: **Insight do caso.** O Lean Canvas do QuintoAndar em 2015 | I169: Cabeçalho pedagógico em negrito, tipo de rótulo já combinado para corte. Repete em L2592. | J169: Entrar direto na frase: "O canvas do QuintoAndar mostra como..." | K169: sim | L169: 2 | M169: não | Q169: Revisor de trecho | R169: Corrigido
A170: 169 | B170: 1 | C170: 2508 | D170: FASE 1 | E170: C5 | F170: Contradição interna | G170: alta | H170: **Se relaciona ao Test Card (Fase 8)**: cada hipótese do Lean Canvas vira um ou mais Test Cards na Fase 7. | I170: Contradição na mesma frase (Fase 8 e Fase 7). E o parágrafo põe o BMC na Fase 2 enquanto L2451 e o fim do parágrafo mandam migrar para o BMC só depois do PMF. | J170: "vira Test Cards na Fase 8 (Vol. 3)". Decidir o papel do BMC: retrato do modelo na Fase 2 ou ferramenta só depois do PMF. Hoje o volume diz as duas coisas. | K170: não | L170: 1 | M170: não | Q170: Revisor de trecho | R170: Corrigido
A171: 170 | B171: 1 | C171: 2522 | D171: FASE 1 | E171: S5 | F171: Duplicação com outro capítulo ou volume | G171: média | H171: W. Chan Kim e Renée Mauborgne, professores do INSEAD, publicaram *Blue Ocean Strategy* em 2005 após quinze anos de pesquisa empírica | I171: Repete quase palavra por palavra a origem do Blue Ocean dada 500 linhas antes (L2027), com tese e vendagem. O ERRC aparece pela terceira vez em L2541. | J171: Fundir Blue Ocean e Strategy Canvas numa só ferramenta, ou abrir o canvas com uma remissão de uma linha ao framework. | K171: não | L171: 1 | M171: não | Q171: Revisor de trecho | R171: Corrigido
A172: 171 | B172: 1 | C172: 2537 | D172: FASE 1 | E172: S7 | F172: Artefato de formatação | G172: média | H172: A linha superior representa o circo tradicional (Ringling, Barnum & Bailey) | I172: As linhas se cruzam (o circo é alto à esquerda, o Cirque à direita), então não há linha superior nem inferior. O xychart não tem legenda e o leitor não sabe qual é qual. | J172: "A linha que começa alta é o circo tradicional", ou trocar o gráfico por tabela com as duas notas lado a lado. O mesmo vale para o gráfico da Stone. | K172: não | L172: 1 | M172: não | Q172: Revisor de trecho | R172: Corrigido
A173: 172 | B173: 1 | C173: 2548 | D173: FASE 1 | E173: S4 | F173: Remissão quebrada ou em excesso | G173: média | H173: Use o Strategy Canvas na Fase 5 (mapeamento de mercado e concorrência) | I173: A Fase 5 é Pesquisa com Usuários, mapeamento de mercado é a Fase 6. E "Fase 15 (reinvenção)" no mesmo parágrafo deveria ser a Fase 19, Reinvenção e Segunda Curva. | J173: Trocar por "na Fase 6 (Vol. 2)" e "na Fase 19 (Vol. 9)". | K173: não | L173: 1 | M173: não | Q173: Revisor de trecho | R173: Corrigido
A174: 173 | B174: 1 | C174: 2564 | D174: FASE 1 | E174: C5 | F174: Contradição interna | G174: média | H174: Pergunte: "Se essas duas opções existissem, qual escolheria? Por quê?". | I174: Manda fazer a pergunta hipotética que o template da mesma fase proíbe ("Se existisse Y, você usaria?", L2679). O leitor recebe duas regras opostas. | J174: Validar por comportamento: mostrar as curvas e perguntar o que o cliente comprou da última vez e por quê, ou testar com página de pré-venda na Fase 8. | K174: não | L174: 1 | M174: não | Q174: Revisor de trecho | R174: Corrigido
A175: 174 | B175: 1 | C175: 2566 | D175: FASE 1 | E175: C5 | F175: Contradição interna | G175: média | H175: Tempo: 4-8 horas para a primeira versão (exige pesquisa de campo dos concorrentes). Revisar a cada 12-18 meses. | I175: O subtítulo da seção promete 30 a 60 minutos (L2554) e L2548 manda revisar a cada 18 a 24 meses. Três números diferentes para a mesma ferramenta. | J175: Subtítulo "Passo a passo (meio dia, com pesquisa)" e um prazo único de revisão. | K175: não | L175: 1 | M175: não | Q175: Revisor de trecho | R175: Corrigido
A176: 175 | B176: 1 | C176: 2575 | D176: FASE 1 | E176: C4 | F176: Caso real com detalhe possivelmente inventado | G176: alta | H176: | Aluguel da máquina | R$ 50-100/mês | R$ 0 (subsidiado) | Reduce | | I176: Tabela da Stone em 2014 com sinais de invenção: aluguel zero, capilaridade baixa por "foco digital" (a Stone apostou em polos locais), "Stone Box", "Ponto-de-Atenção", "Stone Hub" como software. | J176: Verificar cada linha com o prospecto do IPO de 2018. Sem fonte, trocar por fatores qualitativos que se sustentam (atendimento local, troca rápida de máquina, foco no pequeno lojista) e tirar os números. | K176: não | L176: 1 | M176: sim | N176: erro confirmado | O176: O F-1 da StoneCo (2018) lista receita de assinatura e aluguel de equipamentos, 13,7% da receita de 2017 somados. Não há fonte para aluguel zero em 2014. | P176: https://www.sec.gov/Archives/edgar/data/1745431/000119312518289511/d580263df1.htm | Q176: Revisor de trecho | R176: Corrigido
A177: 176 | B177: 1 | C177: 2614 | D177: FASE 1 | E177: S6 | F177: Seção desproporcional ou fora de lugar | G177: média | H177: **Sucede o VPC (Fase 2)**: depois de entender Pains e Gains do cliente | I177: O canvas está na Oficina da Fase 1, mas o próprio texto o põe na Fase 5 ou 6, depois do VPC da Fase 2 e junto da Cunha da Fase 6. Está no lugar errado. | J177: Tirar o Strategy Canvas da Fase 1 (há cópia em v02, L6243) e deixar no Método 7 uma remissão de uma linha. | K177: não | L177: 1 | M177: não | Q177: Revisor de trecho | R177: Corrigido
A178: 177 | B178: 1 | C178: 2626 | D178: FASE 1 | E178: S5 | F178: Duplicação com outro capítulo ou volume | G178: média | H178: #### Template: Entrevista de Problema | I178: Oficina quase toda copiada: Blue Ocean, Três Horizontes, Wardley e Strategy Canvas (v02 e v09), Mom Test (v02 e v03), Inversion e Lean Canvas (v03), os dois templates (v02). | J178: Manter na Fase 1 só o que a fase usa (Lean Canvas, curva S, roteiro curto de conversa de calibragem) e remeter ao resto. | K178: não | L178: 1 | M178: não | Q178: Revisor de trecho | R178: Corrigido
A179: 178 | B179: 1 | C179: 2724 | D179: FASE 1 | E179: E9 | F179: Erro gramatical ou frase corrompida | G179: baixa | H179: - **Fase 1 — `[nome curto]`:** `[o que acontece, quem faz, com que ferramenta, quanto tempo leva]` | I179: "Fase" para etapas do processo do cliente, dentro da Fase 1 de um livro organizado em fases. O leitor mistura as duas numerações. | J179: Usar "Etapa 1", "Etapa 2" no template e nas instruções de L2722 e L2744. | K179: não | L179: 1 | M179: não | Q179: Revisor de trecho | R179: Corrigido
A180: 179 | B180: 1 | C180: 2743 | D180: FASE 1 | E180: E6 | F180: Clichê ou metáfora gasta | G180: baixa | H180: pode ser o ouro do discovery | I180: A metáfora do ouro se repete: "são ouro" (L1701), "o ouro do discovery", "Verbatim é ouro" (L2760). Junto vêm "move a agulha" (L2850) e "trincheira" cinco vezes. | J180: Dizer o valor concreto: "pode ser a descoberta mais útil da rodada", "a citação literal serve de prova no pitch". | K180: sim | L180: 6 | M180: não | Q180: Revisor de trecho | R180: Corrigido
A181: 180 | B181: 1 | C181: 2829 | D181: FASE 1 | E181: C4 | F181: Caso real com detalhe possivelmente inventado | G181: média | H181: Exemplo: a hipótese original do iFood era "redes grandes"; entrevistas acumuladas refinaram para "restaurantes pequenos sem telemarketing". | I181: Detalhe da história do iFood sem fonte e com cara de invenção. O iFood nasceu do Disk Cook, um guia de cardápios com central telefônica. | J181: Verificar. Sem fonte, trocar por exemplo declarado como hipotético: "uma ferramenta para restaurantes que mirou redes e descobriu a dor nos pequenos". | K181: não | L181: 1 | M181: sim | Q181: Revisor de trecho | R181: Corrigido
A182: 181 | B182: 1 | C182: 2887 | D182: FASE 1 | E182: S7 | F182: Artefato de formatação | G182: alta | H182: sai do **Template: Síntese de Rodada de Entrevistas (decisão de avanço · Fase 3 → Fase 4) (Fase 4) (Síntese de Rodada de Entrevistas)** | I182: Remissão corrompida por script: três parênteses em fila, sem link, para um template que está no Vol. 2 (v02, L2034). Texto de bastidor que vazou. | J182: "sai da Síntese de Rodada de Entrevistas, na Fase 4 (Vol. 2)", com link. | K182: não | L182: 1 | M182: não | Q182: Revisor de trecho | R182: Corrigido
A183: 182 | B183: 1 | C183: 2891 | D183: FASE 1 | E183: S6 | F183: Seção desproporcional ou fora de lugar | G183: média | H183: #### Template: Entrevista com Especialista de Mercado (mapa de setor · Fases 3-5) | I183: Os dois templates são de descoberta (Fases 3 a 5) e a fase diz que conversa com cliente não é Fase 1 (L1909). Falta o que ela pede: o roteiro da conversa de calibragem da quinta. | J183: Criar template curto da conversa de calibragem (30 min, cinco perguntas, a pergunta-chave "o que é mais ineficiente no seu trabalho hoje?") e remeter os dois templates longos ao Vol. 2. | K183: não | L183: 1 | M183: não | Q183: Revisor de trecho | R183: Corrigido
A184: 183 | B184: 1 | C184: 2918 | D184: FASE 1 | E184: E10 | F184: Repetição, redundância, enchimento | G184: média | H184: **Confronto à nossa tese (15-20 min — seção mais valiosa).** *Esta é a seção mais importante. Se a pessoa só elogia, você perdeu a conversa.* | I184: A mesma linha diz duas vezes que é a seção mais importante, e a frase inteira volta em L3006. | J184: "Confronto à nossa tese (15 a 20 min)." Manter "Se a pessoa só elogia, você perdeu a conversa" uma vez, na Parte A. | K184: não | L184: 1 | M184: não | Q184: Revisor de trecho | R184: Corrigido
A185: 184 | B185: 1 | C185: 3129 | D185: FASE 1 | E185: E9 | F185: Erro gramatical ou frase corrompida | G185: alta | H185: **Hipóteses de mercado a testar com cliente (entrevista de problema Template: Entrevista de Problema (Fase 1)).** `[...]` | I185: Frase corrompida pela inserção automática do nome do template. Em L2896 o mesmo nome aparece duas vezes seguidas como texto corrido, sem link. | J185: "Hipóteses de mercado a testar com cliente (use a Entrevista de Problema)." Em L2896: "para isso use a Entrevista de Problema, que também tem Parte A e Parte B". | K185: sim | L185: 3 | M185: não | Q185: Revisor de trecho | R185: Corrigido
A186: 185 | B186: 1 | C186: 3139 | D186: FASE 1 | E186: N9 | F186: Título que promete o que o corpo não entrega | G186: média | H186: Business Model Canvas e Lean Canvas. Value Proposition Canvas (Strategyzer). Double Diamond (Design Council). Jobs-to-be-Done Framework. RICE para priorização. | I186: Leituras e recursos sem nenhuma leitura: nomes de ferramenta em fragmentos, quase todos alheios à fase (RICE, OKRs, Kanban). As leituras certas estão na Fase 0 (L1545). | J186: Trazer para cá os ensaios de Graham sobre ideias (How to Get Startup Ideas, Schlep Blindness, Frighteningly Ambitious Startup Ideas), De Zero a Um e The Mom Test, com uma linha de uso para cada. | K186: não | L186: 1 | M186: não | Q186: Revisor de trecho | R186: Corrigido
A187: 186 | B187: 1 | C187: 3145 | D187: FASE 1 | E187: E10 | F187: Repetição, redundância, enchimento | G187: média | H187: A primeira ideia que vem à cabeça não é a melhor. É apenas a mais disponível. | I187: A Lição de bolso recicla quase palavra por palavra L1635 e L1637 (primeira ideia, dois ou três anos, atitude passiva e ativa) e não volta a Lucas e Marina. | J187: Fechar com o que mudou: o caderno de Lucas com três ideias de vitrine virou uma Lista Curta com uma dor B2B. Uma frase de tese ("ideias baratas, filtros caros") e o próximo passo. | K187: não | L187: 1 | M187: não | Q187: Revisor de trecho | R187: Corrigido
A188: 187 | B188: 1 | C188: 3157 | D188: FASE 2 | E188: N2 | F188: Costura ruim entre cena e conteúdo | G188: alta | H188: Henrique levou três horas diante da página em branco e suou frio: por trás do vocabulário bonito, ele tinha três negócios diferentes misturados | I188: Cena de abertura abandonada: Henrique não volta no corpo, nos exemplos, no Espelho nem no fecho. A fase passa para PadariaPro e iFood e a promessa narrativa fica na casca. | J188: Fazer da DII de Henrique o caso guia: a v0 com jargão, a escolha de um comprador (manutenção, financeiro ou sustentabilidade) e a v1 que passa no teste dos 90 segundos. Retomar no Espelho e no fecho. | K188: não | L188: 1 | M188: não | Q188: Revisor de trecho | R188: Corrigido
... A204: 203 | B204: 1 | C204: 3327 | D204: FASE 2 | E204: C5 | F204: Contradição interna | G204: média | H204: O problema de ruptura é documentado, recorrente e diretamente mensurável em margem perdida. | I204: O exemplo ignora a regra do Bloco 6 (3238): nenhuma hipótese está no formato '[Persona] [verbo] [objeto]'. São tendências de mercado, não crenças sobre clientes. | J204: Reescrever ao menos uma: 'Donos de padaria com duas a cinco lojas pagam R$ 290 por mês para evitar duas rupturas de farinha no mês.' | K204: não | L204: 1 | M204: não | Q204: Revisor de trecho | R204: Corrigido
A205: 204 | B205: 1 | C205: 3347 | D205: FASE 2 | E205: C3 | F205: Erro factual provável | G205: alta | H205: No lado restaurante, estabelecimentos com ticket de R$ 30 a R$ 80 sem operação de entrega estruturada. | I205: Anacronismo provável: em 2011 o iFood listava restaurantes que já entregavam com motoboy próprio. A logística própria veio anos depois, o que derruba também 3349 ('custo do motoboy'). | J205: Verificar e reescrever: o lado restaurante são casas com delivery próprio que perdem pedidos no telefone ocupado. A concorrência real era o folheto e o telefone, não o motoboy. | K205: não | L205: 1 | M205: sim | N205: erro confirmado | O205: Em 2011 o iFood atendia só restaurantes que já tinham delivery próprio. A empresa passou a fazer entregas a partir de 2015, porque muitos restaurantes não tinham entregadores. | P205: https://tecnoblog.net/especiais/ifood-domina-o-delivery-no-brasil-mas-restaurantes-e-rivais-contam-como-vao-reagir/ | Q205: Revisor de trecho | R205: Corrigido
...

Sheet Checagem
A1: ID | B1: Volume | C1: Linha | D1: Trecho citado | E1: Desconfiança do revisor | F1: Veredito | G1: O que vale em out/2026 | H1: Fonte | I1: Nota para a correção
A2: r1-caso-045 | B2: 1 | C2: 448 | D2: O terceiro perfil é o especialista de domínio, ou hipster. | E2: Na tríade conhecida hacker, hustler e hipster, o hipster é o designer. O texto redefine o termo e depois cria o design como quarto perfil. Quem conhece a tríade desconfia do resto. | F2: não checada | G2: Não checada nesta rodada. | I2: Sem busca, por limite de esforço. O revisor aponta que, na tríade hacker, hustler e hipster, o hipster é o designer. Conferir antes de corrigir.
A3: r1-juri-023 | B3: 1 | C3: 736 | D3: Walgreens (exemplo de Collins): | E3: Exemplo sem ressalva em 2026: a Walgreens encolheu e saiu da bolsa em 2025, comprada por um fundo. E os 15x de Collins cobrem 1975 a 2000, não 'por 15 anos' como diz a linha 741. | F3: desatualizado | G3: A Walgreens Boots Alliance foi comprada pela Sycamore Partners e saiu da Nasdaq em agosto de 2025, como empresa de capital fechado. O exemplo de Collins pede essa ressalva. | H3: https://www.sec.gov/Archives/edgar/data/1618921/000119312525190603/d87240dex991.htm | I3: O período dos 15x de Collins (1975 a 2000, segundo o revisor) não foi conferido em fonte aberta. Revisar 'por 15 anos' na L741.
A4: r1-caso-001 | B4: 1 | C4: 785 | D4: Fundadores seriais brasileiros. Quando David Vélez criou o Nubank | E4: Vélez é colombiano e o Nubank foi sua primeira empresa. Kalim também não era fundador serial. O pensamento entre aspas é atribuído a Vélez sem fonte, e o Nubank nasceu com aporte de fundos. | F4: erro confirmado | G4: David Vélez é colombiano e vinha de fundos de investimento (General Atlantic e Sequoia), sem empresa própria registrada antes do Nubank. O Nubank começou com cerca de US$ 2 milhões de Sequoia e Kaszek. | H4: https://forbes.com.br/forbes-money/2021/07/como-david-velez-enfrentou-os-gigantes-do-setor-bancario-brasileiro-e-criou-o-banco-digital-mais-valioso-do-mundo/ | I4: O monólogo entre aspas não tem fonte e o rótulo 'fundadores seriais brasileiros' não cabe. Kalim (C6) não foi conferido. Usar fato verificável, sem fala inventada.
A5: r1-fina-043 | B5: 1 | C5: 1537 | D5: *Jobs to Be Done*, de Anthony Ulwick e Clayton Christensen | E5: Não existe livro com esse título escrito pelos dois. Ulwick publicou 'Jobs to be Done: Theory to Practice' (2016) e Christensen 'Competing Against Luck' (2016), de escolas rivais. | F5: erro confirmado | G5: São dois livros: 'Jobs to be Done: Theory to Practice', de Anthony Ulwick (2016), e 'Competing Against Luck', de Clayton Christensen, Taddy Hall e Karen Dillon (2016). | H5: https://www.goodreads.com/book/show/32809558 | I5: Citar as duas obras separadas e dizer em uma linha que divergem. Dados do livro de Christensen conferidos na Porchlight Books.
A6: r1-fina-001 | B6: 1 | C6: 1794 | D6: Wellhub (anteriormente Gympass) não começou pensando "academias para empresas". Começou pelo departamento de RH de empresa grande | E6: Provável erro: o Gympass nasceu vendendo diárias avulsas ao consumidor e depois migrou para o benefício corporativo. E a frase se contradiz: RH pagando academia é "academias para empresas". | F6: erro confirmado | G6: O Gympass, fundado em 2012, começou vendendo ao consumidor final (B2C). Depois de conflitos de repasse com as academias, reestruturou o modelo para venda direta a empresas. | H6: https://neofeed.com.br/videos/vida-de-startup/por-que-as-academias-quase-faliram-o-gympass | I6: Segundo o cofundador João Barbosa, a empresa mudou de modelo quatro vezes. Contar o RH como cunha achada no caminho, não como ponto de partida.
A7: r1-caso-002 | B7: 1 | C7: 2317 | D7: Clark, K. & Vesterlund, L. (2013). "Decision by default". Research sobre como inversion reduz viés. | E7: Referência com cara de inventada: não há trabalho conhecido de Clark e Vesterlund com esse título sobre inversão. Bibliografia falsa basta para desacreditar o livro. | F7: não verificável | G7: Não achei trabalho de Clark e Vesterlund chamado 'Decision by default'. Lise Vesterlund pesquisa doações e diferenças de gênero, não inversão. | H7: https://en.wikipedia.org/wiki/Lise_Vesterlund | I7: Duas buscas sem rastro da obra. Forte sinal de referência inventada. Cortar ou trocar pelas fontes que o revisor sugere (Munger e o pre-mortem de Klein).
A8: r1-fina-044 | B8: 1 | C8: 2575 | D8: | Aluguel da máquina | R$ 50-100/mês | R$ 0 (subsidiado) | Reduce | | E8: Tabela da Stone em 2014 com sinais de invenção: aluguel zero, capilaridade baixa por "foco digital" (a Stone apostou em polos locais), "Stone Box", "Ponto-de-Atenção", "Stone Hub" como software. | F8: erro confirmado | G8: O F-1 da StoneCo (2018) lista receita de assinatura e aluguel de equipamentos, 13,7% da receita de 2017 somados. Não há fonte para aluguel zero em 2014. | H8: https://www.sec.gov/Archives/edgar/data/1745431/000119312518289511/d580263df1.htm | I8: O dado é de 2017, não de 2014. 'Stone Box', 'Ponto-de-Atenção' e 'Stone Hub' não foram conferidos. Sem fonte, tirar os números e manter fatores qualitativos.
A9: r1-fina-002 | B9: 1 | C9: 3347 | D9: No lado restaurante, estabelecimentos com ticket de R$ 30 a R$ 80 sem operação de entrega estruturada. | E9: Anacronismo provável: em 2011 o iFood listava restaurantes que já entregavam com motoboy próprio. A logística própria veio anos depois, o que derruba também 3349 ('custo do motoboy'). | F9: erro confirmado | G9: Em 2011 o iFood atendia só restaurantes que já tinham delivery próprio. A empresa passou a fazer entregas a partir de 2015, porque muitos restaurantes não tinham entregadores. | H9: https://tecnoblog.net/especiais/ifood-domina-o-delivery-no-brasil-mas-restaurantes-e-rivais-contam-como-vao-reagir/ | I9: O lado restaurante em 2011 eram casas com motoboy próprio que perdiam pedidos no telefone. Ajustar também a L3349 sobre o custo do motoboy.
A10: r1-fina-045 | B10: 1 | C10: 4115 | D10: 1 squad (5 pessoas) por 6 meses para MVP + 4 meses de aquisição inicial = ~R$ 1.5M. Reavaliar em 10 meses: se GMV mensal não chegar a R$ 2M ou 5k microcreators ativos, descontinuar. | E10: Orçamento e critério de corte atribuídos à Hotmart sem fonte. O Sparkle conhecido é um app de comunidades, não um checkout simplificado. Parece caso inventado com nome real. | F10: erro confirmado | G10: O Sparkle da Hotmart é app de comunidades com assinaturas, lançado por volta de 2020, não um checkout simplificado para microcreators em 2022. Orçamento e critério de corte não têm fonte. | H10: https://tecnoblog.net/responde/o-que-e-o-sparkle-a-volta-das-comunidades/ | I10: Declarar 'caso hipotético inspirado na Hotmart', sem nome real de produto e sem números, ou usar uma aposta documentada.
A11: r1-juri-024 | B11: 1 | C11: 4553 | D11: Howard Marks, co-fundador da Oaktree Capital (US$ 180B AUM), cunhou o termo no livro *The Most Important Thing* (2011) | E11: Marks fala em 'second-level thinking' e não cunhou a ideia de efeitos de segunda ordem, que vem de Bastiat e Hazlitt. O AUM de US$ 180B precisa de data e checagem. | F11: desatualizado | G11: A Oaktree informa US$ 227 bilhões sob gestão em 30 de junho de 2026, não US$ 180 bilhões. | H11: https://s206.q4cdn.com/629311627/files/doc_financials/2026/q3/OCSL-3Q2026-Investor-Presentation_vF.pdf | I11: Não conferido aqui: o livro de Marks usa 'second-level thinking'. Preferir 'popularizou' a 'cunhou', como sugere o revisor.
A12: r1-trib-001 | B12: 1 | C12: 5515 | D12: o fundador que se remunera via empresa tem opções entre pro-labore (incide INSS) e dividendos (isentos se houver lucro) | E12: Desatualizado. A Lei 15.270/2025 criou, a partir de 2026, retenção de 10% sobre dividendos acima de R$ 50 mil por mês da mesma empresa e imposto mínimo para renda anual acima de R$ 600 mil. | F12: desatualizado | G12: Desde janeiro de 2026, dividendos pagos por uma mesma empresa a uma mesma pessoa física acima de R$ 50 mil no mês sofrem retenção de 10% sobre o valor total (Lei 15.270/2025). Renda anual acima de R$ 600 mil entra no imposto mínimo, de 0% a 10% conforme a faixa, a partir da declaração de 2027. | H12: https://www.planalto.gov.br/ccivil_03/_ato2023-2026/2025/lei/L15270.htm | I12: Lucros apurados até 2025, com distribuição aprovada até 31/12/2025 e pagos nos termos do ato, ficam fora da retenção. A alíquota mínima chega a 10% em R$ 1,2 milhão por ano.
A13: r1-trib-002 | B13: 1 | C13: 5519 | D13: E nunca pegar empréstimo pessoal para a empresa em nome próprio, exceto via contrato formal de mútuo com juros de mercado. Caso contrário, vira distribuição de lucro disfarçada com problemas tributários. | E13: Conceito trocado. Dinheiro do sócio que entra sem contrato arrisca ser tratado como suprimento de caixa sem origem (omissão de receita), não como distribuição disfarçada. Juros não são exigidos. | F13: erro confirmado | G13: Dinheiro do sócio que entra na empresa sem prova da entrega e da origem pode ser tratado como receita omitida (Decreto-Lei 1.598/1977, art. 12, § 3º). O risco não é distribuição disfarçada de lucro. | H13: https://www.planalto.gov.br/ccivil_03/decreto-lei/del1598.htm | I13: Contrato de mútuo e prova da origem na declaração do sócio afastam a presunção. Mútuo com mutuante pessoa física não sofre IOF (Decreto 6.306/2007, art. 5º, III).
A14: r1-trib-003 | B14: 1 | C14: 5523 | D14: Bradesco Prime, Itaú Personnalité, BB Estilo, Santander Select, com entrada tipicamente em duzentos a quinhentos mil em investimentos na instituição | E14: São segmentos de alta renda do varejo, não private banking, que começa muito acima. A mesma frase dá dois pisos diferentes: R$ 500 mil a 1 milhão e R$ 200 mil a 500 mil. | F14: parcialmente certo | G14: Prime, Personnalité, Estilo e Select são segmentos de alta renda do varejo, não private banking. O Itaú Personnalité aceita renda a partir de R$ 15 mil ou investimentos a partir de R$ 250 mil. | H14: https://www.itau.com.br/abrir-conta/personnalite | I14: O piso de investimento cabe na faixa do livro, mas o trecho chama os segmentos de private e fala em PL de R$ 500 mil a 1 milhão. Pisos mudam, mande o leitor conferir no banco.
... A19: r1-juri-002 | B19: 1 | C19: 6386 | D19: Contabilizei. SaaS de contabilidade online, Curitiba. Outro exemplo de crescimento disciplinado, fora do eixo SP-RJ. | E19: Contabilizei e Conta Azul (6388) são empresas conhecidas por ter captado venture capital cedo. Na lista de bootstrap, desacreditam o argumento. | F19: erro confirmado | G19: A Contabilizei foi fundada em 2013, recebeu aporte da Curitiba Angels em 2014 e da Kaszek em junho de 2015. Não é caso de bootstrap. | H19: https://www.baguete.com.br/noticias/contabilizei-recebe-aporte-da-kaszek | I19: Conta Azul (L6388) não foi checada. Se a Contabilizei ficar no livro, mover para 'captação disciplinada', com rodadas e datas.
A20: r1-juri-014 | B20: 1 | C20: 6541 | D20: **Kim Kubo (The.Care).** Cofundadora de healthtech. | E20: Pessoa e empresa não identificáveis e sem nenhum dado (ano, cidade, número). Se não existir, é caso inventado no capítulo sobre diversidade. | F20: não verificável | G20: Nenhuma fonte pública liga uma Kim Kubo a uma healthtech brasileira chamada The.Care. | I20: A busca só trouxe empresas sem relação, como a Kubo Care, da Índia. Apagar o parágrafo, como sugere o revisor.
A21: r1-juri-015 | B21: 1 | C21: 6546 | D21: Marcia Jordão (Accelera). Andrea Bisker (Pacífica Holding). Karen Habib (SERASA Experian). Marina Proença (Solides). Eli Guinther (cofundadora Orion). | E21: Pares nome e empresa não verificáveis. A cofundadora e CEO conhecida da Solides é Mônica Hauck. 'Women in Tech BR' também é vago. Parece lista gerada sem checagem. | F21: erro confirmado | G21: A Sólides foi fundada em 2010 por Mônica Hauck e Alessandro Garcia. Marina Proença não aparece como fundadora. | H21: https://diariodocomercio.com.br/negocios/rh-fundamental-crescimento-pmes-diz-co-ceo-solides/ | I21: Os demais pares nome e empresa não foram checados. Refazer o quadro só com nomes conferidos, com empresa, cidade e fonte, ou apagá-lo.
A22: r1-fina-004 | B22: 1 | C22: 6587 | D22: Empresas híbridas entre for-profit, e impacto (Outbound, VU Brasil, Instituto Trata Brasil em forma empresarial, Gerando Falcões ecosystem). | E22: Trata Brasil é OSCIP e Gerando Falcões é ONG, não empresas híbridas. 'Outbound' e 'VU Brasil' não são identificáveis. 'Framework de Theory of Change, descrever' tem sintaxe quebrada. | F22: erro confirmado | G22: O Instituto Trata Brasil é OSCIP, entidade sem fins lucrativos formada por empresas interessadas no saneamento, e não empresa híbrida. | H22: https://tratabrasil.org.br/wp-content/uploads/2024/03/Codigo-de-Conduta_aprovado.pdf | I22: Gerando Falcões, Outbound e VU Brasil não foram conferidos. Citar só empresas de impacto verificadas e explicar teoria da mudança em uma frase.
A23: r1-fina-005 | B23: 1 | C23: 6589 | D23: Ambipar (gestão ambiental) construiu negócio em torno de serviço ambiental a outras empresas. | E23: A Ambipar entrou em recuperação judicial em 2025, segundo o noticiário econômico. Citá-la como sucesso ESG em 2026 é dado vencido. 'O líder vegetal Fazenda Futuro' é frase truncada. | F23: desatualizado | G23: A Ambipar teve o processamento da recuperação judicial deferido em 30/10/2025 pela Justiça do Rio de Janeiro, com dívidas declaradas de R$ 10,48 bilhões. | H23: https://mercadoeconsumo.com.br/31/10/2025/economia/justica-defere-pedido-de-recuperacao-judicial-da-ambipar/ | I23: Tirar como caso de sucesso ESG ou usar como alerta sobre alavancagem. Status atual da Fazenda Futuro não conferido.
A24: r1-caso-003 | B24: 1 | C24: 7071 | D24: só ocorre em narrativa, não em apresentação de dados | E24: Exagera o estudo de Stephens, Silbert e Hasson (2010), que comparou uma história compreendida com uma incompreensível, não com dados. O mapa de áreas cerebrais é de divulgação, sem fonte. | F24: erro confirmado | G24: Stephens, Silbert e Hasson (PNAS, 2010) usaram só uma história real contada em inglês. O acoplamento entre cérebros sumiu quando o ouvinte não entendia (história em russo), e o estudo não comparou narrativa com dados. | H24: https://pmc.ncbi.nlm.nih.gov/articles/PMC2922522/ | I24: O mapa de áreas ativadas por história contra dados também não vem desse estudo. Usar a redação do revisor: a atividade do ouvinte acompanha a do narrador quando ele entende.
A25: r1-caso-004 | B25: 1 | C25: 8071 | D25: Este capítulo reflete o estado da IA generativa em abril de 2026 e deve ser revisitado todo ano. | E25: A data não se sustenta: o capítulo cita GPT-4 Turbo (8110), Galileo AI e v0.dev (8152, 8242) e "ChatGPT Data Analysis" (8240), e o Cap. 11 (8284) diz que ele traz práticas de 2023 "hoje obsoletas". | F25: desatualizado | G25: Em outubro de 2026 várias ferramentas do capítulo envelheceram. O GPT-4 Turbo, citado na linha 8110, teve o fim anunciado em 22/04/2026 e sai da API da OpenAI em 23/10/2026. | H25: https://developers.openai.com/api/docs/deprecations | I25: Galileo AI, v0.dev e 'ChatGPT Data Analysis' não foram conferidos. Datar a nota só depois de checar cada ferramenta, ou fundir com o Cap. 11.
A26: r1-caso-005 | B26: 1 | C26: 8110 | D26: (Claude, ou GPT-4 Turbo) | E26: GPT-4 Turbo é de 2023 e foi substituído em 2024 e 2025. Num capítulo datado de 2026, o nome denuncia texto velho. | F26: desatualizado | G26: O GPT-4 Turbo teve o fim anunciado em 22/04/2026 e sai da API da OpenAI em 23/10/2026. Não serve como exemplo atual de modelo de contexto longo. | H26: https://developers.openai.com/api/docs/deprecations | I26: Usar a formulação do revisor: um assistente com contexto longo (Claude, ChatGPT ou Gemini, na versão atual).
A27: r1-juri-026 | B27: 1 | C27: 8311 | D27: Em 2026, padrão é ter IA participando de toda reunião importante. Gerando ata, e extraindo compromissos. | E27: Sem ressalva: gravar cliente, candidato ou investidor exige aviso e base legal (LGPD) e pode violar NDA. Idem a triagem de CV por IA (8326), que a LGPD (art. 20) e o PL 2338 tratam como risco. | F27: parcialmente certo | G27: Gravar e transcrever reunião é tratamento de dado pessoal e pede base legal e transparência (LGPD). O PL 2338/2023 segue aguardando parecer na comissão especial da Câmara, sem votação em outubro de 2026. | H27: https://dadosabertos.camara.leg.br/api/v2/proposicoes/2487262 | I27: Acrescentar aviso e consentimento antes de pôr robô na reunião. Na triagem de CV (L8326), a decisão é humana e o candidato pode pedir revisão (LGPD, art. 20).
A28: r1-fina-006 | B28: 1 | C28: 8420 | D28: Finep e BNDES Garagem oferecem capital de fomento público, em geral por empréstimo e não por equity, com taxas abaixo de mercado. | E28: BNDES Garagem é programa de aceleração, não crédito. A Finep também dá subvenção não reembolsável e investe em participação. "BNDES Social Bond" parece título de dívida, não programa para startup. | F28: erro confirmado | G28: O BNDES Garagem é programa de aceleração gratuito, sem crédito e sem exigir participação, com prêmios em dinheiro aos finalistas. A Finep opera crédito e também repassa subvenção do FNDCT, como no Centelha. | H28: https://garagem.bndes.gov.br/wp-content/uploads/2025/08/Edital-Negocios-de-Impacto-2025-TRACAO-Ciclo-2-_-BNDES-Garagem.pdf | I28: Garagem ativo, com ciclo 2025-2026 e Demoday em 16/6/2026. Investimento em participação pela Finep e o 'BNDES Social Bond' não foram conferidos.
A29: r1-caso-006 | B29: 1 | C29: 8422 | D29: O ticket em 2025 e 2026 é de quinhentos mil dólares (cerca de dois milhões e meio de reais) em troca de sete por cento de equity. | E29: No acordo padrão do YC, os 7% compram US$ 125 mil. Os outros US$ 375 mil entram em SAFE sem teto, que converte na rodada seguinte. Erro repetido em 8430. "Ou remota" também envelheceu. | F29: erro confirmado | G29: O YC investe US$ 500 mil: US$ 125 mil em SAFE post-money por 7% e US$ 375 mil em SAFE sem teto com cláusula de nação mais favorecida (MFN). | H29: https://www.ycombinator.com/deal | I29: Mesmo erro na linha 8430. O YC descreve programa de três meses, quatro turmas por ano, kickoff presencial e encontros semanais em San Francisco. Rever 'ou remota'.
A30: r1-fina-007 | B30: 2 | C30: 204 | D30: Hoje a empresa vale mais de US$ 14 bilhões e é peça essencial para OpenAI, Meta, e o Pentágono. | E30: Desatualizado: em 2025 a Meta comprou 49% da Scale AI (avaliação perto de US$ 29 bi), Wang foi para a Meta e OpenAI e Google reduziram o uso. A frase sobre Wang citar Graham pede fonte. | F30: desatualizado | G30: Em junho de 2025 a Meta investiu cerca de US$ 14,3 bilhões por 49% da Scale AI, avaliada em US$ 29 bilhões. Alexandr Wang deixou o cargo de CEO e foi para a Meta. | H30: https://techcrunch.com/2025/06/13/scale-ai-confirms-significant-investment-from-meta-says-ceo-alexandr-wang-is-leaving/ | I30: Os US$ 14 bi do livro batem com a avaliação de 2024 (US$ 13,8 bi). Redução de uso por OpenAI e Google não confirmada nesta fonte. Citação de Wang não conferida.
A31: r1-caso-007 | B31: 2 | C31: 287 | D31: ##### As cinco perguntas canônicas do Mom Test (cheat sheet) | E31: As cinco perguntas (parte mais difícil, última vez, por que foi difícil, o que já fez, o que não gosta nas soluções) são do "How to Talk to Users" de Eric Migicovsky (YC), não do livro de Fitzpatrick. | F31: erro confirmado | G31: As cinco perguntas (parte mais difícil, última vez, por que foi difícil, o que já fez, o que não gosta nas soluções) são da palestra 'How to Talk to Users', de Eric Migicovsky, da Y Combinator. | H31: https://www.indiehackers.com/post/eric-migicovsky-how-to-talk-to-users-summary-e3c4c844cc | I31: Fonte é resumo que remete ao vídeo da YC Library, cuja página não abriu. Atribuir a Migicovsky e dizer que as perguntas são compatíveis com o Mom Test.
A32: r1-juri-003 | B32: 2 | C32: 2849 | D32: Em vez de "otimizar o processo de aluguel", posicionaram como "aluguel sem fiador, sem vistoria, sem caução". | E32: O QuintoAndar faz vistoria de entrada e saída. A promessa pública era sem fiador e sem caução. A "pesquisa qualitativa extensa" de 2013 e a dor "social, não financeira" não têm fonte. | F32: parcialmente certo | G32: A promessa oficial do QuintoAndar é aluguel 'sem fiador, sem caução' e com contrato eletrônico. 'Sem vistoria' não faz parte dela. | H32: https://www.quintoandar.com.br/newsroom/sobre/ | I32: O site recruta vistoriadores, sinal de que há vistoria. A pesquisa qualitativa de 2013 e a dor 'social' não têm fonte pública achada. Tratar como reconstrução.
... A46: r1-juri-005 | B46: 3 | C46: 3386 | D46: A PlayKids, fundada em 2013 por Eric Acher, Marcelo Roque e Gabriel Borges em São Paulo (parte do grupo Movile) | E46: Eric Acher é conhecido como cofundador da gestora Monashees, não da PlayKids, que nasceu dentro da Movile. Os outros nomes e os cem milhões de downloads também pedem checagem. | F46: erro confirmado | G46: A PlayKids foi lançada pela Movile em junho de 2013. Nenhuma fonte a liga a Eric Acher, Marcelo Roque ou Gabriel Borges, e desde 2022 ela pertence à Sandbox & Co, com a Movile minoritária. | H46: https://techcrunch.com/2013/06/25/playkids-tv/ | I46: Em 2022 tinha 4 milhões de usuários mensais em 130 países (Bloomberg Línea). Os 100 milhões de downloads e 180 países não se confirmaram. Usar a versão sem nomes.
A47: r1-juri-018 | B47: 3 | C47: 4220 | D47: ##### Exemplo brasileiro preenchido — Wildlife Studios, MVP de novo mecanismo de monetização (2022) | E47: Coorte de 50 mil jogadores, ARPU de R$ 18 e conversão de 17% atribuídos à Wildlife sem fonte. Dados internos com cara de invenção, de empresa grande, num volume para fundador pré-MVP. | F47: não verificável | G47: Não há fonte pública para a coorte de 50 mil jogadores, o ARPU de R$ 18 e a conversão de 17% atribuídos à Wildlife Studios. | I47: Busca sem resultado. Rotular como ilustração ou trocar por um MVP Canvas do porte do leitor.
A48: r1-trib-007 | B48: 3 | C48: 4624 | D48: Com quinze a vinte respostas, plote as quatro curvas. A intersecção entre "caro" e "barato" indica a faixa de preço psicologicamente aceitável. | E48: No método, o cruzamento de "caro" com "barato" dá um ponto (preço de indiferença), não uma faixa. E 15 a 20 respostas geram curvas instáveis demais para traçar limites. | F48: erro confirmado | G48: No método de Van Westendorp, o cruzamento de 'barato' com 'caro' é o ponto de indiferença, um preço só. A faixa aceitável vai do cruzamento de 'barato demais' com 'não barato' ao de 'caro demais' com 'não caro'. | H48: https://rdrr.io/cran/pricesensitivitymeter/man/psm_analysis.html | I48: O ponto ótimo é o cruzamento de 'barato demais' com 'caro demais'. A fonte não fixa amostra mínima, mas 15 a 20 respostas devem ser tratadas como pista.
A49: r1-juri-006 | B49: 3 | C49: 4755 | D49: Em meados da década de 2010, a Gupy nascia da ideia de Mariana Dias, Bruna Guimarães, e Robinson Idalgo de substituir processos tradicionais de recrutamento | E49: Quadro de fundadores a conferir. As fontes que conheço citam Mariana Dias, Bruna Guimarães, Guilherme Dias e Robson Ventura (2015). "Robinson Idalgo" parece nome trocado. | F49: erro confirmado | G49: A Gupy foi fundada em 2015 por Mariana Dias, Bruna Guimarães, Guilherme Dias e Robson Ventura. 'Robinson Idalgo' não consta. | H49: https://forbes.com.br/forbes-tech/2022/01/os-proximos-passos-da-gupy-apos-meio-bilhao-em-aporte/ | I49: Trocar 'em meados da década de 2010' por 'em 2015' e corrigir os nomes.
A50: r1-caso-015 | B50: 3 | C50: 6036 | D50: Já uma startup de biotech pode estar em TRL 3, mesmo após cinco anos de operação. Se estiver em ensaios clínicos. | E50: Na escala biomédica usada por agências americanas (HHS e DoD), ensaio clínico corresponde a TRL 6 a 8. Quem está em ensaio clínico não está em TRL 3. E a frase foi partida ao meio. | F50: erro confirmado | G50: Na escala biomédica do Departamento de Defesa dos EUA, TRL 3 é prova de conceito inicial em laboratório ou animal, TRL 6 é o ensaio clínico de fase 1 e TRL 7 cobre as fases 2 e 3. | H50: https://cdmrp.health.mil/jwmrp/pdfs/Biomedical%20Product%20Guidelines.pdf | I50: Quem está em ensaio clínico está em TRL 6 ou 7, não 3. Juntar a frase partida e usar a redação do revisor, com TRL 6 no primeiro ensaio clínico.
A51: r1-caso-016 | B51: 3 | C51: 6626 | D51: Empresa de produto de software (SaaS B2B) vende em múltiplo de cinco a quinze vezes receita. Plataforma que alcança escala vende em dez a trinta vezes receita | E51: Múltiplos da bolha de 2020 e 2021. Em 2025 e 2026, Uber e Mercado Livre negociam perto de 3 a 6 vezes a receita, e SaaS privado brasileiro fica bem abaixo de 5. O número sustenta a tese do capítulo. | F51: desatualizado | G51: Em 26/12/2025 a mediana das empresas de software em nuvem listadas nos EUA valia 4,7 vezes a receita projetada para 12 meses, abaixo do piso de cinco vezes do livro. | H51: https://cloudedjudgement.substack.com/p/clouded-judgement-122625-exuberance | I51: Os múltiplos de 10 a 30 vezes para plataformas não foram conferidos. Datar e citar fonte, ou trocar por comparação relativa, como sugere o revisor.
A52: r1-fina-009 | B52: 3 | C52: 6708 | D52: Mercado Livre é a plataforma brasileira que resistiu mais tempo. | E52: O Mercado Livre é argentino, fundado em Buenos Aires em 1999. A 6628 diz que levou "quase vinte anos para estabilizar", mas a empresa já dava lucro quando abriu capital, em 2007. | F52: erro confirmado | G52: O Mercado Livre é argentino, começou a operar na Argentina em agosto de 1999 e tem sede em Buenos Aires. Teve prejuízo de 1999 até 2004 e abriu capital na Nasdaq em agosto de 2007. | H52: https://www.sec.gov/Archives/edgar/data/0001099590/000119312508070409/d10k.htm | I52: Corrigir também a L6628 ('quase vinte anos para estabilizar'). O peso do Brasil na receita não foi conferido.
A53: r1-caso-017 | B53: 3 | C53: 6710 | D53: 99 entrou em mercado com Uber já estabelecido. | E53: A 99 nasceu em 2012 como app de táxi, e a Uber chegou ao Brasil em 2014. Só o 99POP, de 2016, entrou com a Uber já forte no carro particular. | F53: erro confirmado | G53: A 99 nasceu em junho de 2012 como app de táxi, e a Uber só começou no Brasil em 2014, no Rio. O 99POP, com motoristas particulares, veio em agosto de 2016, e a Didi comprou a 99 em janeiro de 2018. | H53: https://www.mobiletime.com.br/museu-movel/05/04/2024/como-a-99-surgiu-e-se-tornou-o-primeiro-unicornio-brasileiro/ | I53: Chegada da Uber em 2014 confirmada no newsroom da Uber. A Mobiletime fala em US$ 1 bilhão na compra pela Didi, que já tinha cerca de 30%.
A54: r1-trib-008 | B54: 3 | C54: 7256 | D54: gera **R$ 9 milhões por ano em dividendos limpos** para os fundadores | E54: Desde janeiro de 2026, a lei da reforma do IR (Lei 15.270/2025) retém 10% sobre dividendos acima de R$ 50 mil por mês por sócio e cria imposto mínimo para alta renda. "Dividendos limpos" envelheceu. | F54: desatualizado | G54: Desde 2026, dividendos acima de R$ 50 mil no mês da mesma empresa a cada sócio sofrem retenção de 10% sobre o total. Quem recebe mais de R$ 600 mil por ano entra no imposto mínimo, que chega a 10% a partir de R$ 1,2 milhão. | H54: https://www.planalto.gov.br/ccivil_03/_ato2023-2026/2025/lei/L15270.htm | I54: Trocar 'dividendos limpos' por 'lucro distribuível' e remeter ao Vol. 5. A retenção mensal é descontada no cálculo anual do imposto mínimo.
A55: r1-fina-010 | B55: 4 | C55: 388 | D55: Baseado em entrevistas, no S-1, e em cobertura pública. | E55: A StoneCo, sediada em Cayman, registrou o IPO no formulário F-1, não S-1. 'Entrevistas' sem nome não se conferem, e os US$ 9,9 bilhões no primeiro pregão (388) pedem fonte. | F55: parcialmente certo | G55: A StoneCo, constituída nas Ilhas Cayman, registrou o IPO no Form F-1, arquivado em 1/10/2018. No primeiro pregão, em 25/10/2018, o valor de mercado passou de US$ 9,9 bilhões. | H55: https://www.sec.gov/Archives/edgar/data/1745431/000119312518289511/d580263df1.htm | I55: Trocar S-1 por F-1. O US$ 9,9 bi veio de relato do dia (LatAm List), não de fechamento oficial. Ação precificada a US$ 24. Entrevistas sem nome não se conferem.
A56: r1-juri-019 | B56: 4 | C56: 1328 | D56: ##### Exemplo brasileiro preenchido — Wildlife Studios, MVP de novo mecanismo de monetização (2022) | E56: Coorte de 50 mil jogadores, ARPU de R$ 18, passe a R$ 15 e 17% de conversão atribuídos à Wildlife sem fonte, e o uso do MVP Canvas também. Caso de empresa grande para leitor com 10 a 50 usuários. | F56: não verificável | G56: Não há fonte pública para a coorte, o ARPU de R$ 18, o passe a R$ 15 e a conversão de 17% atribuídos à Wildlife Studios. | I56: Mesmo caso de v03 L4220. Corrigir os dois juntos, de preferência com o MVP de personagens do próprio livro.
A57: r1-fina-011 | B57: 4 | C57: 1538 | D57: LTV dividido por CAC maior ou igual a três vezes (abaixo disso, custa mais adquirir do que o cliente vale). | E57: Explicação errada: com LTV/CAC de 2, o cliente vale o dobro do que custou. Só abaixo de 1 a aquisição dá prejuízo. As três réguas, chamadas de inegociáveis, não têm fonte. | F57: erro confirmado | G57: LTV/CAC acima de 3 é a meta de David Skok para um SaaS saudável. Só abaixo de 1 o custo de adquirir supera o valor do cliente. | H57: https://www.forentrepreneurs.com/ltv-cac/ | I57: Escrever que abaixo de 3x sobra pouca margem para estrutura e crescimento. Skok também usa recuperar o CAC em menos de 12 meses. Dizer que a régua é de SaaS.
A58: r1-caso-018 | B58: 4 | C58: 3849 | D58: HubSpot próprio: blog com 6000+ artigos, tráfego orgânico de 18M+ visitantes/mês, 60%+ de aquisição via inbound. | E58: Número sem data nem fonte. O tráfego orgânico do blog da HubSpot caiu muito em 2024 e 2025 com mudanças do Google e respostas por IA. Em 2026 o exemplo soa desatualizado. | F58: desatualizado | G58: Estimativas de Ahrefs e Semrush mostram o tráfego orgânico do blog da HubSpot caindo cerca de 80% entre janeiro de 2024 e janeiro de 2025, de 10 a 15 milhões para 2 a 3 milhões de visitas por mês. | H58: https://www.lyntonweb.com/library/hubspot-aeo-traffic-drop | I58: São estimativas de ferramentas de SEO, não dados da HubSpot. '6000+ artigos' e '60% via inbound' não foram conferidos. Usar a queda como alerta, com remissão ao capítulo de GEO.
A59: r1-fina-012 | B59: 4 | C59: 4536 | D59: #### Estágio 3: Expansão e referência (seed late / Series A, R$500K a R$1M ARR) | E59: R$ 500 mil a R$ 1 milhão de ARR é estágio de seed. Série A no Brasil costuma exigir ARR várias vezes maior. A tabela de métricas (4686) repete o rótulo. | F59: parcialmente certo | G59: R$ 500 mil a R$ 1 milhão de ARR é faixa de seed. A referência global mais usada (SaaS Funding Napkin, da Point Nine) põe a Série A em US$ 1 a 5 milhões de ARR. | H59: https://startupi.com.br/guardanapo-saas-estrategia-saas/ | I59: Não achei faixa brasileira com fonte primária. Chamar o estágio de seed, escrever 'Série A' e corrigir o rótulo da tabela da L4686.
A60: r1-juri-020 | B60: 4 | C60: 4565 | D60: Startups que integram WhatsApp Business API ao CRM e fazem cadências com WhatsApp + e-mail + LinkedIn têm métricas de conversão significativamente superiores. | E60: Recomenda cadência fria por WhatsApp sem avisar que a API exige opt-in e modelos aprovados pela Meta, nem tratar da LGPD. Risco de bloqueio do número e de reclamação. | F60: parcialmente certo | G60: A plataforma de WhatsApp Business exige opt-in ativo antes de a empresa iniciar a conversa, e mensagens iniciadas pela empresa só saem em modelos aprovados. Disparo sem opt-in leva a bloqueios, queda de qualidade e suspensão. | H60: https://docs.360dialog.com/docs/guides/best-practices | I60: A conversão 'significativamente superior' não tem fonte. A política da Meta não abriu, a fonte é um provedor da API. Acrescentar base legal e opção de saída.
A61: r1-fina-013 | B61: 4 | C61: 5088 | D61: *Casos brasileiros*: Nubank criou páginas para cada tipo de cartão × perfil de renda × cidade. | E61: Não há registro de páginas do Nubank por cartão, renda e cidade, e o Nubank opera com poucos cartões. Trivago, alemã, entra como "caso brasileiro". Um leitor do setor derruba o exemplo. | F61: não verificável | G61: A afirmação sobre páginas do Nubank por cartão, renda e cidade não tem fonte e não foi confirmada. A Trivago é alemã, fundada em 2005 em Düsseldorf, e não é caso brasileiro. | H61: https://en.wikipedia.org/wiki/Trivago | I61: Manter ZAP e Imovelweb se conferidos e trocar Nubank e Trivago por casos checados.
A62: r1-trib-009 | B62: 4 | C62: 5455 | D62: Disponível no Google Ads e GA4 para contas com volume suficiente (mínimo ~3.000 conversões por mês). | E62: Desde 2023 o data-driven é o padrão no Google Ads e no GA4, sem esse piso, e os modelos linear, time decay e por posição saíram das duas ferramentas. A lista oferece opções que o leitor não vai achar. | F62: erro confirmado | G62: O Google Ads oferece hoje só último clique e data-driven, que é o padrão. Primeiro clique, linear, time decay e por posição deixaram de ser suportados, e não há piso obrigatório de conversões. | H62: https://support.google.com/google-ads/answer/6259715?hl=en | I62: O Google só recomenda 200 conversões e 2.000 interações em 30 dias (support.google.com/google-ads/answer/7002714). Modelos por regra ficam como raciocínio.
A63: r1-fina-014 | B63: 4 | C63: 5767 | D63: A Contabilizei não competiu com escritórios de contabilidade, criou um segmento para MEIs que antes não tinham contabilidade. | E63: MEI não é obrigado a ter contador, e a Contabilizei se vende justamente contra escritórios tradicionais, atendendo ME e EPP. Exemplo de oceano azul factualmente frágil. | F63: erro confirmado | G63: O MEI não é obrigado a ter contador. A Contabilizei se dirige a micro e pequenas empresas, prestadores de serviço e profissionais liberais. | H63: https://www.contabilizei.com.br/contabilidade-online/preciso-de-contador-para-abrir-empresa/ | I63: Reescrever como preço menor e serviço online dentro de mercado que já existia. Não é exemplo de oceano azul com MEI.
A64: r1-juri-027 | B64: 4 | C64: 5841 | D64: Custo por volta de R$ 450 por classe para MEI/ME, R$ 890 para outros. O processo leva de oito a vinte e quatro meses. | E64: Valor único esconde que a taxa vem em duas etapas, pedido e concessão, esta só após o deferimento e sob pena de arquivamento. O desconto vale também para EPP e pessoa física. | F64: correto no livro | G64: Pela tabela do INPI em vigor desde 20/12/2025, o pedido de marca com especificação pré-aprovada custa R$ 880, ou R$ 440 com desconto, e a concessão do primeiro decênio custa R$ 0. Com especificação livre, R$ 1.720 ou R$ 860. | H64: https://www.gov.br/inpi/pt-br/servicos/custos-e-pagamento/NovaTabeladeRetribuiesINPI_MARCAS_Final_20_dez_25.pdf | I64: O desconto de 50% vale também para EPP, pessoa física e outros. A taxa em duas etapas citada pelo revisor acabou. O prazo de 8 a 24 meses não foi checado.
A65: r1-trib-010 | B65: 4 | C65: 6632 | D65: Clawback para churn cedo. Se o cliente cancela nos primeiros três a seis meses, parte da comissão volta. | E65: Para vendedor CLT, estornar comissão já paga porque o cliente cancelou é vedado em regra (art. 462 da CLT. A Lei 3.207/1957 só admite estorno por insolvência do comprador). O checklist repete em 6862. | F65: erro confirmado | G65: Para vendedor CLT, a Lei 3.207/1957 (art. 7º) só autoriza estornar comissão paga se o comprador ficar insolvente. O TST considera indevido o estorno por cancelamento ou inadimplência do cliente, mesmo com cláusula contratual. | H65: https://jurisprudencia-backend2.tst.jus.br/rest/documentos/e21c683230c1788bc9b252f492ffe136 | I65: TST, 2ª Turma, Ag-AIRR-12536-11.2017.5.15.0097 (2022). Alternativa: atrelar a comissão ao recebimento das mensalidades. Clawback só em contrato PJ. Repete em 6862.
A66: r1-juri-028 | B66: 4 | C66: 6685 | D66: Plataforma Comprasnet (federal), ou plataformas estaduais, ou municipais. | E66: O Comprasnet passou a se chamar Compras.gov.br. A seção também omite o PNCP, portal onde a Lei 14.133 obriga a publicar editais e contratos, primeiro lugar para monitorar oportunidades. | F66: desatualizado | G66: Desde 1º de outubro de 2021 o Comprasnet se chama Compras.gov.br, integrado ao PNCP (Portal Nacional de Contratações Públicas). | H66: https://legismap.com.br/conteudos/artigos-e-noticias/sistema-de-contratacoes-do-governo-federal-evolui-e-passa-a-se-chamar-compras-gov-br | I66: Fonte original: Ministério da Economia, 1/10/2021. Incluir o PNCP para monitorar editais. O art. 54 da Lei 14.133 não abriu no Planalto (página truncada).
A67: r1-juri-029 | B67: 4 | C67: 6691 | D67: O Marco Legal das Startups (Lei Complementar 182/2021) introduziu o Contrato Público para Solução Inovadora (CPSI), exatamente para isso. | E67: O CPSI aparece como contratação direta. Na LC 182/2021 ele resulta de uma modalidade especial de licitação (arts. 12 a 15), com teto de valor e prazo que o fundador precisa conhecer. | F67: parcialmente certo | G67: O CPSI foi criado pela LC 182/2021, mas resulta de licitação especial (art. 13), não de contratação direta. Dura até 12 meses, prorrogáveis por mais 12, com teto de R$ 1,6 milhão, e permite fornecimento posterior sem nova licitação por até 24 meses mais 24, até cinco vezes o teto. | H67: https://www.planalto.gov.br/ccivil_03/leis/lcp/lcp182.htm | I67: Edital com no mínimo 30 dias. Valores atualizáveis pelo IPCA (art. 12, § 3º). Dar parágrafo próprio e remeter ao Vol. 8, Cap. 1.
A68: r1-juri-030 | B68: 4 | C68: 7153 | D68: (diferença cobre MDR do cartão de ~10%) | E68: O exemplo contradiz três regras do capítulo: MDR de "~10%" contra 1,5% a 3,5% (7145), desconto anual de 23% (R$ 99 contra R$ 129) contra 10% a 15% (7204) e preço de R$ 99, que 7165 manda evitar. | F68: parcialmente certo | G68: Diferenciar preço por forma de pagamento é permitido, com informação visível ao consumidor (Lei 13.455/2017). Mas o próprio livro põe o MDR em 1,5% a 3,5% (L7145), então os 10% só se explicam com parcelado e antecipação. | H68: https://www.planalto.gov.br/ccivil_03/_ato2015-2018/2017/lei/l13455.htm | I68: Taxas de MDR parcelado não foram checadas. Refazer o exemplo sem contrariar L7165 e L7204 e não anunciar 'sem juros' se o parcelado custa mais.
... A132: r1-fina-034 | B132: 6 | C132: 4049 | D132: Hotmart (bootstrap em parte da trajetoria, com escala internacional sem dependencia de VC) | E132: A Hotmart recebeu aporte de venture capital (rodada liderada pela TCV, salvo engano). O parêntese também não tem relação com a frase, que fala de função de growth madura. | F132: erro confirmado | G132: A Hotmart captou venture capital. Em abril de 2021 levantou US$ 130 milhões em Série C liderada pela TCV, com General Atlantic, GIC, Accomplice e Koolen & Partners já como acionistas. | H132: https://dutchnews.nl/businesswire/hotmart-company-raises-us130-million-in-investment-round-led-by-tcv/ | I132: A rodada é de 2021, não de 2020. Cortar o parêntese, que também não se liga à frase sobre growth.
A133: r1-caso-026 | B133: 6 | C133: 4117 | D133: SaaS Mid-market (ticket R$ 2-8k/mês) R$ 1.500 – R$ 5.000 | E133: CAC de R$ 1.500 a 5.000 para ticket de R$ 2 a 8 mil por mês, ou de R$ 250 a 600 para ticket de R$ 200 a 800, dá payback de semanas a três meses. O volume usa 18 meses como referência (5069). | F133: não verificável | G133: A tabela não tem fonte. Pela conta, CAC de R$ 1.500 a 5.000 com ticket de R$ 2 a 8 mil por mês se paga em cerca de um mês, contra o payback saudável de até 18 meses que o próprio Vol. 6 usa (linha 5069). | I133: Sem busca externa, por limite de esforço. A conta interna mostra a incoerência. Refazer a tabela a partir do payback, como sugere o revisor, e citar fonte.
A134: r1-fina-035 | B134: 6 | C134: 4621 | D134: Você está na prática ajudando a escrever o RFP. Isso é legítimo, útil para o comprador, e cria vantagem competitiva sustentável. | E134: Sem ressalva para comprador público. Quem elabora projeto ou termo de referência pode ficar impedido de disputar (Lei 14.133, art. 14), e dirigir edital pode ser crime (CP, art. 337-F). | F134: parcialmente certo | G134: Ajudar a escrever o RFP é legítimo com comprador privado. Com órgão público, o autor de anteprojeto, projeto básico ou executivo não pode disputar (Lei 14.133, art. 14), e frustrar o caráter competitivo é crime (CP, art. 337-F). | H134: https://www.planalto.gov.br/ccivil_03/_ato2019-2022/2021/lei/l14133.htm | I134: O art. 14 não cita termo de referência. A pena do art. 337-F é de 4 a 8 anos e multa (TCE-SP). Com o setor público, contribuir só por canais formais.
A135: r1-caso-027 | B135: 6 | C135: 4669 | D135: Contra-proposta: foro da cidade onde a empresa contratante tem sede, ou foro neutro (Brasília para questões federais). | E135: Ambíguo: se a cidade remota é a sede do cliente, propor a sede da contratante repete o problema. Foro sem vínculo com as partes foi limitado pela Lei 14.879/2024. Falta a arbitragem. | F135: desatualizado | G135: Desde a Lei 14.879/2024, a eleição de foro só vale se tiver pertinência com o domicílio ou a residência de uma das partes ou com o local da obrigação. Foro 'neutro' sem vínculo, como Brasília, não produz efeito. | H135: https://www.planalto.gov.br/ccivil_03/_ato2023-2026/2024/lei/l14879.htm | I135: Ajuizar em juízo aleatório é prática abusiva e permite declinação de ofício (art. 63, § 5º, do CPC). Propor sede da contratada, local de execução ou arbitragem.
A136: r1-trib-041 | B136: 6 | C136: 5186 | D136: o seu plano de comissionamento estorna automaticamente a comissão (*Clawback*) ou o vendedor embolsa o bônus e o prejuízo fica para a empresa? | E136: Para vendedor CLT, a Lei 3.207/1957 só admite estorno na insolvência do comprador, e o TST costuma barrar estorno por cancelamento ou inadimplência. O Ritual (5191) e o checklist (5164) repetem. | F136: erro confirmado | G136: Para vendedor CLT, estornar comissão por cancelamento ou inadimplência do cliente é indevido segundo o TST. A Lei 3.207/1957 só admite estorno se o comprador ficar insolvente. | H136: https://www.planalto.gov.br/ccivil_03/leis/l3207.htm | I136: Repete em 5164 e 5191. Com CLT, atrelar a comissão ao pagamento do cliente. Clawback só em contrato PJ ou comercial, com cláusula escrita.
A137: r1-trib-042 | B137: 6 | C137: 5358 | D137: Pagamentos de comissão sem contrato formal podem ser requalificados pela Receita Federal como relação de trabalho. | E137: Foco errado. O risco do parceiro pago por comissão é virar representação comercial (Lei 4.886/1965): indenização mínima de 1/12, aviso prévio e comissão na zona se o contrato for omisso. | F137: parcialmente certo | G137: O risco maior de pagar comissão a parceiro sem contrato claro é virar representação comercial (Lei 4.886/1965), com indenização mínima de 1/12 do total recebido e aviso prévio. Se o contrato for omisso, o representante ganha comissão sobre negócios na zona. | H137: https://www.planalto.gov.br/ccivil_03/leis/l4886.htm | I137: Requalificação como vínculo também existe, mas é o risco menor. Contrato escrito deve dizer se é indicação, revenda ou agência, com zona e exclusividade. Remeter à L6195.
A138: r1-caso-028 | B138: 6 | C138: 5687 | D138: Kick BTG Pactual | E138: Nomes não reconhecíveis: o programa do BTG Pactual é conhecido como boostLAB, e o hub da Raízen como Pulse. "Kick" e "Baxter Labs" (L5690) parecem errados ou inventados. | F138: erro confirmado | G138: O programa do BTG Pactual para startups é o boostLAB, hub de negócios feito com a ACE e aberto a vários setores. O hub de inovação da Raízen é o Pulse, inaugurado em Piracicaba em 2017. | H138: https://finsidersbrasil.com.br/reportagem-exclusiva-fintechs/btg-pactual-seleciona-oito-scale-ups-para-nova-edicao-do-boostlab | I138: 'Kick' e 'Baxter Labs' não apareceram na busca. Pulse confirmado no IT Forum (27/09/2017). Status de ambos em 2026 não conferido. Rever a coluna 'Conversão estimada'.
A139: r1-juri-035 | B139: 6 | C139: 6024 | D139: O Boticário (maior rede franqueadora do Brasil por décadas), Cacau Show, Espaçolaser, McDonald's, Subway | E139: No ranking recente da ABF por unidades, a Cacau Show disputa ou lidera. O McDonald's no Brasil (Arcos Dorados) tem muitas lojas próprias, e a master da Subway passou por recuperação judicial. | F139: desatualizado | G139: No ranking ABF de 2025, divulgado em março de 2026, a Cacau Show lidera com 4.713 operações, à frente de O Boticário (3.898) e McDonald's (2.774). Subway não está entre as dez primeiras. | H139: https://istoedinheiro.com.br/maiores-franquias-brasil-2025 | I139: Tirar 'maior rede por décadas'. Wizard é 20ª (1.003) e Espaçolaser 23ª (808). Kumon aparece no ranking de microfranquias.
A140: r1-juri-036 | B140: 6 | C140: 6034 | D140: tipicamente até R$ 100 a 150 mil. Popular no Brasil por permitir que o pequeno empreendedor entre em marca estabelecida com menos capital. Mr. Sheha, muitas redes de limpeza. | E140: A ABF define microfranquia por um teto de investimento que muda com o tempo, e o valor vigente precisa ser conferido. "Mr. Sheha" não corresponde a rede conhecida e parece erro ou invenção. | F140: parcialmente certo | G140: A ABF trata como microfranquia a rede com investimento inicial de até R$ 135 mil (ranking 2025). Não foi achada rede chamada 'Mr. Sheha'. | H140: https://istoedinheiro.com.br/maiores-franquias-brasil-2025 | I140: Trocar 'R$ 100 a 150 mil' por 'até R$ 135 mil (ABF, 2025)'. Kumon é exemplo verificável de microfranquia.
A141: r1-juri-008 | B141: 6 | C141: 6047 | D141: Omissão ou inveracidade em COF dá ao franqueado direito de anular contrato e receber de volta os valores pagos, corrigidos, mais perdas e danos. É cláusula séria. | E141: "Mais perdas e danos" vinha da Lei 8.955/1994, revogada. A Lei 13.966 prevê anulabilidade ou nulidade e devolução corrigida do que foi pago como filiação e royalties. E é regra legal, não cláusula. | F141: desatualizado | G141: Pela Lei 13.966/2019 (art. 2º, § 2º, e art. 4º), omissão ou informação falsa na COF permite arguir anulabilidade ou nulidade e exigir a devolução corrigida do que foi pago como filiação e royalties. 'Mais perdas e danos' vinha da Lei 8.955/1994, revogada. | H141: https://www.planalto.gov.br/ccivil_03/_ato2019-2022/2019/lei/L13966.htm | I141: É regra legal, não cláusula. A lei atual não fala em perdas e danos. O mesmo erro se repete em v06 L6204.
A142: r1-caso-029 | B142: 6 | C142: 6172 | D142: o franqueado pode pedir na Justiça a **nulidade absoluta do contrato e a devolução integral de todas as taxas e royalties pagos, corrigidos monetariamente**, mesmo dois anos depois! | E142: A lei fala em "anulabilidade ou nulidade, conforme o caso", e o dicionário do Vol. 10 diz anulabilidade. Anulável tem prazo de dois anos (CC, art. 179): "dois anos depois" é o limite, não o susto. | F142: parcialmente certo | G142: O prazo de 10 dias da COF está no art. 2º, § 1º, da Lei 13.966/2019. Pelo § 2º, o franqueado pode arguir anulabilidade ou nulidade, conforme o caso, e pedir de volta o que pagou de filiação e royalties, corrigido. | H142: https://www.planalto.gov.br/ccivil_03/_ato2019-2022/2019/lei/L13966.htm | I142: Não é 'nulidade absoluta'. Para ato anulável sem prazo na lei, o prazo para anular é de dois anos (CC, art. 179), então 'dois anos depois' é o limite. Cortar 'implacável e absoluta'.
A143: r1-juri-037 | B143: 6 | C143: 6172 | D143: na Justiça brasileira, vigora o princípio da primazia da realidade | E143: Primazia da realidade é princípio do direito do trabalho. A requalificação de licença em franquia se apoia na intenção acima da letra (CC, art. 112) e na simulação (art. 167). Repetido em L6204. | F143: parcialmente certo | G143: A ideia de requalificar o contrato pelo que ele faz está certa, mas 'primazia da realidade' é princípio trabalhista. No direito civil a base é o art. 112 do Código Civil (intenção acima da letra) e, no limite, a simulação (art. 167). | H143: https://www.planalto.gov.br/ccivil_03/leis/2002/l10406compilada.htm | I143: O mesmo rótulo aparece em v06 L6204. Texto sugerido: 'O juiz olha o que o contrato faz, não o nome que ele tem (CC, art. 112).'
A144: r1-caso-030 | B144: 6 | C144: 6204 | D144: o contrato é declarado **nulo/anulável**, obrigando sua empresa a **devolver 100% de todas as taxas e royalties pagos pelo parceiro desde o dia zero, corrigidos monetariamente, mais perdas e danos**! | E144: A anulação não é automática, depende de pedido. "Perdas e danos" é da lei revogada. "100% do dinheiro de volta" (L6219) exagera: a devolução cobre filiação e royalties, não obra nem estoque. | F144: erro confirmado | G144: A Lei 13.966/2019 deixa o franqueado arguir anulabilidade ou nulidade e pedir a devolução corrigida de filiação e royalties. 'Mais perdas e danos' vinha da Lei 8.955/1994, revogada. | H144: https://www.planalto.gov.br/ccivil_03/_ato2019-2022/2019/lei/L13966.htm | I144: A anulação depende de pedido do franqueado. A devolução cobre filiação e royalties, não obra nem estoque. Alinhar as linhas 6047, 6172, 6219 e 6288.
A145: r1-juri-038 | B145: 6 | C145: 6208 | D145: por que receber R$ 1,00 ou assinar qualquer papel antes do 11º dia anula o contrato inteiro | E145: A lei fala em contrato ou pré-contrato de franquia e em pagamento de taxa. Termo de confidencialidade e recibo da COF não entram. E nada anula sozinho: o franqueado "poderá arguir". Idem L6288. | F145: parcialmente certo | G145: A COF deve ser entregue no mínimo 10 dias antes da assinatura do contrato ou pré-contrato ou do pagamento de qualquer taxa. Se não for, o franqueado 'poderá arguir' anulabilidade ou nulidade e pedir a devolução corrigida de filiação e royalties. | H145: https://www.planalto.gov.br/ccivil_03/_ato2019-2022/2019/lei/L13966.htm | I145: Nada anula sozinho e 'qualquer papel' é exagero, pois NDA e recibo da COF não contam. Ajustar também L6172 ('nulidade absoluta') e L6288.
... A148: r1-trib-043 | B148: 6 | C148: 6262 | D148: **NÃO é receita da franqueadora**! | E148: Afirmação categórica arriscada: a Receita Federal já tratou contribuições ao fundo como receita tributável em soluções de consulta. E o crime é "apropriação indébita", e a via usual é civil. | F148: erro confirmado | G148: A Receita já entendeu que valores repassados por franqueados ao fundo de publicidade, por cláusula obrigatória, são receita da franqueadora e entram na base de IRPJ, CSLL, PIS e Cofins (SC SRRF10/Disit 114/2012). | H148: https://tributodevido.com.br/portal/taxa-de-publicidade-em-contrato-de-franquia/ | I148: A Lei 13.966/2019 pede informar a taxa de publicidade (art. 2º, IX, c) e a gestão dos fundos (XX). Tratar como recurso carimbado e decidir o tributo com o contador.
A149: r1-caso-031 | B149: 6 | C149: 6351 | D149: EXAME, Valor, Folha, InfoMoney, Estadão, The Rider, Brazil Journal. | E149: 'The Rider' não corresponde a veículo de negócios conhecido no Brasil. Parece nome corrompido (The Shift? NeoFeed?). 'EXAME' em caixa alta destoa do resto. | F149: não verificável | G149: Não achei veículo de negócios brasileiro chamado The Rider. | I149: Uma busca só, por limite de esforço. Provável nome corrompido. Confirmar o veículo pretendido e grafar Exame sem caixa alta.
A150: r1-caso-032 | B150: 6 | C150: 6410 | D150: No Brasil, "Acha que é só andar" da Uber, veio disso. "O Itaú é feito para você", durou décadas. | E150: Frase corrompida ('da Uber, veio disso') e atribuição duvidosa: 'Acha que é só andar' não é assinatura conhecida da Uber. O 'Feito para você' do Itaú durou cerca de uma década, não décadas. | F150: não verificável | G150: Não achei 'Acha que é só andar' como assinatura da Uber. A campanha da Uber no Brasil de novembro de 2024 usou 'Bora marcar'. | H150: https://www.uber.com/pt-BR/newsroom/uber-destaca-habito-brasileiro-em-nova-campanha | I150: Uma busca, sem rastro do bordão. A duração de 'Feito para você' do Itaú não foi conferida. Corrigir também a frase quebrada ('da Uber, veio disso').
A151: r1-juri-009 | B151: 6 | C151: 6615 | D151: Vazamento de dados (LGPD) exige comunicação imediata obrigatória para ANPD e clientes afetados. | E151: Impreciso. O dever é do controlador, vale para incidente com risco ou dano relevante e tem prazo de 3 dias úteis (Res. CD/ANPD 15/2024), para ANPD e titulares. SaaS B2B costuma ser operador. | F151: parcialmente certo | G151: O dever é do controlador e vale para incidente que possa gerar risco ou dano relevante. O prazo é de três dias úteis do conhecimento, para ANPD e titulares (Res. CD/ANPD 15/2024, arts. 5º, 6º e 9º). | H151: https://www.legisweb.com.br/legislacao/?id=458235 | I151: Prazo em dobro para agente de pequeno porte. A resolução não fixa dever próprio do operador. O SaaS operador avisa o controlador conforme o contrato. Base: LGPD, art. 48.
A152: r1-caso-033 | B152: 6 | C152: 6645 | D152: ("inconsistências contábeis" para R$ 20-40 bi de fraude) destruiu credibilidade restante. Fundadores (trio 3G) silenciaram publicamente por meses | E152: Lemann, Telles e Sicupira eram acionistas de referência, não fundadores: a empresa é de 1929, como diz o Vol. 9, que fala em R$ 25 bi, não 20 a 40. O trio divulgou nota em janeiro de 2023. | F152: erro confirmado | G152: Lemann, Telles e Sicupira eram acionistas de referência da Americanas e fundadores da 3G, não da varejista. Eles divulgaram nota publicada em 22/01/2023 dizendo que nunca souberam das inconsistências, anunciadas em cerca de R$ 20 bilhões. | H152: https://www.poder360.com.br/economia/trio-da-americanas-diz-que-desconhecia-inconsistencias-contabeis/ | I152: 'Silenciaram por meses' não se sustenta, houve nota logo no início. Usar o valor do Vol. 9 (cerca de R$ 25 bi, não conferido aqui) no lugar de 'R$ 20 a 40 bi'.
A153: r1-juri-010 | B153: 6 | C153: 6776 | D153: Rafael Perez (Loggi no começo). Pedro Arnt (Mercado Livre CFO antes de virar founder). | E153: A Loggi foi fundada por Fabien Mendez e Arthur Debert. Pedro Arnt saiu do Mercado Livre para ser CEO do dLocal, não fundador. Rebeca Vergueiro (Olist) e Lucas Aisenberg não são reconhecíveis. | F153: erro confirmado | G153: A Loggi foi fundada em 2013 por Fabien Mendez e Arthur Debert. Pedro Arnt foi CFO do Mercado Livre por 12 anos e virou co-CEO da dLocal em 2023, sem fundar empresa. | H153: https://www.kaszek.com/company/loggi/ | I153: Arnt: Brazil Journal, 15/8/2023. Rafael Perez, Lucas Aisenberg e Rebeca Vergueiro não foram checados. Manter só nomes conferidos.
A154: r1-caso-034 | B154: 6 | C154: 7655 | D154: Padrão. Mission-driven storytelling, mais compensation competitiva em USD via Delaware C-corp, mais equity meaningful. | E154: A holding do Nubank (Nu Holdings) é constituída nas Ilhas Cayman, não em Delaware. Detalhe fácil de checar, que desacredita o caso. | F154: erro confirmado | G154: A Nu Holdings Ltd. é constituída nas Ilhas Cayman desde 26/02/2016, segundo o formulário 20-F entregue à SEC. Não é uma Delaware C-corp. | H154: https://www.sec.gov/Archives/edgar/data/1691493/000129281426002166/nuform20f_2025.htm | I154: Usar a redação do revisor, sem jurisdição, ou citar Cayman. O resto do padrão de contratação não foi conferido.
A155: r1-trib-044 | B155: 6 | C155: 7792 | D155: Sem documentação, demissão vira risco trabalhista elevado. Com documentação (avaliações sucessivas fracas, e PIP formal), a demissão é defensível, e justa. | E155: Raciocínio do direito americano. No Brasil, a dispensa sem justa causa não exige motivo e documentar baixo desempenho não cria justa causa. "Justa" confunde com o art. 482 da CLT. Idem 7951. | F155: erro confirmado | G155: No Brasil, a dispensa sem justa causa não exige motivo, salvo estabilidades, e a CLT trata das 'dispensas imotivadas' (art. 477-A). Documentar baixo desempenho não cria justa causa, que depende das faltas do art. 482. | H155: https://www.planalto.gov.br/ccivil_03/_ato2015-2018/2017/lei/l13467.htm | I155: O registro protege contra alegação de discriminação e sustenta advertências graduais em caso de desídia. Corrigir também L7951 e remeter ao Vol. 8, Cap. 7.
A156: r1-caso-035 | B156: 6 | C156: 8149 | D156: **Reajuste por IPCA (inflação):** repor o poder de compra, não é promoção. Obrigação implícita — não dar reajuste de inflação é redução real de salário. | E156: O reajuste anual costuma ser obrigatório pela convenção coletiva da categoria (data-base), muitas vezes pelo INPC, não "implícito". Dissídio não aparece aqui nem no mérito do Cap. 14 (7844). | F156: parcialmente certo | G156: Pela Lei 10.192/2001, salários são revistos na data-base anual por negociação coletiva, e é vedada cláusula de reajuste automático atrelado a índice de preços. A obrigação vem da convenção ou do acordo coletivo, não de regra implícita. | H156: https://www.planalto.gov.br/ccivil_03/leis/LEIS_2001/L10192.htm | I156: Está certo que reajuste abaixo da inflação reduz o salário real. O índice e o percentual dependem da negociação da categoria. Levar a ressalva ao Cap. 14 (linha 7844).
A157: r1-trib-045 | B157: 6 | C157: 8160 | D157: O tradeoff deve ser explícito: "oferecemos R$ 12K vs. R$ 18K de mercado, a diferença é equity que vale X em um cenário de exit Y". | E157: Registrar por escrito que a opção substitui parte do salário reforça a tese de natureza remuneratória (trabalhista e previdenciária). Prometer valor X num exit cria expectativa exigível. | F157: parcialmente certo | G157: O STJ (Tema 1.226) afastou a natureza salarial do stock option para o IRPF porque o empregado paga para exercer a opção. Apresentar a opção como a parte do salário que falta enfraquece esse argumento, e a tese não cobre a contribuição previdenciária. | H157: https://www.stj.jus.br/sites/portalp/Paginas/Comunicacao/Noticias/2024/07102024-Primeira-Secao-define-que-stock-option-plan-tem-carater-mercantil-e-deve-ser-tributado-na-revenda-de-acoes.aspx | I157: Transparência é boa. Separar a opção do salário e mostrar cenários depois da preferência de liquidação e da diluição, sem prometer valor. Vale também para L8306.
A158: r1-caso-036 | B158: 6 | C158: 8177 | D158: Deve haver acordo formal com os colaboradores — assinado com **comissão de empregados** (formada pelos próprios empregados) ou via **acordo coletivo com o sindicato**. | E158: A Lei 10.101 fala em comissão paritária (empresa e empregados) com representante indicado pelo sindicato, ou em convenção e acordo coletivo. Falta a antecedência mínima da assinatura. | F158: parcialmente certo | G158: A Lei 10.101/2000 exige negociação por comissão paritária escolhida pelas partes, com um representante indicado pelo sindicato, ou por convenção ou acordo coletivo. As regras valem se assinadas antes da antecipação e ao menos 90 dias antes do pagamento final. | H158: https://www.planalto.gov.br/ccivil_03/leis/l10101.htm | I158: Não basta 'comissão de empregados'. O limite de dois pagamentos por ano civil, com intervalo mínimo de um trimestre civil, está certo no livro.
A159: r1-caso-037 | B159: 6 | C159: 8884 | D159: Em *O Lado Difícil das Situações Difíceis*, Ben Horowitz cita o provérbio samurai e a lição de Bushido | E159: Bushido e samurais são tema de outro livro de Horowitz, What You Do Is Who You Are (2019), não de The Hard Thing About Hard Things. A frase inteira em negrito é paráfrase dada como lição dele. | F159: não verificável | G159: Não achei fonte que ligue o Bushido ou a frase em negrito a The Hard Thing About Hard Things. | I159: Duas buscas sem confirmação nos dois sentidos. Conferir no livro antes de corrigir. O revisor aponta What You Do Is Who You Are (2019). Tirar o negrito da paráfrase.
A160: r1-juri-040 | B160: 6 | C160: 9408 | D160: A política DEI tornou-se tema polarizado em ecossistema global em 2024 a 2026. Este capítulo aborda DEI como prática operacional em startup brasileira. | E160: Capítulo de DEI no Brasil sem o marco legal: Lei 14.611/2023 (igualdade salarial e relatório semestral a partir de 100 empregados), cota PcD (Lei 8.213/1991, art. 93), aprendizes e Lei 14.457/2022. | F160: parcialmente certo | G160: Há obrigações legais que o capítulo omite. A Lei 14.611/2023 exige relatório semestral de transparência salarial de empresas com 100 ou mais empregados, com multa de até 3% da folha. | H160: https://www.planalto.gov.br/ccivil_03/_ato2023-2026/2023/lei/l14611.htm | I160: Cota PcD (Lei 8.213/1991, art. 93), aprendizes e Lei 14.457/2022 não foram abertas aqui. Abrir a parte prática com o quadro 'o que é lei e o que é escolha'.
A161: r1-caso-038 | B161: 6 | C161: 9488 | D161: Quota rígida ("trinta por cento mulheres obrigatoriamente") costuma ser contraproducente. Força compromisso em qualidade ou alimenta ressentimento. | E161: Desaconselha cotas sem dizer que, no Brasil, a cota de PcD (2% a 5% a partir de 100 empregados) e a de aprendizes são obrigatórias, com multa. 'Força compromisso em qualidade' é falso cognato. | F161: não checada | G161: Não checada nesta rodada. | I161: Sem busca, por limite de esforço. Conferir o art. 93 da Lei 8.213/1991 (cota de PcD) e as regras de aprendizes na CLT antes de corrigir.
A162: r1-caso-039 | B162: 6 | C162: 9689 | D162: Mesma compensação global, paga igual independente de localização (Stripe, GitLab). | E162: GitLab é o exemplo clássico do contrário: paga por fator de localização, com calculadora pública. A Stripe também ajusta. Em 9747 o erro volta, com a lógica de custo invertida. | F162: erro confirmado | G162: A GitLab paga conforme o mercado local. O salário depende da função, da senioridade e de onde a pessoa mora, o que a torna exemplo de pagamento por localização. | H162: https://about.gitlab.com/blog/why-we-pay-local-rates/ | I162: Post da GitLab de 28/02/2019. A calculadora do handbook hoje pede login. Stripe e Basecamp não foram conferidos. O erro se repete na linha 9747.
A163: r1-juri-041 | B163: 6 | C163: 9697 | D163: PJ. Comum em tech. Atenção a não ser pejotização (relação de emprego disfarçada). | E163: Não menciona o julgamento do STF sobre pejotização (Tema 1.389), que suspendeu processos em 2025 e define a validade de contratos PJ. Em outubro de 2026 o cenário pode ter mudado. | F163: parcialmente certo | G163: Em outubro de 2026 o STF ainda não julgou o mérito do Tema 1.389 e não há data de pauta. A suspensão nacional de abril de 2025 foi parcialmente retirada em 18/06/2026, e os processos voltam a ficar sobrestados após o TRT. | H163: https://www.felsberg.com.br/tema-1389-pejotizacao-retomada-processos-stf/ | I163: Status de 21/10/2026 visto em mixvale.com.br (autos conclusos ao relator em 18/10/2026). Avisar que a tese pode mudar o risco do PJ remoto.
A164: r1-juri-011 | B164: 6 | C164: 9825 | D164: Todos os seus colaboradores remotos ou híbridos assinaram o **Contrato/Aditivo formal de Teletrabalho na modalidade "Por Produção ou Tarefa"** | E164: Manda enquadrar todo remoto 'por produção' para afastar hora extra. Vale a realidade: com core hours (9759), 1:1 semanal e rituais obrigatórios com câmera (9233), o enquadramento cai. | F164: parcialmente certo | G164: A CLT admite teletrabalho por jornada ou por produção ou tarefa, e só este fica fora do controle de jornada (arts. 62, III, e 75-B, §§ 2º e 3º, pela Lei 14.442/2022). O aditivo não basta se a rotina impõe horário. | H164: https://www.planalto.gov.br/ccivil_03/_ato2019-2022/2022/lei/l14442.htm | I164: Com core hours, 1:1 semanal e rituais com câmera, o enquadramento por produção fica frágil. Ajustar também o Ritual (L9830) e o título L9701.
A165: r1-caso-040 | B165: 7 | C165: 438 | D165: Teresa Torres, coach de produto com carreira em empresas como SurveyMonkey e HubSpot | E165: Não há registro conhecido de passagem de Teresa Torres por SurveyMonkey ou HubSpot. Credencial possivelmente inventada para uma autora viva. | F165: erro confirmado | G165: Antes de fundar a Product Talk em 2011, Teresa Torres passou por HighWire Press, Become.com e Affinity Circles, onde chegou a presidente e CEO. Não há registro de SurveyMonkey nem HubSpot. | H165: https://yespress.io/teresa-torres.md | I165: Fonte secundária, coerente com a bio oficial de palestrante (Rosenfeld Media), que não cita essas empresas. Usar 'coach de discovery de produto, autora do blog Product Talk'.
A166: r1-fina-037 | B166: 7 | C166: 3739 | D166: Codeium, ou Windsurf. Alternativa open-source-leaning. Similar em output. | E166: Mapa de 2024 vendido como 2026. Codeium virou Windsurf, vendida à Cognition em 2025, e não é open source. Faltam Codex, Gemini CLI e o agente do Copilot. Claude Code está nos tiers 1 e 2. | F166: desatualizado | G166: A Windsurf teve o CEO contratado pelo Google e foi comprada pela Cognition, dona do Devin, em julho de 2025. É produto comercial, não open source. | H166: https://pulse2.com/cognition-acquiring-windsurf-on-the-heels-of-google-deal | I166: A troca de nome de Codeium para Windsurf não está nesta fonte. Reescrever o mapa por categoria, com dois exemplos atuais e a data da checagem.
A167: r1-caso-041 | B167: 7 | C167: 3741 | D167: Copilot Workspace. Interpretação de issues, e geração de PRs. | E167: O Copilot Workspace foi encerrado em maio de 2025 e deu lugar ao agente de codificação do Copilot. "AI Software Engineer", na mesma linha, não é produto. | F167: não verificável | G167: O agente de codificação do GitHub Copilot entrou em prévia pública em 19/05/2025. Ele recebe uma issue atribuída, trabalha sozinho e devolve o trabalho para revisão em pull request. | H167: https://github.blog/changelog/2025-05-19-github-copilot-coding-agent-in-public-preview/ | I167: Não confirmei em fonte aberta o fim do Copilot Workspace. Citar o agente de codificação no lugar. Conferir 'AI Software Engineer', que parece descrição, não produto.
A168: r1-fina-039 | B168: 7 | C168: 3857 | D168: METR (Model Evaluation and Threat Research) publicou estudos mais recentes, com achados mistos. | E168: O METR (jul/2025) achou devs experientes 19% mais lentos com IA, embora se achassem 20% mais rápidos. Não é "ganho menor ou nulo". Os 55% do GitHub mediam tempo numa tarefa, não percepção. | F168: erro confirmado | G168: O estudo do METR de julho de 2025 (16 devs experientes, 246 tarefas em repositórios maduros) mediu 19% mais tempo com IA. Eles esperavam ganho de 24% e depois acreditavam ter ganho 20%. | H168: https://metr.org/blog/2025-07-10-early-2025-ai-experienced-os-dev-study/ | I168: O METR diz que o resultado está desatualizado e publicou novos dados em fevereiro de 2026, não conferidos. O estudo do GitHub (55%) também não foi conferido.
A169: r1-juri-012 | B169: 7 | C169: 3884 | D169: Código em empresa que processa dados pessoais (maioria das startups brasileiras) não pode ser compartilhado com API de terceiro, se contiver dados pessoais. | E169: A LGPD não proíbe usar operador terceiro. Exige base legal, contrato e, com fornecedor no exterior, mecanismo de transferência internacional (art. 33, Res. CD/ANPD 19/2024). Não treinar não basta. | F169: erro confirmado | G169: A LGPD não proíbe enviar dados a fornecedor de IA. Exige base legal, instruções ao operador e, se o fornecedor estiver no exterior, um mecanismo do art. 33, como as cláusulas-padrão da Res. CD/ANPD 19/2024. | H169: https://www.demarest.com.br/anpd-aprova-o-regulamento-de-transferencia-internacional-de-dados/ | I169: Não treinar é cláusula comercial, não condição legal. Regra prática: código não deve conter dado pessoal. Remeter ao Vol. 8.
A170: r1-fina-038 | B170: 7 | C170: 3937 | D170: Este capítulo descreve o estado da arte em abril de 2026. | E170: A data não bate com o conteúdo (Codeium, Copilot Workspace, Cody, Angular 19). Há três prazos de revisão: anual (3737), seis a doze meses (aqui), anual mínima com "superada em seis meses" (3906). | F170: erro confirmado | G170: O capítulo não reflete abril de 2026. O Copilot Workspace saiu do ar em maio de 2025, substituído pelo agente de código do Copilot, e a Windsurf foi vendida à Cognition em julho de 2025. | H170: https://aiwiki.ai/wiki/copilot_workspace/raw | I170: Fonte secundária, o changelog da GitHub foi bloqueado nesta checagem. Cody e Angular 19 não conferidos. Usar uma nota única com data real e um prazo de revisão.
A171: r1-caso-042 | B171: 7 | C171: 4055 | D171: Para a maioria das tarefas de AI Ops, GPT-4o ou Claude Sonnet são suficientes. Modelos maiores (GPT-4 Turbo, Claude Opus) só se justificam | E171: Tabela e conselhos de 2024 (GPT-4o, Claude 3.5/3.7, Gemini 1.5 Pro, Llama 3, GPT-4 Turbo), vários aposentados em 2025. Os marcos de preço (4289) e as dicas de 4212 param em 2024. | F171: desatualizado | G171: O GPT-4 Turbo sai da API em 23/10/2026 e o GPT-4o e o GPT-4o mini têm desligamento marcado para 14/01/2027. Gemini 1.5 Pro e Claude Sonnet 3.5 e 3.7 já não aparecem nas listas do Google e da Anthropic. | H171: https://developers.openai.com/api/docs/deprecations | I171: Ver ai.google.dev/gemini-api/docs/models e platform.claude.com/docs/en/about-claude/pricing. Refazer a tabela por faixa, datada. Revisar também 4212 e 4289.
A172: r1-juri-042 | B172: 7 | C172: 4138 | D172: verifique se o contrato com o fornecedor inclui cláusulas de processamento de dados (Data Processing Agreement — DPA) | E172: Enviar dados a OpenAI, Anthropic ou Google é transferência internacional (art. 33). Desde 2025 a ANPD exige mecanismo próprio, como as cláusulas-padrão da Res. CD/ANPD 19/2024. DPA sozinho não basta. | F172: parcialmente certo | G172: O DPA é necessário, mas mandar dados a fornecedor no exterior é transferência internacional (LGPD, art. 33). Quem usa cláusulas contratuais teve até agosto de 2025 para adotar as cláusulas-padrão da ANPD, na íntegra e sem alteração (Res. CD/ANPD 19/2024). | H172: https://www.demarest.com.br/anpd-aprova-o-regulamento-de-transferencia-internacional-de-dados/ | I172: Acrescentar: confirmar a região de processamento, exigir as cláusulas-padrão da ANPD e registrar a transferência no inventário. Repetir no checklist (L4334).
A173: r1-juri-043 | B173: 7 | C173: 4152 | D173: - Dados de menores de 18 anos sem consentimento dos responsáveis | E173: Simplifica a regra. O consentimento parental do art. 14 vale para crianças, e o Enunciado CD/ANPD 1/2023 admite outras bases legais no melhor interesse de crianças e adolescentes. | F173: parcialmente certo | G173: O consentimento de pai ou responsável (art. 14, § 1º) vale para crianças. O Enunciado CD/ANPD 1/2023 admite as bases dos arts. 7º e 11 para crianças e adolescentes, desde que prevaleça o melhor interesse. | H173: https://www.felsberg.com.br/importante-anpd-publica-enunciado-sobre-o-tratamento-de-dados-pessoais-de-criancas-e-adolescentes/ | I173: O ECA Digital (Lei 15.211/2025) vigora desde 17/03/2026, data fixada pela Lei 15.352/2026. Manter a cautela no LLM, com a regra certa.
... A235: r2v9-caso-024 | B235: 9 | C235: 1608 | D235: Q1{"Empresa tem<br/>receita ≥ R$10M ARR<br/>e crescendo?"} | E235: Quem fatura menos de R$ 10 milhões só tem acqui-hire ou encerramento. Some a venda estratégica pequena, a mais comum no Brasil, a venda a fundo ou search fund e a Cash Cow. | F235: parcialmente certo | G235: Abaixo de R$ 10 milhões de ARR ainda há venda a comprador estratégico menor, venda a search fund ou PE pequeno e a via Cash Cow, que o próprio volume discute. O nó Q4 não tem saída para 'não'. | H235: /home/claude/ignicao/src/v09.md, l. 1606-1623 (checagem interna) | I235: Trocar o primeiro corte por lucro ou ativo estratégico. Padronizar 'defensibilidade', grafia da l. 1637, no lugar de 'defensabilidade' (l. 1617).
A236: r2v9-fina-021 | B236: 9 | C236: 1687 | D236: Em exit (M&A ou IPO), os proceeds não são divididos pro-rata | E236: Em IPO as preferenciais costumam converter em ordinárias e não há cascata de preferências. Em secondary, quem vende vende as próprias ações. A l. 2816 repete o erro. | F236: não checada | G236: Não checada. O limite de acesso a fontes da sessão acabou antes desta afirmação. | I236: O revisor parece certo: conversão automática das preferenciais no IPO é cláusula padrão de term sheet. Conferir no modelo da NVCA antes de corrigir 1687 e 2816.
A237: r2v9-fina-022 | B237: 9 | C237: 1770 | D237: *Anti-sandbagging na métrica*: se o adquirente tomar ação que torne a métrica impossível de atingir | E237: Termo usado errado. Em M&A, sandbagging é o comprador pedir indenização por falha que já conhecia. O texto descreve obrigação de conduta do comprador. O checklist (l. 1992) repete. | F237: não checada | G237: Não checada. O limite de acesso a fontes da sessão acabou antes desta afirmação. | I237: Em M&A, sandbagging costuma designar o comprador que conhecia a falha antes do closing. Confirmar e reescrever 1770 e 1992 como obrigação de não frustrar o earn-out.
A238: r2v9-trib-002 | B238: 9 | C238: 1776 | D238: Isso muda a interpretação fiscal e pode reduzir o imposto pago quando recebido. | E238: Conselho tributário sem ressalva. O rótulo não muda a substância: se o earn-out depende de o fundador seguir empregado, o Fisco pode tratá-lo como salário, com IR de até 27,5% e encargos. | F238: parcialmente certo | G238: Parcela de preço sob condição suspensiva integra o preço e é tributada como ganho de capital, de 15% a 22,5% (SC Cosit 96/2026). Pagamento atrelado à permanência no emprego tende a ser visto como remuneração, como fez o CARF com bônus de retenção (Acórdão 2302-004.194, 2026). | H238: https://fenacon.org.br/wp-content/uploads/2026/07/SC-Cosit-no-96-2026.pdf | https://rotadajurisprudencia.com.br/2026/01/hiring-bonus-e-bonus-de-retencao-entram-na-base-da-contribuicao-previdenciaria-decide-carf-por-voto-de-qualidade/ | I238: O nome ajuda, mas não basta. Desvincular o earn-out da permanência, pôr a retenção em bônus separado e validar com tributarista.
A239: r2v9-caso-003 | B239: 9 | C239: 1796 | D239: Seção 1202 QSBS para empresas americanas (isenção em até US$ 10 milhões se ações mantidas por cinco anos ou mais) | E239: QSBS é benefício do IR federal americano. Fundador residente no Brasil paga IR aqui sobre o ganho. A regra mudou em julho de 2025 (teto de US$ 15 milhões, isenção parcial em 3 e 4 anos). | F239: desatualizado | G239: QSBS é exclusão do IR federal dos EUA. Para ações emitidas após 4/7/2025 o teto é US$ 15 milhões, com exclusão de 50% em 3 anos, 75% em 4 e 100% em 5. US$ 10 milhões e 5 anos valem só para ações anteriores. | H239: https://www.jonesday.com/en/insights/2025/07/qualified-small-business-stock-benefits-expanded-in-new-tax-bill | I239: Não é estrutura 'no Brasil' e não reduz o IR brasileiro de quem é residente aqui. O limite de ativos brutos da empresa subiu para US$ 75 milhões.
A240: r2v9-trib-003 | B240: 9 | C240: 1796 | D240: holding pessoal (dividendos isentos na regra atual, mas há IR sobre ganho de capital na venda subjacente) | E240: Desatualizado em outubro de 2026. A Lei 15.270/2025 criou IR mínimo para alta renda e retenção de 10% sobre dividendos acima de R$ 50 mil por mês, desde janeiro de 2026. | F240: desatualizado | G240: Desde 1/1/2026 (Lei 15.270/2025), lucros e dividendos acima de R$ 50 mil por mês de uma mesma empresa a uma pessoa física têm retenção de 10% sobre o total. A renda acima de R$ 600 mil por ano entra na tributação mínima de até 10%, com redutor. | H240: https://www.planalto.gov.br/ccivil_03/_ato2023-2026/2025/lei/L15270.htm | I240: Lucros até 2025 com distribuição aprovada até 31/12/2025 seguem isentos se pagos até 2028. Avisar que a holding que vende a participação paga IRPJ e CSLL sobre o ganho.
A241: r2v9-trib-004 | B241: 9 | C241: 1796 | D241: estrutura offshore (Delaware, Cayman, BVI — legal se estruturada cedo, com compliance alto) | E241: Ignora a Lei 14.754/2023. Desde 2024, lucros de controladas no exterior e ganhos de pessoa física com ativos fora do país pagam 15%, muitas vezes ano a ano. A vantagem encolheu. | F241: desatualizado | G241: Desde 2024 (Lei 14.754/2023), a pessoa física paga 15% no ajuste anual sobre o lucro de controlada no exterior em 31/12, distribuído ou não, se a controlada está em paraíso fiscal ou tem renda ativa própria abaixo de 60%. Participação não controlada paga 15% na venda. | H241: https://www.planalto.gov.br/ccivil_03/_ato2023-2026/2023/lei/l14754.htm | I241: A estrutura segue legal, mas o diferimento acabou em boa parte dos casos. O próprio livro cita a lei em 3872. Avaliar com tributarista antes de montar.
A242: r2v9-trib-005 | B242: 9 | C242: 1802 | D242: E fazer errado, em deal de R$ 100 milhões, custa R$ 10-30 milhões em imposto evitável. | E242: Conta impossível. O IR de pessoa física sobre ganho de R$ 100 milhões soma R$ 21,4 milhões (15% a 22,5%). Não dá para evitar R$ 30 milhões, nem 30 a 50% (l. 2015) ou 20 a 40% (l. 1794). | F242: parcialmente certo | G242: Pela tabela da Lei 8.981, art. 21 (redação da Lei 13.259/2016), o IR da pessoa física sobre ganho de R$ 100 milhões é de R$ 21,375 milhões. Contra a venda pela holding a 34%, conta que o próprio livro usa, a diferença fica perto de R$ 12,6 milhões, então R$ 30 milhões evitáveis é exagero. | H242: https://www.planalto.gov.br/ccivil_03/leis/l8981.htm | I242: Unificar as faixas de 1794 (20 a 40%) e 2015 (30 a 50%), que excedem o próprio imposto da pessoa física, de no máximo 22,5% do ganho.
A243: r2v9-caso-004 | B243: 9 | C243: 1843 | D243: Não para pedir permissão — a decisão é sua. | E243: Com sócios e investidores, encerrar exige deliberação societária (quórum do Código Civil ou da Lei das S.A.) e o acordo costuma dar veto ao investidor. A ordem dos Passos 3 a 5 ignora isso. | F243: erro confirmado | G243: Havendo sócios, encerrar é decisão da sociedade. Na Ltda, a dissolução exige votos de mais da metade do capital social (art. 1.076, II, c/c art. 1.071, VI, do CC, redação da Lei 14.451/2022), e o acordo de investimento pode dar veto ao investidor. | H243: https://www2.camara.leg.br/legin/fed/lei/2022/lei-14451-21-setembro-2022-793229-publicacaooriginal-166092-pl.html | I243: Na S.A., a dissolução é deliberada em assembleia. Reordenar os passos: sócios, time, clientes e fornecedores, público.
...
